Workbook

Sheet 框架对标原文底稿
A1: 一级指标 | B1: 二级指标 | C1: 三级指标 | D1: 关键字说明 | E1: 人民银行转型金融要求 | F1: 人民银行钢铁行业转型金融标准 | G1: 企业可持续披露准则第1号——气候（试行） | H1: 《河北省钢铁行业转型金融工作指引（2025年版）》 | I1: 沪深北上市公司可持续披露指引 | J1: 工业和信息化部《钢铁行业规范条件（2025年版）》 | K1: 其他国内政策 | L1: IIGCC《净零投资框架1.0》 | M1: ICMA气候转型债券指引（CTB）和气候转型融资手册（CTF） | N1: 《TPI方法论报告：管理质量和碳绩效》第五版 | O1: 惠誉常青《转型评估方法：石油和天然气部门》 | P1: 《TCFD 指标、目标和转型计划指南》 | Q1: TPT《英国转型计划工作组的转型计划披露框架》 | R1: SASB——《对可持续核算准则理事会（SASB）标准的修订（征求意见稿）》 | S1: GFANZ《金融机构净零转型计划框架》 | T1: 企业信息披露情况（宝山钢铁） | U1: 企业信息披露情况（中信特钢） | V1: 分析
A2: 目标与战略 | B2: 目标和承诺 | C2: 碳中和目标 | D2: 企业承诺转型目标与国家碳达峰碳中和目标一致，服务于国家碳达峰碳中和目标；制定减排目标是指企业制定短期（如2024—2025年）、中期（2026—2030年）和长期（至2060年）的目标，且目标符合所在行业的先进性水平 | E2: 转型主体应当对照国家碳达峰碳中和目标，制定并披露科学合理的碳减排目标，主要内容和要求包括：（1）转型主体层面的碳达峰碳中和目标不得落后于国家碳达峰碳中和目标要求；（2）包括短期、中期和长期目标，以定量的碳排放总量或者单位产品碳排放强度表示。 | G2: 第四十一条 企业应当披露其为监控实现战略目标的进展而设定的定量和定性气候目标，以及国家法律法规、战略规划要求其实现的气候目标，包括温室气体排放目标 | H2: 一（一）2.有整体转型方案。方案应遵循以下原则：一是有科学合理的碳减排目标。目标要坚持显著贡献原则和一致性原则”，应将商业可持续与双碳目标有机结合，不得落后于国家碳达峰碳中和目标要求。短期目标要以定量的碳排放强度表示，中、长期目标要兼顾碳排放总量。 | L2: 1. 根据法律义务、信托义务和行业最佳实践（如TCFD和ISSB）； 2.承诺到2050年或更早实现投资组合净零排放，并获得董事会的明确认可； | M2: CTF：要素1.发行人的气候转型战略和治理：推荐信息和指标： • 长期、以科学为基础的目标，以符合《巴黎协定》的目标； CTB：高排放SLBs发行人应根据具体行业和本地情况选择KPI，并设定具有雄心的SPT，基于多种基准方法的结合，例如历史和经外部验证的数据、同行选择的数据以及行业或部门标准，融入公认的“最佳可用技术”（BAT）或其他行业/部门的替代指标。目标至少应与官方国家/地区/国际目标保持一致，并在可能的情况下，力求超越这些水平。 | N2: 企业设定了温室气体减排目标，目标可能是以定量或非定量形式，可能覆盖范围1和范围2和/或范围3温室气体排放。 企业以相对或绝对方式设定了温室气体减排的定量目标（范围1和范围2和/或范围3）。 | O2: （钢铁）对于2050目标从排放量、排放强度进行了等级划分： （1）有针对性地减少范围1和范围2的绝对排放量：按照企业是否有目标与数据及其详细程度（有无、详细程度），分6个评分阈值（0-5）进行评价； （2）有目标地减少范围3的绝对排放量:按照企业是否有目标与数据及其详细程度（有无、详细程度），分6个评分阈值（0-5）进行评价； （3）有针对性地减少范围1和范围2排放强度:按照企业是否有目标与数据及其详细程度（有无、详细程度），分6个评分阈值（0-5）进行评价； | P2: （1）与战略保持一致：组织的转型计划与其整体战略保持一致，并且描述了下列内容：  举措——组织将如何在规定的时间范围内实现目标。  温控目标——与全球升温目标、相关监管要求和/或部门脱碳战略保持一致。 | Q2: 1.1 战略愿景 主体应当披露其转型计划中的战略愿景。这包括主体在向低温室气体排放、气候韧性经济转型过程中，为响应并推动转型而设定的目标与优先事项，同时说明主体将如何以把握机遇、避免对利益相关方和社会造成不利影响、保护自然环境的方式来追求这些目标和优先事项。 披露建议 作为此部分的内容，主体应当披露： a. 其目标与优先事项： i. 旨在减少其运营或价值链中范围 1、范围 2 和范围 3 温室气体排放的目标与优先事项 ii. 旨在增强其对气候变化的适应能力，并应对向低温室气体排放、气候韧性经济转型所带来的风险与机遇的目标与优先事项 iii. 旨在利用其可用的杠杆与能力，嵌入并加速向低温室气体排放、气候韧性经济转型的目标与优先事项 b. 其是否以及如何识别、评估并考量转型计划对利益相关方（如员工、价值链合作伙伴、客户、社会（如当地社区）、经济和自然环境）的影响与依赖关系，以及这些影响与依赖关系在整个价值链中可能引发的可持续性相关风险与机遇 c. 其在多大程度上考量并遵循了外部要求、承诺、基于科学的目标、转型路径、路线图或情景，其中可能包括： i. 政府做出的国家或国际承诺 ii. 法律或法规要求其达成的任何目标 iii. 行业路径、路线图或其他气候情景 iv. 自愿性承诺（例如，现有的公开承诺、组织和行业标准、合同关系、行为准则等） d. 在 1.1a 的目标与优先事项之间识别出的任何潜在权衡、协同效应或共同效益 e. 其为衡量进展而设定的任何短期、中期和长期目标及里程碑，包括在转型规划背景下如何定义短期、中期和长期 | R2: 主体应当披露其管理范围 1 温室气体（GHG）排放的长期与短期战略或计划，包括减排目标，以及针对这些目标的绩效分析。 1.1 目标披露 1.2 目标设定与监控 1.3 绩效分析 | S2: 目标与优先事项 目标，即在 2050 年或更早实现净零排放，该目标需符合基于科学的路径，以将升温限制在 1.5℃以内。明确界定可衡量的中期和长期目标与战略时间线，为推动实体经济减排而需采取的净零转型融资优先战略。 ・为 2050 年净零目标制定的短期、中期和长期战略愿景、承诺及实现路径 | T2: 来源：24年可持续发展报告 制定了中长期减碳目标，以2020年为基准年，2025年减碳8%，2035年力争减碳30%，2050年力争实现碳中和。 2035年力争减碳30%脚注：以公司运营范围为边界，包括范围一和范围二 | U2: 来源：24年可持续发展报告 2060 年前实现“碳中和”的目标 | V2: 碳达峰、碳中和目标属于企业转型战略层面的核心承诺指标，能够直接反映企业对国家“双碳”政策目标的响应程度及其长期转型方向。相关目标在政策框架中具有明确定位，且上市钢铁企业普遍存在定性或定量披露，具备较好的可比性与可得性，建议作为目标与战略维度的基础性指标予以保留。
C3: 碳达峰目标 | D3: 企业承诺转型目标与国家碳达峰碳中和目标一致，服务于国家碳达峰碳中和目标；制定减排目标是指企业制定短期（如2024—2025年）、中期（2026—2030年）和长期（至2060年）的目标，且目标符合所在行业的先进性水平 | E3: 转型主体应当对照国家碳达峰碳中和目标，制定并披露科学合理的碳减排目标，主要内容和要求包括：（1）转型主体层面的碳达峰碳中和目标不得落后于国家碳达峰碳中和目标要求；（2）包括短期、中期和长期目标，以定量的碳排放总量或者单位产品碳排放强度表示。 | G3: 第四十一条 企业应当披露其为监控实现战略目标的进展而设定的定量和定性气候目标，以及国家法律法规、战略规划要求其实现的气候目标，包括温室气体排放目标 | H3: 一（一）2.有整体转型方案。方案应遵循以下原则：一是有科学合理的碳减排目标。目标要坚持显著贡献原则和一致性原则”，应将商业可持续与双碳目标有机结合，不得落后于国家碳达峰碳中和目标要求。短期目标要以定量的碳排放强度表示，中、长期目标要兼顾碳排放总量。 | L3: 4. 脱碳计划：一套量化的措施，通过减少温室气体和增加相关的绿色收入来实现中短期科学目标； 6. 目标：减少温室气体排放的短期和中期科学目标； 7. 雄心：2050年的长期目标与实现全球净零排放相一致。 6. 雄心：2050年的长期目标与实现全球净零排放目标一致，以及与之一致的中期目标（国家自主贡献绝对排放目标）。 | M3: CTF：要素1.发行人的气候转型战略和治理：推荐信息和指标： • 与长期目标发展轨迹相关的短期和中期科学基础的中间目标，符合相关区域、行业或国际气候变化情景。 CTB：高排放SLBs发行人应根据具体行业和本地情况选择KPI，并设定具有雄心的SPT，基于多种基准方法的结合，例如历史和经外部验证的数据、同行选择的数据以及行业或部门标准，融入公认的“最佳可用技术”（BAT）或其他行业/部门的替代指标。目标至少应与官方国家/地区/国际目标保持一致，并在可能的情况下，力求超越这些水平。 | N3: 企业以相对或绝对的形式设定了定量且长期（超过5年）的减排目标（范围1和范围2和/或范围3）。 | O3: （钢铁）对于2030目标从排放量、排放强度进行了等级划分： （1）有针对性地减少范围1和范围2的绝对排放量：按照企业是否有目标与数据及其详细程度（有无、详细程度），分6个评分阈值（0-5）进行评价； （2）有目标地减少范围3的绝对排放量:按照企业是否有目标与数据及其详细程度（有无、详细程度），分6个评分阈值（0-5）进行评价； （3）有针对性地减少范围1和范围2排放强度:按照企业是否有目标与数据及其详细程度（有无、详细程度），分6个评分阈值（0-5）进行评价； | P3: （2）目标：制定基于科学的定量和定性目标。对于温室气体排放目标而言，明确温室气体排放类型和范围，以及跨地区、时间范围或活动的温室气体排放程度。 | Q3: 4. 指标与目标 4.3 温室气体指标与目标 主体应当披露其为推动和监控转型计划战略愿景进展所使用的温室气体排放与清除指标及目标，并至少每年针对这些指标和目标进行一次报告。 披露建议…… | R3: 绩效分析的详细要求 主体应当讨论其减排目标，并分析针对这些目标的绩效表现，包括（如适用）： 2.1 减排目标的范围（例如，目标所覆盖的总排放量占比） 2.2 目标类型：说明目标是绝对目标还是强度目标；若为强度目标，需披露指标分母 2.3 基准年减排比例：说明相对于基准年的减排百分比，基准年是评估目标达成情况的起始年份 2.4 减排时间线：包括起始年、目标年和基准年 2.5 目标达成机制 | S3: 1) 指标与目标 建立一套指标与目标，以推动净零转型计划的执行，并监控短期、中期和长期的成果进展。包括专注于：1）使金融活动与实体经济净零转型保持一致；2）执行转型计划；3）衡量客户与投资组合温室气体排放变化的指标与目标。 ・明确定义将跨类别追踪的指标：实体经济转型（通过四大融资策略）、计划执行、已融资排放，包括每项的范围与覆盖度 ・定量与定性的中期和最终目标 ・基准线、当前及预计的已融资温室气体足迹，包括范围 1、2 和 3 排放，以及排放中和里程碑，说明如何计划在 2050 年前通过高质量、永久性清除来最终中和任何剩余排放 ・假设的方法论与范围，概述目标所依据的相关科学 ・为目标背景提供信息的重大决策或选择 ・针对明确的投资组合一致性指标的进展 ・对碳信用使用与质量的监控指标 ・指标与目标的复核及更新频率，以及过往更新记录 ・在实体经济转型与已融资排放中使用行业路径设定目标 | T3: 来源：公开信息 该公司发布的《2030年前碳达峰行动方案》 | U3: 来源：24年可持续发展报告 2030 年前实现“碳达峰”，2030 年前吨钢碳排放强度较基准年（2021 年）下降 5%。到 2035 年具备降碳 20% 的技术能力。 | V3: 碳达峰目标作为企业转型承诺的具体节点，能够反映企业是否将减排承诺与国家政策时间表对齐，在政策框架中与碳中和目标共同构成转型目标体系的基础层。建议与碳中和目标合并评价，综合反映企业在分阶段减排目标设置上的完整性与科学性。
C4: 其他环境目标 | D4: 指除碳达峰 / 碳中和目标之外，用于支撑低碳转型路径落地的能效、资源、污染与过程优化类目标。 可识别目标类型包括但不限于： 1. 能效提升（如吨钢综合能耗下降） 2. 能源结构优化（如清洁电力占比、余热利用） 3. 污染物减排（SO₂ / NOx / PM / VOCs） 4. 水资源管理（吨钢取水量、回用率） 5. 资源循环与废弃物（废钢比、固废利用率） 6. 工艺与流程优化（短流程占比、关键工序效率） | E4: 无重大损害原则：转型金融支持的经济活动或企业，应当对污染防控、资源节约和生态保护等其他环境目标无重大损害 | G4: 第四十条 企业应当披露与特定业务模式、活动或者表明企业所处行业的其他共同特征相关的行业特定指标。企业在确定披露的行业特定指标时，应当充分考虑相关法律法规和政策的要求（如行业应用指南），以及行业内其他企业的披露惯例。 | I4: 第三十条（污染防治）、第三十五条（能源利用）、第三十六条（水资源利用）、第三十七条（循环经济）等条款要求披露相关目标、措施及成效。 | L4: 1. 为能源投资和森林砍伐政策制定明确的指令，并适当披露这些指令； | N4: 如果企业制定关于气候变化政策或承诺陈述，承诺会解决相关问题，或减少或避免气候变化的影响（如减少碳排放或提高能源效率） | Q4: 4. 指标与目标 4.1 治理、业务与运营指标及目标 主体应当披露其为推动和监控转型计划战略愿景进展所使用的治理、参与、业务与运营指标及目标，并至少每年针对这些指标和目标进行一次报告。 披露建议…… 4.2 财务指标与目标 主体应当披露与其业务、行业及战略相关的财务指标与目标，这些指标和目标用于推动和监控转型计划战略愿景的进展，并至少每年针对这些指标和目标进行一次报告。 披露建议…… | T4: 来源：24年可持续发展报告 吨钢综合能耗、污染物减排、能源结构优化、水资源管理、资源循环与废弃物、工艺与流程优化 | U4: 来源：24年可持续发展报告 能源管理目标（吨钢综合能耗、能源消费用量、绿电装机容量） | V4: 其他环境目标（如能效提升、污染物减排、水资源管理等）虽与低碳转型并非直接关联，但在主要转型金融、气候政策及行业转型路径框架中，通常以协同目标、约束条件或补充要求的形式出现，可辅助反映企业的环境治理水平和综合可持续发展能力。因此暂作为可选指标纳入转型绩效评价体系，用于补充说明企业的综合环境表现。
B5: 战略和规划 | C5: 转型规划 | D5: 企业制定明确的转型路线图、行动方案或分阶段规划 | E5: 转型主体应当制定并披露技术可行的转型计划，主要内容和要求包括：（1）对照短、中、长期碳减排目标，明确每个阶段的转型技术路径，该技术路径应当具有可行性和先进性；（2）明确每个阶段的工作计划及重点工作任务；（3）测算每个阶段转型工作的碳减排效果。 | G5: 第十二条（四）企业已有的气候转型计划，包括制定转型计划时使用的关键假设和依据。 | H5: 一（一）2.有整体转型方案。方案应遵循以下原则：二是有清晰可行的技术路径。技术路径应当具有可行性，要遵循先进性原则、无重大损害原则和避免“碳锁定”原则'。 | I5: 第二十三条 披露主体应当披露为应对气候相关风险和机遇的转型计划、措施及其进展，包括但不限于下列内容： （一）公司为应对气候相关风险和机遇而对当前和未来战略、商业模式和资源分配进行调整的情况；（二）公司已经或者计划为直接或间接应对气候相关风险和机遇所采取的改进生产工艺、更新设备等措施；（三）公司为应对气候相关风险和机遇所制定的转型计划，及制定该计划所依赖的基本假设；（四）公司为实施转型计划提供的资源；（五）公司实施转型计划的进展情况。 | L5: 治理和战略： 5. 转型计划的实施； 7. 将转型计划纳入投资和投资组合经理的任务和目标； 4. 审查转型计划中假设和依赖性的影响，包括假设未实现时的影响； 6. 更新将影响转型计划有效性的支持性财务计划、预算和相关财务目标。 | M5: CTF：要素1.发行人的气候转型战略和治理：气候过渡主要关注发行人减排温室气体（GHG）策略、承诺和实践的可信度。气候转型策略应清晰传达并提供详细信息，说明发行人打算如何随着时间调整其商业模式以实现《巴黎协定》的目标。 CTB：发行人需满足以下要求： 制定发行人层面的可持续发展和/或转型战略，合格气候转型项目须对该战略形成支撑，且相关披露文件应尽量与《气候转型金融手册》四大核心要素保持一致； 若气候转型项目与化石燃料基础设施或活动存在重大关联，且未被涵盖入前述分类目录、脱碳路径与路线图或政策框架，则还可以具备以下内容：活动/资产层面的转型计划； 承诺在符合可验证情景的时间框架内，退役/逐步淘汰相关资产，或转向低碳替代方案；关于前瞻性指标的年度报告，包括关键里程碑、最后期限及其外部核验情况； | N5: 企业阐述在转型计划中为达到中长期目标所使用的抵消和/或负排放技术的种类及作用。 企业明确承诺有时限地逐步淘汰对碳密集型资产或产品的投资（而不是只包括提取现有资产的承诺。 1.5摄氏度 与《巴黎协定》的总体目标一致，即“与工业化前水平相比，将全球平均气温升幅控制在低于2°C的水平，并努力将气温升幅限制1.5°C”。 该场景与将全球平均气温上升限制在1.5°C，可能性为50%的碳预算一致。 低于2摄氏度 符合《巴黎协定》限制全球变暖的总体目标，尽管处于目标范围的中间。 该场景与将全球平均气温上升限制在1.65°C，可能性为50%的碳预算一致。 国家承诺 建立在国际能源署2020年既定政策情景的基础上，该情景考虑了至少到2020年年中已经实施或正在制定的政策，具体取决于行业； 目前这一总量不足以使世界走上将升温限制在2°C的道路。 该场景与将全球平均气温上升限制在2100年的2.6°C，可能性为50%的碳预算一致。 | O5: 早期转型 ・2050 年目标：削减范围 1 和 2 绝对排放量（指标 1.1） ・2030 年目标：削减范围 1 和 2 绝对排放量（指标 1.4） 进展中转型 满足早期转型所有前提条件，且： ・2050 年目标：实质性削减（至少）范围 1 和 2 排放量（指标 1.1） ・目标：削减范围 3 绝对排放量（到 2030 年和 2050 年）或削减排放强度（到 2030 年和 2050 年）（指标 1.2、1.5 或 1.3、1.6） ・承诺将年度投资的一部分用于转型（指标 3.3） 充分转型 满足进展中转型所有前提条件，且： ・目标：到 2050 年范围 1 和 2 实现净零，并设定可量化且具雄心的范围 3 减排目标（指标 1.1、1.2、1.3） ・短期内展示范围 1 和 2 减排进展（指标 2.4） ・展示转型收入进展（至少部分收入来自转型活动或产品）（指标 3.5 或 3.6） 先进转型 满足充分转型所有前提条件，且： ・将年度转型投资的实质性部分投向绿色活动、服务或产品（指标 3.3、3.4） ・展示进一步转型进展（至少部分收入来自绿色活动或产品）（指标 3.6） ・目标：到 2050 年所有范围实现净零，且可信的愿景覆盖相关实质性边界（指标 1.1、1.2、1.3） ・展示所有范围的减排进展（指标 2.1、2.2、2.3、2.4、2.5、2.6） 转型领导者 满足先进转型所有前提条件，且： ・将年度投资的绝大部分投向绿色活动、服务或产品（指标 3.3、3.4） ・展示实质性转型进展（收入中很大一部分来自绿色活动或产品）（指标 3.6） ・实现所有范围的深度减排（指标 2.1、2.2、2.3、2.4、2.5、2.6） | P5: （4）日期：转型计划规定了计划达成的目标，包括在计划的时间范围内应达成的目标（例如，计划时间路线图）。 （2）计划假设：转型计划中描述相关假设，尤其是围绕转型路径的不确定性和实施挑战的假设。这些假设应该与组织财务情况、资本支出和投资决策方面使用的假设保持一致。 （4）行动计划：概述短期和中期战略和行动计划，并描述相关行动如何解决温室气体排放，包括减少气候相关风险和增加气候相关机遇的计划举措。 （5）财务计划：转型计划描述了支持性财务计划、预算和相关财务目标（例如，支持脱碳战略的资本和其他支出金额）。 | Q5: 1.1 战略愿景 主体应当披露其转型计划中的战略愿景。这包括主体在向低温室气体排放、气候韧性经济转型过程中，为响应并推动转型而设定的目标与优先事项，同时说明主体将如何以把握机遇、避免对利益相关方和社会造成不利影响、保护自然环境的方式来追求这些目标和优先事项。 披露建议 作为此部分的内容，主体应当披露： a. 其目标与优先事项： i. 旨在减少其运营或价值链中范围 1、范围 2 和范围 3 温室气体排放的目标与优先事项 ii. 旨在增强其对气候变化的适应能力，并应对向低温室气体排放、气候韧性经济转型所带来的风险与机遇的目标与优先事项 iii. 旨在利用其可用的杠杆与能力，嵌入并加速向低温室气体排放、气候韧性经济转型的目标与优先事项 b. 其是否以及如何识别、评估并考量转型计划对利益相关方（如员工、价值链合作伙伴、客户、社会（如当地社区）、经济和自然环境）的影响与依赖关系，以及这些影响与依赖关系在整个价值链中可能引发的可持续性相关风险与机遇 c. 其在多大程度上考量并遵循了外部要求、承诺、基于科学的目标、转型路径、路线图或情景， 1.2 商业模式与价值链 主体应当披露其战略愿景对当前及预期商业模式与价值链的影响描述。 披露建议 作为此部分的内容，主体应当披露： a. 其商业模式与价值链当前及预期的战略变化概览（详见第 2 部分《实施策略》和第 3 部分《参与策略》） b. 预期发生这些变化的时间范围 1.3 关键假设与外部因素 主体应当披露其为实现转型计划的战略愿景所做出的关键假设，以及所依赖的外部因素。 | R5: 3 主体应当披露：为实现其计划或目标所需的活动与投资，以及任何可能影响这些计划或目标达成的风险或限制因素。 4 主体应当讨论：其战略、计划或减排目标的适用范围，例如这些目标是否针对不同业务单元、地区或排放源而有所差异。 5 主体应当讨论：其战略、计划或减排目标是否与限排或排放报告计划 / 法规相关联，例如欧盟排放交易体系（EU ETS）、魁北克总量控制与交易体系、加州总量控制与交易计划，包括地区、国家、国际或州级层面的相关计划。 6 战略、计划或减排目标的披露范围：应仅限于报告期内正在进行（活跃）或已完成的活动。 | S5: 活动和决策过程 将金融机构的净零目标与优先事项嵌入其核心评估与决策工具及流程中，以支持其净零承诺。这适用于自上而下的监督架构与自下而上的工具与行动。 ・描述转型战略如何嵌入决策流程、工具与政策中 ・核心决策流程的重大变化摘要 ・为决策流程变化提供背景的重大事件或决策 | T5: 来源：24年可持续发展报告 中国宝武和宝钢股份碳中和技术路线图 | U5: 来源：2024年可持续发展报告 中信泰富特钢碳中和路径：绿色技术、绿色产品、绿色协同 公司为实现经济增长与能源资源使用高质量均衡发展，制定了于 2030 年前实现“碳达峰”，2060 年前实现“碳中和”的目标， 并设立了阶段性计划...... | V5: 转型规划能够体现企业是否将低碳转型系统性地纳入中长期发展战略，是目标向实施转化的重要承接环节，也是国内外主流政策框架中的普遍要求。企业通常能够披露转型路线图、阶段性目标及主要行动措施，具备一定的评价区分度，建议作为核心指标予以保留。
C6: 其他战略 | D6: 企业如尚未制定专门的转型规划，是否已建立低碳与可持续发展相关的其他制度与行动框架 | I6: 第十二条 披露主体应当建立健全公司治理结构和内部制度，确保公司相关内部机构具备足够的专业能力并有效履行可持续发展相关影响、风险和机遇的识别、评估、管理、监督等职能。 第十五条 披露主体应当披露可持续发展相关影响、风险和机遇对公司战略和决策的影响。 | S6: 政策和条件 制定行业政策：针对动力煤、石油和天然气，以及森林砍伐等高优先级行业制定政策和条件；覆盖其他高排放或对气候有害的行业，以符合机构的净零目标和优先事项 | U6: 来源：2024年可持续发展报告 绿色低碳三年行动计划（2023—2025 年） | V6: "其他战略"口径相对宽泛，主要用于覆盖尚未制定专项转型规划的企业是否已建立相关低碳治理与行动框架，发挥一定的补偿作用。建议将该指标的评分权重设置低于"转型规划"，以强化对明确指向低碳转型的专项规划的评价重心。亦可视后续企业评分取样情况，决定是否作为可选指标纳入体系。
A7: 实施举措与保障 | B7: 转型举措 | C7: 自身减排措施 | D7: 企业为实现低碳转型与应对气候变化，当前已实施或计划实施的关键减排与转型措施，包括发生在企业自身运营与资产层面的直接措施。 | E7: 转型主体应当制定并披露技术可行的转型计划，主要内容和要求包括：(1)对照短、中、长期碳减排目标，明确每个阶段的转型技术路径，该技术路径应当具有可行性和先进性； (2)明确每个阶段的工作计划及重点工作任务； | G7: 第十二条（二）当前和计划采取的用于减缓和适应气候变化的直接措施（如节能产品认证、碳标识认证，改变生产工艺或者设备、搬迁设施、调整劳动力结构以及改变产品规格等）。 | I7: 第二十七条 披露主体应当披露温室气体减排实践的相关信息，包括参与各项减排机制的情况、减排目标、减排措施（如管理措施、资金投入、技术开发等）及其成效等。 | L7: 3. 将净零目标与标准指标一起纳入投资组合建设。理想情况下，额外的调整目标应涵盖脱碳和气候解决方案； 5. 监测调整目标的实现情况，包括组合碳强度和气候解决方案的分配情况； | N7: 问题19：企业是否将减排战略和为达到标所采取的行动的影响进行量化？ 企业量化了减排战略的关键因素，包括范围3排放，并且披露每一项行动的量化贡献，即该行动将占温室气体总目标的大致比例。 | O7: 钢铁行业调整系数说明——钢（条目3）：若主体用相对新的（<25 年）的高炉 - 转炉（BF-BOF）产能替换为废钢基电弧炉（EAF）产能，加 1 分，采用正向修正。 钢铁行业调整系数说明——钢（条目4）：若主体投资新建无碳捕集的高炉 - 转炉（BF-BOF）产能，采用否定性修饰语。 钢铁行业调整系数说明——钢（条目5）：若减排量中使用抵消额度占比超过 10%，采用否定性修饰语。 | Q7: 2. 实施策略 2.1 业务运营 主体应当披露其为实现转型计划的战略愿景，在业务运营中已采取或计划采取的短期、中期和长期行动相关信息。 披露建议 作为此部分的内容，主体应当披露： a. 当前及预期行动的相关信息（包括时间线），涉及以下事项： i. 生产流程或设备 ii. 劳动力调整 iii. 供应链与采购 b. 与主体设施及其他实物资产相关的当前及预期变化，例如： i. 办公场所与运营地点 ii. 温室气体高排放资产的负责任退役或逐步淘汰 iii. 应对气候变化风险所涉及的资产管理 iv. 向低温室气体排放、气候韧性经济转型过程中可能受影响的长期资产管理 c. 各项行动对实现其战略愿景的预期主要贡献 2.2 产品与服务 主体应当披露其为实现转型计划的战略愿景，已采取或计划采取的短期、中期和长期行动相关信息，以改变其产品与服务组合。 披露建议 作为此部分的内容，主体应当披露： a. 当前及预期行动的相关信息（包括时间线），以改变其提供或促成的产品与服务组合（例如，通过特许经营、融资或承保活动） b. 用于对此部分下的产品与服务进行分类的任何基础分类体系、工具、方法或定义 c. 各项行动对实现其战略愿景的预期主要贡献 | S7: 产品及服务 利用现有及新产品与服务，支持并提升客户与投资组合公司的转型努力，使其符合 1.5℃净零排放路径。包括加速并扩大实体经济中的净零转型，提供转型相关的教育与建议，并按照机构的净零转型战略支持投资组合脱碳。 ・描述转型战略如何嵌入产品与服务设计中，以最大化机遇 ・与转型目标一致的产品与服务摘要 ・核心产品与服务的任何重大变化摘要 | T7: 来源：24年可持续发展报告 | U7: 来源：24年可持续发展报告 | V7: 前期设置"自身减排措施"和"供应链减排措施"两个指标，希望从企业内部运营和外部供应链两个维度分别评价具体减排行动。但在实际梳理企业报告的过程中发现，上述指标内容与"转型规划"及"转型表现"存在较大内容重叠，独立设置将导致评价体系冗余。因此，建议将相关内容统一整合至"转型规划"指标中，通过综合评价系统呈现企业在自身运营和供应链层面的减排措施，以提高指标体系的简洁性与内部一致性。
C8: 供应链减排措施 | D8: 企业为实现低碳转型与应对气候变化，当前已实施或计划实施的关键减排与转型措施，包括通过价值链协同实现的间接措施。 | E8: 1.转型主体应当对照国家碳达峰碳中和目标，制定并披露科学合理的碳减排目标，主要内容和要求包括：(3）温室气体排放核算范围至少包括范围一和范围二的温室气体排放；条件成熟时，酌情将范围三的温室气体排放纳入核算范围。 转型主体应当制定并披露技术可行的转型计划，主要内容和要求包括：(1)对照短、中、长期碳减排目标，明确每个阶段的转型技术路径，该技术路径应当具有可行性和先进性；(2)明确每个阶段的工作计划及重点工作任务； | G8: 第十二条（三）当前和计划采取的用于减缓和适应气候变化的间接措施（如与客户、供应链合作等） | I8: 第四十五条 披露主体应当披露报告期内加强供应链风险管理、保障供应链安全稳定的情况，包括但不限于下列内容： （一）供应链风险管理的基本情况，包括但不限于公司制定的供应链风险管理目标及具体计划、供应链风险应对机制、措施及实施效果；（二）通过并购重组、科技创新等保障自身供应链安全、强化供应链优势等方面的举措和积极效果。本所鼓励披露主体披露加强供应链管理、促进供应链可持续发展的行动和举措。 | L8: 参与监管机构行业倡议，制定自愿和强制性的转型计划标准和其他披露，如与巴黎协定一致的账户； 参与投资者行业网络协会，以提高有关《巴黎协定》目标基准投资组合的知识； 2. 与现有和潜在的资产管理者接触，鼓励管理者提供战略和产品，以实现资产所有者的净零投资目标； 3. 与现有和潜在客户接触，鼓励采用净零投资战略和产品，提供研究和分析，以支持气候风险评估和净零投资； 4. 促进跨行业企业转型计划的披露，例如根据IIGCC的转型计划行业中性指南和涵盖高影响力行业的净零标准； 5. 让私人数据供应商参与进来，以确保评估与气候行动100+《净零公司基准》的最新详细指标指南中的一致标准一致； 6. 与私人数据供应商合作，确保范围3排放数据详细说明评估中使用的类别及其准确性； 7. 参与投资者网络的活动，促进与净零投资相关的知识创造； 8. 表达与资产类别一致性标准相关的预期（例如，债券发行前）； 9. 与指数提供商合作，提供更符合净零的基准； 10. 与债券指数提供商接触，这些指数可能会无意中迫使投资者购买新债券，而不考虑气候影响； | Q8: 3. 参与策略 3.1 价值链参与 主体应当披露其为实现转型计划的战略愿景，正在或计划与价值链中其他主体开展的参与活动相关信息。 披露建议 作为此部分的内容，主体应当披露： a. 解释其如何优先安排参与活动，以最大程度地推动实现转型计划的战略愿景；此部分可参考在 1.3《关键假设与外部因素》中披露的关键假设和外部因素 b. 描述当前及计划的参与活动；对于金融服务主体，这可能包括与被投公司、贷款客户及相关金融市场中介的互动，以及相关的治理活动 c. 说明当参与活动未能带来预期变化时，所采用的升级处理流程或判定标准 d. 各项活动对实现其战略愿景的预期主要贡献 | R8: 供应链管理流程描述；讨论因环境和社会问题引起的铁矿石或焦煤采购风险的管理流程。—— 1 企业应披露有关其供应链中管理环境和社会风险的政策和程序的信息。讨论其管理供应链中环境和社会风险的政策和程序。可能会影响采购的铁矿石或焦煤供应链中存在的环境和社会风险。 2 企业应披露其采购原材料中经第三方验证的与环境或社会问题相关的供应链认证或认可的比例（按成本计算） | S8: 1) 客户与投资组合公司：积极且建设性地向客户和投资组合公司提供反馈与支持，鼓励其制定与净零目标一致的转型战略、计划与进展，并建立当参与无效时的升级处理框架及相应后果。 ・参与目标与方法的摘要，包括客户与投资组合公司的优先级排序、升级处理流程及时间线 ・参与活动的进展详情 ・如适用，描述与公司就其受控淘汰计划设计及进展的沟通情况，以及达成的关键指标 2) 行业：积极与行业同行进行接触，适时交流转型专业知识，共同应对行业挑战，并代表金融部门向外部利益相关方（如客户与政府）进行连贯一致的发声。 ・参与目标与方法的摘要，包括客户与投资组合公司的优先级排序、升级处理流程及时间线 ・参与活动的进展详情 ・如适用，描述与公司就其受控淘汰计划设计及进展的沟通情况，以及达成的关键指标 3) 政府与公共部门：直接与间接的游说及公共部门参与应保持一致，以支持有序向净零转型，并在适当时鼓励客户与投资组合公司的游说及倡导工作与机构自身的净零目标保持一致。 ・参与活动的摘要，包括议题与受众（如适用，使间接游说活动与净零转型保持一致的努力） ・参与活动如何被评估及与净零转型保持一致的概述 ・参与活动的进展详情 | T8: 来源：24年可持续发展报告 公司根据已发布的降碳行动方案，制定了供应链减碳规划，并严格督促落实，形成了“量化、评估、减碳”的供应链低碳发展路径。通过这一系列举措，宝钢股份携手产业链上下游企业，为应对全球气候变化做出实质性贡献。 ·我们累计引导 1,500 余家供应商开展产品碳核算，累计与 50多家重点供应商开展减碳技术交流，发布产品碳核算报告超过 5,000 份，为减碳奠定坚实基础 ·基于已量化的工业品实际碳足迹数据，我们开展碳足迹数据“评估”。我们通过横向评估（同一产品不同供应商）和纵向评估（同一供应商同一产品不同年份）两个维度开展碳数据评估，持续发挥工业品碳数据的实际应用价值 ·在持续推进“量化”与“评估”工作的基础上，我们成功引导1,000 余家供应商提升低碳管理 能 力，并助力100余家重点供应商的500多个工业品实际碳排放量较上一年度下降超过5% | U8: 来源：24年可持续发展报告 公司已制定并实施了严格的采购及供应商管理规范，包括《供应商管理制度》《统购物资集中购销管理办法》《统购物资 招标管理细则》等制度，以确保采购流程的合规性与高效性。公司要求所有供应商签署并执行《供应商行为准则》，在管 理中将 ESG 行动列为对供应商的评价加分项，并就人权与劳工权益、环境保护、安全生产以及隐私保护等关键议题向供应 商提出明确要求，旨在有效降低供应链中的 ESG 相关风险。 公司积极响应国家“双碳”战略目标，致力于推动供应链向节能低碳转型。公司持续采购获得环境标志产品认证、节能产品认证或国家权威机构认可的其他认证的节能环保产品，并严格禁止采购“高污染、高环境风险”类产品，旨在为推进环境友好型社会的构建贡献力量。2024 年度，公司共有合格供应商 371 家。 公司持续优化供应链生态，促进产业链上下游企业绿色发展，积极履行国有企业社会责任，推动全产业链低碳发展。本年度，公司在《采购中心供应商管理办法》中将碳排放管理纳入原材料供应商准入、年审考评机制中，致力于将供应链管理与环保要求相融合，响应公司绿色低碳战略。公司要求参与合金类产品招标的供应商原则上需提交碳足迹数据，并广泛鼓励所有供应商采取措施以降低碳排放并提升能源利用效率。 本年度，公司召开首次绿色供应链碳核算报告交付评审会，签署《产品碳核算服务验收单》，完成对 11 家大宗物资供应商的评估，并发布 14 份详尽的正式报告。公司已面向相关供应商推进 626 项产品碳足迹核算报告收集工作，旨在全面评估上游供应商的碳排放水平，为制定碳减排策略提供可靠数据支持，也为构建公司绿色供应链数据库奠定坚实基础。 公司与供应商建立了良好的绿色低碳交流与合作机制。本年度，公司在绿色供应链管理方面积极行动，成功举办两场绿色供应链管理宣贯会，针对提升供应商管理水平与绿色采购效率等两个核心要点，进行了深入且全面的探讨。公司邀请知名专家对供应商进行碳排放意识培养与指导，传达公司在采购策略上的最新绿色理念。此外，针对供应商在准入及执行阶段可能遭遇的环保风险，提出了一系列针对性的建议，旨在促进上下游供应链合作共赢，推动绿色协同发展实现 | V8: 供应链减排措施与自身减排措施同属转型规划的实施行动层面，两者均偏向描述性披露，难以独立进行定量评价，且内容易与"转型规划"评价产生重叠。因此，建议与"自身减排措施"同步删除，将相关内容统一整合至"转型规划"模块中进行综合评价，以保持指标体系的简洁性。
B9: 治理 | C9: 治理架构 | D9: 企业围绕低碳/绿色/可持续/转型/ESG议题建立的治理层级完整性与权责清晰度 | E9: 4.转型主体应当制定并披露切实可行的治理计划，主要内容和要求包括：(1）落实转型计划的治理模式和实施方案，例如董事会和高管责任安排、内部分工与激励计划、温室气体排放监测与报告体系、信息披露机制等； | G9: 第六条：企业应当披露负责监督气候相关风险和机遇的治理机构（包括董事会及其下设委员会或者其他类似机构）或者人员的情况。 | H9: 一（一）3.四是有落实转型方案的治理模式和实施方案。 | I9: 第十二条 披露主体应当建立健全公司治理结构和内部制度，确保公司相关内部机构具备足够的专业能力并有效履行可持续发展相关影响、风险和机遇的识别、评估、管理、监督等职能。 | L9: 2. 建立一个内部系统，定期监督实施情况； 3. 净零战略实现净零目标的能力（包括审查和更新净零目标、战略和指标）； 4. 制定计划以确保整个组织拥有适当的资源、技能和能力，以有效实施净零战略； 5. 将净零目标和战略以及目标纳入薪酬激励措施，视情况而定，并小心避免意外后果； 6. 制定向董事会、高级管理层和外部利益相关者报告净零目标、战略和目标的进度报告计划，包括预期和非预期结果； | M9: CTF：要素1.发行人的气候转型战略和治理：推荐信息和指标：对发行人气候转型策略的明确监管和治理，包括管理层/董事会层级的问责 | N9: 提供清晰的董事会或董事委员会对气候变化监督的证据，或有在董事会层面任命负责气候变化的人员或职位。 | P9: 治理： （1）审批：董事会或者相关董事会委员会审批转型计划和气候相关目 标。 （2）监督：董事会或者相关董事委员会监督转型计划的实施情况。 （3）责任：高级管理层负责执行转型计划，相关人员有足够权力和资 源确保转型计划的有效执行。 （4）激励措施：薪酬和其他激励措施应与组织的气候目标保持一致。 （5）报告：定期披露低碳转型现状报告。 （6）审查：组织定期审查和更新自身计划、活动、指标和目标。 （7）透明度：组织向外部利益相关方报告转型计划目标和绩效，包括 财务、目标完成情况以及对组织业务造成的影响等。 （8）保证：组织的报告受到独立审查或者第三方保证的约束。 | Q9: 5. 治理 5.1 董事会监督与报告 主体应当披露关于负责监督转型计划的治理机构（可包括董事会、委员会或等效治理机构）或个人的相关信息。 披露建议 作为此部分的内容，主体应明确该治理机构或个人，并披露： a. 其对转型计划及其战略愿景的审核与批准机制，包括对任何变更、更新及报告的监督安排 b. 转型计划的相关责任如何体现在该治理机构或个人的职权范围、授权、角色描述及其他相关政策中 c. 该治理机构或个人如何确定是否具备或是否需要培养监督转型计划的适当技能与能力 d. 该治理机构或个人获取转型计划相关信息的方式与频率 e. 该治理机构或个人在监督主体战略、重大转型决策及其风险管理流程与相关政策时，如何纳入转型计划的考量，包括是否已考虑转型计划相关的权衡取舍 f. 该治理机构或个人如何监督转型计划中目标的设定，以及对这些目标和转型计划更广泛战略愿景的进展情况进行监控 5.2 角色、责任与问责 主体应当披露管理层在转型计划的治理流程、控制与程序中的监督、管理和履职相关信息，以及这些内容如何嵌入主体更广泛的控制、复核与问责机制中。 披露建议 作为此部分的内容，主体应当披露： a. 负责执行监督与交付转型计划的管理机构或个人的身份 b. 5.2.a 中所述机构或个人在定义转型计划的战略愿景、设定目标及监控进展方面的角色 c. 对 5.2.a 中所述机构或个人的监督机制 d. 5.2.a 中所述机构或个人是否使用控制措施与程序来支持转型计划的监督，并确保所披露信息的可靠性；如果是，主体应当披露这些控制措施与程序如何与其他内部职能整合，以及转型计划的哪些内容接受外部鉴证或核查，包括鉴证或核查的性质 e. 转型计划是否需要经过股东批准，包括通过股东投票的方式 5.4 激励与薪酬 主体应当披露其如何或将如何使激励与薪酬结构与转型计划的战略愿景保持一致的相关信息。 披露建议 作为此部分的内容，主体应当披露： a. 说明其高管激励与薪酬结构是否与转型计划的战略愿景保持一致，可包含以下信息： i. 所采用的指标 ii. 该指标是否纳入短期及 / 或长期激励计划 iii. 高管激励计划中，转型计划相关指标的典型权重占比 iv. 与转型计划相关指标挂钩的高管薪酬占总薪酬的比例 b. 说明全公司范围内的激励与薪酬结构是否及如何与转型计划的战略愿景保持一致，包括其采用的方式是否与 5.4.a 保持一致，或是针对特定岗位或角色采取了差异化的方式 | S9: 1) 角色、责任与薪酬：为董事会或战略监督机构及高级管理层明确角色，确保其对净零目标拥有所有权、监督权与责任。为转型计划的设计与交付各方面指派合适的人员与团队。尽可能为所有角色使用薪酬激励。定期复核转型计划，以确保纳入重大更新与进展，将挑战视为修正方向的机会，并妥善管理实施风险。 ・与净零转型计划相关的审批、监督及报告的治理结构与流程 ・明确转型计划执行责任与问责机制的政策，以及相关的授权 ・实施或修订政策、产品与服务所需的资源 ・与净零转型计划目标、优先事项、战略及目标挂钩的激励与薪酬方法 ・任何独立复核或第三方鉴证的结果与成果 | T9: 来源：24年可持续发展报告 宝钢股份制定<<ESG工作管理制度>>等管理制度 -2 成立了以董事会为领导主体，战略、风险及 ESG 委员会为核心，ESG 工作小组为执行落地主力的自上而下多层次管理架构-2，--2，-2 | U9: 来源：24年可持续发展报告 公司制定了《环境、社会及管治工作管理办法》-2 公司构建董事会，战略、风险及ESG 委员会，ESG 协同管理工作组，ESG 推进工作组四级 ESG 管理模式，明晰各单位工 作职责，搭建长效 ESG 工作机制，有力保障公司中长期战略目标的落地实施，为公司的可持续发展筑牢根基。 公司双碳管理体系下设 8 个职能工作组，包括低碳战略规划组、低碳技术研用组、低碳产品与标准创新组、节能降碳与碳 核查组、绿色供应链建设组、碳资产管理与绿色金融组、低碳人才培养组和低碳品牌宣传组。各子公司在双碳领导小组的 指导下，积极开展当地的气候变化相关工作。 | V9: 治理架构反映企业是否建立了与低碳转型相关的决策、执行与监督机制，是转型得以持续推进的重要保障条件。企业通常能够披露董事会、管理层职责安排及相关委员会设置情况，具备一定的可比性，且在国内外主流政策框架中均有明确要求，建议作为实施保障维度的基础性指标予以保留。
C10: 薪酬激励 | D10: ESG/可持续发展/低碳/转型目标是否通过绩效与薪酬机制转化为真实的管理激励与约束 | E10: 4.转型主体应当制定并披露切实可行的治理计划，主要内容和要求包括：(1）落实转型计划的治理模式和实施方案，例如董事会和高管责任安排、内部分工与激励计划、温室气体排放监测与报告体系、信息披露机制等； | G10: 第三十九条 企业应当披露在决定高级管理人员薪酬时是否以及如何考虑气候相关因素。 | L10: 5. 将净零目标和战略以及目标纳入薪酬激励措施，视情况而定，并小心避免意外后果 | N10: 企业高管薪酬考虑了气候变化表现。 | O10: 钢铁行业调整系数说明——钢（条目6）：若高管薪酬与可量化排放相关目标挂钩（占可变薪酬总额≥20%），则可进行正向调整。 | P10: （4）激励措施：薪酬和其他激励措施应与组织的气候目标保持一致。 | Q10: 5.4 激励与薪酬 主体应当披露其如何或将如何使激励与薪酬结构与转型计划的战略愿景保持一致的相关信息。 | S10: ・与净零转型计划目标、优先事项、战略及目标挂钩的激励与薪酬方法 | T10: 来源：24年可持续发展报告 我们将董事及高级管理层的薪酬与 ESG 绩效指标相挂 钩，将安全、环境、社会、治理、合规管理等议题指标 纳入高管激励及薪酬计划中。 将 ESG 体系能力提升（安全、环境、社会、治理、 合规管理等）作为 1 个专门的指标项，纳入 2024 年度 相关经理层成员经营业绩目标。其中宝钢股份总经理“践 行绿色低碳发展，推进美丽宝钢建设”考核所占权重 15%；分管相关工作的两位副总经理“践行绿色低碳发 展，推进美丽宝钢建设”“ESG 体系能力提升”两项考 核指标分别占总权重的 15%、5%。 | U10: 来源: 24年可持续发展报告 我们根据公司实际对包括总裁在内的高级管理人员薪酬方案进行了调整，包括对本财年财务业绩的评估和对关键管理活动（如碳排放管理、水资源管理、健康与安全等可持续发展相关绩效）的评估。 此外，公司将 ESG 相关绩效表现与公司高级管理层的薪酬绩效挂钩，设立了详细的定量、定性考核标准，根据职责分工，设置 5%-40% 不同的绩效考核权重，包括环境保护、碳排放管理、节能降耗、水资源管理、健康与安全、人才梯队建设、信息安全、知识产权、客户服务、廉洁建设、ESG 信息披露和 ESG 评级等方面。公司根据考核结果对高级管理层人员采取奖惩措施，以确保公司的 ESG 核心目标和措施得到有效执行，全面提升公司可持续管理水平。 | V10: 在企业信息披露中，薪酬激励通常与综合ESG绩效或经营绩效挂钩，鲜有企业明确将薪酬激励与低碳转型目标或减排指标直接绑定。若单独设置该指标，一方面容易与ESG综合评价体系产生混淆，另一方面可比性较弱。综合考虑数据可得性与指标区分度，建议不作为独立三级指标，而将碳相关薪酬挂钩情况作为"治理架构"评价框架中的加分项，以体现企业治理的深度与约束力。
B11: 风险管理 | C11: 气候风险管理体系 | D11: 1. 全面风险嵌入（ERM化）：将气候风险由单一环保议题上升为公司级战略风险，实质性嵌入ERM及全价值链决策流程。 2. 治理架构多级化：构建“董事会—管理层—执行层”的三级或四级垂直穿透式治理架构。 3. 管控手段数智化：建设并运行“智能气候风险管理信息系统”或数字化管理平台，实现风险数据的常态化监测与可视化。 4. 责任落实绩效化：形成“目标—执行—考核—追责”闭环，并将气候/碳相关指标刚性挂钩领导班子或管理层年度经营业绩评价。 | G11: 第二十二条 企业应当披露其识别、评估、排序和监控气候相关风险的流程和相关政策。 第二十四条 企业应当披露其识别、评估、排序和监控气候相关风险和机遇的流程在多大程度上以及如何融入企业的整体风险管理流程。 | H11: 三（二）4.鼓励金融机构建立健全转型风险管理制度，明确责任和流程，探索建立风险监测及评估指标体系，对转型金融风险状况进行监测和分析，确保商业可持续与降碳目标相协同。 | I11: 第十八条 披露主体应当披露用于识别、评估及管理可持续发展相关影响、风险和机遇的流程。 （一）公司识别、评估可持续发展相关影响、风险和机遇的方法，以及评估这些影响、风险和机遇发生的可能性、大小和影响的途径； （二）公司对可持续发展相关影响、风险与机遇的优先级排序及排序标准； （三）公司监测可持续发展相关影响、风险和机遇的情况，如管理机制、具体流程等； （四）可持续发展相关影响、风险和机遇管理流程融入公司内部管理流程的情况，以及报告期内的调整情况 | L11: 6. 治理：董事会对气候风险和气候战略执行情况的监督。理事会每年至少讨论一次气候风险管理和战略。 | N11: 问题2：企业是否认识到气候变化对业务是相关风险/机遇 /企业能够证明对“气候变化对业务而言是相关风险/机遇”的认识，或如果他们将以下至少两项融入到管理实践中：Q12. 有管理气候相关风险的过程；Q14. 为减少温室气体排放设定长期定量目标；Q15. 将气候变化表现融入高管薪酬；Q16. 将气候变化风险和机会融入战略；Q17. 采取气候场景计划；Q18. 披露内部碳定价；Q19. 确保气候变化政策和其所属行业协会立场一致 问题11： 企业是否有管理气候相关风险的流程？ 企业将气候变化纳入全公司风险管理，或者他们有特定的气候相关风险管理流程。 | P11: （1）描述风险：转型计划描述了组织在向低碳经济转型过程中面临的风险。 （2）计划挑战和不确定性：转型计划描述了组织在顺利执行其转型计划过程中面临的假设、不确定性和挑战。 | R11: 供应链管理流程描述；讨论因环境和社会问题引起的铁矿石或焦煤采购风险的管理流程。—— 1 企业应披露有关其供应链中管理环境和社会风险的政策和程序的信息。讨论其管理供应链中环境和社会风险的政策和程序。可能会影响采购的铁矿石或焦煤供应链中存在的环境和社会风险。 2 企业应披露其采购原材料中经第三方验证的与环境或社会问题相关的供应链认证或认可的比例（按成本计算） | T11: 来源：24年可持续发展报告 我们设立战略、风险及 ESG 委员会，碳中和推进委员会和碳中和办公室，相关管理人员具备气候相关战略及风险管理能力。我们建立了定期的汇报机制，确保治理架构各层级分工明确。-2 我们对未来不同情景下可能发生的气候变化状况进行预测与分析，评估其对宝钢股份的影响状况，并基于分析结果，明确应对气候变化的战略目标及路径。我们定期回顾更新应 对气候变化战略目标及路径，确保其有效性。-2 宝钢股份建立了完整的气候变化风险管理流程，并将气候风险管理融入企业风险管理流程，确保在面对气候变化带来的挑战时能够做出及时有效的应对策略。我们将气候风险相关工作进行评估和归类，组建跨部门的项目团队，并定期对各项目进行监测评估，保障气候风险相关工作的有效性。-2 公司建立了覆盖多基地的智能化气候风险管理信息系统，不断识别气候变化带来的风险，为经营决策提供有力支持。-2 | U11: 来源: 24年可持续发展报告 为有效应对气候变化风险和机遇，公司建立了完善的气候变化管理体系，以双碳工作组织架构为基础，贯彻落实董事会制定的气候变化相关制度、战略和目标。 | V11: 气候风险管理体系反映企业对气候风险的识别、评估与应对能力，是国内外政策框架和监管要求对金融机构及重点排放行业的核心关注内容之一。企业披露以定性描述为主，但在是否建立完整体系、风险识别是否覆盖转型风险与实体风险等方面具备一定区分度，建议保留并采用定性分档评价方式。
C12: 气候相关风险和机遇 | D12: 1. 风险与机遇识别完整性：同时识别转型风险与实体风险，涵盖政策/法律、技术、市场、供应链、声誉、急性与慢性物理风险等；同时识别低碳产品、能源结构优化、政策支持等机遇。 2. 时间维度清晰性：在短期（1–2年）、中期（3–6年）、长期（7年及以上）不同时间框架下开展识别与评估。 3. 财务影响关联性：识别风险和机遇对成本、收入、投资、融资、信用风险等财务事项的影响。 4. 量化深度差异：区分定性判断、间接量化（环保投入、节能降本）与直接量化（营收变化、成本变化、溢价比例、履约成本节约等）。 | G12: 第十一条 企业在披露可合理预期会影响企业发展前景的气候相关风险和机遇时，应当：（二）针对企业识别出的每项气候相关风险，说明企业将该风险认定为气候相关物理风险还是气候相关转型风险；（三）披露这些风险和机遇对企业的业务模式和价值链的当期和预期影响，以及企业的业务模式和价值链中气候相关风险和机遇集中的领域（如特定活动、业务关系、地理区域、设施和资产类型等）；（四）针对企业识别出的每项气候相关风险和机遇，明确其可合理预期影响企业发展前景的时间范围（包括短期、中期或者长期），如何定义短期、中期和长期，以及这些定义如何与企业用于战略决策的时间范围相关联。 第十三条 企业应当披露气候相关风险和机遇的当期和预期财务影响。 | I12: 第十四条 披露主体应当识别并充分评估可能在短期、中期或长期内对公司商业模式、业务运营、发展战略、财务状况、经营成果、现金流、融资方式及成本等产生重大影响的可持续发展相关风险和机遇。 | L12: 2. 使用系统方法识别影响资产的因素，以增加气候解决方案的风险敞口并降低碳强度（例如，自定义基准、气候倾斜指数、以气候为重点的影响因素）； | M12: CTB：发行人需满足以下要求：识别、分析碳锁定风险，尽力缓解该风险，并进行披露。 | N12: 问题2：企业是否认识到气候变化对业务是相关风险/机遇 /企业能够证明对“气候变化对业务而言是相关风险/机遇”的认识， 问题15：企业是否将气候变化风险和机会融入战略中？ 详细说明企业是如何将气候变化风险和机会融入战略中的，并且披露气候变化风险和机会对财务计划的影响（运营支出、资本支出、并购、债务）。 | P12: （3）优先机遇：说明组织在向全球低碳经济转型的过程中打算如何最大限度地利用气候机遇。 | T12: 来源：24年可持续发展报告 转型风险：宝钢股份紧密结合自身业务范畴与行业现状，并针对不同排放情景假设下可能面临的风险与机遇进行分析。同时，我们评估了各类风险与机遇可能引发的财务损失或增益，据此按照低、中、高确定了风险和机遇的影响程度，并明确了影响的时间范围，目前碳定价、消费者行为转变风险较大，宝钢股份已根据市场、政策等采取举措。根据情景分析结果，我们评估并列举了 2050 年零碳排放情景（NZE）、中国钢铁行业低碳转型情景中可能会对本公司运营造成潜在影响的转型风险，并通过定量分析对比各类风险可能导致的财务金额减损 / 增加，按照低、中、高确定了风险的影响程度 实体风险：随着极端天气频率和严重程度的增加，企业的生产运营以及和生产相关的原材料数量和供应的波动性将受到影响。根据情景分析结果，我们评估并列举了 RCP4.5 和 RCP6.0 情景中可能会对本公司运营造成潜在影响的实体风险，并对比各类风险可能导致的财务金额减损 / 增加，按照低、中、高确定了风险的影响程度。 | U12: 来源：24年可持续发展报告 风险覆盖了6类，并进行了应对举措：政策和法律风险、技术风险、市场风险、声誉风险、急性物理风险、慢性物理风险 政策和法律风险应对措施：加强能源消耗、低碳政策研究，及时应对政策变化；公司已制定碳中和路线图，每年投资节能减排项目；公司积极推进碳管理数字化平台建设，持续完善申报工作流程。 技术风险应对措施：与国内外科研机构联合，加大科技研发，有序开展低碳技术研究。 市场风险应对措施：利用沿江沿海优势，深挖光伏、风电潜力，提升绿电占比，研发推广低碳产品。 声誉风险应对措施：积极回应利益相关方关于应对气候变化相关的要求；定期披露ESG报告，以回应各利益相关方关注 物理风险应对措施：制定针对极端自然灾害的应急管理方案；推进供应商的社会责任评估工作，减少供应链风险。 | V12: 气候相关风险与机遇的识别和评估是风险管理能力的重要组成部分，相关披露能够体现企业对气候议题的战略整合程度。该指标在TCFD、IFRS S2等主流框架中均有明确要求，且部分企业已开始在报告中进行具体描述。建议保留并采用定性分档评价方式，重点考察识别维度的完整性和财务影响的关联程度。
C13: 气候压力测试 | D13: 1. 开展情况：明确披露已开展气候情景分析或压力测试。 2. 情景设置特征：情景覆盖转型风险与实体风险，包含中长期时间尺度。 3. 方法论来源：参考国际或行业权威情景与框架（如 IFRS S2、IEA、IPCC、钢铁行业低碳转型情景）。 4. 结果应用：情景分析结果用于评估对经营、成本、收入、资产或融资的潜在影响，并支撑风险管理或战略判断。 | G13: 第十七条 为使可持续信息基本使用者了解企业的战略和业务模式对气候相关变化、发展和不确定性的韧性，企业应当考虑已识别的气候相关风险和机遇，使用气候相关情景分析评估其气候韧性，并披露下列信息：（一）报告日气候韧性评估的内容；（二）进行气候相关情景分析时使用的输入值信息；（三）进行气候相关情景分析时运用的关键假设；（四）进行气候相关情景分析的报告期间。 第十八条 企业应当结合其面临的气候相关风险和机遇以及进行情景分析可用的技能、能力和资源，确定其使用的气候相关情景分析方法。 第十九条 企业可以按照战略规划周期（如每三至五年）进行气候相关情景分析。如果企业并未每年进行气候相关情景分析，则企业根据第十七条（二）至（四）规定对气候相关情景分析的披露可能与上一个报告期间相同，但需每年对气候韧性进行评估，并按照第十七条（一）规定披露相关信息，以反映气候相关变化、发展或者不确定性对企业业务模式和战略的影响。 | I13: 第二十二条 披露主体应当结合所识别的气候相关风险和机遇，评估公司的战略、商业模式等对气候变化的适应性，并披露下列事项： （一）公司关于气候变化对其战略和商业模式影响的评估情况，以及应对相关影响的方法； （二）公司在评估其气候适应性时考虑的重大不确定性因素； （三）公司在短期、中期和长期内为适应气候变化调整其战略和商业模式的能力。 本所鼓励有条件的披露主体采用情景分析等方式进行气候适应性评估，并披露情景分析关键假设、分析过程等。 | L13: 1. 描述用于指导目标设定和评估公司一致性的基于科学的情景或路径，包括这些情景或路径如何满足关键参数和使用的关键假设； 1. 进行情景分析，以更新资本市场假设、资产水平风险/回报预期，并对投资组合进行压力测试； | N13: 问题16：企业是否采取气候场景计划？ 提到与商业规划相关的2摄氏度情景，或者确认已经进行与气候相关的情景分析，并且描述了一个或多个气候情景分析的商业影响。 | P13: （6）情景分析：组织使用多种气候相关情景测试转型计划和相关目标的可实现性。 | T13: 来源：24年可持续发展报告 宝钢股份遵循气候相关财务信息披露工作组（Task Force on Climate-related Financial Disclosure, 即 TCFD）的披露方 法及建议，利用情景分析模型等分析技术对气候变化趋势及其与公司运营之间的关系进行预测评估。我们参考了中国钢 铁工业协会和国际能源署（IEA）所模拟的情景，对宝钢股份进行转型风险的情景分析： 宝钢股份紧密结合自身业务范畴与行业现状，并基于公开的数据来源，包括政府间气候变化专门委员会(IPCC)和国际能源署(IEA)关于气候排放路径的评估和报告，针对不同排放情景假设下可能面临的风险与机遇进行分析。在此基础上，我们内部采用定量分析方法，确定了影响的时间范围包括短期(1年~2年)，中期(3年~6年)及长期(7年及以上)同时，我们评估了各类风险与机遇可能引发的财务损失或增益 针对气候实体风险的情景分析，我们参考了政府间气候变化专门委员会(IPCC)所制定的代表性浓度路径RCP4.5与RCP6.0情景: 根据情景分析结果，我们评估并列举了2050年零碳排放情景(NZE)、中国钢铁行业低碳转型情景中可能会对本公司运营造成潜在影响的转型风险，并通过定量分析对比各类风险可能导致的财务金额减损/增加，按照低、中、高确定了风险的影响程度。根据情景分析结果，我们评估并列举了 RCP4.5和 RCP6.0情景中可能会对本公司运营造成潜在影响的实体风险，并对比各类风险可能导致的财务金额减损/增加，按照低、中、高确定了风险的影响程度。 | U13: 无 | V13: 气候情景分析与压力测试是企业转型韧性评估的重要工具，有助于识别不同升温路径下的潜在风险与财务影响。该指标在TCFD、IFRS S2等权威框架中均被明确要求，部分领先企业已具备相关披露，但整体普及率仍有待提升。建议保留并采用定性分档评价，重点关注情景覆盖的完整性和结果的实际应用深度。
C14: 环境行政处罚（负向指标） | D14: 衡量企业在战略转型期（如前/后3年）因环境违法行为受到地方监管部门行政处罚的严重程度。 | E14: 无重大损害原则：转型金融支持的经济活动或企业，应当对污染防控、资源节约和生态保护等其他环境目标无重大损害 | G14: 第四条 企业还应当披露本准则第二章至第五章未涵盖的重要的气候相关影响信息。 气候相关影响包括企业活动对气候变化产生的实际或潜在影响，环境行政处罚可能属于此类影响的负面表现。 | H14: 二（一）4.做好转型信息披露。企业参照《钢铁企业转型信息披露模板》(附5)，在贷款存续期内按年度向提供融资支持的金融机构履行信息披露义务。内容包括但不限于：转型方案落实情况、转型融资使用情况、转型关键绩效指标完成情况、是否有重大环境违法违规行为、第三方机构跟踪评估意见等。企业碳排放相关数据以温室气体排放核查报告为准。 | I14: 第三十条（五）报告期内因污染物排放受到重大行政处罚或被追究刑事责任的情况，以及公司环境监测方案和风险管理措施是否存在重大缺陷。 | J14: 基础指标（三）环境保护。符合生态环境分区管控、环境影响评价、环境保护设施“三同时”、环境保护竣工验收等要求。依法申领排污许可证，履行依证排污责任，落实重点污染物排放总量控制要求。2026 年起完成全流程超低排放改造并公示。 | T14: 来源：各地生态环境局官网（行政处罚公告栏） | U14: 来源：各地生态环境局官网（行政处罚公告栏） | V14: 环境行政处罚属于转型过程中的合规约束类负向指标，能够从风险管控角度反映企业在监管合规方面的表现。相关信息公开性强、可核验性高，具有较强的约束意义。建议至少将环境行政处罚作为必选负向指标予以保留；安全生产行政处罚和失信事件管理因与转型主题直接关联度相对较低，可作为可选指标纳入体系，综合评价企业合规经营水平。
C15: 安全生产行政处罚（负向指标） | D15: 衡量企业因违反安全生产法规受到处罚或发生生产安全责任事故的严重程度 | G15: 第四条 企业还应当披露本准则第二章至第五章未涵盖的重要的气候相关影响信息。 安全生产事故可能与气候相关物理风险（如极端天气导致的安全事故）有关，或因转型措施不当引发。 | I15: 第五十条（二）职业健康与安全的基本情况，包括但不限于针对公司职业安全风险及来源的识别与评估情况，职业健康安全管理体系的建立及实施情况、相应资质认证获得情况、相关培训情况，工伤保险、安全生产责任险的投入金额及人员覆盖率，报告期内安全事故的具体情况（如有）等； | J15: 基础指标（五）安全生产。落实安全生产主体责任，遵守《冶金企业和有色金属企业安全生产规定》，配套建设安全设施、职业卫生防护设施，具备安全、职业卫生、消防竣工验收等相关手续。上年度以来未发生较大及以上生产安全事故，未发生重大及以上网络安全事件、数据安全事件。 引领指标（五）安全化。积极提升本质安全、生产安全水平，强化网络安全、数据安全管理能力。积极推进资源保障能力建设，提升铁矿、废钢/直接还原铁/镍铁等主要生产原料的保障能力。 | R15: （1）死亡人数（2）总可记录事故率（TRIR）（3）死亡率（4）未遂事故频率（NMFR）（a）直接雇员和（b）非雇员合同工 ——1 企业应分别披露（1）（a）员工和（b）非员工工人因工伤和工作相关疾病造成的死亡人数； 2 实体应分别披露（2）（1）其（a）雇员和（b）非雇员工人的工作相关伤害和疾病的总可记录事故率（TRIR）； 3 披露包括所有工人，无论其地点或就业类型如何；4 所有披露的费率应按以下方式计算：（统计数量×200,000）报告年度内所有员工的工作总小时数。 5 如果报告期内劳动力总数发生重大变化，实体应解释这些变化。 6 实体应披露以下每个员工类别的费率； 7 披露范围包括所有员工，无论员工地点或就业类型如何。 | T15: 来源：各地方应急管理局（厅/局）官网（行政处罚或事故通报栏） | U15: 来源：各地方应急管理局（厅/局）官网（行政处罚或事故通报栏） | V15: 安全生产行政处罚能够从劳工权益保护和企业安全管理角度反映企业合规水平，在转型过程中对员工影响的评价维度具有一定参考意义。但与转型绩效的直接关联度相对弱于环境行政处罚，建议作为可选负向指标纳入体系，与环境行政处罚配合使用，综合反映企业的合规经营状况。
C16: 失信事件管理（负向指标） | D16: 量化转型期企业面临的诉讼压力与现金流风险，案件常涉及合同（供应链）、劳动（安置）、金融（偿债）纠纷。 | G16: 第四条 企业还应当披露本准则第二章至第五章未涵盖的重要的气候相关影响信息。失信事件可能影响企业声誉和财务稳定性，与气候相关转型风险（如政策、法律、市场风险）相关。 | I16: 第四十六条 披露主体或者其控股子公司通过国家企业信用信息公示系统向社会公示逾期尚未支付中小企业款项信息的，应当披露逾期未支付中小企业款项的金额、对中小企业供应商的账期设置、逾期账款的形成原因、是否涉及诉讼仲裁等情况，并披露解决方案。 | J16: 基础指标（一）基本要求。依法依规开展生产经营活动，不存在严重违法违规行为，未列入“严重失信主体名单”，维护行业自律。正常生产，未列入“经营异常名录”。依法依规缴纳税款及社会保险费，按规定支付职工薪酬。不存在从事《中华人民共和国 反垄断法》规定的垄断行为。规范企业公告前，不存在国家有关专项督察通报问题未整改完成事项。 | K16: 工信部《钢铁行业规范条件（2025 年版）》基本要求：依法依规开展生产经营活动，不存在严重违法违规行为，未列入“严重失信主体名单”，维护行业自律。正常生产，未列入“经营异常名录”。依法依规缴纳税款及社会保险费，按规定支付职工薪酬。不存在从事《中华人民共和国反垄断法》规定的垄断行为。规范企业公告前，不存在国家有关专项督察通报问题未整改完成事项。 | T16: 来源：各地高级人民法院被执行人查询系统 | U16: 来源：各地高级人民法院被执行人查询系统 | V16: 失信事件（如法院被执行人等）能够从合同履约和信用管理角度反映企业的诚信经营状况，在转型融资过程中对金融机构的授信决策具有参考价值。但其与低碳转型绩效的直接关联较弱，建议作为可选负向指标纳入体系，作为企业整体合规风险评估的辅助依据。
A17: 转型表现 | B17: 财务表现 | C17: 吨产品净收入 | D17: 按利润表、季度或年度报告等口径中披露的钢铁产量（吨）、归属于上市公司股东的扣除非经常性损益的净利润（元）等业务和财务数据，考虑自身历史和行业水平分析吨钢净利润变化情况 | G17: 第十三条（一） 气候相关风险和机遇对企业报告期间的财务状况、经营成果和现金流量的影响。 | H17: 金融机构根据转型方案，综合考虑企业经营情况、降碳力度等因素，提供建设和运营融资支持 | O17: 转型收入：3.5 绿色和脱碳的年收入增长；3.6 绿色和脱碳年收入（占总收入的百分比）。按照企业是否有目标和数据及其器详细程度，并根据减少提数据梯度，分6个评分阈值进行评价； 钢铁行业调整系数说明——转型领导者：通过绿色活动或产品（至少部分）收入证明转型进展；展示转型的实质性进展，其中绿色活动或产品贡献了显着的收入份额。 | T17: 来源：24年可持续发展报告、24年年度报告 可持续发展报告：附录 1 主要数据指标-净利润 公司年报：产销量情况分析表-生产量合计 | U17: 来源：24年年度报告 钢产品生产量；主营业务收入-成本=净利润 | V17: 前期设置"吨产品净收入"指标，初衷是从单位产品收益视角观察企业在转型过程中的盈利能力变化。但进一步分析后发现，该指标主要反映企业整体财务表现及产品定价能力，受市场价格波动等外部因素影响较大，与低碳转型绩效之间缺乏直接因果关系，无法有效衡量企业转型的实际进展。因此建议删除该指标，以增强指标与转型主题的相关性。
C18: 高附加值产品竞争力 | D18: 采用季度或年度报告等口径中披露的钢铁业务收入、钢铁销售量等业务、财务数据，通过吨钢销售均价（元/吨）得到企业的销售均价相对于行业均价的差距，反应市场对该企业高附加值产品的溢价支付意愿。 | F18: 9、产品结构优化 9.1 开发高强高韧、耐蚀耐磨、轻量化、长寿命的钢铁绿色设计产品 | H18: 一（一）3.投资活动要在《河北省钢铁行业转型金融支持经济活动目录（2025年版）》范围内（目录中包含开发高强高韧、耐蚀耐磨、轻量化、长寿命的钢铁绿色设计产品） | K18: 《钢铁行业稳增长工作方案（2025—2026年）》：增强高端产品供给能力。聚焦高端装备、核心基础零部件等领域所需高性能轴承钢、齿轮钢、高温合金、工模具钢等关键钢材，组织钢铁企业联合上下游企业、高校、科研院所等开展产业链协同攻关。持续发挥船舶与海工、超超临界等新材料重点平台作用，加快产品应用验证和迭代升级。 2022年9月，工信部等四部门联合印发的《原材料工业“三品”实施方案》明确提出，到2025年要实现“高温合金、高性能特种合金、半导体材料、高性能纤维及复合材料等产品和服务，对重点领域支撑能力显著增强”的目标。该方案特别将“高性能特种钢”列为需要支持鼓励研发和产业化的关键基础材料，表明超高强钢已成为国家战略的重要组成部分。 《标准提升引领原材料工业优化升级行动方案（2025—2027年）》进一步将“特种装备用钢”、“高性能特种钢”等先进基础材料标准修订列为重点。 | T18: 来源：24年可持续发展报告、24年年度都报告 环披报告：附录 1 主要数据指标-营业总收入、 年度报告：产销量情况分析表-钢材销售量、24年度报告-合并资产负债表- EBITDA（税息折旧及摊销前利润）-营业利润+固定资产折旧+使用权资产折旧 + 无形资产摊销+长期待摊费用摊销 | U18: 来源：24年年度报告 钢产品销售量；主营业务收入 | V18: 前期设置"高附加值产品竞争力"指标，初衷是通过产品价格溢价衡量企业产品结构升级与技术含量提升情况。但进一步审视后发现，产品溢价主要反映市场对该企业产品的支付意愿，受供需关系影响较大，与企业低碳转型绩效并无直接关联。同时，该指标拟体现的产品结构升级内容已通过"产品结构优化"指标得到覆盖。因此建议删除该指标，避免重复计量，增强体系聚焦性。
C19: 绿色低碳转型债券 | D19: 公司在近五年内为绿色低碳转型相关债券发行人，且披露相关债券运用情况 | K19: 《关于进一步优化绿色及转型债券相关机制的通知》拓宽转型债券发行人范围，拓展转型债券募集资金用途，指出转型债券将支持有转型需求的企业，不限于钢铁、有色、石化等传统八大行业，进一步拓展转型债券发行人主体范围，对于募集资金用途，通知指出企业可按有关部委或相关主管部门制定的转型目录等标准发行转型债券，用于与碳达峰碳中和目标相适应、具有减污降碳和能效提升作用的项目及其他相关经济活动，将有助于推动传统行业转型升级，促进转型债券市场进一步扩容。 | L19: 确定资本分配一致性，明确表明资本支出与到2050年实现净零排放是一致的。在构建投资组合时，考虑能够推动实体经济脱碳的不同的资产类别和投资；使用系统方法识别资产类别变体，以增加气候解决方案的风险敞口并降低碳强度；将净零目标与标准指标一起纳入投资组合建设。理想情况下，额外的调整目标应涵盖脱碳和气候解决方案。 | M19: CTB要求将募集资金用于合格气候转型项目，而气候转型项目的定义包含以下范畴：资产、投资与经营活动，高排放资产的提前淘汰与拆除，以及与高排放活动相关的研发支出等——这些活动须能够实现显著且可量化的温室气体规避、减排或清除。 | N19: 企业承诺将所有未来资本支出与其长期温室气体目标或《巴黎协定》将全球气温增幅限制在1.5摄氏度的目标保持一致。企业同时必须披露将未来资本支出与其减碳目标相一致的方法。 | T19: 来源：2024年度报告-第九节 债券相关情况 披露了低碳转型绿色债券募集资金所投向的绿色项目进展情况、募集资金所投向的绿色项目环境效益，所遴选的绿色项目环境效益测算的标准、方法、依据和重要前提条件、募集资金所投向的绿色项目预期与/或实际环境效益情况（具体环境效益情况原则上应当根据《绿色债券存续期信息披露指南》相关要求进行披露，对于无法披露的环境效益指标应当进行说明、评估认证机构相关情况 | U19: 无 | V19: 绿色或低碳转型债券的发行本身并不直接等同于转型成效，单纯以发行次数或规模进行量化评价，可能误判企业真实转型水平。该指标如果被认为有必要纳入评价体系，可能更适合拆解为“是否参与”“资金用途清晰度”“项目实施与效果披露”“第三方评估”等要素，通过分项赋分方式反映企业在转型金融工具运用方面的规范性与成熟度。例如： （一）是否作为绿色 / 低碳转型债券发行人，是-2分；否-0分 （二）募集资金用途与转型相关性，用途表述笼统（如“用于绿色项目”）-1 分；明确对应具体转型项目/技术路径-2 分；披露项目进展-3分；披露测量的减排效果-4分 （三）是否有第三方评估/认证，是-2分；否-0分
B20: 碳排放表现 | C20: 碳价敏感度 | D20: 采用季度或年度报告等口径中披露的EBITDA（税息折旧及摊销前利润）、市场碳价等业务、财务数据，形成理论碳成本占企业经营利润的比例，衡量企业盈利对碳价（尤其是潜在或未来碳价格）的敏感程度。 | G20: 第三十八条 对于内部碳定价，企业应当说明在决策中是否以及如何应用碳价格（如投资决策、转移定价以及情景分析），披露其内部用于评估温室气体排放成本的每吨温室气体排放的价格。企业可以使用影子价格、内部税费等内部碳定价方法。 | K20: 《全国碳排放权交易市场覆盖钢铁、水泥、铝冶炼行业工作方案》：四、实施配额管理 （一）制定年度配额总量和分配方案。生态环境部会同国务院有关部门根据国家温室气体排放控制目标，制定钢铁、水泥、铝冶炼行业年度碳排放配额总量和分配方案。在启动实施阶段，2024 年度配额分配量与其经核查的实际碳排放量相等，2025 年度和 2026 年度配额基于碳排放强度控制思路进行分配。在深化完善阶段，对标行业先进水平优化配额分配方法，推动单位产品产量（产出）碳排放不断下降。 | T20: 来源：24年可持续发展报告、2024年年度报表 可持续发展报告：附录 宝钢股份总温室气体排放总量表：温室气体排放总量(类别1+类别2)11024万吨二氧化碳当量 年度报告：合并利润表-EBITDA = 营业利润 + 固定资产折旧 + 使用权资产折旧 + 无形资产摊销 + 长期待摊费用摊销 | U20: 来源：24年可持续发展报告-附录：ESG指标数据（当年数据和基准年数据） 温室气体排放量 年度报告：EBITDA = 营业利润 + 固定资产折旧 + 使用权资产折旧 + 无形资产摊销 + 长期待摊费用摊销 | V20: 碳价敏感度通过企业理论碳成本占经营利润的比例，衡量企业盈利对潜在碳价格变化的敏感程度，有助于识别企业面临的碳价风险敞口及低碳转型的财务必要性。该指标所需数据可从财务报告和企业碳排放披露中提取，在国际转型评估框架中具有一定参考基础，建议作为碳排放表现维度的定量指标纳入评价体系。
C21: 碳排放披露情况 | D21: 1. 核心词：范围1、直接排放、范围2、能源间接排放、范围3、价值链排放 2. 范围3类别词：类别1、采购商品、上下游运输、差旅、员工通勤、废弃物 | E21: 1.转型主体应当对照国家碳达峰碳中和目标，制定并披露科学合理的碳减排目标，主要内容和要求包括：(3）温室气体排放核算范围至少包括范围一和范围二的温室气体排放；条件成熟时，酌情将范围三的温室气体排放纳入核算范围。 | G21: 第二十七条（一）温室气体排放。 第二十八条 企业应当按照范围一、范围二和范围三温室气体排放，分类披露报告期内产生的温室气体绝对排放总量（以吨二氧化碳当量表示）。 | H21: 二（一）企业碳排放相关数据以温室气体排放核查报告为准。 三（二）2.鼓励企业在披露碳排放范围1、范围2数据的基础上，开展范围3的信息披露。 | I21: 第二十四条 披露主体应当核算并披露报告期内的温室气体排放总量，并将不同温室气体排放量换算成二氧化碳当量公吨数。披露主体应当披露温室气体范围1排放量、范围2排放量，鼓励有条件的披露主体披露温室气体范围3排放量。 | K21: 《全国碳排放权交易市场覆盖钢铁、水泥、铝冶炼行业工作方案》：钢铁行业需披露二氧化碳温室气体排放数据，覆盖化石燃料燃烧、工业过程等产生的温室气体直接排放，不覆盖因消耗电力、热力等带来的间接排放。 | L21: 1. 披露基线投资组合范围1和2融资排放量，投资组合范围3排放量单独披露，主权相关资产单独披露； 5披露：披露运营范围1、2，以及重大范围3的排放； | N21: 企业报告了范围1和范围2，或范围1、范围2和范围3的温室气体排放信息。如果企业仅披露范围1温室气体排放，应被评为“否”。 企业单独披露范围3排放，全部或一个或多个类别，或者提供范围1、范围2和范围3温室气体排放量总额。 在一些部门，范围3排放的特定类别具有重大意义，在生命周期排放中占很大份额。在这些行业，要求企业具体披露相关类别的排放量： （1）对于汽车制造、煤矿开采、石油天然气生产和石油天然气分销公司，要求披露使用销售产品产生的范围3排放； （2）对于食品生产商，要求披露采购商品和服务的范围3排放； （3）对于多元化的矿工，要求披露销售产品加工过程中的范围3排放； 对于化学品公司，要求披露采购商品和服务以及销售产品使用的范围3排放。 | R21: 1 主体应当披露其全球范围内的范围 1 温室气体（GHG）总排放量，以《京都议定书》涵盖的七种温室气体的二氧化碳当量（CO₂-e）公吨为单位， 2. 范围 1 排放的定义与计算方法 范围 1 排放的定义和计算，必须遵循《温室气体核算体系：企业核算与报告标准》（GHG Protocol）（修订版，2004 年 3 月）中所载的方法，该标准由世界资源研究所（WRI）与世界可持续发展工商理事会（WBCSD）共同发布。 3 受限排法规约束的排放占比主体应当披露其全球范围 1 温室气体总排放量中，受相关司法管辖区限排法律、法规或计划约束的排放占比。这些法规旨在直接限制或减少温室气体排放，例如：总量控制与交易机制碳税或收费 / 免税制度 其他排放控制措施（如命令控制型措施）许可机制 4 主体应当讨论自上一报告期以来的排放变化，包括该变化是否是由于减排、撤资、收购、合并、产出变化或计算方法变化造成的。 5 与其他披露的协调：如果主体向 CDP 或其他实体（如国家监管披露计划）报告的温室气体排放，在范围或合并方法上与本指引存在差异，主体可披露这些数据，但主要披露仍需遵循本指引。 6 主体可以选择以下方法进行排放披露，只要数据来源可靠：连续排放监测系统（CEMS）、工程计算、物料平衡计算。 | T21: 来源：24年可持续发展报告 附录 宝山钢铁股份有限公司钢铁板块：购买货物和服务的运输、员工通勤、产品运输、废物处置、采购货物和服务的排放（制造相关）等 | U21: 来源：24年可持续发展报告-附录：ESG指标数据（当年数据和基准年数据） 温室气体排放总量 | V21: 碳排放披露是开展后续定量评价的基础性前提，体现企业信息透明度与管理成熟度，建议作为基础指标保留。
C22: 物理碳排放强度 | D22: 单位粗钢产量所产生的范围一和范围二的碳排放量 | E22: 1.转型主体应当对照国家碳达峰碳中和目标，制定并披露科学合理的碳减排目标，主要内容和要求包括：(2）短、中、长期的碳减排目标，以定量的碳排放总量或者单位产品碳排放强度表示。 2.转型主体应当制定并披露技术可行的转型计划，主要内容和要求包括：(3）测算每个阶段转型工作的碳减排效果，说明碳减排效果的累积能够实现短、中、长期碳减排目标。 | G22: 第二十七条（一）温室气体排放。 第四十条 企业应当披露与特定业务模式、活动或者表明企业所处行业的其他共同特征相关的行业特定指标。 | H22: 一（一）2.短期目标要以定量的碳排放强度表示，中、长期目标要兼顾碳排放总量 一（一）3.二是投资计划涉及的主要工序碳排放预期值要低于河北省钢铁行业碳排放基准值。 | K22: 《全国碳排放权交易市场覆盖钢铁、水泥、铝冶炼行业工作方案》：四、实施配额管理 （一）制定年度配额总量和分配方案中明确提出“2025 年度和 2026 年度配额基于碳排放强度控制思路进行分配。在深化完善阶段，对标行业先进水平优化配额分配方法，推动单位产品产量（产出）碳排放不断下降。” 2025 年最新发布的《绿色工厂评价通则》（GB/T 36132-2025）；单位产值（或单位产品）的二氧化碳当量（CO₂e）排放量需明确年度减排目标，且近 3 年平均降幅≥3%；需覆盖范围 1（直接排放，如燃烧） 和范围 2（外购能源间接排放），重点行业（如化工、火电）需额外核算范围 3（供应链间接排放）。 | L22: 1、排放强度符合部门和地区2050年路径，并且其运营模式将保持这一表现的资产； 2. 排放表现：当前的绝对值或排放强度至少等于相关净零路径； | M22: CTB：3.1 关键绩效指标的选择 对于高排放的可持续发展挂钩债券（SLBs）发行人，一个或多个关键绩效指标（“KPIs”）应监测温室气体（GHG）减排——可以是直接结果（即绝对/强度温室气体排放指标）或辅助指标（即推动温室气体减排目标的杠杆指标） | O22: 减排量（长期）： （1）有针对性的减少绝对1、2级排放强度：按照企业是否有目标与数据及其详细程度、减排数据梯度（有无-35%），分6个评分阈值（0-5）进行评价； （2）实现的减少绝对范围3排放:按照企业是否有目标与数据及其详细程度、减排数据梯度（有无-35%），分6个评分阈值（0-5）进行评价； （3）实现的减少排放强度（范围1、2排放）:按照企业是否有目标与数据及其详细程度、减排数据梯度（有无-35%），分6个评分阈值（0-5）进行评价； 减排量（短期）： （1）有针对性的减少绝对1、2级排放强度：按照企业是否有目标与数据及其详细程度、减排数据梯度（有无-35%），分6个评分阈值（0-5）进行评价； （2）实现的减少绝对范围3排放:按照企业是否有目标与数据及其详细程度、减排数据梯度（有无-35%），分6个评分阈值（0-5）进行评价； （3）实现的减少排放强度（范围1、2排放）:按照企业是否有目标与数据及其详细程度、减排数据梯度（有无-35%），分6个评分阈值（0-5）进行评价； | P22: （5）温室气体减排：减少、清除和抵消排放量对于实现温室气体减排目标的相对贡献。 | R22: 1 主体应当披露其全球范围内的范围 1 温室气体（GHG）总排放量，以《京都议定书》涵盖的七种温室气体的二氧化碳当量（CO₂-e）公吨为单位， | T22: 来源：24年可持续发展报告、24年年度报告（当年与基准年数据） 环披报告：附录 宝钢股份总温室气体排放总量表：温室气体排放总量(类别1+类别2)11024万吨二氧化碳当量 公司年报：产销量情况分析表-生产量合计 | U22: 来源：24年可持续发展报告-附录：ESG指标数据（当年数据和基准年数据） 温室气体排放总量 24年年度报告-钢产品产量 | V22: 两类碳强度指标分别从产量与经济产出角度反映企业排放效率，营收碳排放强度从经济产出角度衡量单位营业收入的碳排放量，能够反映企业在创造经济价值的同时实现减排的效率，与物理碳排放强度形成互补，共同构成碳排放表现的量化评价维度。建议保留该指标，采用与物理碳排放强度相同的分档评价逻辑，结合绝对水平和年际变化综合评分。
C23: 营收碳排放强度 | D23: 单位营业收入所产生的范围一和范围二的碳排放量 | E23: 1.转型主体应当对照国家碳达峰碳中和目标，制定并披露科学合理的碳减排目标，主要内容和要求包括：(2）短、中、长期的碳减排目标，以定量的碳排放总量或者单位产品碳排放强度表示。 2.转型主体应当制定并披露技术可行的转型计划，主要内容和要求包括：(3）测算每个阶段转型工作的碳减排效果，说明碳减排效果的累积能够实现短、中、长期碳减排目标。 | G23: 第二十七条（一）温室气体排放。 第四十条 企业应当披露与特定业务模式、活动或者表明企业所处行业的其他共同特征相关的行业特定指标。 | M23: CTB：3.1 关键绩效指标的选择 对于高排放的可持续发展挂钩债券（SLBs）发行人，一个或多个关键绩效指标（“KPIs”）应监测温室气体（GHG）减排——可以是直接结果（即绝对/强度温室气体排放指标）或辅助指标（即推动温室气体减排目标的杠杆指标） | T23: 来源：24年可持续发展报告（当年与基准年数据） 附录 1 主要数据指标：营业总收入3,221.16亿元；附录 宝钢股份总温室气体排放总量表：温室气体排放总量(类别1+类别2)11024万吨二氧化碳当量 | U23: 来源：24年可持续发展报告-附录：ESG指标数据（当年数据和基准年数据） 温室气体排放总量下面的“温室气体排放强度”单位是吨二氧化碳当量/每百万元营收
C24: 碳排放效率 | D24: 碳减排效率用于衡量企业在实现营业收入增长的同时，其碳排放减少与经济增长之间的协同程度，反映企业“低碳增长”的质量。 | G24: 第四十四条 企业应当披露其每项气候目标实现情况的绩效信息，以及对企业绩效趋势或者变化的分析 | I24: 第二十七条 披露主体应当披露温室气体减排实践的相关信息，包括参与各项减排机制的情况、减排目标、减排措施（如管理措施、资金投入、技术开发等）及其成效等。 | T24: 来源：24年可持续发展报告（近两年数据） 附录 1 主要数据指标：营业总收入3,221.16亿元；附录 宝钢股份总温室气体排放总量表：温室气体排放总量(类别1+类别2)11024万吨二氧化碳当量 | U24: 来源：24年可持续发展报告、24年年度报告（当年数据和基准年数据） 可持续报告：附录：ESG指标数据：温室气体排放总量（范围 1+ 范围 2） 2024年 35,612,055.11吨二氧化碳当量； 年度报告：营业收入1092.03亿元 | V24: 前期设置"碳排放效率"指标，主要是希望从碳排放与经济产出的协调性角度，衡量企业低碳增长的质量。但进一步分析后发现，该指标与"物理碳排放强度"和"营收碳排放强度"在概念上高度重叠，独立设置将导致指标体系内部冗余。建议将相关内涵通过已有强度指标的分档设计加以体现，删除单独的碳排放效率指标，以提升体系的精简度。
C25: 自身减排速度 | D25: 企业当年的“同比减排幅度”，相对于行业当年的“平均同比减排幅度”，处在什么位置。 | G25: 第四十四条 企业应当披露其每项气候目标实现情况的绩效信息，以及对企业绩效趋势或者变化的分析 | H25: 一（一）3.二是投资计划涉及的主要工序碳排放预期值要低于河北省钢铁行业碳排放基准值。 | I25: 第二十七条 披露主体应当披露温室气体减排实践的相关信息，包括参与各项减排机制的情况、减排目标、减排措施（如管理措施、资金投入、技术开发等）及其成效等。 | O25: 钢铁行业调整系数说明——钢：1. 若当前排放强度显著高于行业平均水平（+30%），则采用否定性修饰语。2. 若当前排放强度已显著低于行业平均水平（-30%），则采用正向修正系数。 | R25: 4 主体应当讨论自上一报告期以来的排放变化，包括该变化是否是由于减排、撤资、收购、合并、产出变化或计算方法变化造成的。 | T25: 来源：24年可持续发展报告、24年年度报告（近两年数据） 环披报告：附录 宝钢股份总温室气体排放总量表：温室气体排放总量(类别1+类别2)11024万吨二氧化碳当量 公司年报：产销量情况分析表-生产量合计 | U25: 来源：24年可持续发展报告、24年年度报告（当年数据和基准年数据） 可持续报告：附录：ESG指标数据：温室气体排放总量（范围 1+ 范围 2） 2024年 35,612,055.11吨二氧化碳当量； 年度报告：钢产品生产量 2,016.22 万吨 | V25: 前期设置"自身减排速度"指标，主要是希望从动态视角衡量企业减排行动的相对速度，考察企业减排进展与行业均值的对比关系。但进一步分析后发现，该指标计算需要逐年对标行业均值，数据处理复杂度较高，且横向可比性受行业样本选取与更新的影响，实操难度较大。此外，其所反映的内容已部分包含于碳排放强度等核心指标的年际变化分析中。建议暂不纳入，视数据积累情况在后续版本中酌情引入。
B26: 能源使用 | C26: 可再生能源占比 | D26: 自发可再生能源电量，是指企业在自身生产经营边界内，通过自建或控股的可再生能源发电设施，所产生并被企业自身消费的电力。 能源消耗总量：企业当期披露的能源消耗总量（单位 MWh） | F26: 2. 清洁能源替代: 2.1 分布式光伏发电技术; 2.2 储热调峰; 2.3可再生能源制氢气和氧气用于钢铁冶炼 | G26: 第十二条（二）当前和计划采取的用于减缓和适应气候变化的直接措施（如节能产品认证、碳标识认证，改变生产工艺或者设备、搬迁设施、调整劳动力结构以及改变产品规格等）； | H26: 一（一）3.投资活动要在《河北省钢铁行业转型金融支持经济活动目录（2025年版）》范围内（目录中包含分布式光伏发电技术、风力发电设施建设和运营） | I26: 第三十五条（二）清洁能源使用情况，包括但不限于风能、太阳能、水能、地热能、生物质资源、海洋能、天然气等清洁能源的种类、总量、比例等； | M26: CTB：项目类别的初步且非详尽清单包括但不限于： 4. 低碳燃料，包括其生产、使用、采购及相关基础设施投资。 | R26: (3) 消耗的可再生电力百分比：企业应披露其消耗的来自可再生能源的电力数量（以 GJ 为单位），分为自发电和直接合同。其消耗的可再生能源百分比。 | T26: 来源：24年可持续发展报告（当年与基准年数据） 附录 1 主要数据指标：可再生能源-自发可再生能源电量：2024合计 377,164兆瓦时 附录 1 主要数据指标：能源消耗-能源总量：2024年合计267,429,687兆瓦时 | U26: 来源：2024年可持续发展报告（当年数据和基准年数据） 附录：ESG指标数据：自发绿电（屋顶光伏、风电）2024年 105,387兆瓦时；能源消耗总量 2024年 86,280,115兆瓦时 | V26: 可再生能源占比反映企业能源结构的清洁化程度，是国内外政策框架普遍关注的能源转型核心指标。上市钢铁企业在可持续发展报告中对可再生能源相关数据通常具有较好的披露基础，且指标计算方法标准化程度较高，具备较好的横向可比性，建议作为能源结构表现维度的核心指标予以保留。
D27: 外购绿电包括： 绿电交易电量 绿证对应电量（如披露） 能源消耗总量：企业当期披露的能源消耗总量（单位 MWh） | G27: 第四十五条 企业计划使用外购减排量作为补充手段抵销其温室气体排放量，以实现温室气体净排放量目标的，应当在说明其计划使用的减排量时披露下列信息：（一）实现温室气体净排放量目标依赖外购减排量使用的程度和方式；（二）对减排量进行认证的独立第三方名称及认证体系；（三）减排量所属的自愿减排交易机制名称，产生减排量的项目所处国别；（四）减排量的类型，包括抵销所用减排量源自何种自愿减排项目；（五）为使可持续信息基本使用者了解企业计划使用的减排量的可信度和完整性所需的其他因素（如项目业主对所提供材料真实性、完整性和有效性负责的承诺书）。 | K27: 《关于2025年可再生能源电力消纳责任权重及有关事项的通知》明确在电解铝行业基础上，2025年增设钢铁、水泥、多晶硅行业和国家枢纽节点新建数据中心绿色电力消费比例。《通知》要求，2025年，钢铁、水泥、多晶硅行业要求绿电消费比例为25.2%～70%之间， | R27: 企业应披露（3）其消耗的来自可再生能源的电力数量（以 GJ 为单位），分为（3a）自发电和（3b）直接合同。其消耗的可再生能源百分比。 可再生能源的范围包括实体消耗的可再生燃料、实体直接生产的可再生能源和实体购买的可再生能源，如果通过明确包含可再生能源证书 (REC) 或原产地保证 (GO)、Green-e Energy 认证的公用事业或供应商计划或明确包含 REC 或 GO 的其他绿色电力产品购买，或 Green-e Energy 认证的 REC 与电网电力配对。 | T27: 来源：24年可持续发展报告（当年与基准年数据） 附录 1 主要数据指标：可再生能源-外购可再生能源电量：2024合计1,916,874兆瓦时，外购可再生能源绿证电量：2024合计2,660,300兆瓦时 附录 1 主要数据指标：能源消耗-能源总量：2024年合计267,429,687兆瓦时 | U27: 来源：2024年可持续发展报告（当年数据和基准年数据） 附录：ESG指标数据：外购绿电 2024年302,054兆瓦时，能源消耗总量 2024年 86,280,115兆瓦时 | V27: 外购绿电在一定程度上可降低企业范围二排放，但其转型含义具有明显的阶段性和外部依赖性： 受制于区域绿电供给、市场机制和政策补贴安排； 不一定伴随企业自身生产系统或能源结构的实质性改变。 因此，可将外购绿电作为可选指标，用于补充刻画企业在现阶段条件下的减排努力，但不作为转型绩效的刚性判断依据。
C28: 能耗强度or能耗达标？ | D28: 能耗强度指标吨钢综合能耗，而能耗达标就是看单位产品能源消耗量是否满足国家及地方政府相关规定要求。 | F28: 1. 系统能效提升; 1.1 上升管余热回收 1.2 烧结漏风率综合治理 1.3 水封式烧结环冷机 1.4 烧结返矿冷压球团矿 1.5 球团固固换热显热回收 1.6 高炉大比例球团冶炼 1.7 高炉炉顶均压煤气回收 1.8 转炉一次干法净化回收 1.9 转炉中低温余热回收 1.10 电炉烟气显热回收 1.11 高效煤气发电 1.12 低温余热有机工质朗肯循环（ORC）发电 1.13 电机、变压器、水泵、风机等公辅设施能效提升 | K28: 通过环评审批的新建和在建钢铁企业高炉、转炉或电弧炉冶炼工序的单位产品能耗应达到《工业重点领域能效标杆水平和基准水平（2023年版）》中的高耗能行业能效标杆水平：高炉工序能效标杆水平为 361 千克标准煤/吨（对原料中钒钛磁铁矿用量每增加 10%，高炉工序能耗增加 3 千克标准煤/吨）；转炉工序能效标杆水平为-30 千克标准煤/吨；电弧炉冶炼（30 吨＜公称容量＜50 吨）能效标杆水平为 67 千克标准煤/吨；电弧炉冶炼（公称容量≥50 吨）能效标杆水平为 61 千克标准煤/吨（注：电弧炉冶炼全不锈钢单位产品能耗提高 10%）。现有钢铁企业高炉、转炉或电弧炉冶炼工序的单位产品能耗达到能效基准水平以上，基准水平分别为435千克标准煤/吨、-10千克标准煤/吨、86千克标准煤/吨、72千克标准煤/吨。 铸造用生铁企业单位产品能耗应达到地方标准。如《铸铁生产主要工序单位产品能源消耗限额》（DB13/T 2129-2014 ）中单位产品能耗限定值烧结工序≤59 千克标准煤/吨，球团工序≤35 千克标准煤/吨，高炉工序≤435 千克标准煤/吨。 《钢铁行业节能降碳专项行动计划》，至2030年底，钢铁行业主要工序能效进一步提升，主要用能设备能效基本达到先进水平，吨钢综合能耗和碳排放明显降低，用能结构持续优化 | R28: 能源管理主题下，企业应披露（1）其消耗的能源总量，以千兆焦耳（GJ）为单位。 | T28: 来源：2024年可持续发展报告 吨钢综合能耗达4.5兆瓦时/吨粗钢 | U28: 来源：2024年可持续发展报告 吨钢综合能耗535.47千克标准煤/吨粗钢 | V28: 能耗强度与碳排放强度存在较高同质性；而能耗达标指标在政策上依据具体工序设定限额，但企业披露通常不按工序拆分，导致数据可得性较差。综合考虑指标区分度与可操作性，建议不单独设置该指标。
B29: 水资源利用 | C29: 用水效率 | D29: 单位粗钢水消耗量，指企业在生产过程中对水资源的消耗情况 用水效率 = 当期总用水量 ÷ 当期粗钢产量 | E29: 无重大损害原则。即转型金融支持的经济活动或企业应当对污染防控、资源节约和生态保护等其他环境目标无重大损害。 | G29: 第四十条 企业应当披露与特定业务模式、活动或者表明企业所处行业的其他共同特征相关的行业特定指标。 | H29: 一（一）3.投资活动要在《河北省钢铁行业转型金融支持经济活动目录（2025年版）》范围内（目录中包含钢铁生产不同工序水质分质供水技术、废水深度处理回用组合工艺、废水零排放处理和回用技术、循环水水质动态监测与水处理优化技术，适用于节水节能、钢铁行业废水处理回用等场景） | I29: 第三十六条 （一）水资源使用的基本情况，包括但不限于总耗水量（以吨计算）及使用强度（如以每产量单位计算）等； （二）水资源节约目标以及具体措施，水资源回收利用情况及水资源使用存在的具体困难（如有）。 | J29: 基础指标（四）资源消耗。资源综合利用符合国家有关规定。水资源消耗符合国家有关强制标准规定，不存在未经批准擅自取用地下水行为。 | K29: 《工业用水定额：钢铁》按照主要生产工序进一步细分制定，分别制定了烧结、球团、焦化、炼铁、炼钢、轧钢等工序用水定额。 | R29: （1）按来源划分的总取水量 （2）总用水量； （3）从缺水地区取水和消耗的水量百分比，以及基线水压力高或极高地区的用水量百分比 1 实体应披露从所有来源取水的数量，以兆升、千立方米为单位，按来源分类。 2 如果很大一部分取水来自非淡水源，则实体可按来源披露其供应部分。 3 该实体应披露其直接运营中消耗的水量，以兆升、千立方米为单位。 4 企业应披露在基线水资源压力高或极高地区，从水资源紧张地区消耗的水量占总消耗水量的百分比。 5 如果此披露的信息是估算或模拟的，而不是来自直接测量，则企业应解释其估算方法。 | T29: 来源：24年可持续发展报告、24年年度报告（当年数据和基准年数据） 环披报告：附录 1 主要数据指标：水资源-年度总用水量：135.67百万立方米 年度报告：产销量情况分析表-生产量合计 | U29: 来源：24年可持续发展报告、24年年度报告（当年数据和基准年数据） 可持续报告：附录 ESG指标数据：水资源管理-总耗水量 50,146,778立方米 年度报告：钢产品生产量 2,016.22 万吨 | V29: 用水效率以单位粗钢产量水消耗量衡量企业对水资源的利用效率，是多个转型金融和企业可持续披露框架中明确要求的环境绩效指标。上市钢铁企业通常在可持续发展报告中具备相关数据披露，且具有一定的行业可比基础，建议作为水资源表现维度的核心指标予以保留。
C30: 水资源回收利用率 | D30: 企业在生产过程中回用的水量占总用水量的比率，衡量企业是否通过技术手段有效回收和再利用水资源，减少对外部水资源的依赖 | E30: 无重大损害原则。即转型金融支持的经济活动或企业应当对污染防控、资源节约和生态保护等其他环境目标无重大损害。 | G30: 第四十条 企业应当披露与特定业务模式、活动或者表明企业所处行业的其他共同特征相关的行业特定指标。 | H30: 一（一）3.投资活动要在《河北省钢铁行业转型金融支持经济活动目录（2025年版）》范围内（目录中包含废水深度处理回用组合工艺、废水零排放处理和回用技术、循环水水质动态监测与水处理优化技术，适用于节水节能、钢铁行业废水处理回用等场景） | I30: 第三十六条 （一）水资源使用的基本情况，包括但不限于总耗水量（以吨计算）及使用强度（如以每产量单位计算）等； （二）水资源节约目标以及具体措施，水资源回收利用情况及水资源使用存在的具体困难（如有）。 | K30: 《工业废水循环利用实施方案》（工信部联节〔2021〕213号）明确提出到2025年，钢铁行业规模以上工业用水重复利用率要达到97%以上，推动钢铁企业加强节水管理和技术改造，推广应用高效循环用水处理、高浓度有机废水回用等先进工艺技术。 | T30: 没有披露 | U30: 来源：24年可持续发展报告-附录：ESG指标数据 2024年水循环利用比例为98% | V30: 前期设置"水资源回收利用率"指标，主要是希望从循环利用角度补充衡量企业的水资源管理水平。但在实际数据收集过程中发现，该指标企业间披露口径不统一，可比性受限，且所反映的水资源管理内容与"用水效率"指标存在较大重叠。综合考虑数据可得性与体系简洁性，建议暂不独立保留，可在"用水效率"评价框架中将水资源回收利用情况作为加分项加以考量。
B31: 生态保护 | C31: 生物多样性 | D31: 企业在生物多样性保护方面表现，比如制度或组织架构建设、具体措施和实际成效，包括保护区域的生态恢复、物种多样性保护及生态环境修复等。 | E31: 无重大损害原则。即转型金融支持的经济活动或企业应当对污染防控、资源节约和生态保护等其他环境目标无重大损害。 | G31: 第四条 企业还应当披露本准则第二章至第五章未涵盖的重要的气候相关影响信息。 | H31: 一（一）2.技术路径应遵循无重大损害原则 | I31: 第三十二条 披露主体生产经营活动对生态系统和生物多样性产生重大影响的， | S31: 2) 技能与文化：为设计、实施与监督转型计划的团队和个人提供培训与发展支持，使其具备足够的技能与知识以履行职责（包括董事会及高级管理层层面）。实施变革管理计划，促进开放沟通，并将净零转型计划融入组织的文化与实践中。 ・现有及所需的能力、技能与知识摘要，以及评估方法 ・资源需求与将转型计划要素融入文化与实践的变革管理计划摘要 ・获取气候相关资源的渠道摘要 | T31: 来源：24年可持续发展报告 宝钢股份通过建立贯穿项目规划、建设、运营全过程的生物多样性保护管理体系，系统推进生态保护战略落地。报告期内，我们开展了一系列以生物多样性保护为主题的项目，持续完善工业活动与自然生态的协同发展路径。严格遵守《中华人民共和国环境影响评价法》及其相关法律法规的规定，确保新建项目选址避开自然保护区范围。依据 IUCN 红色名录及国家保护物种名录，对运营点所在区域的生物多样性现状进行综合评估与分析，并据此制定科学的管理与保护规划。对海外采购的原材料进行严格检测，以预防外来物种的入侵风险。严格监控并管理废气、废水及废弃物的排放，以确保不对自然生态环境造成不利影响。与地方监测站携手合作，共同实施物种监测项目，积极推进野生动物保护行动。 | U31: 来源：24年可持续发展报告 根据生物多样性风险评估的结论，公司制定了旨在最小化 业务运营对生物多样性影响的短期及长期管理规划。公司 针对高风险区域，特别制定了生物多样性风险缓解行动方 案，并广泛实施了生态保护和补偿措施，确保运营活动不 对生物多样性构成任何负面影响 在新项目建设与运营全流程中，需参照相关要求进行生物多样性保护和土地利用评估，确保项目开发与运营 地点远离生态保护红线及生态多样性脆弱地区，以保护自然栖息地、湿地、森林、野生动物廊道和农业用地， 尽量降低对周边环境和社区的不利影响 | V31: 生物多样性保护已成为国际可持续披露框架（如TNFD）的重要议题，部分国内可持续发展报告亦开始涉及相关内容。虽然目前钢铁行业企业的披露深度有限，但作为ESG综合绩效的重要组成部分，建议采用定性评价方式，以有无相关制度建设、具体措施和实际成效为评价依据，纳入评价体系以体现企业在生态保护方面的关注程度。
B32: 公正转型 | C32: 公益捐赠 | D32: 公益捐赠可以适当反映企业在转型过程中对社会公共利益与弱势群体的支持能力，是公正转型中“社会缓冲机制”的重要体现评估企业在公益捐赠上表现出的投入力度与行为稳定性，综合判断其社会承诺的财务实质性及长期可信度。 | T32: 来源：24年可持续发展报告 公益捐赠-社会捐赠总额：8121.33万元 | U32: 来源：2024年可持续发展报告-附录：ESG指标数据 对外捐赠金额：75万元 | V32: 公益捐赠在一定程度上可反映企业对社会公共利益的关注，但与转型绩效评价的核心逻辑相关度较低，且受企业经营状况、行业景气周期等外部因素影响较大，难以有效体现公正转型的实质性内涵。更重要的是，目前主要转型评价框架中鲜有将公益捐赠纳入转型评价指标体系的先例。因此建议删除该指标，转而聚焦员工培训和稳就业与促就业等更具转型针对性的公正转型指标。
C33: 员工培训 | D33: 本指标用于评估企业是否关注并投入员工能力建设，尤其是在转型相关技能方面。 考虑到企业披露口径差异较大，本指标采用是否类累加赋分方式，不对不同披露口径进行强制可比性要求。 | E33: 公正转型原则。应当关注转型可能产生的经济社会影响，并采取措施缓解负面影响。 | G33: 第四条 企业还应当披露本准则第二章至第五章未涵盖的重要的气候相关影响信息。 | H33: 一（一）2.三是对转型过程中可能产生的经济社会影响，要遵循公正转型原则，做好评估及应对预案。 | I33: 第五十条（三）员工职业发展与培训的基本情况，包括但不限于公司职位体系设置情况，员工晋升、选拔与职业发展机制，员工培训类型、次数、开展情况，以及年度培训支出金额、员工培训覆盖率等。 | Q33: 5.5 技能、能力与培训 主体应当披露其为实现转型计划的战略愿景，已采取或计划采取的、用于在全公司范围内评估、维持和培养相应技能、能力与知识的行动相关信息。 披露建议 作为此部分的内容，主体应当披露： a. 关于主体如何评估其在全公司范围内是否具备有效设计、制定、交付和治理转型计划所需的技能、能力与知识的信息，以符合其战略愿景 b. 当识别到技能缺口时，说明其已采取或计划采取的、用于获取或培养所需技能的行动 c. 关于其已采取或计划采取的、为董事会及高管层提供有效监督转型计划所需的技能、能力与知识的行动信息 | T33: 来源：24年可持续发展报告（当年数据和基准年数据） 报告期内，宝钢股份共开展环保相关培训 5 场，培训总时长为 34 小时，培训 100% 覆盖宝钢股份四大基地及子公司。 | U33: 来源：2024年可持续发展报告（当年数据和基准年数据） 员工培训总人次 72,029，培训费用 865.13 万元 技术人才培训主要着眼于设备类、安全管理类等专技培训。其 中，后备安全专家培训组织了相关技术人员赴各子公司进行现场 实践，该培训历时 18 天，共计 76 人参与，共完成炼铁、炼钢、 轧钢、焦化四个专业新安全风险辨识管控模版的编制；数智化人 才类共计组织 6 个培训项目，包括人工智能平台、数据库应用高 阶等各类培训，共计 166 人参与。此次培训储备了后备安全专家， 提升了技术人才占比。 面向员工和利益相关方开展生物多样性主题教育和培训，提升生物多样性保护意识和专业性 公司重视提升全体员工对能源高效利用的认识与能力，策划并面向全体员工开展了一系列提升能源使用效率的培训项目，包括日常操作工艺节能减排操作要求、管理层面节能减碳软件应用等。同时，公司邀请行业专家进行授课，通过案例与实操演练，让员工深刻理解节能减排的重要性，并掌握实际应用中的节能技巧。 | V33: 员工培训是公正转型的重要维度，反映企业在转型过程中通过能力建设降低技术变革对员工的负面冲击。钢铁行业在推进工艺升级和技术转型过程中，员工技能培训尤为关键，在多个政策框架中均有明确引导。企业通常具备相关披露基础，建议保留该指标，采用定性分档评价方式，重点考察培训投入规模及与转型技能的相关性。
C34: 稳就业与促就业 | D34: 衡量企业在转型过程中是否避免通过大规模裁员转嫁成本，并通过稳定或扩大就业规模，体现对劳动者和社会的责任承担。 | E34: 公正转型原则。应当关注转型可能产生的经济社会影响，并采取措施缓解负面影响。 | G34: 第四条 企业还应当披露本准则第二章至第五章未涵盖的重要的气候相关影响信息。 | H34: 一（一）2.三是对转型过程中可能产生的经济社会影响，要遵循公正转型原则，做好评估及应对预案。 | I34: 第五十条（一）员工的聘用与待遇等方面的政策及执行情况，包括但不限于报告期内吸纳就业、创造灵活就业岗位的情况，期末在职员工的性别、年龄等构成情况，报告期内支付员工工资和缴纳员工社保、公司劳工纠纷、员工变动、对灵活就业人员的权益保障、招聘录用程序合规与公平透明情况等； | R34: 劳工实践: 1 集体协议涵盖的员工百分比，企业应披露报告日集体协议涵盖的员工总数的百分比。 2 该百分比的计算方法是将集体协议涵盖的员工人数除以雇用的员工总数。 （1）停工次数，实体应披露停工次数、因停工导致的停工总天数（2）总闲置天数 3 该披露不包括因非技术原因导致的停工，例如因待决监管许可而导致的停工，或与社区担忧、社区或利益相关者抵抗或抗议或武装冲突有关的其他延误。 4 实体应提供有关停工的信息，包括相关成本、每次停工的原因（由劳工说明）、对生产的影响、持续停工的状况以及采取的纠正措施。 | T34: 来源：24年可持续发展报告（近三年数据） 附录 1 主要数据指标：雇佣与多元化-员工总数2024年46,048人。 | U34: 来源：24年可持续发展报告（近三年数据） 附录：ESG指标数据-员工基本信息-员工总人数 30,960人 | V34: 稳就业与促就业能够体现企业在转型过程中对劳动者和社会责任的履行程度，是公正转型框架的核心关注点之一。钢铁行业转型可能涉及工艺淘汰和产能调整，就业稳定性评价具有重要的现实意义，且在多个国内政策文件中有明确导向。建议保留该指标，重点评价企业是否避免借转型名义大规模裁员，并通过积极行动稳定和扩大就业。
C35: 劳动纠纷（负向指标） | D35: 衡量因转型调整（如岗位重组、合同解除）引发的、并已进入正式法律或仲裁程序的劳资纠纷数量与严重性。 案由关键字：船员劳务合同纠纷、辞退争议、经济性裁员争议、劳动合同纠纷、劳动争议、劳务合同纠纷、离退休人员返聘合同纠纷、确认劳动关系纠纷、社会保险纠纷、职工破产债权确认纠纷、追索劳动报酬纠纷 | E35: 公正转型原则。应当关注转型可能产生的经济社会影响，并采取措施缓解负面影响。 | G35: 第四条 企业还应当披露本准则第二章至第五章未涵盖的重要的气候相关影响信息。 劳动纠纷可能属于气候相关转型风险（如政策、法律风险）或公正转型影响的体现。 | H35: 一（一）2.三是对转型过程中可能产生的经济社会影响，要遵循公正转型原则，做好评估及应对预案。 | I35: 第五十条（一）员工的聘用与待遇等方面的政策及执行情况，包括但不限于报告期内吸纳就业、创造灵活就业岗位的情况，期末在职员工的性别、年龄等构成情况，报告期内支付员工工资和缴纳员工社保、公司劳工纠纷、员工变动、对灵活就业人员的权益保障、招聘录用程序合规与公平透明情况等； | J35: 基础指标（一）基本要求。依法依规开展生产经营活动，不存在严重违法违规行为，未列入“严重失信主体名单”，维护行业自律。正常生产，未列入“经营异常名录”。依法依规缴纳税款及社会保险费，按规定支付职工薪酬。不存在从事《中华人民共和国 反垄断法》规定的垄断行为。规范企业公告前，不存在国家有关专项督察通报问题未整改完成事项。 | T35: 来源：中国裁判文书网、地方人社局公布的年度劳动争议典型案例/分析报告 | U35: 来源：中国裁判文书网、地方人社局公布的年度劳动争议典型案例/分析报告 | V35: 劳动纠纷能够从负面视角衡量企业在转型调整过程中劳资关系的稳定程度，是公正转型实施质量的直接佐证。相关数据可通过企业法律纠纷公开记录进行核查，具有较强的可核验性。建议作为可选负向指标纳入体系，与"重大负面舆情"指标共同评价企业在公正转型方面的合规性与社会影响。
C36: 重大负面舆情（负向指标） | D36: 系统性量化企业因“公正转型”措施失当，在公开舆论场引发的负面关注与声誉风险。 关键字： 劳工权益类：转型裁员、安置纠纷、买断工龄、再培训缺失、拖欠补偿金、员工抗议、工会协商破裂； 社区影响类：关停冲击、地方经济衰退、税收锐减、产能退出、搬迁争议、环境遗留问题 过程公正类：决策黑箱、缺乏沟通、无视职工意见、突击式关停、政策套利 | E36: 公正转型原则。应当关注转型可能产生的经济社会影响，并采取措施缓解负面影响。 | G36: 第四条 企业还应当披露本准则第二章至第五章未涵盖的重要的气候相关影响信息。负面舆情可能属于气候相关转型风险中的声誉风险。 | H36: 一（一）2.三是对转型过程中可能产生的经济社会影响，要遵循公正转型原则，做好评估及应对预案。 | J36: 基础指标（一）基本要求。依法依规开展生产经营活动，不存在严重违法违规行为，未列入“严重失信主体名单”，维护行业自律。正常生产，未列入“经营异常名录”。依法依规缴纳税款及社会保险费，按规定支付职工薪酬。不存在从事《中华人民共和国 反垄断法》规定的垄断行为。规范企业公告前，不存在国家有关专项督察通报问题未整改完成事项。 | T36: 来源：公开网络 | U36: 来源：公开网络 | V36: 重大负面舆情是企业公正转型措施失当所引发的社会反应，能够综合反映企业在转型过程中对员工、社区等利益相关方影响的处置质量。舆情信息来源公开，可核验性较强，且能够捕捉到其他定量指标难以覆盖的软性社会影响。建议作为可选负向指标纳入体系，尤其关注与转型行为直接相关的负面事件。
B37: 研发与创新 | C37: 研发投入占比 | D37: 以“研发投入 / 研发费用 / 研究与开发支出”等为核心关键词，结合财务报表附注中“研发支出”相关披露，提取企业当期研发投入金额；分母采用“营业收入”口径计算研发投入占比。 | G37: 第十四条 企业应当披露在生产经营过程中开展的有助于减缓和适应气候变化的创新措施和效果，以及为此支付的成本。 | H37: 一（一）2.技术路径应当具有可行性，要遵循先进性原则。（鼓励技术创新） | I37: 第二十条 披露主体应当积极通过改进工艺、升级生产设备、优化能源结构、提高生产能效、研发和提供绿色产品与服务、改进和强化管理等措施，实现绿色低碳发展，支持美丽中国建设。 第四十二条 （二）开展科技创新的具体情况，包括研发创新管理制度体系建设，参与研发创新、科技合作项目的情况，研发投入金额及占主营业务收入比例、研发人员数量及占比、应用于主营业务的发明专利数量等； | J37: 引领指标——一级指标高端化——二级指标研发投入占比 | K37: 关于用好绿色金融政策支持绿色工厂建设的通知：研发和产业化应用项目。重点支持传统产业绿色低碳重大工艺革新、“卡脖子”技术、短板装备等攻关和产业化应用项目，以及绿色低碳产业新技术新产品新模式研发应用项目。 | T37: 来源：24年可持续发展报告（近三年数据） 附录 1 主要数据指标：产品及客户服务-研发支出：2024年250.12亿元；经济绩效-营业总收入：2024年3,221.16亿元 | U37: 来源：24年可持续发展报告（当年数据和基准年数据） 附录：ESG指标数据-研发创新与知识产权-研发投入 460,234.09万元 | V37: 研发投入占比能够直接反映企业在创新与技术研发方面的资源投入强度，是衡量企业转型能力的重要前瞻性指标。该指标所需数据在企业财务报告中通常具有较好的披露基础，且在多个国内政策框架中被明确列为评价要素。但考虑到部分企业研发投入与低碳技术的直接关联度难以识别，建议作为可选指标，与"节能技改投资占比"配合使用，从不同维度共同衡量企业的转型投入能力。
C38: 科研平台 | D38: 是否具备相应资质的研发中心、技术中心、创新中心、重点实验室等企业科研机构。（自有、母公司或控股的钢铁企业亦可） | G38: 第十四条 企业应当披露在生产经营过程中开展的有助于减缓和适应气候变化的创新措施和效果，以及为此支付的成本。 | H38: 一（一）2.技术路径应当具有可行性，要遵循先进性原则。（鼓励技术创新） | J38: 引领指标——一级指标高端化——二级指标科研平台 | K38: 关于用好绿色金融政策支持绿色工厂建设的通知：研发和产业化应用项目。重点支持传统产业绿色低碳重大工艺革新、“卡脖子”技术、短板装备等攻关和产业化应用项目，以及绿色低碳产业新技术新产品新模式研发应用项目。 | T38: 无明确提及 | U38: 来源：24年可持续发展报告 建立系统、高效、覆盖全公司的低碳技术创新研发协同平台 | V38: 前期设置"科研平台"指标，主要是希望通过企业是否拥有国家级或省级研发机构来评价科研实力。但进一步梳理后发现，该指标更多反映的是历史积累与行政认定结果，与低碳转型动态推进的关联度有限，且不同级别平台之间可比性较差。建议删除该指标，将企业科研能力通过研发投入占比和节能技改投资占比等更具直接性的指标予以体现。
C39: 专利情况 | D39: 以“专利数量、发明专利数量”等关键词为核心，识别分子；分母采用营业收入，计算每单位营收专利拥有量。 | G39: 第十四条 企业应当披露在生产经营过程中开展的有助于减缓和适应气候变化的创新措施和效果，以及为此支付的成本。 | H39: 一（一）2.技术路径应当具有可行性，要遵循先进性原则。（鼓励技术创新） | J39: 引领指标——一级指标高端化——二级指标专利情况 | T39: 来源：24年可持续发展报告 附录 1 主要数据指标：产品及客户服务-有效专利数9,707，应用于主营业务的发明专利数量7,292。 | U39: 来源：24年可持续发展报告（当年数据和基准年数据） 附录：ESG指标数据-研发创新与知识产权-累计专利量2,934个，年度新增授权专利总数476个 | V39: 前期设置"专利情况"指标，主要是希望通过单位营收的专利拥有量来衡量企业技术创新能力。但实际梳理中发现，专利数量受行业属性和战略布局差异影响较大，存量专利与低碳转型技术的关联度难以有效识别，且不同企业专利申请策略和口径差异明显，横向可比性受限。建议删除该指标，转而通过研发投入占比和节能技改投资占比等更聚焦的指标评价企业转型技术投入能力。
C40: 节能技改投资占比 | D40: 以“节能技改 / 技术改造 / 节能改造/超低排放改造投资”等关键词识别企业披露的节能相关技改投资金额，结合“投资金额 / 固定资产投资 / 资本性支出”等表述进行提取；分母统一采用当期营业收入，计算节能技改投资占比。 | E40: 2.转型主体应当制定并披露技术可行的转型计划，主要内容和要求包括： (2)明确每个阶段的工作计划及重点工作任务； 3.转型主体应当制定并披露清晰合理的融资计划，主要内容和要求包括：(2）计划使用的转型金融工具及不同工具筹集资金的主要用途。 | F40: 1. 系统能效提升; 1.1 上升管余热回收 1.2 烧结漏风率综合治理 1.3 水封式烧结环冷机 1.4 烧结返矿冷压球团矿 1.5 球团固固换热显热回收 1.6 高炉大比例球团冶炼 1.7 高炉炉顶均压煤气回收 1.8 转炉一次干法净化回收 1.9 转炉中低温余热回收 1.10 电炉烟气显热回收 1.11 高效煤气发电 1.12 低温余热有机工质朗肯循环（ORC）发电 1.13 电机、变压器、水泵、风机等公辅设施能效提升 4. 环保减排改造： 4.2 颗粒物、SO₂、NOₓ等超低排放改造 | G40: 第十二条（一）业务模式当期和预期的变化，包括其应对气候相关风险和机遇的资源配置（如管理或者退出关于碳、能源或者水密集型业务的计划，因需求或者供应链变化导致的资源配置，通过资本支出或者额外研发支出进行业务发展所产生的资源配置，收购或者剥离等）。 第二十七条（五）资本配置——针对气候相关风险和机遇发生的资本支出、融资或者投资金额。 | H40: 一（一）3.投资活动要在《河北省钢铁行业转型金融支持经济活动目录（2025年版）》范围内（目录中包含重点工序节能提效活动） | I40: 第二十条 披露主体应当积极通过改进工艺、升级生产设备、优化能源结构、提高生产能效、研发和提供绿色产品与服务、改进和强化管理等措施，实现绿色低碳发展，支持美丽中国建设。 第三十五条 （三）能源节约目标以及具体措施，包括但不限于采购节能生产设备、节能照明设备、节能温控设备，采用余热余压利用、能源梯级利用等措施，能源使用存在的具体困难（如有）。 | K40: 关于用好绿色金融政策支持绿色工厂建设的通知：技术改造升级项目。重点支持企业实施节能降碳、节水减污、资源循环利用、清洁原料燃料替代、环保装备升级、数字化绿色化协同升级以及工业绿色微电网、数字化能碳管理中心、绿色数据中心等绿色低碳改造升级项目。 《绿色金融支持项目目录（2025 年版）》：重点工业行业绿色低碳转型，针对钢铁、有色金属、石化化工、建材等高碳排行业，从节能降碳改造和能效提升、工艺改进和流程优化以及数字化、智能化升级三大路径支持工业领域低碳转型，并严格要求单位产品能耗指标值达到最新版《工业重点领域能效标杆水平和基准水平》（2023年版）规定的相应行业产品能效标杆水平。 | M40: CTF：要素1.发行人的气候转型战略和治理：推荐信息和指标：应具体列出实现温室气体减排的主要杠杆，例如详细的资本支出（CapEx）计划及相关技术影响（即计划支出金额、实施此类CapEx项目所考虑的碳成本、运营影响、监管考虑等） CTB：在无法制定范围3温室气体排放KPI/SPT的情况下，发行人可以考虑使用“绿色”资本支出（CapEx）KPI或辅助指标，以展示他们在行业内减少温室气体排放的承诺和进展 | N40: 企业承诺将所有未来资本支出与其长期温室气体目标或《巴黎协定》将全球气温增幅限制在1.5摄氏度的目标保持一致。企业同时必须披露将未来资本支出与其减碳目标相一致的方法。 | O40: 转型投资： 3.3 绿色和脱碳的百分比（占年度投资）；按照企业是否有目标和数据及其器详细程度，并根据降碳数据梯度，分6个评分阈值（0-75%）进行评价； 3.4 绿色脱碳投资比率（绿色转型与脱碳的比值）。按照企业是否有目标和数据及其详细程度，并根据降碳数据梯度，分6个评分阈值（0-75%）进行评价； | T40: 来源：24年可持续发展报告（近三年数据） 2024 年节能低碳投资18.9亿元； 附录 1 主要数据指标：营业总收入3,221.16亿元； | U40: 来源：24年可持续发展报告 节能项目总投资2.3亿元 | V40: 节能技改投资占比直接反映企业在节能降碳技术改造方面的资金投入力度，是衡量企业转型实施进度的核心量化指标之一。相关数据通常在可持续发展报告或企业公告中有所披露，且在国内多个转型金融和行业政策框架中均被明确列为评价要素，具备较好的横向可比性，建议作为转型表现维度的核心量化指标予以保留。
C41: 环保投入金额占比 | D41: 以“环保投入 / 环保投资 / 环境保护支出”等关键词为核心，识别企业披露的污染防治、环保设施及相关投入金额；分母采用营业收入，计算环保投入占比。 | E41: 无重大损害原则。即转型金融支持的经济活动或企业应当对污染防控、资源节约和生态保护等其他环境目标无重大损害。 | H41: 一（一）2.技术路径应遵循无重大损害原则 | I41: 第三十条（二）对污染物的处理技术和处理方式，污染防治设施的建设、运行情况和实施成果（例如排放浓度、强度或排放总量的降幅）； | T41: 来源：24年可持续发展报告（近三年数据） 报告期内，宝钢股份在环保方面的费用化投入为100.755 亿元，资本化项目投入为4.835亿元。 附录 1 主要数据指标：营业总收入3,221.16亿元； | U41: 来源：24年可持续发展报告 环保项目总投资4.5亿元 | V41: 环保投入金额占比能够反映企业在污染防治与环保设施方面的资金投入强度，与减污降碳协同治理目标高度契合。该指标所需数据通常可从可持续发展报告中提取，但各企业口径存在一定差异，跨企业可比性有待进一步统一。建议作为可选指标纳入评价体系，与"节能技改投资占比"形成互补，从污染防治投入角度丰富转型绩效维度的评价内涵。
C42: 前沿技术 | D42: 企业是否布局钢铁行业前沿技术研发，例如高炉富氢改造、氢直接还原铁、氢熔融还原铁工艺的研发和试验项目建设 | E42: 2.转型主体应当制定并披露技术可行的转型计划，主要内容和要求包括： (1)对照短、中、长期碳减排目标，明确每个阶段的转型技术路径，该技术路径应当具有可行性和先进性； | F42: 6.冶炼技术突破 6.1电炉短流程炼钢 6.2副产煤气或天然气直接还原炼铁 6.3富氢碳循环高炉 6.4熔融还原炼铁 6.5全氢气基直接还原炼铁 8.碳回收利用 8.1二氧化碳捕集利用与封存 8.2炉窑等尾气回收二氧化碳及利用 8.3喷吹二氧化碳炼钢 | G42: 第十四条 企业应当披露在生产经营过程中开展的有助于减缓和适应气候变化的创新措施和效果，以及为此支付的成本。 | H42: 一（一）2.技术路径应当具有可行性，要遵循先进性原则。 一（一）3.投资活动要在《河北省钢铁行业转型金融支持经济活动目录（2025年版）》范围内（目录中包含可再生能源制氢 气和氧气用于钢铁冶炼、富氢碳循环高炉、全氢气基直接还原炼铁、二氧化碳捕集利用与封存等先进技术） | I42: 第四十二条（三）取得的研发进展及成果、获得的专业资质和重要奖项等，包括报告期内发明专利的申请数和授权数、有效专利数，高新技术企业认定情况、国家科学技术奖项获奖情况等； | K42: 《钢铁行业稳增长工作方案（2025—2026年）》：推进绿色低碳改造。......支持氢冶金等低碳共性技术攻关，加快推进绿电、绿氢、纯氢冶金一体化工艺技术和装备中试验证和产业化....... | T42: 来源：24年可持续发展报告 报告期内，作为中国宝武氢还原电熔炼工艺HyRESP）的核心装备，220t 高效绿色电炉于 2024 年 4 月 11 日在宝钢股份湛江钢铁开工建设，拉开了宝钢湛江钢铁零碳高等级薄钢板工厂项目开工的序幕，预计 2025 年底建成，届时与前期建成的氢基竖炉结合，将具备年产约 180 万吨低碳板材能力。 | U42: 来源：24年可持续发展报告 公司积极发展低碳冶金技术，通过持续探索氢冶金技术、智能全氧燃烧技术等，在提高生产效率的同时减少钢铁生产过程中 的碳排放，实现钢铁生产的绿色化、低碳化 案例：大冶特钢——利用氢能全氧燃烧技术优势，成功实施全国首例低碳加热炉应用实践 案例：天津钢管——环形加热炉纯氧改造项目，绿色低碳先进技术新典范 案例：靖江特钢——近零碳排电炉示范项目 案例：青岛特钢——成功研发特焊材料，助力突破 CCUS 技术瓶颈 案例：天津钢管——突破 CCUS 抗腐管线管技术，为管材应用树立新标杆 | V42: 前期设置"前沿技术"指标，主要是希望通过识别氢冶金、CCUS等低碳前沿技术的研发与应用情况，评价企业技术转型的深度与前瞻性。但进一步梳理后发现，该指标与"冶炼技术突破"在评价对象和内容上高度重叠，存在重复计量风险。因此建议删除单独设置的"前沿技术"指标，将相关内容统一纳入"冶炼技术突破"模块，通过前沿低碳冶炼技术相关关键字进行综合识别和定性评价。
B43: 行业特定 | C43: 煤炭消耗比例 | D43: 企业在生产过程中，煤炭（包含焦炭、动力煤、喷吹煤等）提供的能量占综合能源消耗总量的比例。该比例下降，意味着企业正在使用天然气、氢能或绿电来替代煤炭。这是能源结构清洁化的直接体现。 | F43: 1.系统能效提升: 1.1 上升管余热回收；1.7高炉炉顶均压煤气回收； 1.8转炉一次干法净化回收；1.9转炉中低温余热回收；1.10电炉烟气显热回收；1.11高效煤气发电 2. 清洁能源替代: 2.1 分布式光伏发电技术; 2.2 储热调峰; 2.3可再生能源制氢气和氧气用于钢铁冶炼 6.冶炼技术突破 6.1电炉短流程炼钢 6.5全氢气基直接还原炼铁 | R43: 实体应披露 （2） 消耗的煤炭燃料的百分比。 2.1 百分比应按煤炭消耗量（以 GJ 为单位）除以燃料消耗总量（以 GJ 为单位）计算。 2.2 消耗的煤炭范围可能包括动力煤、冶金煤、焦炭和焦粉。 | T43: 没有披露 | U43: 来源：2024年可持续发展报告-附录：ESG指标数据 无烟煤消耗量、烟煤消耗量、洗精煤消耗量、焦炭消耗量 | V43: 前期设置"煤炭消耗比例"、"入炉球团矿比例"、"高炉燃料比"、"余能余热回收"和"电炉钢产量占比"五个指标，目的是从多维度细化评价企业生产过程中的降碳表现。但进一步对照《转型金融支持经济活动目录（钢铁行业）》政策文件后发现，上述五个指标本质上均可归纳为钢铁行业"系统能效提升"这一核心领域，分散设置容易造成指标口径不齐和重复识别。因此，建议将上述指标统一归纳为"系统能效提升"模块，通过能效提升相关技术关键字进行综合定性评价，突出钢铁行业系统性降碳的整体转型路径。
C44: 入炉球团矿比例 | D44: 钢铁行业的长流程（炼铁）环节有“烧结”和“球团”这两个工序。 传统的“烧结”工序是钢铁厂最大的污染源和高耗能环节之一；而“球团”工序相对更清洁、能耗更低。提高球团矿比例（降低烧结矿比例），可以直接降低炼铁前工序的能耗和碳排放。 | F44: 1. 系统能效提升; 1.4 烧结返矿冷压球团矿 1.5 球团固固换热显热回收 1.6 高炉大比例球团冶炼 | T44: 没有披露 | U44: 没有披露 | V44: 入炉球团矿比例与煤炭消耗比例、高炉燃料比、余能余热回收等同属钢铁行业系统能效提升的具体技术路径，其本质均体现企业通过工艺优化降低单位产出能耗和碳排放的实践。分散设置难以保持口径统一，建议统一纳入"系统能效提升"综合模块进行定性评价。
C45: 高炉燃料比 | D45: 高炉燃料比是指每炼1吨合格生铁所消耗的入炉燃料总量，通常以千克/吨（kg/t）为单位。它综合反映了高炉冶炼过程中燃料的消耗水平，是衡量高炉炼铁效率和能源利用效果的关键指标。 | F45: 1. 系统能效提升; 1.1 上升管余热回收 1.2 烧结漏风率综合治理 1.3 水封式烧结环冷机 1.4 烧结返矿冷压球团矿 1.5 球团固固换热显热回收 1.6 高炉大比例球团冶炼 1.8 转炉一次干法净化回收 | K45: 《钢铁行业（高炉炼铁）清洁生产评价指标体系》高炉燃料比的清洁生产等级一级≤495，二级≤515，三级≤530kg/t 《工业重点领域能效标杆水平和基准水平（2023年版）》：高炉工序单位产品千克标准煤能耗标杆水平为361kgce/t，对应燃料比需结合具体工艺和原燃料条件综合评估，但该指标更侧重综合能耗。 | T45: 没有披露 | U45: 来源：2024年可持续发展报告-附录：ESG指标数据 高炉燃料比2024年数据是514.68千克/吨铁 | V45: 高炉燃料比是衡量高炉炼铁效率和能源利用水平的关键指标，与煤炭消耗比例、入炉球团矿比例等共同反映钢铁长流程的能效表现。但由于单项指标披露不稳定，难以在企业间进行有效横向对比，建议统一纳入"系统能效提升"模块进行综合定性评价。
C46: 余能余热回收 | D46: 钢铁行业余能余热是指在钢铁生产过程中，除满足生产工艺本身需求外剩余的热能和能量，主要包括余热、余压、余气等形式。 余能余热的来源：高温烟气余热、冷却水余热、炉渣余热、煤气余能、余压能量 余能余热的利用方式：余热发电、余热供热、煤气综合利用、余热制冷 | F46: 1.系统能效提升: 1.1 上升管余热回收；1.7高炉炉顶均压煤气回收；1.9转炉中低温余热回收；1.10电炉烟气显热回收；1.11高效煤气发电；1.12低温余热有机工质朗肯循环（ORC）发电 | K46: 《钢铁行业节能降碳专项行动计划》（发改环资〔2024〕730号），提出以下重点任务：到2025年，余热余能自发电率提高3个百分点以上 《工业绿色微电网建设与应用指南（2026—2030年）》明确要求充分利用钢铁行业焦炉、高炉、转炉副产煤气及其显热、余压，建设工业余能分级高效回收利用体系。中高品位余热资源优先供给区域内有用热需求的企业，用于驱动蒸汽轮机、预热空气、干燥物料等；剩余余热、余压、余气用于发电、接入储能或供应暖（冷）气、热水等。 | T46: 没有披露 | U46: 来源：2024年可持续发展报告-附录：ESG指标数据 余热发电下披露了“自有余热发电消耗量”和“余热发电系统装机容量” | V46: 余能余热回收是钢铁行业通过过程能量梯级利用实现节能降碳的重要路径，涵盖余热发电、余压利用、煤气综合利用等多种形式。该技术路径已在多个行业政策文件中有明确要求，但独立披露情况参差不齐，建议统一纳入"系统能效提升"模块，通过关键字识别进行定性综合评价。
C47: 电炉钢产量占比 | D47: 钢铁电炉钢属于短流程炼钢工艺。短流程炼钢以废钢为主要原料，通过电炉冶炼、精炼、连铸和轧制等工序生产钢材，省去了传统长流程炼钢中的焦化、烧结、高炉炼铁等环节，具有流程短、投资少、能耗低、碳排放少等优势。 | F47: 6.冶炼技术突破 6.1电炉短流程炼钢 | G47: 第十四条 企业应当披露在生产经营过程中开展的有助于减缓和适应气候变化的创新措施和效果，以及为此支付的成本。 | K47: 《工业领域碳达峰实施方案》（工信部联节〔2022〕88号），进一步提出推进氢基竖炉直接还原铁、碳捕集利用封存等技术的示范推广，稳步提高电炉短流程的发展，并在2025年短流程炼钢占比达15%以上、2030年达20%以上的量化目标。 《2024-2025年节能降碳行动方案》（国发〔2024〕12号），到2025年底，电炉钢产量占粗钢总产量比例力争提升至15%，废钢利用量达到3亿吨。 | R47: 活动指标包括： 粗钢产量，百分比来自：(1) 碱性氧气炉工艺、(2) 传统电弧炉工艺和 (3) 氢直接还原工艺 铁矿石总产量 焦煤总产量 再生钢产量 | T47: 没有披露 | U47: 没有披露 | V47: 电炉钢产量占比是体现钢铁短流程转型进度的核心指标，直接反映企业工艺路线向低碳方向转变的实质程度。与煤炭消耗比例等行业指标并列，共同构成系统能效评价框架的重要组成部分，建议统一纳入"系统能效提升"模块，并根据相关数据披露情况决定是否提取为独立定量子指标。
C48: 违反产能置换（负面指标） | D48: 根据《钢铁行业产能置换实施办法》及相关政策要求，对于违反产能置换规定的企业，相关部门会采取公示、通报等措施进行公开曝光。例如，中央环保督察组在检查中发现企业存在违规产能问题后，会将问题企业及整改情况向社会公示，接受公众监督。此外，省级工业和信息化主管部门也会对违规企业的产能置换方案及整改情况在官方网站进行公示，公示期一般不少于15个工作日。 | E48: 无重大损害原则。即转型金融支持的经济活动或企业应当对污染防控、资源节约和生态保护等其他环境目标无重大损害。 | J48: 基础指标（二）工艺装备。所有冶炼设备须具备完备的项目建设手续，严格执行《钢铁行业产能置换实施办法》要求，现有主体工艺技术及装备符合《产业结构调整指导目录》要求，不存在淘汰类工艺技术及装备。 | K48: 工信部原材料工业司2025年发布了《钢铁行业产能置换实施办法（征求意见稿）》：各省（区、市）炼铁、炼钢产能置换比例均不低于1.5:1。对2021年6月1日之后兼并重组新取得的合规产能用于项目建设的，各省（区、市）炼铁、炼钢产能置换比例均不低于1.25:1。 关于促进钢铁工业高质量发展的指导意见 工信部联原〔2022〕6号：坚持总量控制。优化产能调控政策，深化要素配置改革，严格实施产能置换，严禁新增钢铁产能，扶优汰劣，鼓励跨区域、跨所有制兼并重组，提高产业集中度。 | T48: 来源：公开信息 | U48: 来源：公开信息 | V48: 违反产能置换属于重大合规风险事件，能够从行业政策合规角度反映企业的转型遵从度，具有一定的评价参考价值。但考虑到此类事件通常会引发较大范围的负面舆情，其影响已基本涵盖于"重大负面舆情"指标的识别范围之内，存在重复计量风险。为避免指标体系冗余，建议不单独设置，相关情形通过"重大负面舆情"指标加以综合覆盖。
C49: 超低排放改造进程 | D49: 超低排放改造进程=（SOx排放量+NOx排放量+颗粒物排放量）/当年粗钢产量​ 超低排放改造是指对工业生产过程中的重点行业（如火电、钢铁、水泥、焦化等）实施全面的大气污染治理升级改造，旨在使企业生产过程中产生的大气污染物排放浓度达到极低水平，接近或低于天然气燃气轮机组的排放标准。 具体而言，超低排放改造的核心目标是通过技术手段，对生产环节中的有组织排放（如烟囱排放）、无组织排放（如物料储存、输送过程中的逸散）以及运输环节的污染物排放进行严格控制，实现颗粒物、二氧化硫、氮氧化物等主要污染物排放浓度显著降低。 | E49: 无重大损害原则。即转型金融支持的经济活动或企业应当对污染防控、资源节约和生态保护等其他环境目标无重大损害。 | F49: 4.环保减排改造； 4.2 颗粒物、SO2、NOx等超低排放改造 | G49: 第四十条 企业应当披露与特定业务模式、活动或者表明企业所处行业的其他共同特征相关的行业特定指标。 | H49: 一（一）3.投资活动要在《河北省钢铁行业转型金融支持经济活动目录（2025年版）》范围内（目录中包含超低排放改造活动） | I49: 第三十条（二）对污染物的处理技术和处理方式，污染防治设施的建设、运行情况和实施成果（例如排放浓度、强度或排放总量的降幅）； | J49: 基础指标（三）环境保护。符合生态环境分区管控、环境影响评价、环境保护设施“三同时”、环境保护竣工验收等要求。依法申领排污许可证，履行依证排污责任，落实重点污染物排放总量控制要求。2026 年起完成全流程超低排放改造并公示。 | K49: 《关于推进实施钢铁行业超低排放的意见》:到2025年底前，重点区域钢铁企业超低排放改造基本完成，全国力争80%以上产能完成改造。 关于促进钢铁工业高质量发展的指导意见 工信部联原〔2022〕6号：全面推动钢铁行业超低排放改造，加快推进钢铁企业清洁运输， 2025 年最新发布的《绿色工厂评价通则》（GB/T 36132-2025）；废气（SO₂、NOx、VOCs）、废水（COD、氨氮）的排放浓度需严于国家或地方标准 50% 以上，且满足区域污染物总量控制要求；无组织排放需符合《挥发性有机物无组织排放控制标准》（GB 37822）。 | R49: 1 该实体应披露其排放到大气中的空气污染物排放量，以每种污染物的公吨为单位。 3 该实体应披露其（1）（2）氮氧化物（NOx）的排放量，报告为NOx。 4 实体应披露其 (2)(3) 硫氧化物SOx的排放量，报告为 SOx。 5 该实体应披露其（4）直径为10微米或更小的颗粒物（PM10）的排放量，报告为PM10。 | T49: 来源：24年可持续发展报告 废气指标下披露了硫氧化物、氮氧化物、颗粒物的排放总量 | U49: 来源：24年可持续发展报告-附录：ESG指标数据 废气排放下披露了硫氧化物、氮氧化物、颗粒物的排放总量 | V49: 前期曾考虑删除"超低排放改造进程"指标，主要因其在不同企业间披露口径不一致，定量评价存在困难。但在进一步对照《转型金融支持经济活动目录（钢铁行业）》等政策文件后发现，超低排放改造是钢铁行业转型评价的关键维度，具有重要的政策导向意义。因此，建议调整评价方式，将企业是否已完成或正在推进超低排放改造的定性表述作为识别依据，纳入"环保减排改造"模块，采用关键字识别和定性分档评价。
C50: 系统能效提升 | D50: 企业通过全流程深度优化与多种相关技术手段协同提升能源利用效率，从而降低单位产出能耗和碳排放，最终使能源利用效率达到行业最优甚至接近极限水平。包括相关节能降碳技术与“极致能效”称号。 | V50: "系统能效提升"综合反映企业通过工艺优化、能源利用效率提升及余能回收等措施实现节能降碳的整体表现，覆盖传统行业指标（煤炭消耗比例、高炉燃料比、余能余热回收等）所描述的多个降碳路径，是钢铁行业转型实施层面的核心综合性指标。建议采用定性分档评价方式，依据企业是否具有具体实践项目进行赋分，重点突出转型实施的深度与系统性。
C51: 环保减排改造 | D51: 企业通过系统性工程改造与全国全过程控制，使污染物排放水平大幅低于常规标准，实现钢铁等高排放行业的深度环境治理与绿色转型。主要包括超低排放改造完成情况。 | V51: "环保减排改造"集中反映企业超低排放改造的推进情况，具有明确的政策导向与行业标准支撑。通过识别企业是否已完成或正在推进超低排放改造，能够从实施层面直接判断企业的减排进展，是钢铁行业绿色转型的重要评价依据。建议作为定性指标予以保留，重点关注改造完成率和达标程度。
C52: 冶炼技术突破 | D52: 企业通过开发和应用前沿性关键低碳冶炼技术，改变传统高碳生产路径。包括氢冶金、CCUS、电炉短流程炼钢等前沿技术。 | V52: "冶炼技术突破"聚焦钢铁生产过程中前沿低碳冶炼技术（如氢冶金、CCUS、富氧冶炼等）的研发与应用情况，能够体现企业在突破性技术路径上的实质性投入与进展，是衡量企业长期减排潜力的重要前瞻性指标。建议设置技术清单，采用关键字识别方式，按照有无具体项目实践进行定性分档评价，以体现不同技术成熟度和推进阶段的差异。
C53: 数字化赋能 | D53: 企业在智能制造方面的相关表现，包括人工智能应用、数字化工厂、工业互联网、物联网等。 | V53: "数字化赋能"从新质生产力应用视角反映企业智能制造与数字化转型的实践情况，包括人工智能应用、数字化工厂、工业互联网等领域，既是提升生产效率和降低能耗的重要手段，也是支撑能源管理和碳排放精准监测的技术基础。建议采用关键字识别方式，对企业披露的数字化智能化技术实践情况进行定性分档评价。
C54: 产品结构优化 | D54: 企业通过调整产品类型与生产结构，用更高性能、更高附加值、更低碳的产品替代高消耗、低性能、低附加值的传统产品。主要包括高端产品布局与质量奖等。 | V54: "产品结构优化"集中反映企业通过调整产品结构、提高高端产品占比和质量认证水平，实现从低附加值、高能耗产品向高性能、绿色化产品的转型升级。该指标能够从产品维度综合评价企业转型的市场成效，建议采用关键字识别方式进行定性评价，重点关注企业高端产品比例、绿色认证及质量荣誉等维度的综合表现。
C55: 废钢回收率 | D55: 衡量企业利用废钢资源的效率，包括内部回收和社会回收的废钢量占总粗钢产量的比例。 | F55: 3. 资源循环利用： 3.3 废钢回收加工配送 | G55: 第四十条 企业应当披露与特定业务模式、活动或者表明企业所处行业的其他共同特征相关的行业特定指标。 | H55: 一（一）3.投资活动要在《河北省钢铁行业转型金融支持经济活动目录（2025年版）》范围内（目录中包含废钢回收加工配送活动） | K55: 《产业结构调整指导目录（2024年本）》：《目录》在鼓励类中增加了黑色金属矿山开采和废钢回收、拆解、除油、加工、分类、配送一体化等方向，鼓励企业开展铁矿山开发和废钢回收加工，提升钢铁产业链资源保障水平，补足资源短板。 《再生材料应用推广行动方案》二、提升再生材料供给保障能力 （一）增强再生钢铁供应保障能力。鼓励在电炉钢产能集中区 域建设大型废钢加工配送中心，推动废钢铁回收、拆解、加工、配送一体化发展，提高废钢铁分类分级水平，推动废钢铁资源高效回收利用。鼓励有条件的钢铁企业对现有高炉－转炉炼钢进行工艺改造，有序发展全废钢电弧炉短流程炼钢，加强优质再生钢铁生产供应，探索建立从回收加工到生产冶炼的全流程溯源体系。 | R55: 1 （1）废物产生的废物量，（2）产生的危险废物百分比，（3）废物回收百分比 3 该实体应披露（3）产生的废物中已回收利用的质量百分比，以公吨为单位。 4 企业应披露用于定义废物、危险废物和可回收废物的框架，以及根据每个适用框架定义的相关数量和百分比。 | T55: 来源：24年可持续发展报告、24年年度报告（近三年数据） 附录 1 主要数据指标：循环经济-废钢回收量：2024年1,074万吨 公司年报：产销量情况分析表-生产量合计 | U55: 没有披露，只披露了一家子公司从社会回收的废钢比例 | V55: 废钢回收率是衡量企业资源循环利用效率的重要指标，直接反映企业在原料端的绿色化程度。提高废钢利用比例是钢铁行业实现减碳的重要路径之一，与电炉短流程炼钢密切相关，且在多个行业政策文件中均有明确要求。企业通常具备相关披露基础，数据可比性较好，建议保留该指标并采用定量评价方式，作为行业特定指标纳入评价体系。
A56: 未来潜力 | B56: 产业布局 | C56: 数智化布局 | D56: 核心含义：企业在智能制造、数字化工厂、工业互联网、物联网上的规划。 例子：建设智能工厂、数字化物流系统、能源管理系统。 | F56: 7. 数字化赋能 7.1高级计划排程技术 7.2加热炉智能燃烧系统 7.3煤气预测与调度优化 7.4高炉数字孪生 7.5操作远程化、无人化、集控化技术 7.6产线智能化改造 | G56: 第十二条（一）业务模式当期和预期的变化，包括其应对气候相关风险和机遇的资源配置（如管理或者退出关于碳、能源或者水密集型业务的计划，因需求或者供应链变化导致的资源配置，通过资本支出或者额外研发支出进行业务发展所产生的资源配置，收购或者剥离等）。 | H56: 一（一）3.投资活动要在《河北省钢铁行业转型金融支持经济活动目录（2025年版）》范围内（目录中包含产线智能化改造、高炉数字孪生、数字智能供电、智慧能源管理系统等技术） | I56: 第四十二条（四）科技创新成果及其应用对推动发展新质生产力的作用，以及对经济、社会、环境和利益相关方的影响等。 | J56: 工业和信息化部《钢铁企业规范条件（2025年版）》中智能化引领指标：积极推进数字化转型和智能化升级，落实《钢铁行业数字化转型实施指南》，开展智能制造能力成熟度评估评价，开展场景化、图谱化数字化转型，参与制定钢铁行业智能制造、数字化转型领域标准，创建智能工厂，参考《智能制造典型场景参考指引》《工业互联网与钢铁行业融合应用参考指南》，创新典型应用场景。 | K56: 《绿色金融支持项目目录（2025 年版）》：重点工业行业绿色低碳转型，针对钢铁、有色金属、石化化工、建材等高碳排行业，从节能降碳改造和能效提升、工艺改进和流程优化以及数字化、智能化升级三大路径支持工业领域低碳转型，并严格要求单位产品能耗指标值达到最新版《工业重点领域能效标杆水平和基准水平》（2023年版）规定的相应行业产品能效标杆水平。 《钢铁行业稳增长工作方案（2025—2026年）》：加快数字化转型。落实《钢铁行业数字化转型实施指南》，研究制定钢铁行业数字化转型水平评估标准，开展数字化转型评估诊断，培育数字化转型典型场景、标杆工厂、标杆企业。推动“人工智能+钢铁行业”发展，支持优势企业、科研院所、高校等建立数据资源节点，建设高质量数据集；加快推进工艺装备智能化适配性改造，以应用场景为牵引、通用大模型为底座、冶金机理为基础同步推进通用垂直大模型和场景小模型应用。加快推动钢铁行业重点企业工业操作系统更新替代。 关于促进钢铁工业高质量发展的指导意见 工信部联原〔2022〕6号：（十）大力发展智能制造。开展钢铁行业智能制造行动计划，推进5G、工业互联网、人工智能、商用密码、数字孪生等技术在钢铁行业的应用，在铁矿开采、钢铁生产领域突破一批智能制造关键共性技术，遴选一批推广应用场景，培育一批高水平专业化系统解决方案供应商。开展智能制造示范推广，打造一批智能制造示范工厂。建设钢铁行业大数据中心，提升数据资源管理和服务能力。依托龙头企业推进多基地协同制造，在工业互联网框架下实现全产业链优化。鼓励企业大力推进智慧物流，探索新一代信息技术在生产和营销各环节的应用，不断提高效率、降低成本。构建钢铁行业智能制造标准体系，积极开展基础共性、关键技术和行业应用标准研究。 | T56: 数字化转型水平 来源：公开信息，关键字“两化融合管理体系认证” 人工智能应用 来源：24年可持续发展报告-深化智慧制造，加快基于机器学习的数智化转型 智能制造成熟度 来源：无 智能制造标准 来源：24年可持续发展报告-宝钢股份持续探索与供应商及其他行业引领者的战略合作，充分发挥自身技术和创新优势。我们积极参与行业交流与分享，通过参与行业标准制定、开展行业伙伴战略合作以及推进产学研合作，助力钢铁工业高质量发展。宝钢股份参与《钢铁企业 ( 超低排放 ) 无组织颗粒物排放源清单编制技术指南》与《钢铁企业 ( 超低排放 ) 无组织颗粒物排放源监测监控系统技术要求》标准的编制并完成发布。 智能制造示范 来源：工业和信息化部https://www.miit.gov.cn/jgsj/zbys/wjfb/art/2025/art_a5307d7932024d56bf3be162b2ed065b.html、工业互联网试点示范名单等等。/24年可持续披露报告-2024 年，宝钢全面启动智慧制造战略，致力于在钢铁行业中树立智能工厂的国家标杆。宝钢股份宝山基地电工钢全业务要素协同智能工厂、东山基地超高强钢精益柔性生产智能工厂成功入选、获评首批国家卓越级智能工 厂。 | U56: 数字化转型水平 来源：公开信息，关键字“两化融合管理体系认证”-无 人工智能应用 来源：24年可持续发展报告-组织落实2024年人工智能 推进工作：公司结合特钢多品种小批量、工艺流程复杂、产品技术含量高等 特点，确定13项人工智能核心项目。同时，公司组建以特钢技术人员为主的 专业推进组，并携手百度、阿里等科技领军企业，成立了人工智能联合攻关团队，共同为技术突破提供坚实支撑 智能制造成熟度 来源：。2024年，兴澄特钢通过智能制造能力成熟度4级评估 智能制造标准 来源：24年可持续发展报告-主持制定团体标准2项，参与制定国际标准、行业标准、铁路标准各1项。中信泰富特钢参与审定中钢协团体标准“低碳排放钢评价方法”，助力价值链低碳转型 智能制造示范 来源：24年可持续发展报告-；大冶特钢获评“工信部2024数字领航企业”、；青岛特钢获评全国首批卓越级智能工厂；青岛特钢、扬州特材两大案例成功入选工信部“钢铁行业重点场景数字化转型典型案例”；靖江特钢、扬州特材入选江苏省工业互联网平台名单。 | V56: 在报告梳理过程中发现，前期在"数智化布局"中分别设置的"数字化转型水平"、"智能制造成熟度"、"智能制造标准"和"智能制造示范"四个指标，存在数据缺失、口径不统一和横向可比性不足等问题，独立评价的操作性有限。因此建议删除"数智化布局"模块，将相关内容统一整合为"数字化赋能"，通过《转型金融支持经济活动目录（钢铁行业）》所涵盖的数字化赋能技术关键字，对企业在智能制造方面的实践情况进行综合定性评价，兼顾覆盖范围和指标精简性。
C57: 高端化布局 | D57: 核心含义：企业产品结构升级、高附加值钢材研发、国际市场开拓。 例子：高强钢、汽车用钢、航空航天用钢生产线。 | F57: 9、产品结构优化 9.1 开发高强高韧、耐蚀耐磨、轻量化、长寿命的钢铁绿色设计产品 | G57: 第十二条（一）业务模式当期和预期的变化，包括其应对气候相关风险和机遇的资源配置（如管理或者退出关于碳、能源或者水密集型业务的计划，因需求或者供应链变化导致的资源配置，通过资本支出或者额外研发支出进行业务发展所产生的资源配置，收购或者剥离等）。 | H57: 一（一）3.投资活动要在《河北省钢铁行业转型金融支持经济活动目录（2025年版）》范围内（目录中包含开发高强高韧、耐蚀耐磨、轻量化、长寿命的钢铁绿色设计产品） | J57: 工业和信息化部《钢铁企业规范条件（2025年版）》中高端化引领指标：（一）高端化。强化科技创新能力培育，建立科研机构，加大研发投入，持续提升企业工艺技术和产品创新能力，注重标准制修订和知识产权保护，强化企业质量品牌建设，积极培育制造业单项冠军企业。 | K57: 《钢铁行业稳增长工作方案（2025—2026年）》：增强高端产品供给能力。聚焦高端装备、核心基础零部件等领域所需高性能轴承钢、齿轮钢、高温合金、工模具钢等关键钢材，组织钢铁企业联合上下游企业、高校、科研院所等开展产业链协同攻关。持续发挥船舶与海工、超超临界等新材料重点平台作用，加快产品应用验证和迭代升级。 《钢铁行业稳增长工作方案（2025—2026年）》：促进国际化发展。落实《关于应征国内环节税货物出口优化服务规范管理有关事项的公告》要求。强化钢铁产品出口管理，维护出口竞争秩序。开展高技术含量钢铁产品界定工作，优化钢铁出口产品结构。推动形成互相认可的产品标准、碳足迹核算体系。支持企业遵循国际贸易规则，依法依规开展钢铁产品国际贸易，融入国际供应链体系，提高国际竞争力。加强与共建“一带一路”国家及地区产业协作，引导钢铁产品与装备、技术、服务等协同走出去 | T57: 国际市场 来源：24年年度报告（近三年数据）—出口销量 606.7 万吨，产销量情况分析表-销售量 5,159万吨 高端产品布局 来源：24年可持续发展报告-公司提出“2+2+N”产品战略，即以汽车用钢和硅钢为核心，长材和厚板为重点，拓展其他产品领域，全面布局精品长材与高端厚板两大战略产品。 质量奖 来源：24年可持续发展报告/公司年报/公开信息 单项冠军 来源：全国/各省工业和信息化厅 | U57: 国际市场 来源：24年年度报告（近三年数据）-。2024 年公司实现钢材销量1889.0万吨，其中出口销量220.2万吨； 高端产品布局 来源：24年年度报告-中信泰富特钢《（汽车用）特殊钢PCR》再获行业殊荣，树立低碳高质量发展典范；天津钢管——突破CCUS抗腐管线管技术，为管材应用树立新标杆 质量奖 来源：24年可持续发展报告/公司年报/公开信息 单项冠军 来源：全国/各省工业和信息化厅/24年可持续披露报告-青岛特钢——“钢帘线用硬线材”荣登国家制造业单项冠军榜单，创新引领产业链绿色转型与低碳突破；青岛特钢、天津钢管分别荣获工信部制造业单项冠军 | V57: 前期在"高端化布局"中设置"国际市场"和"单项冠军"两个指标，初衷是从国际竞争力和专项认定角度综合反映企业高端化发展水平。但进一步梳理后发现，两个指标与低碳转型绩效的关联度较弱，且数据完整性和可比性均有不足，难以作为稳定评价指标使用。因此建议删除上述两个指标，仅保留"高端产品布局"和"质量奖"内容，统一整合至"产品结构优化"模块，通过关键字识别进行聚焦性定性评价。
C58: 绿色低碳布局 | D58: 核心含义：企业未来在绿色生产、低碳产品、节能减排设施上的投资计划和产能布局。 例子：增加绿色钢材产线、建设氢冶金试验装置、绿色原料采购基地。 | E58: 转型金融是指为减缓气候变化、推动高碳排放领域向低碳排放或净零排放转型的经济活动和企业提供的金融服务。 | F58: 钢铁行业转型金融标准的目的就是帮助行业绿色低碳化 | G58: 第十二条（一）业务模式当期和预期的变化，包括其应对气候相关风险和机遇的资源配置（如管理或者退出关于碳、能源或者水密集型业务的计划，因需求或者供应链变化导致的资源配置，通过资本支出或者额外研发支出进行业务发展所产生的资源配置，收购或者剥离等）。 第二十七条（五）资本配置——针对气候相关风险和机遇发生的资本支出、融资或者投资金额。 | H58: 一（一）3.投资活动要在《河北省钢铁行业转型金融支持经济活动目录（2025年版）》范围内（目录中包含开发高强高韧、耐蚀耐磨、轻量化、长寿命的钢铁绿色设计产品） | J58: 工业和信息化部《钢铁企业规范条件（2025年版）》中绿色化引领指标：绿色化。积极推进绿色、低碳发展，推广应用先进绿色低碳工艺技术，建设应用工业绿色微电网，开展节能降碳技术改造，争创环保绩效 A 级、能效“标杆水平”。开发生产绿色产品，创建绿色工厂，鼓励培育创建“无废企业”。鼓励企业关停退出烧结机、焦炉、高炉等传统设备，转型发展低碳炼铁、电炉炼钢。鼓励开展产品碳足迹（CFP）、环境产品声明（EPD）、产品全生命周期评价（LCA）及环境、社会和公司治理（ESG）等工作。 | K58: 《钢铁行业稳增长工作方案（2025—2026年）》：推进绿色低碳改造。推进落实《关于推进实施钢铁行业超低排放的意见》，2025 年底前全面完成超低排放改造目标任务。支持钢铁企业实施能效提升改造，推进清洁能源替代。推动开展钢铁行业减污降碳协同增效技术路径研究。支持氢冶金等低碳共性技术攻关，加快推进绿电、绿氢、纯氢冶金一体化工艺技术和装备中试验证和产业化。推动行业企业建设一批数字化能碳管理中心。加快构建钢铁产品碳足迹核算标准体系，加强碳计量管理，提高碳核算数据质量，做好纳入全国碳排放权交易市场后的配额交易与清缴工作。 关于促进钢铁工业高质量发展的指导意见 工信部联原〔2022〕6号：深入推进绿色低碳。落实钢铁行业碳达峰实施方案，统筹推进减污降碳协同治理。支持建立低碳冶金创新联盟，制定氢冶金行动方案，加快推进低碳冶炼技术研发应用。支持构建钢铁生产全过程碳排放数据管理体系，参与全国碳排放权交易。开展工业节能诊断服务，支持企业提高绿色能源使用比例。全面推动钢铁行业超低排放改造，加快推进钢铁企业清洁运输，完善有利于绿色低碳发展的差别化电价政策。积极推进钢铁与建材、电力、化工、有色等产业耦合发展，提高钢渣等固废资源综合利用效率。大力推进企业综合废水、城市生活污水等非常规水源利用。推动绿色消费，开展钢结构住宅试点和农房建设试点，优化钢结构建筑标准体系；建立健全钢铁绿色设计产品评价体系，引导下游产业用钢升级。 | T58: 可再生能源资产配置 来源：24年可持续发展报告（近三年)-厂内可再生能源装机累计容量 419MW ；24年年度报告（近三年)-固定资产149,566,709,306.48元 超低排放改造 来源：24年可持续发展报告-宝钢股份持续推进废气排放设备升级工作，搭建了废气处理设备提升改造体系，牢筑废气治理屏障，支撑公司实现全面 的超低排放。2024 年，宝钢股份深入开展设备升级工作，对所有设备的运行情况进行全面的评估，持续提升设备运行效率， 将超低排放管理理念融入生产制造环节。 绿色制造 来源：全国/各省工业和信息化部官方发布的绿色制造单位名单（绿色工厂和绿色供应链管理企业名单） 极致能效 来源：中国钢铁工业协会官网发布的“极致能效工程能效标杆示范企业”或“双碳最佳实践能效标杆示范厂”名单 环境管理 来源： 24年可持续发展报告-宝钢股份生产基地全获 ISO 50001能源管理体系认证 | U58: 可再生能源资产配置 来源：24年可持续发展报告-可再生能源装机容量：光伏185兆瓦，风电12兆瓦。 超低排放改造 来源：23年可持续发展报告-截至2024年底，兴澄特钢、青岛特钢、天津钢管已完成全流程超低排放改造，同时被评定为环保绩效“A级企 业”，大冶特钢已开展全流程超低排放改造工作，努力实现创A绩效目标。 绿色制造 来源：24年可持续发展报告-兴澄特钢、大冶特钢、青岛特钢、扬州特材被列入工信部“绿色工厂”名单 极致能效 来源：中国钢铁工业协会官网/24年可持续披露报告-兴澄特钢、大冶特钢、青岛特钢、天津钢管入选“双碳最佳实践能效标杆示范厂”培育企 环境管理 来源：24年可持续披露报告-中信泰富特钢旗下各子公司100%通过ISO 50001能源管理体系认证；。公司不断强化环境管理体系建设，旗下各子公司100%通过了ISO 14001 环境管理体系认证； | V58: 前期在"绿色低碳布局"中设置"可再生能源资产配置"、"绿色制造"和"环境管理"三个指标，旨在全面反映企业绿色低碳布局情况。但进一步梳理后发现，上述指标数据缺失较为严重，横向可比性不足，且与转型实际表现的直接关联度有限。因此建议删除该子模块，将其中有价值的内容分别纳入已有指标框架：将"超低排放改造"整合至"环保减排改造"，将"极致能效"整合至"系统能效提升"，通过关键字识别进行评价，在保持内容覆盖的同时避免冗余。

Sheet 框架对标结果
A1: 一级指标 | B1: 二级指标 | C1: 三级指标 | D1: 关键字说明 | E1: 人民银行转型金融要求 | F1: 人民银行钢铁行业转型金融标准 | G1: 企业可持续披露准则第1号—气候 | H1: 河北省钢铁转型金融指引 | I1: 沪深北披露指引 | J1: 工信部《钢铁行业规范条件（2025年版）》 | K1: 其他国内政策 | L1: IIGCC | M1: ICMA气候转型债券指引（CTB）和气候转型融资手册（CTF） | N1: TPI | O1: 惠誉常青 | P1: TCFD | Q1: TPT | R1: SASB | S1: GFANZ
A2: 目标与战略 | B2: 目标和承诺 | C2: 碳中和目标 | D2: 企业承诺转型目标与国家碳达峰碳中和目标一致，服务于国家碳达峰碳中和目标；制定减排目标是指企业制定短期（如2024—2025年）、中期（2026—2030年）和长期（至2060年）的目标，且目标符合所在行业的先进性水平 | E2: ✔ | G2: ✔ | H2: ✔ | L2: ✔ | M2: ✔ | N2: ✔ | O2: ✔ | P2: ✔ | Q2: ✔ | R2: ✔ | S2: ✔
C3: 碳达峰目标 | D3: 企业承诺转型目标与国家碳达峰碳中和目标一致，服务于国家碳达峰碳中和目标；制定减排目标是指企业制定短期（如2024—2025年）、中期（2026—2030年）和长期（至2060年）的目标，且目标符合所在行业的先进性水平 | E3: ✔ | G3: ✔ | H3: ✔ | L3: ✔ | M3: ✔ | N3: ✔ | O3: ✔ | P3: ✔ | Q3: ✔ | R3: ✔ | S3: ✔
C4: 其他环境目标 | D4: 指除碳达峰 / 碳中和目标之外，用于支撑低碳转型路径落地的能效、资源、污染与过程优化类目标。 可识别目标类型包括但不限于： 1. 能效提升（如吨钢综合能耗下降） 2. 能源结构优化（如清洁电力占比、余热利用） 3. 污染物减排（SO₂ / NOx / PM / VOCs） 4. 水资源管理（吨钢取水量、回用率） 5. 资源循环与废弃物（废钢比、固废利用率） 6. 工艺与流程优化（短流程占比、关键工序效率） | E4: ✔ | G4: ✔ | I4: ✔ | L4: ✔ | M4: ✔ | N4: ✔ | Q4: ✔
B5: 战略和规划 | C5: 转型规划 | D5: 企业制定明确的转型路线图、行动方案或分阶段规划 | E5: ✔ | G5: ✔ | H5: ✔ | I5: ✔ | L5: ✔ | M5: ✔ | N5: ✔ | O5: ✔ | P5: ✔ | Q5: ✔ | R5: ✔ | S5: ✔
C6: 其他战略 | D6: 企业如尚未制定专门的转型规划，是否已建立低碳与可持续治理的制度与行动框架 | I6: ✔ | S6: ✔
A7: 实施保障 | B7: 治理 | C7: 治理架构 | D7: 企业围绕低碳/绿色/可持续/转型/ESG议题建立的治理层级完整性与权责清晰度 | E7: ✔ | G7: ✔ | H7: ✔ | I7: ✔ | L7: ✔ | M7: ✔ | N7: ✔ | P7: ✔ | Q7: ✔ | S7: ✔
B8: 风险管理 | C8: 气候风险管理体系 | D8: 1. 全面风险嵌入（ERM化）：将气候风险由单一环保议题上升为公司级战略风险，实质性嵌入ERM及全价值链决策流程。 2. 治理架构多级化：构建“董事会—管理层—执行层”的三级或四级垂直穿透式治理架构。 3. 管控手段数智化：建设并运行“智能气候风险管理信息系统”或数字化管理平台，实现风险数据的常态化监测与可视化。 4. 责任落实绩效化：形成“目标—执行—考核—追责”闭环，并将气候/碳相关指标刚性挂钩领导班子或管理层年度经营业绩评价。 | G8: ✔ | H8: ✔ | I8: ✔ | L8: ✔ | N8: ✔ | P8: ✔ | R8: ✔
C9: 气候相关风险和机遇 | D9: 1. 风险与机遇识别完整性：同时识别转型风险与实体风险，涵盖政策/法律、技术、市场、供应链、声誉、急性与慢性物理风险等；同时识别低碳产品、能源结构优化、政策支持等机遇。 2. 时间维度清晰性：在短期（1–2年）、中期（3–6年）、长期（7年及以上）不同时间框架下开展识别与评估。 3. 财务影响关联性：识别风险和机遇对成本、收入、投资、融资、信用风险等财务事项的影响。 4. 量化深度差异：区分定性判断、间接量化（环保投入、节能降本）与直接量化（营收变化、成本变化、溢价比例、履约成本节约等）。 | G9: ✔ | I9: ✔ | L9: ✔ | M9: ✔ | N9: ✔ | P9: ✔
C10: 气候压力测试 | D10: 1. 开展情况：明确披露已开展气候情景分析或压力测试。 2. 情景设置特征：情景覆盖转型风险与实体风险，包含中长期时间尺度。 3. 方法论来源：参考国际或行业权威情景与框架（如 IFRS S2、IEA、IPCC、钢铁行业低碳转型情景）。 4. 结果应用：情景分析结果用于评估对经营、成本、收入、资产或融资的潜在影响，并支撑风险管理或战略判断。 | G10: ✔ | H10: ✔ | I10: ✔ | L10: ✔ | N10: ✔ | P10: ✔
C11: 环境行政处罚（负向指标） | D11: 衡量企业在战略转型期（如前/后3年）因环境违法行为受到地方监管部门行政处罚的严重程度。 | E11: ✔ | G11: ✔ | H11: ✔ | I11: ✔ | J11: ✔
C12: 安全生产行政处罚（负向指标） | D12: 衡量企业因违反安全生产法规受到处罚或发生生产安全责任事故的严重程度 | G12: ✔ | I12: ✔ | J12: ✔ | R12: ✔
C13: 失信事件管理（负向指标） | D13: 量化转型期企业面临的诉讼压力与现金流风险，案件常涉及合同（供应链）、劳动（安置）、金融（偿债）纠纷。 | G13: ✔ | I13: ✔ | J13: ✔
A14: 转型表现 | B14: 碳排放表现 | C14: 碳价敏感度 | D14: 采用季度或年度报告等口径中披露的EBITDA（税息折旧及摊销前利润）、市场碳价等业务、财务数据，形成理论碳成本占企业经营利润的比例，衡量企业盈利对碳价（尤其是潜在或未来碳价格）的敏感程度。 | G14: ✔ | K14: ✔
C15: 碳排放披露情况 | D15: 1. 核心词：范围1、直接排放、范围2、能源间接排放、范围3、价值链排放 2. 范围3类别词：类别1、采购商品、上下游运输、差旅、员工通勤、废弃物 | E15: ✔ | G15: ✔ | H15: ✔ | I15: ✔ | K15: ✔ | L15: ✔ | N15: ✔ | R15: ✔
C16: 物理碳排放强度 | D16: 单位粗钢产量所产生的范围一和范围二的碳排放量 | E16: ✔ | G16: ✔ | H16: ✔ | K16: ✔ | L16: ✔ | M16: ✔ | O16: ✔ | P16: ✔ | R16: ✔
C17: 营收碳排放强度 | D17: 单位营业收入所产生的范围一和范围二的碳排放量 | E17: ✔ | G17: ✔ | M17: ✔
B18: 其他环境表现 | C18: 可再生能源占比 | D18: 自发可再生能源电量，是指企业在自身生产经营边界内，通过自建或控股的可再生能源发电设施，所产生并被企业自身消费的电力。 能源消耗总量：企业当期披露的能源消耗总量（单位 MWh） | F18: ✔ | G18: ✔ | H18: ✔ | I18: ✔ | K18: ✔ | M18: ✔ | R18: ✔
D19: 外购绿电包括： 绿电交易电量 绿证对应电量（如披露） 能源消耗总量：企业当期披露的能源消耗总量（单位 MWh） | G19: ✔ | R19: ✔
C20: 用水效率 | D20: 单位粗钢水消耗量，指企业在生产过程中对水资源的消耗情况 用水效率 = 当期总用水量 ÷ 当期粗钢产量 | E20: ✔ | G20: ✔ | H20: ✔ | I20: ✔ | J20: ✔ | R20: ✔
C21: 生物多样性 | D21: 企业在生物多样性保护方面表现，比如制度或组织架构建设、具体措施和实际成效，包括保护区域的生态恢复、物种多样性保护及生态环境修复等。 | E21: ✔ | G21: ✔ | H21: ✔ | I21: ✔
B22: 公正转型 | C22: 员工培训 | D22: 本指标用于评估企业是否关注并投入员工能力建设，尤其是在转型相关技能方面。 考虑到企业披露口径差异较大，本指标采用是否类累加赋分方式，不对不同披露口径进行强制可比性要求。 | E22: ✔ | G22: ✔ | H22: ✔ | I22: ✔ | Q22: ✔ | S22: ✔
C23: 稳就业与促就业 | D23: 衡量企业在转型过程中是否避免通过大规模裁员转嫁成本，并通过稳定或扩大就业规模，体现对劳动者和社会的责任承担。 | E23: ✔ | G23: ✔ | H23: ✔ | I23: ✔ | Q23: ✔
C24: 劳动纠纷（负向指标） | D24: 衡量因转型调整（如岗位重组、合同解除）引发的、并已进入正式法律或仲裁程序的劳资纠纷数量与严重性。 案由关键字：船员劳务合同纠纷、辞退争议、经济性裁员争议、劳动合同纠纷、劳动争议、劳务合同纠纷、离退休人员返聘合同纠纷、确认劳动关系纠纷、社会保险纠纷、职工破产债权确认纠纷、追索劳动报酬纠纷 | E24: ✔ | G24: ✔ | H24: ✔ | I24: ✔
C25: 重大负面舆情（负向指标） | D25: 系统性量化企业因“公正转型”措施失当，在公开舆论场引发的负面关注与声誉风险。 关键字： 劳工权益类：转型裁员、安置纠纷、买断工龄、再培训缺失、拖欠补偿金、员工抗议、工会协商破裂； 社区影响类：关停冲击、地方经济衰退、税收锐减、产能退出、搬迁争议、环境遗留问题 过程公正类：决策黑箱、缺乏沟通、无视职工意见、突击式关停、政策套利 | E25: ✔ | G25: ✔ | H25: ✔
B26: 研发与创新 | C26: 研发投入占比 | D26: 以“研发投入 / 研发费用 / 研究与开发支出”等为核心关键词，结合财务报表附注中“研发支出”相关披露，提取企业当期研发投入金额；分母采用“营业收入”口径计算研发投入占比。 | G26: ✔ | H26: ✔ | I26: ✔ | J26: ✔ | K26: ✔
C27: 节能技改投资占比 | D27: 以“节能技改 / 技术改造 / 节能改造/超低排放改造投资”等关键词识别企业披露的节能相关技改投资金额，结合“投资金额 / 固定资产投资 / 资本性支出”等表述进行提取；分母统一采用当期营业收入，计算节能技改投资占比。 | E27: ✔ | F27: ✔ | G27: ✔ | H27: ✔ | I27: ✔ | K27: ✔ | M27: ✔ | N27: ✔ | O27: ✔
C28: 环保投入金额占比 | D28: 以“环保投入 / 环保投资 / 环境保护支出”等关键词为核心，识别企业披露的污染防治、环保设施及相关投入金额；分母采用营业收入，计算环保投入占比。 | E28: ✔ | H28: ✔ | I28: ✔
B29: 行业特定 | C29: 超低排放改造进程 | D29: 超低排放改造进程=（SOx排放量+NOx排放量+颗粒物排放量）/当年粗钢产量​ 超低排放改造是指对工业生产过程中的重点行业（如火电、钢铁、水泥、焦化等）实施全面的大气污染治理升级改造，旨在使企业生产过程中产生的大气污染物排放浓度达到极低水平，接近或低于天然气燃气轮机组的排放标准。 具体而言，超低排放改造的核心目标是通过技术手段，对生产环节中的有组织排放（如烟囱排放）、无组织排放（如物料储存、输送过程中的逸散）以及运输环节的污染物排放进行严格控制，实现颗粒物、二氧化硫、氮氧化物等主要污染物排放浓度显著降低。 | E29: ✔ | F29: ✔ | G29: ✔ | H29: ✔ | I29: ✔ | J29: ✔ | K29: ✔ | R29: ✔
C30: 系统能效提升 | D30: 企业通过全流程深度优化与多种相关技术手段协同提升能源利用效率，从而降低单位产出能耗和碳排放，最终使能源利用效率达到行业最优甚至接近极限水平。包括相关节能降碳技术与“极致能效”称号。 | F30: ✔ | G30: ✔ | H30: ✔ | K30: ✔ | R30: ✔
C31: 环保减排改造 | D31: 企业通过系统性工程改造与全国全过程控制，使污染物排放水平大幅低于常规标准，实现钢铁等高排放行业的深度环境治理与绿色转型。主要包括超低排放改造完成情况。 | F31: ✔ | G31: ✔ | H31: ✔ | K31: ✔ | R31: ✔
C32: 冶炼技术突破 | D32: 企业通过开发和应用前沿性关键低碳冶炼技术，改变传统高碳生产路径。包括氢冶金、CCUS、电炉短流程炼钢等前沿技术。 | F32: ✔ | G32: ✔ | H32: ✔ | K32: ✔ | R32: ✔
C33: 数字化赋能 | D33: 企业在智能制造方面的相关表现，包括人工智能应用、数字化工厂、工业互联网、物联网等。 | F33: ✔ | G33: ✔ | H33: ✔ | K33: ✔ | R33: ✔
C34: 产品结构优化 | D34: 企业通过调整产品类型与生产结构，用更高性能、更高附加值、更低碳的产品替代高消耗、低性能、低附加值的传统产品。主要包括高端产品布局与质量奖等。 | F34: ✔ | G34: ✔ | H34: ✔ | K34: ✔ | R34: ✔
C35: 废钢回收率 | D35: 衡量企业利用废钢资源的效率，包括内部回收和社会回收的废钢量占总粗钢产量的比例。 | F35: ✔ | G35: ✔ | H35: ✔ | K35: ✔ | R35: ✔
A36: 未入选指标
A37: 一级指标 | B37: 二级指标 | C37: 三级指标 | D37: 关键字说明
A38: 实施保障 | B38: 转型举措 | C38: 自身减排措施 | D38: 企业为实现低碳转型与应对气候变化，当前已实施或计划实施的关键减排与转型措施，包括发生在企业自身运营与资产层面的直接措施。 | E38: ✔ | G38: ✔ | I38: ✔ | L38: ✔ | N38: ✔ | O38: ✔ | Q38: ✔ | S38: ✔
C39: 供应链减排措施 | D39: 企业为实现低碳转型与应对气候变化，当前已实施或计划实施的关键减排与转型措施，包括通过价值链协同实现的间接措施。 | E39: ✔ | G39: ✔ | I39: ✔ | L39: ✔ | Q39: ✔ | R39: ✔ | S39: ✔
B40: 治理 | C40: 薪酬激励 | D40: ESG/可持续发展/低碳/转型目标是否通过绩效与薪酬机制转化为真实的管理激励与约束 | E40: ✔ | G40: ✔ | L40: ✔ | N40: ✔ | O40: ✔ | P40: ✔ | Q40: ✔ | S40: ✔
A41: 转型表现 | B41: 财务表现 | C41: 绿色低碳转型债券 | D41: 公司在近五年内为绿色低碳转型相关债券发行人，且披露相关债券运用情况 | L41: ✔ | M41: ✔ | N41: ✔
C42: 吨产品净收入 | D42: 按利润表、季度或年度报告等口径中披露的钢铁产量（吨）、归属于上市公司股东的扣除非经常性损益的净利润（元）等业务和财务数据，考虑自身历史和行业水平分析吨钢净利润变化情况 | G42: ✔ | H42: ✔ | P42: ✔
C43: 高附加值产品竞争力 | D43: 采用季度或年度报告等口径中披露的钢铁业务收入、钢铁销售量等业务、财务数据，通过吨钢销售均价（元/吨）得到企业的销售均价相对于行业均价的差距，反应市场对该企业高附加值产品的溢价支付意愿。 | F43: ✔ | K43: ✔
B44: 碳排放表现 | C44: 碳排放效率 | D44: 碳减排效率用于衡量企业在实现营业收入增长的同时，其碳排放减少与经济增长之间的协同程度，反映企业“低碳增长”的质量。 | G44: ✔ | I44: ✔
C45: 自身减排速度 | D45: 企业当年的“同比减排幅度”，相对于行业当年的“平均同比减排幅度”，处在什么位置。 | G45: ✔ | H45: ✔ | I45: ✔ | O45: ✔ | R45: ✔
B46: 能源使用 | C46: 能耗强度/能耗达标 | D46: 能耗强度指标吨钢综合能耗，而能耗达标就是看单位产品能源消耗量是否满足国家及地方政府相关规定要求。 | F46: ✔ | G46: ✔ | H46: ✔ | J46: ✔ | K46: ✔ | R46: ✔
B47: 行业特定 | C47: 煤炭消耗比例 | D47: 企业在生产过程中，煤炭（包含焦炭、动力煤、喷吹煤等）提供的能量占综合能源消耗总量的比例。该比例下降，意味着企业正在使用天然气、氢能或绿电来替代煤炭。这是能源结构清洁化的直接体现。 | F47: ✔ | G47: ✔ | H47: ✔ | K47: ✔ | R47: ✔
C48: 入炉球团矿比例 | D48: 钢铁行业的长流程（炼铁）环节有“烧结”和“球团”这两个工序。 传统的“烧结”工序是钢铁厂最大的污染源和高耗能环节之一；而“球团”工序相对更清洁、能耗更低。提高球团矿比例（降低烧结矿比例），可以直接降低炼铁前工序的能耗和碳排放。 | F48: ✔ | G48: ✔ | H48: ✔ | K48: ✔
C49: 高炉燃料比 | D49: 高炉燃料比是指每炼1吨合格生铁所消耗的入炉燃料总量，通常以千克/吨（kg/t）为单位。它综合反映了高炉冶炼过程中燃料的消耗水平，是衡量高炉炼铁效率和能源利用效果的关键指标。 | F49: ✔ | G49: ✔ | H49: ✔ | K49: ✔
C50: 余能余热回收 | D50: 钢铁行业余能余热是指在钢铁生产过程中，除满足生产工艺本身需求外剩余的热能和能量，主要包括余热、余压、余气等形式。 余能余热的来源：高温烟气余热、冷却水余热、炉渣余热、煤气余能、余压能量 余能余热的利用方式：余热发电、余热供热、煤气综合利用、余热制冷 | F50: ✔ | G50: ✔ | H50: ✔ | K50: ✔
C51: 电炉钢产量占比 | D51: 钢铁电炉钢属于短流程炼钢工艺。短流程炼钢以废钢为主要原料，通过电炉冶炼、精炼、连铸和轧制等工序生产钢材，省去了传统长流程炼钢中的焦化、烧结、高炉炼铁等环节，具有流程短、投资少、能耗低、碳排放少等优势。 | F51: ✔ | G51: ✔ | H51: ✔ | J51: ✔ | K51: ✔ | R51: ✔
C52: 违反产能置换（负面指标） | D52: 根据《钢铁行业产能置换实施办法》及相关政策要求，对于违反产能置换规定的企业，相关部门会采取公示、通报等措施进行公开曝光。例如，中央环保督察组在检查中发现企业存在违规产能问题后，会将问题企业及整改情况向社会公示，接受公众监督。此外，省级工业和信息化主管部门也会对违规企业的产能置换方案及整改情况在官方网站进行公示，公示期一般不少于15个工作日。 | E52: ✔ | J52: ✔ | K52: ✔
C53: 超低排放改造进程 | D53: 超低排放改造进程=（SOx排放量+NOx排放量+颗粒物排放量）/当年粗钢产量​ 超低排放改造是指对工业生产过程中的重点行业（如火电、钢铁、水泥、焦化等）实施全面的大气污染治理升级改造，旨在使企业生产过程中产生的大气污染物排放浓度达到极低水平，接近或低于天然气燃气轮机组的排放标准。 具体而言，超低排放改造的核心目标是通过技术手段，对生产环节中的有组织排放（如烟囱排放）、无组织排放（如物料储存、输送过程中的逸散）以及运输环节的污染物排放进行严格控制，实现颗粒物、二氧化硫、氮氧化物等主要污染物排放浓度显著降低。 | E53: ✔ | F53: ✔ | G53: ✔ | H53: ✔ | I53: ✔ | J53: ✔ | K53: ✔ | R53: ✔
B54: 水资源利用 | C54: 水资源回收利用率 | D54: 企业在生产过程中回用的水量占总用水量的比率，衡量企业是否通过技术手段有效回收和再利用水资源，减少对外部水资源的依赖 | E54: ✔ | G54: ✔ | H54: ✔ | I54: ✔ | K54: ✔
B55: 公正转型 | C55: 公益捐赠 | D55: 公益捐赠可以适当反映企业在转型过程中对社会公共利益与弱势群体的支持能力，是公正转型中“社会缓冲机制”的重要体现评估企业在公益捐赠上表现出的投入力度与行为稳定性，综合判断其社会承诺的财务实质性及长期可信度。
B56: 研发与创新 | C56: 科研平台 | D56: 是否具备相应资质的研发中心、技术中心、创新中心、重点实验室等企业科研机构。（自有、母公司或控股的钢铁企业亦可） | G56: ✔ | H56: ✔ | J56: ✔ | K56: ✔
C57: 专利情况 | D57: 以“专利数量、发明专利数量”等关键词为核心，识别分子；分母采用营业收入，计算每单位营收专利拥有量。 | G57: ✔ | H57: ✔ | J57: ✔
A58: 未来潜力 | B58: 产业布局 | C58: 数智化布局 | D58: 核心含义：企业在智能制造、数字化工厂、工业互联网、物联网上的规划。 例子：建设智能工厂、数字化物流系统、能源管理系统。 | F58: ✔ | G58: ✔ | H58: ✔ | J58: ✔ | K58: ✔
C59: 高端化布局 | D59: 核心含义：企业产品结构升级、高附加值钢材研发、国际市场开拓。 例子：高强钢、汽车用钢、航空航天用钢生产线。 | F59: ✔ | G59: ✔ | H59: ✔ | J59: ✔ | K59: ✔
C60: 绿色低碳布局 | D60: 核心含义：企业未来在绿色生产、低碳产品、节能减排设施上的投资计划和产能布局。 例子：增加绿色钢材产线、建设氢冶金试验装置、绿色原料采购基地。 | E60: ✔ | F60: ✔ | G60: ✔ | H60: ✔ | J60: ✔ | K60: ✔

Sheet 正向指标
A1: 一级指标 | B1: 二级指标 | C1: 三级指标 | D1: 关键字说明 | E1: 分值关系 | F1: 指标因子 | G1: 问题 | H1: 判断依据/计算公式 | I1: 分档 | J1: 对应分值 | K1: 空值处理 | L1: 数据长度 | M1: 必填 | N1: 获取频度 | O1: 数据粒度 | P1: 参考数据 | Q1: 技术校验规则 | R1: 业务校验规则 | S1: 数据来源 | T1: 数据来源接口 | U1: 备注 | V1: 比重系数
A2: 目标与战略（25分） | B2: 目标和承诺 | C2: 碳中和目标 | D2: 企业承诺转型目标与国家碳达峰碳中和目标一致，服务于国家碳达峰碳中和目标；制定减排目标是指企业制定短期（如2024-2025年）、中期（2026-2030年）和长期（至2060年）的目标，且目标符合所在行业的先进性水平 | E2: 相等 | F2: 中和年份承诺与覆盖度 | H2: 计算原始得分 = 基础分 × 范围系数 1. 基础分（时间维度） 若无目标或年份 > 2060：0 分 若年份 ≤ 2050：10 分 若 2050 < 年份 ≤ 2060： 基础分 = 10 − 0.4 × (年份 − 2050) （说明：每晚 1 年扣 0.4 分，2060 年得 6 分） 2. 范围系数 仅覆盖部分区域 / 子公司 / 单一工序范围1：0.5 仅覆盖部分区域 / 子公司 / 单一工序范围1+2：0.6 覆盖部分区域 / 子公司 / 单一工序范围1+2+3：0.7 覆盖全集团范围 1：0.8 覆盖全集团范围 1+2：1 覆盖全集团范围 1+2+3（含重要供应链）：1.2 对计算结果做0-12的分布 | I2: 0 | J2: 0 | K2: 适用规则A（强制-赋0） | S2: 公司可持续发展报告 | V2: 1
I3: (0, 3] | J3: 2.5
I4: (3, 6] | J4: 5
I5: (6, 9] | J5: 7.5
I6: (9, 12] | J6: 10
C7: 碳达峰目标 | D7: 企业承诺转型目标与国家碳达峰碳中和目标一致，服务于国家碳达峰碳中和目标；制定减排目标是指企业制定短期（如2024-2025年）、中期（2026-2030年）和长期（至2060年）的目标，且目标符合所在行业的先进性水平 | E7: 相等 | F7: 达峰年份承诺与覆盖度 | H7: 计算原始得分 = 基础分 × 范围系数 1. 基础分（时间维度，0–10 分） 无目标：0分 承诺年份 > 2030：3 分 承诺年份=2030，6分 承诺年份 ≤ 2025 或已明确达峰：10 分 2025 < 年份 ≤ 2030： 基础分 = 10 − 0.8 × (年份 − 2025) （说明：2030 年达峰得 6 分，每提前 1 年加 0.8 分） 2. 范围系数 仅覆盖部分区域 / 子公司 / 单一工序范围1：0.5 仅覆盖部分区域 / 子公司 / 单一工序范围1+2：0.6 覆盖部分区域 / 子公司 / 单一工序范围1+2+3：0.7 覆盖全集团范围 1：0.8 覆盖全集团范围 1+2：1 覆盖全集团范围 1+2+3（含重要供应链）：1.2 对计算结果做0-12的分布 | I7: 0 | J7: 0 | K7: 适用规则A（强制-赋0） | S7: 公司可持续发展报告、公开网络信息 | V7: 0.9
I8: (0, 3] | J8: 2.5
I9: (3, 6] | J9: 5
I10: (6, 9] | J10: 7.5
I11: (9, 12] | J11: 10
C12: 其他环境目标 | D12: 指除碳达峰 / 碳中和目标之外，用于支撑低碳转型路径落地的能效、资源、污染与过程优化类目标。 可识别目标类型包括但不限于： 1. 能效提升（如吨钢综合能耗下降） 2. 能源结构优化（如清洁电力占比、余热利用） 3. 污染物减排（SO₂ / NOx / PM / VOCs） 4. 水资源管理（吨钢取水量、回用率） 5. 资源循环与废弃物（废钢比、固废利用率） 6. 工艺与流程优化（短流程占比、关键工序效率） | E12: 相等 | F12: 企业制定的环境目标的结构完整性与目标质量 | H12: 公式：得分=目标数量得分(S)+目标质量得分(Q) S按企业覆盖的不同目标类型数量计分： 覆盖 0 类：S = 0 覆盖 1 类：S = 1 覆盖 2 类：S = 2 覆盖 3 类：S = 3 覆盖 ≥4 类：S = 4 Q对每一项目标按质量赋值 • 定性表述（无量化）：0.5 分 • 部分量化（有数值但无基准年或目标年）：1.0 分 • 完整量化（指标 + 基准年 + 目标年）：2.0 分 选取质量得分最高的 3 项目标，相加后Q满分 6 分 | I12: 0 | J12: 0 | K12: 适用规则D（补充-P50） | S12: 公司可持续发展报告 | V12: 0.1
I13: (0, 2] | J13: 2
I14: (2, 4] | J14: 4
I15: (4, 6] | J15: 6
I16: (6, 8] | J16: 8
I17: (8, 10] | J17: 10
B18: 战略和规划 | C18: 转型规划 | D18: 企业制定明确的转型路线图、行动方案或分阶段规划 | E18: 相等 | F18: 是否制定转型规划以及完善程度 | H18: 以下按单项累加赋分: 1、企业编制并披露正式的转型规划、转型战略或减排路径图 2、明确路径：披露覆盖短中长期的关键里程碑和实施路线图。 3、定量测算：对主要转型措施的预期减排量或减排贡献进行量化测算（tCO₂e、强度变化等）。 4、温控对标：明确说明转型路径与全球 2°C 目标或更先进的温控目标保持一致。 5、国家对标：转型目标或阶段性指标达到或优于国家相关部门发布的能效、排放或技术基准（如能效标杆、行业规范条件）。 6、国际先进性：说明所采用的方法或情景（如 IEA NZE、SBTi）。 7、自身减排措施：是否披露为实现低碳转型，当前已实施或计划实施的关键减排与转型措施（能源替代、循环经济、低碳工艺、低碳资本支出、碳管理与碳交易、绿色供应链等） | I18: 0 | J18: 0 | K18: 适用规则A（强制-赋0） | S18: 公司可持续发展报告 | V18: 0.6
I19: (0, 2] | J19: 2
I20: (2, 4] | J20: 4
I21: (4, 6] | J21: 6
I22: (6, 8] | J22: 8
I23: (8, 14] | J23: 10
C24: 其他战略 | D24: 企业如尚未制定专门的转型规划，是否已建立低碳与可持续发展相关的其他制度与行动框架 | E24: 相等 | F24: 若企业没有指定专门的转型规划，是否形成覆盖公司层面的低碳/可持续发展顶层战略或专项行动框架 | H24: 若企业尚未制定专门的转型规划，企业是否编制并披露至少一项以低碳、节能、气候、ESG或可持续发展为核心主题的公司层级顶层战略文件或专项行动方案 （一）文件形式关键词（至少命中 1 类） • 规划 / 战略 / 行动方案 / 行动计划 / 管理办法 / 实施方案• 中长期规划• 专项方案• 指导意见 （二）主题关键词（至少命中 1 类） 低碳/气候/能效类：• 绿色低碳• 双碳• 减碳 / 碳减排• 能效提升• 节能降碳• 气候变化 / 气候风险 ESG / 可持续治理类：• ESG• 可持续发展• 环境、社会及管治• 绿色发展• 供应链减碳 / 绿色供应链 | I24: 否 | J24: 0 | K24: 适用规则D（补充-P50） | S24: 公司可持续发展报告 | V24: 0.1
I25: 是 | J25: 10
A26: 实施保障（20分） | B26: 治理 | C26: 治理架构 | D26: 企业围绕低碳/绿色/可持续/转型/ESG议题建立的治理层级完整性与权责清晰度 | E26: 相等 | F26: 治理架构完善程度 | H26: 以下按单项累加赋分: • 设立专职部门或明确牵头部门：2分 • 明确由高管层成员分管相关事务：2分 • 建立跨部门协作机制，例如设立工作小组：2分 • 董事会下设专门委员会：2分 • 董事会在章程/议事规则中明确承担ESG/可持续/低碳/转型等战略统筹和监督职责：2分 • 明确将低碳转型目标和战略纳入薪酬激励措施：2分 | I26: 0 | J26: 0 | K26: 适用规则A（强制-赋0） | S26: 公司可持续发展报告 | V26: 0.4
I27: (0, 2] | J27: 2
I28: (2, 4] | J28: 4
I29: (4, 6] | J29: 6
I30: (6, 8] | J30: 8
I31: (8, 12] | J31: 10
B32: 风险管理 | C32: 气候风险管理体系 | D32: 1. 全面风险嵌入（ERM化）：将气候风险由单一环保议题上升为公司级战略风险，实质性嵌入ERM及全价值链决策流程。 2. 治理架构多级化：构建“董事会—管理层—执行层”的三级或四级垂直穿透式治理架构。 3. 管控手段数智化：建设并运行“智能气候风险管理信息系统”或数字化管理平台，实现风险数据的常态化监测与可视化。 4. 责任落实绩效化：形成“目标—执行—考核—追责”闭环，并将气候/碳相关指标刚性挂钩领导班子或管理层年度经营业绩评价。 | E32: 相等 | F32: 气候风险管理体系完善程度 | H32: 以下按单项累加赋分: • 流程：是否明确描述 ≥2 个气候风险管理环节（如识别、评估、监测、应对）—2分 • 战略：是否明确表述气候风险被纳入公司整体风险管理、战略规划或ESG重大决策—2分 • 治理：是否明确气候风险管理治理架构（董事会/委员会/管理层）—2分 • 制度：是否有气候风险管理规章制度或管理办法文件—2分 • 是否有气候风险管理数字化系统，或建立常态化监测机制—2分 • 是否将气候风险纳入考核机制或激励政策—2分 | I32: 0 | J32: 0 | K32: 适用规则A（强制-赋0） | S32: 公司可持续发展报告 | V32: 0.5
I33: (0, 2] | J33: 2
I34: (2, 4] | J34: 4
I35: (4, 6] | J35: 6
I36: (6, 8] | J36: 8
I37: (8, 12] | J37: 10
C38: 气候相关风险和机遇 | D38: 1. 风险与机遇识别完整性：同时识别转型风险与实体风险，涵盖政策/法律、技术、市场、供应链、声誉、急性与慢性物理风险等；同时识别低碳产品、能源结构优化、政策支持等机遇。 2. 时间维度清晰性：在短期（1–2年）、中期（3–6年）、长期（7年及以上）不同时间框架下开展识别与评估。 3. 财务影响关联性：识别风险和机遇对成本、收入、投资、融资、信用风险等财务事项的影响。 4. 量化深度差异：区分定性判断、间接量化（环保投入、节能降本）与直接量化（营收变化、成本变化、溢价比例、履约成本节约等）。 | E38: 相等 | F38: 风险与机遇识别完善程度 | H38: 以下按单项累加赋分: （1）识别完整性 — 同时识别转型风险与实体风险/物理风险：2 分 — 风险类型覆盖 3 类及以上（政策/技术/市场/声誉/信用等）：2 分 — 同时识别明确的气候相关机遇：2 分 （2）财务影响识别 — 明确风险或机遇与财务结果存在关联：2 分 — 对财务影响进行量化分析：2 分 （3）应对气候影响的措施 — 针对上述识别风险制定了应对措施：2分 | I38: 0 | J38: 0 | K38: 适用规则A（强制-赋0） | S38: 公司可持续发展报告 | V38: 0.4
I39: (0, 2] | J39: 2
I40: (2, 4] | J40: 4
I41: (4, 6] | J41: 6
I42: (6, 8] | J42: 8
I43: (8, 12] | J43: 10
C44: 气候压力测试 | D44: 1. 开展情况：明确披露已开展气候情景分析或压力测试。 2. 情景设置特征：情景覆盖转型风险与实体风险，包含中长期时间尺度。 3. 方法论来源：参考国际或行业权威情景与框架（如 IFRS S2、IEA、IPCC、钢铁行业低碳转型情景）。 4. 结果应用：情景分析结果用于评估对经营、成本、收入、资产或融资的潜在影响，并支撑风险管理或战略判断。 | E44: 相等 | F44: 气候压力测试完善程度 | H44: 以下按单项累加赋分: （1）情景分析开展与情景设置 明确披露已开展气候情景分析或压力测试：2 分 情景同时覆盖转型风险与实体风险：2 分 情景包含短中长期时间维度（如 2030 / 2050 或等效表述）：2分 设置多个情景用于对比分析（如低碳转型情景与基准情景、不同实体风险情景）：2分 （2）方法论参考与结果应用 明确引用 IFRS S2、IEA、IPCC 或行业权威研究作为情景或方法论来源：2 分 情景分析结果用于评估对经营、财务或风险管理的影响：1 分 明确说明情景分析结果被用于战略、投资、风险应对或管理决策：1 分 | I44: 0 | J44: 0 | K44: 适用规则D（补充-P50） | S44: 公司可持续发展报告 | V44: 0.1
I45: (0, 2] | J45: 2
I46: (2, 4] | J46: 4
I47: (4, 6] | J47: 6
I48: (6, 8] | J48: 8
I49: (8, 12] | J49: 10
A50: 转型表现（55分） | B50: 碳排放表现 | C50: 碳排放披露情况 | D50: 1. 核心词：范围1、直接排放、范围2、能源间接排放、范围3、价值链排放 2. 范围3类别词：类别1、采购商品、上下游运输、差旅、员工通勤、废弃物 | E50: 相等 | F50: 披露完整度 | H50: 企业披露情况，按分档进行赋分； - 0分：企业未披露范围1、范围2、范围3任意一个，直接赋分0； - 2.5分：仅披露“范围1”或仅披露总量未区分范围 - 5分：完整披露范围1 和 范围2，未披露范围3 - 7.5分：披露范围1、范围2和范围3中的1-2个类别 - 10分：披露范围1、范围2，范围3的披露满足以下任一条件 a) 类别数量 ≥3 b) 包含“类别1：购买的商品/服务”关键项 | I50: 未披露 | J50: 0 | K50: 适用规则A（强制-赋0） | S50: 公司可持续发展报告 | V50: 1
I51: 仅披露范围1 | J51: 2.5
I52: 披露范围1和范围2 | J52: 5
I53: 披露范围1、范围2和范围3中的1-2个类别 | J53: 7.5
I54: 披露范围1、范围2和范围3中的至少3个类别，或至少包含“类别1：购买的商品/服务”关键项 | J54: 10
C55: 物理碳排放强度 | D55: 单位粗钢产量所产生的范围一和范围二的碳排放量 | E55: 环比变化（30%） + 当期横向位置（70%） | F55: 环比变化 | H55: （一）当期物理碳强度计算 当期物理碳强度=当年碳排放量÷当年粗钢产量 单位：吨二氧化碳 / 吨钢 （二）环比变化维度（30%） 1. 环比变化率计算 环比变化率 = (上年物理碳强度 - 当期物理碳强度) ÷ 上年物理碳强度 说明：环比变化率大于0表示碳强度较上年下降，转型表现为正；数值越大表现越好。 2. 行业分位区间确定 对行业内所有企业的"环比变化率"进行排序，确定以下分位点： P10 变化率 = 行业内环比变化率的第 10 分位值 P90 变化率 = 行业内环比变化率的第 90 分位值 3. 归一化赋分 在区间 [P10 变化率，P90 变化率] 内进行线性归一映射： • 当 企业环比变化率 ≤ P10 变化率 时，环比得分 = 0 • 当 企业环比变化率 ≥ P90 变化率 时，环比得分 = 10 • 当 P10 变化率 < 企业环比变化率 < P90 变化率 时： 环比得分 = 10 ×（企业环比变化率 − P10 变化率）÷（P90 变化率 − P10 变化率） | I55: 企业改进率 ≤ P10 改进率 | J55: 0 | K55: 适用规则B（强制-赋0） | S55: 公司可持续发展报告、公司年度报告 | V55: 1
I56: P10 改进率 < 企业改进率 < P90 改进率 | J56: 环比得分 = 10 ×（企业环比变化率 − P10 变化率）÷（P90 变化率 − P10 变化率）
I57: 企业改进率 ≥ P90 改进率 | J57: 10
F58: 当期横向位置 | H58: 当期横向位置维度（70%） 1. 指标表现排序 物理碳强度为反向指标，数值越低表示碳排放控制表现越好。 对行业内披露了当期物理碳强度的所有有效样本企业，按数值从小到大（由优到劣）进行排序，确定企业名次。数值最小的排名第1。2. 排名归一化赋分 计算公式： 当期得分 = 10 × (N - 企业当期名次) ÷ (N - 1) 说明： • N 为参与排名的有效样本总数（即披露了该项数据的企业数量）。 • 排名第1（碳强度最低）的企业得满分10分，排名最后（第N名，碳强度最高）的企业得0分。 • 若企业未披露当期碳排放及产量数据，该项得分为0分。 | I58: 企业排名最后 | J58: 0
I59: P10 < 企业指标值 < P90 | J59: 当期得分 =10 × (N - 企业当期名次) ÷ (N - 1)
I60: 企业指标值 ≥ P90 | J60: 10
C61: 营收碳排放强度 | D61: 单位营业收入所产生的范围一和范围二的碳排放量 | E61: 环比变化（30%） + 当期横向位置（70%） | F61: 环比变化 | H61: （一）当期营收碳排放强度计算 当期营收碳排放强度 = 当年碳排放量 ÷ 营业收入 单位：吨二氧化碳 / 万元 （二）环比变化维度（30%） 1. 环比变化率计算 环比变化率 =（上年营收碳排放强度 − 当期营收碳排放强度）÷ 上年营收碳排放强度 环比变化率大于 0 表示单位营收对应的碳排放水平较上年下降，转型表现为正。 2. 行业分位区间确定 对行业内所有企业的"环比变化率"进行排序，确定以下分位点： P10 变化率 = 行业内环比变化率的第 10 分位值 P90 变化率 = 行业内环比变化率的第 90 分位值 3. 归一化赋分 在区间 [P10 变化率，P90 变化率] 内进行线性归一映射： • 当 企业环比变化率 ≤ P10 变化率 时，环比得分 = 0 • 当 企业环比变化率 ≥ P90 变化率 时，环比得分 = 10 • 当 P10 变化率 < 企业环比变化率 < P90 变化率 时： 环比得分 = 10 ×（企业环比变化率 − P10 变化率）÷（P90 变化率 − P10 变化率） | I61: 企业改进率 ≤ P10 改进率 | J61: 0 | K61: 适用规则B（强制-赋0） | S61: 公司可持续发展报告、公司年度报告 | V61: 0.3
I62: P10 改进率 < 企业改进率 < P90 改进率 | J62: 环比得分 = 10 ×（企业环比变化率 − P10 变化率）÷（P90 变化率 − P10 变化率）
I63: 企业改进率 ≥ P90 改进率 | J63: 10
F64: 当期横向位置 | H64: 当期横向位置维度（70%） 1. 行业分位区间确定 对行业内所有企业当期营收碳排放强度进行排序，确定： P10 营收碳排放强度 = 行业内当期营收碳排放强度的第 10 分位值 P90 营收碳排放强度 = 行业内当期营收碳排放强度的第 90 分位值 说明：营收碳排放强度为反向指标，数值越低表示单位营收对应的碳排放水平越低，表现越好。 2. 行业维度归一化赋分 在区间 [P10 营收碳排放强度，P90 营收碳排放强度] 内进行反向线性归一映射： 当 企业当期营收碳排放强度 ≥ P90 营收碳排放强度 时，当期得分 = 0 当 企业当期营收碳排放强度 ≤ P10 营收碳排放强度 时，当期得分 = 10 当 P10 营收碳排放强度 < 企业当期营收碳排放强度 < P90 营收碳排放强度 时： 当期得分 = 10 ×（P90 营收碳排放强度 − 企业当期营收碳排放强度）÷（P90 营收碳排放强度 − P10 营收碳排放强度） | I64: 企业指标值 ≤ P10 | J64: 0
I65: P10 < 企业指标值 < P90 | J65: 当期得分 = 10 ×（企业当期指标值 − P10）÷（P90 − P10）
I66: 企业指标值 ≥ P90 | J66: 10
B67: 能源使用 | C67: 可再生能源占比 | D67: 自发可再生能源电量，是指企业在自身生产经营边界内，通过自建或控股的可再生能源发电设施，所产生并被企业自身消费的电力。 能源消耗总量：企业当期披露的能源消耗总量（单位 MWh） | E67: 环比变化（30%） + 当期横向位置（70%） | F67: 环比变化 | H67: （一）当期自发可再生能源电量占比计算 当期自发可再生能源电量占比 = 当年企业自发可再生能源发电量 ÷ 当年总能源消耗量 单位：% 注： 自发可再生能源包括但不限于：光伏、风电、生物质能、水电等企业自建或自持发电设施所产生的电量； 能源消耗总量以企业披露的当期能源消耗总量（统一折算为 MWh）为准。 （二）环比变化维度（30%） 1. 环比变化率计算 环比变化率 =（当期自发可再生能源电量占比 − 上年自发可再生能源电量占比）÷ 上年自发可再生能源电量占比 环比变化率大于 0 表示企业自发可再生能源使用水平较上年提升。 2. 行业分位区间确定 对行业内所有企业的"环比变化率"进行排序，确定以下分位点： P10 变化率 = 行业内环比变化率的第 10 分位值 P90 变化率 = 行业内环比变化率的第 90 分位值 3. 归一化赋分 在区间 [P10 变化率，P90 变化率] 内进行线性归一映射： 当 企业环比变化率 ≤ P10 变化率 时，环比得分 = 0 当 企业环比变化率 ≥ P90 变化率 时，环比得分 = 10 当 P10 变化率 < 企业环比变化率 < P90 变化率 时： 环比得分 = 10 ×（企业环比变化率 − P10 变化率）÷（P90 变化率 − P10 变化率） | I67: 企业改进率 ≤ P10 改进率 | J67: 0 | K67: 适用规则C（鼓励-P25） | S67: 公司可持续发展报告 | V67: 0.3
I68: P10 改进率 < 企业改进率 < P90 改进率 | J68: 环比得分 = 10 ×（企业环比变化率 − P10 变化率）÷（P90 变化率 − P10 变化率）
I69: 企业改进率 ≥ P90 改进率 | J69: 10
F70: 当期横向位置 | H70: 当期横向位置维度（70%） 1. 行业分位区间确定 对行业内所有企业当期自发可再生能源电量占比进行排序，确定： P10 占比 = 行业内当期自发可再生能源电量占比的第 10 分位值 P90 占比 = 行业内当期自发可再生能源电量占比的第 90 分位值 说明：自发可再生能源电量占比为正向指标，数值越高表示表现越好。 2. 行业维度归一化赋分 在区间 [P10 占比，P90 占比] 内进行线性归一映射： 当 企业当期占比 ≤ P10 占比 时，当期得分 = 0 当 企业当期占比 ≥ P90 占比 时，当期得分 = 10 当 P10 占比 < 企业当期占比 < P90 占比 时： 当期得分 = 10 ×（企业当期占比 − P10 占比）÷（P90 占比 − P10 占比） | I70: 企业指标值 ≤ P10 | J70: 0
I71: P10 < 企业指标值 < P90 | J71: 当期得分 = 10 ×（企业当期指标值 − P10）÷（P90 − P10）
I72: 企业指标值 ≥ P90 | J72: 10
D73: 外购绿电包括： 绿电交易电量 绿证对应电量（如披露） 能源消耗总量：企业当期披露的能源消耗总量（单位 MWh） | E73: 环比变化（30%） + 当期横向位置（70%） | F73: 环比变化 | H73: （一）当期外购绿电占比计算 当期外购绿电占比= 当年企业外购绿电电量 ÷ 当年总能源消耗量 单位：% 注： 外购绿电包括通过绿电交易、清洁电力采购、绿色电力协议（PPA）以及绿证对应电量等方式获得的可再生能源电力； 若企业明确披露当期未采购绿电，则该指标取值为 0。 （二）环比变化维度（30%） 1. 环比变化率计算 环比变化率 =（当期外购绿电占比 − 上年外购绿电占比）÷ 上年外购绿电占比 2. 行业分位区间确定 对行业内所有企业的"环比变化率"进行排序，确定： P10 变化率 = 行业内环比变化率的第 10 分位值 P90 变化率 = 行业内环比变化率的第 90 分位值 3. 归一化赋分 当 企业环比变化率 ≤ P10 变化率 时，环比得分 = 0 当 企业环比变化率 ≥ P90 变化率 时，环比得分 = 10 当 P10 变化率 < 企业环比变化率 < P90 变化率 时： 环比得分 = 10 ×（企业环比变化率 − P10 变化率）÷（P90 变化率 − P10 变化率） | I73: 企业改进率 ≤ P10 改进率 | J73: 0 | K73: 适用规则C（鼓励-P25） | S73: 公司可持续发展报告 | V73: 0.2
I74: P10 改进率 < 企业改进率 < P90 改进率 | J74: 环比得分 = 10 ×（企业环比变化率 − P10 变化率）÷（P90 变化率 − P10 变化率）
I75: 企业改进率 ≥ P90 改进率 | J75: 10
F76: 当期横向位置 | H76: 当期横向位置维度（70%） 1. 行业分位区间确定 对行业内所有企业当期外购绿电占比进行排序，确定： P10 占比 = 行业内当期外购绿电占比的第 10 分位值 P90 占比 = 行业内当期外购绿电占比的第 90 分位值 说明：外购绿电占比为正向指标，数值越高表示表现越好。 2. 行业维度归一化赋分 当 企业当期占比 ≤ P10 占比 时，当期得分 = 0 当 企业当期占比 ≥ P90 占比 时，当期得分 = 10 当 P10 占比 < 企业当期占比 < P90 占比 时： 当期得分 = 10 ×（企业当期占比 − P10 占比）÷（P90 占比 − P10 占比） （四）综合得分 综合得分 = 环比得分 × 30% + 当期得分 × 70% | I76: 企业指标值 ≤ P10 | J76: 0
I77: P10 < 企业指标值 < P90 | J77: 当期得分 = 10 ×（企业当期指标值 − P10）÷（P90 − P10）
I78: 企业指标值 ≥ P90 | J78: 10
B79: 水资源利用 | C79: 用水效率 | D79: 吨钢耗新水量，指企业在生产过程中对粗钢生产所消耗的新鲜水资源量 用水效率（吨钢耗新水量）= 当期新水消耗量 ÷ 当期粗钢产量 单位：立方米/吨粗钢 | E79: 环比变化（30%） + 当期横向位置（70%） | F79: 环比变化 | H79: （一）计算指标 用水效率（吨钢耗新水量）= 当期新水消耗量 ÷ 当期粗钢产量 单位：立方米/吨粗钢 说明： 用水效率为反向指标，数值越低表示单位产量新水消耗水平越优。 （二）环比变化维度（30%） 1. 环比变化率计算 环比变化率 =（上年吨钢耗新水量 − 当期吨钢耗新水量）÷ 上年吨钢耗新水量 环比变化率大于 0 表示单位产量新水消耗量较上年下降，转型表现为正。 2. 行业分位区间确定 对行业内所有企业的环比变化率进行排序，确定： P10 变化率 = 行业内环比变化率的第 10 分位值 P90 变化率 = 行业内环比变化率的第 90 分位值 3. 归一化赋分 在区间 [P10 变化率，P90 变化率] 内进行线性归一映射： • 当 企业环比变化率 ≤ P10 变化率 时，环比得分 = 0 • 当 企业环比变化率 ≥ P90 变化率 时，环比得分 = 10 • 当 P10 变化率 < 企业环比变化率 < P90 变化率 时： 环比得分 = 10 ×（企业环比变化率 − P10 变化率）÷（P90 变化率 − P10 变化率） | I79: 企业改进率 ≤ P10 改进率 | J79: 0 | K79: 适用规则C（鼓励-P25） | S79: 公司可持续发展报告 | V79: 0.6
I80: P10 改进率 < 企业改进率 < P90 改进率 | J80: 环比得分 = 10 ×（企业环比变化率 − P10 变化率）÷（P90 变化率 − P10 变化率）
I81: 企业改进率 ≥ P90 改进率 | J81: 10
F82: 当期横向位置 | H82: 当期横向位置维度（70%） 1. 行业分位区间确定 对行业内所有企业当期吨钢耗新水量进行排序，确定： P10 吨钢耗新水量 = 行业内当期吨钢耗新水量的第 10 分位值 P90 吨钢耗新水量 = 行业内当期吨钢耗新水量的第 90 分位值 2. 行业维度归一化赋分（反向） 在区间 [P10 吨钢耗新水量，P90 吨钢耗新水量] 内进行反向线性归一映射： • 当 企业当期吨钢耗新水量 ≥ P90 吨钢耗新水量 时，当期得分 = 0 • 当 企业当期吨钢耗新水量 ≤ P10 吨钢耗新水量 时，当期得分 = 10 • 当 P10 吨钢耗新水量 < 企业当期吨钢耗新水量 < P90 吨钢耗新水量 时： 当期得分 = 10 ×（P90 吨钢耗新水量 − 企业当期吨钢耗新水量）÷（P90 吨钢耗新水量 − P10 吨钢耗新水量） | I82: 企业指标值 ≤ P10 | J82: 0
I83: P10 < 企业指标值 < P90 | J83: 当期得分 = 10 ×（企业当期指标值 − P10）÷（P90 − P10）
I84: 企业指标值 ≥ P90 | J84: 10
B85: 生态保护 | C85: 生物多样性 | D85: 企业在生物多样性保护方面表现，比如制度或组织架构建设、具体措施和实际成效，包括保护区域的生态恢复、物种多样性保护及生态环境修复等。 | E85: 累加 | F85: 企业是否在报告或规划文件中披露其在生物多样性或生态保护方面建立了相应的管理制度、组织安排或管理机制。 | H85: 关键词范围（示例） （一）生物多样性 / 生态 / 自然相关关键词（A 类） 生物多样性 生物多样性保护 生物多样性管理 生态保护 生态系统保护 自然生态保护 自然栖息地 栖息地保护 生态红线 生态敏感区 重要生态功能区 自然资源保护 自然资本 生态环境保护 （二）管理 / 制度 / 治理关键词 管理制度 管理办法 管理体系 管理机制 管理要求 管理责任 治理体系 内部控制 工作机制 组织架构 职责分工 管理流程 管理规划 保护制度 保护规划 保护方案 行动方案 工作方案 专项规划 专项管理办法 管理细则 指引 工作要求 企业披露以下任一情形 → 得 3 分： - 披露与生物多样性、生态保护或自然栖息地保护相关的管理制度、管理办法或制度性文件； - 在公司治理或环境管理体系中，明确将生物多样性或生态保护纳入管理范畴（如作为环境管理、自然资源管理的一部分）； - 披露设立或明确负责生态保护、生物多样性或自然保护事务的管理部门、工作机制或职责分工； - 在企业环境、ESG 或可持续发展管理框架中，明确提出生物多样性保护的管理要求或管理目标。 | I85: 否 | J85: 0 | K85: 适用规则D（补充-P50） | S85: 公司可持续发展报告 | V85: 0.1
I86: 是 | J86: 5
F87: 企业是否披露其在自然栖息地保护、生物多样性保护或生态修复方面采取了具体行动或措施。 | H87: 关键词范围（示例） - 栖息地保护 / 恢复 - 生物多样性恢复 - 生态修复 - 生态治理 - 矿区复绿 / 厂区复绿 - 湿地保护 / 修复 - 物种保护 - 自然生态修复工程 企业披露以下任一情形 ： - 开展生态修复或栖息地保护项目 - 实施生物多样性恢复或生态治理行动 - 对生产活动造成的生态影响采取修复措施 | I87: 否 | J87: 0
I88: 是 | J88: 5
B89: 公正转型 | C89: 员工培训 | D89: 本指标用于评估企业是否关注并投入员工能力建设，尤其是在转型相关技能方面。 考虑到企业披露口径差异较大，本指标采用是否类累加赋分方式，不对不同披露口径进行强制可比性要求。 | E89: 相等 | F89: 企业是否真实投入并系统性披露员工能力建设，并通过加分识别其是否将培训与绿色低碳、数字化等转型目标相结合。 | H89: 分档赋分： 企业报告或相关文件中未披露员工转型相关培训、能力建设、技能提升相关信息→ 0 分 披露转型间接相关技能培训：“环境相关培训”“数字化技能”“智能制造培训”“ESG培训”→ 5分 披露转型直接相关技能培训：“绿色技能”“低碳培训”“转型培训”“节能减排培训”→10分 | I89: 0 | J89: 0 | K89: 适用规则C（鼓励-P25档） | S89: 公司可持续发展报告 | V89: 0.1
I90: 5 | J90: 5
I91: 10 | J91: 10
C92: 稳就业与促就业 | D92: 衡量企业在转型过程中是否避免通过大规模裁员转嫁成本，并通过稳定或扩大就业规模，体现对劳动者和社会的责任承担。 | E92: 相等 | F92: 就业变化率 | H92: （一）就业变化率计算 就业变化率 =（当期员工人数 − 上年员工人数）÷ 上年员工人数 单位：% 说明： 就业变化率为正向指标，数值越高表示企业就业规模扩张越快。若就业变化率为负，说明企业员工规模缩减。 （二）环比变化维度（30%） 说明： 该指标的环比变化维度与当期横向位置维度使用相同的就业变化率数据，为避免重复计算，环比变化维度得分的计算逻辑与横向位置维度一致，均基于行业内P10-P90分位归一化。此处不再重复设置独立的环比变化维度，直接取当期横向位置维度得分作为该指标的总得分。 （三）当期横向位置维度 1. 行业分位区间确定 对行业内所有企业的就业变化率进行排序，确定： P10 就业变化率 = 行业内就业变化率的第 10 分位值 P90 就业变化率 = 行业内就业变化率的第 90 分位值 2. 行业维度归一化赋分（正向） • 当 企业就业变化率 ≤ P10 就业变化率 时，得分 = 0 • 当 企业就业变化率 ≥ P90 就业变化率 时，得分 = 10 • 当 P10 就业变化率 < 企业就业变化率 < P90 就业变化率 时： 得分 = 10 ×（企业就业变化率 − P10 就业变化率）÷（P90 就业变化率 − P10 就业变化率） | K92: 适用规则B（强制-赋0） | S92: 公司可持续发展报告 | V92: 0.5
B93: 研发与创新 | C93: 研发投入占比 | D93: 以“研发投入 / 研发费用 / 研究与开发支出”等为核心关键词，结合财务报表附注中“研发支出”相关披露，提取企业当期研发投入金额；分母采用“营业收入”口径计算研发投入占比。 | E93: 环比变化（30%） + 当期横向位置（70%） | F93: 环比变化 | H93: （一）研发投入占比计算 研发投入占比 = 研发投入 ÷ 当期营业收入 单位：% 说明： 研发投入占比为正向指标，数值越高表示企业对技术进步和转型的资源投入力度越大。 （二）环比变化维度（30%） 1. 环比变化率计算 环比变化率 =（当期研发投入占比 − 上年研发投入占比）÷ 上年研发投入占比 2. 行业分位区间确定 P10 变化率 = 行业内环比变化率的第 10 分位值 P90 变化率 = 行业内环比变化率的第 90 分位值 3. 归一化赋分 • 企业环比变化率 ≤ P10 变化率，环比得分 = 0 • 企业环比变化率 ≥ P90 变化率，环比得分 = 10 • 中间区间： 环比得分 = 10 ×（企业环比变化率 − P10 变化率）÷（P90 变化率 − P10 变化率） | I93: 企业改进率 ≤ P10 改进率 | J93: 0 | K93: 适用规则B（强制-赋0） | S93: 公司可持续发展报告、公司年度报告 | V93: 0.5
I94: P10 改进率 < 企业改进率 < P90 改进率 | J94: 环比得分 = 10 ×（企业环比变化率 − P10 变化率）÷（P90 变化率 − P10 变化率）
I95: 企业改进率 ≥ P90 改进率 | J95: 10
F96: 当期横向位置 | H96: 当期横向位置维度（70%） 1. 行业分位区间确定 P10 研发投入占比 = 行业内当期研发投入占比的第 10 分位值 P90 研发投入占比 = 行业内当期研发投入占比的第 90 分位值 2. 行业维度归一化赋分（正向） • 企业当期占比 ≤ P10，占比得分 = 0 • 企业当期占比 ≥ P90，占比得分 = 10 • 中间区间： 当期得分 = 10 ×（企业当期研发投入占比 − P10）÷（P90 − P10） | I96: 企业指标值 ≤ P10 | J96: 0
I97: P10 < 企业指标值 < P90 | J97: 当期得分 = 10 ×（企业当期指标值 − P10）÷（P90 − P10）
I98: 企业指标值 ≥ P90 | J98: 10
C99: 节能技改投资占比 | D99: 以“节能技改 / 技术改造 / 节能改造/超低排放改造投资”等关键词识别企业披露的节能相关技改投资金额，结合“投资金额 / 固定资产投资 / 资本性支出”等表述进行提取；分母统一采用当期营业收入，计算节能技改投资占比。 | E99: 环比变化（30%） + 当期横向位置（70%） | F99: 环比变化 | H99: （一）节能技改投资占比计算 节能技改投资占比 = 节能技改投资 ÷ 当期营业收入 单位：% 说明： 节能技改投资包括但不限于节能设备更新、工艺流程优化、能效提升改造等与降低能耗和碳排放相关的资本性支出。 节能技改投资占比为正向指标，数值越高表示企业对节能降碳改造的投入力度越大。 （二）环比变化维度（30%） 1. 环比变化率计算 环比变化率 =（当期节能技改投资占比 − 上年节能技改投资占比）÷ 上年节能技改投资占比 环比变化率大于 0 表示企业在节能技改方面的投入强度较上年有所提升。 2. 行业分位区间确定 对行业内所有企业的"节能技改投资占比环比变化率"进行排序，确定： P10 变化率 = 行业内环比变化率的第 10 分位值 P90 变化率 = 行业内环比变化率的第 90 分位值 3. 归一化赋分 在区间 [P10 变化率，P90 变化率] 内进行线性归一映射： • 当 企业环比变化率 ≤ P10 变化率 时，环比得分 = 0 • 当 企业环比变化率 ≥ P90 变化率 时，环比得分 = 10 • 当 P10 变化率 < 企业环比变化率 < P90 变化率 时： 环比得分 = 10 ×（企业环比变化率 − P10 变化率）÷（P90 变化率 − P10 变化率） | I99: 企业改进率 ≤ P10 改进率 | J99: 0 | K99: 适用规则C（鼓励-P25） | S99: 公司可持续发展报告 | V99: 0.1
I100: P10 改进率 < 企业改进率 < P90 改进率 | J100: 环比得分 = 10 ×（企业环比变化率 − P10 变化率）÷（P90 变化率 − P10 变化率）
...

Sheet 负向指标
A1: 一级指标 | B1: 二级指标 | C1: 三级指标 | D1: 关键字说明 | E1: 分值关系 | F1: 数据类型 | G1: 指标因子 | H1: 问题 | I1: 判断依据/计算公式 | J1: 分档 | K1: 对应分值 | L1: 空值处理 | M1: 数据长度 | N1: 必填 | O1: 获取频度 | P1: 数据粒度 | Q1: 参考数据 | R1: 技术校验规则 | S1: 业务校验规则 | T1: 数据来源 | U1: 数据来源接口 | V1: 备注
A2: 实施举措和保障 | B2: 风险管理 | C2: 环境行政处罚 | D2: 衡量企业在战略转型期（如前/后3年）因环境违法行为受到地方监管部门行政处罚的严重程度。 | E2: 累加 | F2: 分档型 | G2: 处罚类型 | I2: 因子1：近五年发生环境处罚事件的次数， 因子2：近五年发生环境处罚事件的最严重处罚类型， 因子3：近五年发生环境处罚事件的累计被处罚金额/近五年内被处罚次数， 指标得分=次数得分*0.4+类型得分*0.2+强度金额*0.4 | J2: 其他 | K2: 0 | L2: 0 | T2: 各地生态环境局官网（行政处罚公告栏）
J3: 警告 | K3: -2
J4: 罚款 | K4: -5
J5: 没收违法 | K5: -5
J6: 停产停业 | K6: -8
J7: 停产整顿 | K7: -8
J8: 暂扣吊销 | K8: -8
J9: 行政拘留 | K9: -10
F10: 连续型 | G10: 处罚强度 | J10: 【0,10000) | K10: x/10000*-2 | L10: 0
J11: 【10000,100000) | K11: (x-10000)/90000*（-3）-3
J12: 【100000,300000) | K12: (x-100000)/200000*（-3）-7
J13: 【300000,+) | K13: -10
F14: 连续型 | G14: 处罚次数 | J14: 0 | K14: 0 | L14: 0
J15: 【1,5) | K15: (x-1)/4*（-3）-3
J16: 【5,10) | K16: (x-6)/4*（3）-7
J17: 【10,+) | K17: -10
C18: 安全生产行政处罚 | D18: 衡量企业因违反安全生产法规受到处罚或发生生产安全责任事故的严重程度 | E18: 累加 | F18: 分档型 | G18: 处罚类型 | I18: 因子1：近五年发生安全生产处罚事件的次数， 因子2：近五年发生安全生产处罚事件的最严重处罚类型， 因子3：近五年发生安全生产处罚事件的累计被处罚金额/近五年内被处罚次数， 指标得分=次数得分*0.4+类型得分*0.2+强度金额*0.4 | J18: 其他 | K18: 0 | L18: 0 | T18: 各地方应急管理局（厅/局）官网（行政处罚或事故通报栏）
J19: 警告 | K19: -2
J20: 罚款 | K20: -5
J21: 没收 | K21: -5
J22: 责令停产 | K22: -8
J23: 暂扣吊销 | K23: -8
J24: 关闭 | K24: -8
J25: 拘留 | K25: -10
F26: 连续型 | G26: 处罚强度 | J26: 【0,10000) | K26: x/10000*-3 | L26: 0
J27: 【10000,30000) | K27: (x-10000)/20000*（-4）-3
J28: 【30000,100000) | K28: (x-30000)/70000*（-2）-8
J29: 【100000,+) | K29: -1
F30: 分档型 | G30: 处罚次数 | J30: 0 | K30: 0 | L30: 0
J31: 1 | K31: -2.5
J32: 2 | K32: -5
J33: 3 | K33: -7.5
J34: (3,+) | K34: -10
C35: 失信事件管理（法律被执行人） | D35: 量化转型期企业面临的诉讼压力与现金流风险，案件常涉及合同（供应链）、劳动（安置）、金融（偿债）纠纷。 | E35: 累加 | F35: 连续型 | G35: 执行次数 | I35: 因子1：企业近五年被列为被执行人的次数 因子2：企业未履行部分总额占销售收入的比例（空值填充：未履行部分总额为为空，赋值0，未履行部分总额不为空，赋值-1） 指标得分=0.5*因子1+0.5*因子2 | J35: 【0,10】 | K35: x/10*-5 | L35: 0 | T35: 各地高级人民法院被执行人查询系统
J36: (10,20】 | K36: (1-(20-x)/10)*（-2.5）-5
J37: (20,30】 | K37: (1-(30-x)/20)*（-2.5）-7.5
J38: (30,+) | K38: -10
F39: 连续型 | G39: 未履行部分 | J39: 【0,0.1】 | K39: x/0.1*-5 | L39: 0
J40: (0.1,0.2】 | K40: (1-(0.2-x)/0.1)*（-1）-5
J41: (0.2,0.3】 | K41: (1-(0.3-x)/0.1)*（-2）-6
J42: (0.3,0.5】 | K42: (1-(0.5-x)/0.2)*（-2）-8
J43: (0.5,+) | K43: -10
A44: 转型表现 | B44: 公正转型 | C44: 劳动纠纷 | D44: 衡量因转型调整（如岗位重组、合同解除）引发的、并已进入正式法律或仲裁程序的劳资纠纷数量与严重性。 案由关键字：船员劳务合同纠纷、辞退争议、经济性裁员争议、劳动合同纠纷、劳动争议、劳务合同纠纷、离退休人员返聘合同纠纷、确认劳动关系纠纷、社会保险纠纷、职工破产债权确认纠纷、追索劳动报酬纠纷 | E44: 相等 | F44: 连续型 | G44: 企业近三年劳动纠纷发生次数 | I44: 企业近三年劳动纠纷发生次数 | J44: 【0,5） | K44: (x/5)*-2.5 | L44: 0 | T44: 中国裁判文书网、地方人社局公布的年度劳动争议典型案例/分析报告
J45: 【5,10） | K45: ((x-5)/5)*（-2.5）-2.5
J46: 【10,15） | K46: ((x-10)/5)*（-2.5）-5
J47: 【15,20） | K47: ((x-15)/5)*（-2.5）-7.5
J48: 【20，+） | K48: -10
C49: 重大负面舆情 | D49: 系统性量化企业因“公正转型”措施失当，在公开舆论场引发的负面关注与声誉风险。 关键字： 劳工权益类：转型裁员、安置纠纷、买断工龄、再培训缺失、拖欠补偿金、员工抗议、工会协商破裂； 社区影响类：关停冲击、地方经济衰退、税收锐减、产能退出、搬迁争议、环境遗留问题 过程公正类：决策黑箱、缺乏沟通、无视职工意见、突击式关停、政策套利 | E49: 相等 | F49: 连续型 | G49: 企业近两年所有相关负面报道，按其发布媒体的权威性和影响力 进行分级赋值后，所得累计总分值。 | I49: 企业近两年所有相关负面报道，按其发布媒体的权威性和影响力 进行分级赋值后，所得累计总分值。 单次事件赋分（Ei）： 地方/行业媒体：0.5 省级/全国网络媒体：1 中央级主流媒体：1.5 释：针对同一新闻事件的多次报道，只计算其中Ei最高的一次，避免重复加权。 | J49: 【0,2） | K49: (x/2)*-3 | L49: 0 | T49: 公开网络
J50: 【2,4） | K50: ((x-2)/2)*(-3)-3
J51: 【4,6） | K51: ((x-4)/2)*(-4)-6
J52: 【6,+） | K52: -10

Sheet 试评分
A1: 指标 | K1: 宝钢股份（宝山钢铁） | O1: 宝武钢铁 | S1: 河钢股份 | W1: 华菱钢铁 | AA1: 中信特钢 | AE1: 鞍钢股份 | AI1: 太钢不锈 | AM1: 马钢股份 | AQ1: 山东钢铁 | AU1: 柳钢股份 | AY1: 包钢股份 | BC1: 重庆钢铁 | BG1: 南钢股份 | BK1: 首钢股份 | BO1: 中南股份 | BS1: 本钢板材 | BW1: 杭州钢铁 | CA1: 凌钢股份 | CE1: 新钢股份 | CI1: 八一钢铁
A2: 一级指标 | B2: 二级指标 | C2: 三级指标 | D2: 关键字说明 | E2: 分值关系 | F2: 指标因子 | G2: 问题 | H2: 判断依据/计算公式 | I2: 分档 | J2: 对应分值 | K2: 信息 | L2: 分数（原始得分+对应分数） | M2: 单项得分（初始权重） | N2: 单项得分（调整后权重） | O2: 信息 | P2: 分数（原始得分+对应分数） | Q2: 单项得分（初始权重） | R2: 单项得分（调整后权重） | S2: 信息 | T2: 分数（原始得分+对应分数） | U2: 单项得分（初始权重） | V2: 单项得分（调整后权重） | W2: 信息 | X2: 分数（原始得分+对应分数） | Y2: 单项得分（初始权重） | Z2: 单项得分（调整后权重） | AA2: 信息 | AB2: 分数（原始得分+对应分数） | AC2: 单项得分（初始权重） | AD2: 单项得分（调整后权重） | AE2: 信息 | AF2: 分数（原始得分+对应分数） | AG2: 单项得分（初始权重） | AH2: 单项得分（调整后权重） | AI2: 信息 | AJ2: 分数（原始得分+对应分数） | AK2: 单项得分（初始权重） | AL2: 单项得分（调整后权重） | AM2: 信息 | AN2: 分数（原始得分+对应分数） | AO2: 单项得分（初始权重） | AP2: 单项得分（调整后权重） | AQ2: 信息 | AR2: 分数（原始得分+对应分数） | AS2: 单项得分（初始权重） | AT2: 单项得分（调整后权重） | AU2: 信息 | AV2: 分数（原始得分+对应分数） | AW2: 单项得分（初始权重） | AX2: 单项得分（调整后权重） | AY2: 信息 | AZ2: 分数（原始得分+对应分数） | BA2: 单项得分（初始权重） | BB2: 单项得分（调整后权重） | BC2: 信息 | BD2: 分数（原始得分+对应分数） | BE2: 单项得分（初始权重） | BF2: 单项得分（调整后权重） | BG2: 信息 | BH2: 分数（原始得分+对应分数） | BI2: 单项得分（初始权重） | BJ2: 单项得分（调整后权重） | BK2: 信息 | BL2: 分数（原始得分+对应分数） | BM2: 单项得分（初始权重） | BN2: 单项得分（调整后权重） | BO2: 信息 | BP2: 分数（原始得分+对应分数） | BQ2: 单项得分（初始权重） | BR2: 单项得分（调整后权重） | BS2: 信息 | BT2: 分数（原始得分+对应分数） | BU2: 单项得分（初始权重） | BV2: 单项得分（调整后权重） | BW2: 信息 | BX2: 分数（原始得分+对应分数） | BY2: 单项得分（初始权重） | BZ2: 单项得分（调整后权重） | CA2: 信息 | CB2: 分数（原始得分+对应分数） | CC2: 单项得分（初始权重） | CD2: 单项得分（调整后权重） | CE2: 信息 | CF2: 分数（原始得分+对应分数） | CG2: 单项得分（初始权重） | CH2: 单项得分（调整后权重） | CI2: 信息 | CJ2: 分数（原始得分+对应分数） | CK2: 单项得分（初始权重） | CL2: 单项得分（调整后权重）
A3: 目标与战略（25分） | B3: 目标和承诺 | C3: 碳中和目标 | D3: 企业承诺转型目标与国家碳达峰碳中和目标一致，服务于国家碳达峰碳中和目标；制定减排目标是指企业制定短期（如2024-2025年）、中期（2026-2030年）和长期（至2060年）的目标，且目标符合所在行业的先进性水平 | E3: 相等 | F3: 中和年份承诺与覆盖度 | H3: 计算原始得分 = 基础分 × 范围系数 1. 基础分（时间维度） 若无目标或年份 > 2060：0 分 若年份 ≤ 2050：10 分 若 2050 < 年份 ≤ 2060： 基础分 = 10 − 0.4 × (年份 − 2050) （说明：每晚 1 年扣 0.4 分，2060 年得 6 分） 2. 范围系数 仅覆盖部分区域 / 子公司 / 单一工序范围1：0.5 仅覆盖部分区域 / 子公司 / 单一工序范围1+2：0.6 覆盖部分区域 / 子公司 / 单一工序范围1+2+3：0.7 覆盖全集团范围 1：0.8 覆盖全集团范围 1+2：1 覆盖全集团范围 1+2+3（含重要供应链）：1.2 对计算结果做0-12的分布 | I3: 0 | J3: 0 | K3: 基础分来源：24年可持续发展报告 p49 “以2020年为基准年，2025年减碳8%，2035年力争减碳30%，2050年力争实现碳中和。” 范围系数来源：24年可持续发展报告 p49 p78 p77 “以公司运营范围为边界，包括范围一和范围二”“宝钢股份对自身直接、间接温室气体排放量及排放强度进行严格的常态化追踪监控。同时聘请第三方专业机构对公司运营控制范围内的直接和间接温室气体排放进行年度核查。”“提供供应链碳排放信息管理服务”“营销部门负责收集客户对供应链减碳的具体指标” | L3: 10 | M3: =L3*初始权重设定说明!E5 -> 7 | N3: =L3*权重调整机制!K19 -> 9 | O3: 来源：24年可持续发展报告 p18 “力争2050年实现碳中和” | P3: 10 | Q3: =P3*初始权重设定说明!E5 -> 7 | R3: =P3*权重调整机制!K19 -> 9 | S3: 来源：24年ESG报告 p39 ”2030年较碳排放峰值降低30%，并力争在2050年实现碳中和的发展目标” | T3: 10 | U3: =T3*初始权重设定说明!E5 -> 7 | V3: =T3*权重调整机制!K19 -> 9 | W3: 来源：24年可持续发展报告 p103 “2030年前碳达峰，力争2060年前实现碳中和” | X3: 5 | Y3: =X3*初始权重设定说明!E5 -> 3.5 | Z3: =X3*权重调整机制!K19 -> 4.5 | AA3: 来源：24年可持续发展报告 p72 “2030年前实现碳达峰，2060年前实现碳中和” | AB3: 5 | AC3: =AB3*初始权重设定说明!E5 -> 3.5 | AD3: =AB3*权重调整机制!K19 -> 4.5 | AE3: 来源：24年社会责任报告 p33 碳排放总量预计在2025年达峰 2051-2060为中和期 | AF3: 5 | AG3: =AF3*初始权重设定说明!E5 -> 3.5 | AH3: =AF3*权重调整机制!K19 -> 4.5 | AI3: 来源：24年可持续发展报告 p54 “2023年实现碳达峰，2050年力争实现碳中和” | AJ3: 10 | AK3: =AJ3*初始权重设定说明!E5 -> 7 | AL3: =AJ3*权重调整机制!K19 -> 9 | AM3: 来源：23年ESG报告 p55 （但24年可持续报告未披露） “力争2023年实现碳达峰，2050年力争实现碳中和” | AN3: 10 | AO3: =AN3*初始权重设定说明!E5 -> 7 | AP3: =AN3*权重调整机制!K19 -> 9 | AQ3: 来源：24年可持续发展报告 p42 “确保2030年前实现碳达峰”“2050年力争实现碳中和” | AR3: 10 | AS3: =AR3*初始权重设定说明!E5 -> 7 | AT3: =AR3*权重调整机制!K19 -> 9 | AU3: 来源：24年ESG报告 p48 “明确2030年前实现碳达峰、2050年实现碳中和的总体目标” | AV3: 10 | AW3: =AV3*初始权重设定说明!E5 -> 7 | AX3: =AV3*权重调整机制!K19 -> 9 | AY3: 24年可持续发展报告未明确表述 | AZ3: 0 | BA3: =AZ3*初始权重设定说明!E5 -> 0 | BB3: =AZ3*权重调整机制!K19 -> 0 | BC3: 来源：24年ESG报告 p52 2025年具备减碳30%工艺技术能力、2050年力争实现碳中和“ | BD3: 10 | BE3: =BD3*初始权重设定说明!E5 -> 7 | BF3: =BD3*权重调整机制!K19 -> 9 | BG3: 来源：24年可持续发展报告 p49 2050年实现“碳中和“的目标 | BH3: 10 | BI3: =BH3*初始权重设定说明!E5 -> 7 | BJ3: =BH3*权重调整机制!K19 -> 9 | BK3: 来源：24年可持续发展报告 p41 首钢股份为达成2025年碳达峰、2050至2060年实现碳中和的目标，制定了分阶段的详细规划 | BL3: 5 | BM3: =BL3*初始权重设定说明!E5 -> 3.5 | BN3: =BL3*权重调整机制!K19 -> 4.5 | BO3: 来源：24年可持续发展报告 p52 2023年实现碳达峰，2050年力争实现碳中和 | BP3: 10 | BQ3: =BP3*初始权重设定说明!E5 -> 7 | BR3: =BP3*权重调整机制!K19 -> 9 | BS3: 未披露具体目标年份 | BT3: 0 | BU3: =BT3*初始权重设定说明!E5 -> 0 | BV3: =BT3*权重调整机制!K19 -> 0 | BW3: 24年可持续发展报告 p51 仅表述了“遵循国家及省级层面的碳达峰碳中和目标，结合公司的实际运营状况和长远发展规划，已制定出相应的目标和行动计划” 未披露具体年份 | BX3: 0 | BY3: =BX3*初始权重设定说明!E5 -> 0 | BZ3: =BX3*权重调整机制!K19 -> 0 | CA3: 24年可持续报告 P74 仅表达“凌钢股份积极响应“碳达峰、碳中和”战略目标” | CB3: 0 | CC3: =CB3*初始权重设定说明!E5 -> 0 | CD3: =CB3*权重调整机制!K19 -> 0 | CE3: 来源：24年可持续发展报告 p33 力争2025年实现碳达峰，2050年实现碳中和 | CF3: 10 | CG3: =CF3*初始权重设定说明!E5 -> 7 | CH3: =CF3*权重调整机制!K19 -> 9 | CI3: 来源：24年可持续发展报告 p38 2023年实现碳达峰，2050年实现碳中和 | CJ3: 10 | CK3: =CJ3*初始权重设定说明!E5 -> 7 | CL3: =CJ3*权重调整机制!K19 -> 9
I4: (0, 3] | J4: 2.5
I5: (3, 6] | J5: 5
I6: (6, 9] | J6: 7.5
I7: (9, 12] | J7: 10
C8: 碳达峰目标 | D8: 企业承诺转型目标与国家碳达峰碳中和目标一致，服务于国家碳达峰碳中和目标；制定减排目标是指企业制定短期（如2024-2025年）、中期（2026-2030年）和长期（至2060年）的目标，且目标符合所在行业的先进性水平 | E8: 相等 | F8: 达峰年份承诺与覆盖度 | H8: 计算原始得分 = 基础分 × 范围系数 1. 基础分（时间维度，0–10 分） 无目标：0分 承诺年份 > 2030：3 分 承诺年份=2030，6分 承诺年份 ≤ 2025 或已明确达峰：10 分 2025 < 年份 ≤ 2030： 基础分 = 10 − 0.8 × (年份 − 2025) （说明：2030 年达峰得 6 分，每提前 1 年加 0.8 分） 2. 范围系数 仅覆盖部分区域 / 子公司 / 单一工序范围1：0.5 仅覆盖部分区域 / 子公司 / 单一工序范围1+2：0.6 覆盖部分区域 / 子公司 / 单一工序范围1+2+3：0.7 覆盖全集团范围 1：0.8 覆盖全集团范围 1+2：1 覆盖全集团范围 1+2+3（含重要供应链）：1.2 对计算结果做0-12的分布 | I8: 0 | J8: 0 | K8: 基础分来源：24年可持续发展报告 p71 “宝钢股份全面贯彻《2030年前碳达峰行动方案》等一系列政策文件精神。” 范围系数来源：24年可持续发展报告 p49 “以公司运营范围为边界，包括范围一和范围二” | L8: 5 | M8: =L8*初始权重设定说明!E6 -> 3.5 | N8: =L8*权重调整机制!K20 -> 3.5 | O8: 来源：24年可持续发展报告 p18 “2035年力争减排30%” 参考宝山钢铁《2030年前碳达峰行动方案》 | P8: 5 | Q8: =P8*初始权重设定说明!E6 -> 3.5 | R8: =P8*权重调整机制!K20 -> 3.5 | S8: 来源：24年ESG报告 p39 ”2030年较碳排放峰值降低30%，并力争在2050年实现碳中和的发展目标” | T8: 5 | U8: =T8*初始权重设定说明!E6 -> 3.5 | V8: =T8*权重调整机制!K20 -> 3.5 | W8: 来源：24年可持续发展报告 p103 “2030年前碳达峰，力争2060年前实现碳中和” | X8: 5 | Y8: =X8*初始权重设定说明!E6 -> 3.5 | Z8: =X8*权重调整机制!K20 -> 3.5 | AA8: 来源：24年可持续发展报告 p72 “2030年前实现碳达峰，2060年前实现碳中和” | AB8: 5 | AC8: =AB8*初始权重设定说明!E6 -> 3.5 | AD8: =AB8*权重调整机制!K20 -> 3.5 | AE8: 来源：24年社会责任报告 p33 碳排放总量预计在2025年达峰 2051-2060为中和期 | AF8: 10 | AG8: =AF8*初始权重设定说明!E6 -> 7 | AH8: =AF8*权重调整机制!K20 -> 7 | AI8: 来源：24年可持续发展报告 p54 “2023年实现碳达峰，2050年力争实现碳中和” | AJ8: 10 | AK8: =AJ8*初始权重设定说明!E6 -> 7 | AL8: =AJ8*权重调整机制!K20 -> 7 | AM8: 来源：23年ESG报告 p55 （但24年可持续报告未披露） “力争2023年实现碳达峰，2050年力争实现碳中和” | AN8: 10 | AO8: =AN8*初始权重设定说明!E6 -> 7 | AP8: =AN8*权重调整机制!K20 -> 7 | AQ8: 来源：24年可持续发展报告 p42 “确保2030年前实现碳达峰”“2050年力争实现碳中和” | AR8: 6 | AS8: =AR8*初始权重设定说明!E6 -> 4.2 | AT8: =AR8*权重调整机制!K20 -> 4.2 | AU8: 来源：24年ESG报告 p48 “明确2030年前实现碳达峰、2050年实现碳中和的总体目标” | AV8: 6 | AW8: =AV8*初始权重设定说明!E6 -> 4.2 | AX8: =AV8*权重调整机制!K20 -> 4.2 | AY8: 24年可持续发展报告未明确表述 | AZ8: 0 | BA8: =AZ8*初始权重设定说明!E6 -> 0 | BB8: =AZ8*权重调整机制!K20 -> 0 | BC8: 来源：24年ESG报告 p51 “公司在2023年实现碳达峰的基础上” | BD8: 10 | BE8: =BD8*初始权重设定说明!E6 -> 7 | BF8: =BD8*权重调整机制!K20 -> 7 | BG8: 来源：24年可持续发展报告 p49 公司确立了2030年前实现“碳达峰” | BH8: 6 | BI8: =BH8*初始权重设定说明!E6 -> 4.2 | BJ8: =BH8*权重调整机制!K20 -> 4.2 | BK8: 来源：24年可持续发展报告 p41 首钢股份为达成2025年碳达峰、2050至2060年实现碳中和的目标，制定了分阶段的详细规划 | BL8: 10 | BM8: =BL8*初始权重设定说明!E6 -> 7 | BN8: =BL8*权重调整机制!K20 -> 7 | BO8: 来源：24年可持续发展报告 p52 2023年实现碳达峰，2050年力争实现碳中和 | BP8: 10 | BQ8: =BP8*初始权重设定说明!E6 -> 7 | BR8: =BP8*权重调整机制!K20 -> 7 | BS8: 来源：24年可持续发展报告 p33 双碳目标：“十四五”时期，公司以“格局流程再造为主，实现碳达峰 | BT8: 10 | BU8: =BT8*初始权重设定说明!E6 -> 7 | BV8: =BT8*权重调整机制!K20 -> 7 | BW8: 24年可持续发展报告中未披露具体碳达峰时间，但25年可持续发展报告中对此进行了披露：25年可持续发展报告 p39 “力争2030年前实现碳达峰” | BX8: 6 | BY8: =BX8*初始权重设定说明!E6 -> 4.2 | BZ8: =BX8*权重调整机制!K20 -> 4.2 | CA8: 24年可持续报告 P74 仅表达“凌钢股份积极响应“碳达峰、碳中和”战略目标” | CB8: 0 | CC8: =CB8*初始权重设定说明!E6 -> 0 | CD8: =CB8*权重调整机制!K20 -> 0 | CE8: 来源：24年可持续发展报告 p33 力争2025年实现碳达峰，2050年实现碳中和 | CF8: 10 | CG8: =CF8*初始权重设定说明!E6 -> 7 | CH8: =CF8*权重调整机制!K20 -> 7 | CI8: 来源：24年可持续发展报告 p38 2023年实现碳达峰，2050年实现碳中和 | CJ8: 10 | CK8: =CJ8*初始权重设定说明!E6 -> 7 | CL8: =CJ8*权重调整机制!K20 -> 7
I9: (0, 3] | J9: 2.5
I10: (3, 6] | J10: 5
I11: (6, 9] | J11: 7.5
I12: (9, 12] | J12: 10
C13: 其他环境目标 | D13: 指除碳达峰 / 碳中和目标之外，用于支撑低碳转型路径落地的能效、资源、污染与过程优化类目标。 可识别目标类型包括但不限于： 1. 能效提升（如吨钢综合能耗下降） 2. 能源结构优化（如清洁电力占比、余热利用） 3. 污染物减排（SO₂ / NOx / PM / VOCs） 4. 水资源管理（吨钢取水量、回用率） 5. 资源循环与废弃物（废钢比、固废利用率） 6. 工艺与流程优化（短流程占比、关键工序效率） | E13: 相等 | F13: 企业制定的环境目标的结构完整性与目标质量 | H13: 公式：得分=目标数量得分(S)+目标质量得分(Q) S按企业覆盖的不同目标类型数量计分： 覆盖 0 类：S = 0 覆盖 1 类：S = 1 覆盖 2 类：S = 2 覆盖 3 类：S = 3 覆盖 ≥4 类：S = 4 Q对每一项目标按质量赋值 • 定性表述（无量化）：0.5 分 • 部分量化（有数值但无基准年或目标年）：1.0 分 • 完整量化（指标 + 基准年 + 目标年）：2.0 分 选取质量得分最高的 3 项目标，相加后Q满分 6 分 | I13: 0 | J13: 0 | K13: 来源：24年可持续发展报告 p78 p68 p84 p94 吨钢二氧化碳排放量2025年目标（完整量化 -2） 清洁电力采购（完整量化 -2）、 包钢股份已下达了各单位废水污染物总量约束性目标和废水治理重点任务（定性表述 -0.5） 宝钢股份始终秉持着“一水多用、分级利用、串级使用”原则，并基于2023-2030年水资源管理策略，全面探索节水项目的可行性（部分量化 -1） | L13: 10 | M13: =L13*初始权重设定说明!E7 -> 2 | N13: =L13*权重调整机制!K21 -> 1 | O13: 来源：24年可持续发展报告 p18 2035年力争减碳30% （完整量化 -2） 2025年具备减碳30%工艺技术能力（完整量化 -2） | P13: 6 | Q13: =P13*初始权重设定说明!E7 -> 1.2 | R13: =P13*权重调整机制!K21 -> 0.6 | S13: 来源：24年ESG报告 p39 p48 p54 p43 积极支撑河钢集团实现2025年较碳排放峰值降低10%（完整量化 -2） 到2026年，完成全部企业能效标杆示范厂培育，公司分布式可再生发电规模达到250MW以上（完整量化 -2） 2025年，公司将继续保持废气污染物排放达标（定性表述 -0.5） 公司持续加大绿色低碳技术研发和推广力度，促进资源循环利用（定性表述 -0.5） | T13: 10 | U13: =T13*初始权重设定说明!E7 -> 2 | V13: =T13*权重调整机制!K21 -> 1 | W13: 来源：24年可持续发展报告 p105 p120 p95 p104 产品吨钢排放量-2030年目标（完整量化 -2） 计划到2030年，在VAMA所在工业园区完成100MWp光伏项目的建设（完整量化 -2） 污染物排放全面稳定达标（定性表述 -0.5） 提高废钢比例（定性表述 -0.5） | X13: 10 | Y13: =X13*初始权重设定说明!E7 -> 2 | Z13: =X13*权重调整机制!K21 -> 1 | AA13: 来源：24年可持续发展报告 p73 p74 p91 p72 能源管理目标：“以2021年为基准年，到2025年：吨钢综合能耗较基准年下降5%”（完整量化 -2） 完成余热回收技术迭代更新（定性表述-0.5） 水资源目标：吨钢耗新水量（完整量化 -2） “回收社会废钢再生占比从2021年的9%提升至20%”（部分量化 -1） “着力提升绿色生产工艺水平”（定性表述-0.5） | AB13: 10 | AC13: =AB13*初始权重设定说明!E7 -> 2 | AD13: =AB13*权重调整机制!K21 -> 1 | AE13: 来源：24年社会责任报告 p33 p43 p42 2026-2030年进入达峰平台期2030年预计碳达峰总量较峰值降低4.5%（完整量化 -2） 推动清洁能源发展（定性表述 -0.5） 节水目标：短期、中期、长期（完整量化 -2） 开展生态办公，针对废水、废气、固体废物等污染物，制定并执行相应的管控规范（定性表述 -0.5） | AF13: 10 | AG13: =AF13*初始权重设定说明!E7 -> 2 | AH13: =AF13*权重调整机制!K21 -> 1 | AI13: 来源：24年可持续发展报告 p54 p48 p56 p18 2025年降低碳排放强度6%，2030年降低碳排放强度16%（完整量化 -2） 坚持“引好水、少用水、零排放”理念（定性表述 -0.5） 调整生产结构，增加废钢利用比例（定性表述 -0.5） 革新技术工艺（定性表述 -0.5） | AJ13: 8 | AK13: =AJ13*初始权重设定说明!E7 -> 1.6 | AL13: =AJ13*权重调整机制!K21 -> 0.8 | AM13: 来源：24年ESG报告 p45 p54 策略-极致能效（定性表述 -0.5） 加强能源管理和水资源管控（定性表述 -0.5） 马钢股份大力发展循环经济，重视资源管理与循环利用（定性表述 -0.5） 流程降碳-工艺流程优化 | AN13: 6 | AO13: =AN13*初始权重设定说明!E7 -> 1.2 | AP13: =AN13*权重调整机制!K21 -> 0.6 | AQ13: 来源：24年可持续发展报告 p42 p51 p43 p55 到2030年，具备较2020年CO2排放强度降低30%的资源条件和技术能力，碳排放强度较2020年降低20%（完整量化 -2） 采用清洁能源替代传统高碳能源（定性表述 -0.5） 大气污染治理-制定环境绩效保A三年行动方案（2024-2026）》等文件（部分量化 -1） 提高废钢比（定性表述 -0.5） 结合实际，制定了2023-2025年能效提升实施方案，从管理节能、技术节能、工艺节能三个维度，…年节能量为14.4万吨标准煤（完整量化 -2） | AR13: 10 | AS13: =AR13*初始权重设定说明!E7 -> 2 | AT13: =AR13*权重调整机制!K21 -> 1 | AU13: 来源：24年ESG报告 p23 p56 p49 全面推进清洁生产，大力推进极致能效工程，有序推进“双碳”规划落实。2025年底前，完成超低排放改造（部分量化 -1） 提升废钢掺入比例（定性表述 -0.5） 优化用能结构（定性表述 -0.5） 全面推动能源结构优化、工艺低碳化和绿色产品体系建设（定性表述 -0.5） | AV13: 6 | AW13: =AV13*初始权重设定说明!E7 -> 1.2 | AX13: =AV13*权重调整机制!K21 -> 0.6 | AY13: 来源：24年可持续发展报告 p26 p30 p35 包钢“双碳”技术路径图：极致能效减碳3%-5%、极致能效减碳30%-50% 到2025年吨钢综合能耗降幅5%（完整量化 -2） 冶金资源循环减碳10%-20%（完整量化 -2） 到2025年，公司大宗固废综合利用率达到97%（完整量化 -2） | AZ13: 10 | BA13: =AZ13*初始权重设定说明!E7 -> 2 | BB13: =AZ13*权重调整机制!K21 -> 1 | BC13: 来源：24年ESG报告 p52 推广清洁能源使用（定性表述 -0.5） 2025年具备减碳30%工艺技术能力（完整量化 -2） 持续推动能源结构优化（定性表述 -0.5） | BD13: 6 | BE13: =BD13*初始权重设定说明!E7 -> 1.2 | BF13: =BD13*权重调整机制!K21 -> 0.6 | BG13: 来源：24年可持续发展报告 p40 p39 p55 p61 p65 目标为在系统规划措施落地后，吨钢综合能耗较“十四五”再降低10千克标准煤（完整量化 -2） 公司积极推进清洁能源使用（定性表述 -0.5） 公司持续完善污染物排放治理机制（定性表述 -0.5） 公司高度重视水资源的可持续利用和管理，坚持合法合规取水，最大限度降低取水活动对生态环境的影响（定性表述 -0.5） 公司积极践行循环经济理念，合理利用肥料和副产品...减少对环境的影响（定性表述- 0.5） | BH13: 8 | BI13: =BH13*初始权重设定说明!E7 -> 1.6 | BJ13: =BH13*权重调整机制!K21 -> 0.8 | BK13: 来源：24年可持续发展报告 p58 p60 短期目标：公司2021年制定了到2025年吨钢综合能耗较2020年降低2%（完整量化 -2） 吨钢耗新水较2020年降低1%（完整量化 -2） 绿电占比达到总用电量的5%以上的目标（完整量化 -2） 公司围绕“消纳、增值、引领”管理理念，在减量化、资源化的同时，利用先进技术，加快固体废弃物回收利用（定性表述 -0.5） | BL13: 10 | BM13: =BL13*初始权重设定说明!E7 -> 2 | BN13: =BL13*权重调整机制!K21 -> 1 | BO13: 来源：24年可持续发展报告 p52 p55 p57 p54 p56 p50 2021-2025年公司碳排放强度变化趋势图中2025年数值为1.750（完整量化 -2） 加快光伏发电及氢能等清洁能源发展，提高清洁能源使用率，推进能源结构绿色低碳转型，构建清洁高效能源体系（定性表述 -0.5） 公司认真贯彻落实集团“废气超低排、废水零排放、固废不出厂”行动方案要求，坚持精准治污、科学治污、依法治污（定性表述 -0.5） 加强水资源里（定性表述 -0.5） 积极响应国家《“十四五”循环经济发展规划》号召，将资源再生与经济循环深度融入企业发展战略之中（定性表述 -0.5） 工艺降碳（定性表述 -0.5） | BP13: 8 | BQ13: =BP13*初始权重设定说明!E7 -> 1.6 | BR13: =BP13*权重调整机制!K21 -> 0.8 | BS13: 来源：24年可持续发展报告 p33 p36 到2035年吨钢碳排放强度降低30%以上（完整量化 -2） 大力推进能源结构优化（定性表述 -0.5） 污水治理（定性表述 -0.5） 固废治理（定性表述 -0.5） 2035年之后，在前期技术研发、试验成功的基础上，规模化应用低碳工艺技术，深度降碳，最终实现碳中和（部分量化 -1） | BT13: 8 | BU13: =BT13*初始权重设定说明!E7 -> 1.6 | BV13: =BT13*权重调整机制!K21 -> 0.8 | BW13: 来源：24年可持续发展报告 p51-53 p71 p63 p60 气候行动-降碳计划：提高公司钢厂能效水平+完成时间（部分量化 -1） 推进能源消费结构低碳转型+完成时间（部分量化 -1） 废弃物管理：公司建立了完善的专门管理体系...最大限度降低固废的产生（定性表述 -0.5） 废气管理:为有效减少废弃排放并预防超标排放风险...确保环保目标的实现（定性表述 -0.5） | BX13: 8 | BY13: =BX13*初始权重设定说明!E7 -> 1.6 | BZ13: =BX13*权重调整机制!K21 -> 0.8 | CA13: 来源：24年可持续报告P81-91 “三废治理”（完整量化-2） P84 能源管理（完整量化-2） P85水资源管理（完整量化-2） P86 循环经济 “报告期内，烧结、球团、高炉、转炉等工序产生的除尘灰全部自身利用或回原料系 统混合后回用。煤气布袋灰、水渣等全部委托有资质单位利用” （定性 -0.5） | CB13: 10 | CC13: =CB13*初始权重设定说明!E7 -> 2 | CD13: =CB13*权重调整机制!K21 -> 1 | CE13: 来源：24年可持续发展报告 p33 p29 p28 到2030年，吨钢CO2排放强度较2020年降低20%左右（完整量化 -2） 绿色低碳技术实现普遍应用，非化石能源消费量比重提高（定性表述 -0.5） 以“实现水效标杆、创建节水型企业”为最终目标（定性表述 -0.5） 推进节能技改（定性表述 -0.5） | CF13: 8 | CG13: =CF13*初始权重设定说明!E7 -> 1.6 | CH13: =CF13*权重调整机制!K21 -> 0.8 | CI13: 来源：24年可持续发展报告 p38 p37 p39 2025年具备降碳30%工艺技术能力（完整量化 -2） 推行清洁能源替代，如太阳能、风能和水能等，减少化石燃料的使用（定性表述 -0.5） 开展水资源管理工作，通过多元取水、工艺创新、废水再生等方式降低水资源消耗（定性表述 -0.5） 降低污染排放（定性表述 -0.5） | CJ13: 8 | CK13: =CJ13*初始权重设定说明!E7 -> 1.6 | CL13: =CJ13*权重调整机制!K21 -> 0.8
I14: (0, 2] | J14: 2
I15: (2, 4] | J15: 4
I16: (4, 6] | J16: 6
I17: (6, 8] | J17: 8
I18: (8, 10] | J18: 10
B19: 战略和规划 | C19: 转型规划 | D19: 企业制定明确的转型路线图、行动方案或分阶段规划 | E19: 相等 | F19: 是否制定转型规划以及完善程度 | H19: 以下原始得分按单项累加赋分（一项2分）: 1、企业编制并披露正式的转型规划、转型战略或减排路径图 2、明确路径：披露覆盖短中长期的关键里程碑和实施路线图。 3、定量测算：对主要转型措施的预期减排量或减排贡献进行量化测算（tCO₂e、强度变化等）。 4、温控对标：明确说明转型路径与全球 2°C 目标或更先进的温控目标保持一致。 5、国家对标：转型目标或阶段性指标达到或优于国家相关部门发布的能效、排放或技术基准（如能效标杆、行业规范条件）。 6、国际先进性：说明所采用的方法或情景（如 IEA NZE、SBTi）。 7、自身减排措施：是否披露为实现低碳转型，当前已实施或计划实施的关键减排与转型措施（能源替代、循环经济、低碳工艺、低碳资本支出、碳管理与碳交易、绿色供应链等） | I19: 0 | J19: 0 | K19: 来源：24年可持续发展报告 p49 p52 p58 p66 p69 p64 p156 p61 p118 p53 p77 中国宝武和宝钢股份碳中和技术路线图；-2 “制定了中长期减碳目标，以2020年为基准年，2025年减碳8%，2035年力争减碳30%，2050年力争实现碳中和”-2 “中国钢铁协会2024年度极致能效工程能效标杆示范企业”-2 “我们评估并列举了2050年零碳排放情景（NZE）”-2 “基于零碳能源替代的加热技术研究和系统开发”、“废钢回收量”、“作为国内首家布局氢还原-电熔炼工艺（HyRESP）的核心装备”、环保资本化投入、“搭建了数字化碳管理平台”、“与用户携手推进整体供应链的减碳设计工作”-2 | L19: 10 | M19: =L19*初始权重设定说明!E8 -> 7 | N19: =L19*权重调整机制!K22 -> 6 | O19: 来源：24年可持续发展报告 p17 p8 p38 p16 p8 p61 p71 p88 中国宝武碳中和冶金技术路线图 -2 “双碳最佳实践标杆示范”-2 “2024年直接回收用户废钢60万吨”、“加强低碳工艺技术研发”、“7家公司完成中国钢铁工业协会双碳最佳实践能效标杆示范公示或现场验收”、“以碳核算助推供应链低碳发展的一系列低碳管理模式…四项荣誉”、“环保投入”-2 | P19: 6 | Q19: =P19*初始权重设定说明!E8 -> 4.2 | R19: =P19*权重调整机制!K22 -> 3.6 | S19: 来源：24年ESG报告 p34 p47 p48 p35 p36 p89 p11 实施“6+2”低碳发展技术路线图 -2 “预计每年将为公司增加4300万度绿电，减少4.41万吨的二氧化碳排放”-2 “到2026年，完成全部企业能效标杆示范厂培育”-2 拓展低碳铁素资源循环利用、“低碳技术变革”、极致能效工程能效标杆 、“推动开发‘CManage碳管理’”、“环保投入”推动开发“CSCM”绿色供应链 -2 | T19: 8 | U19: =T19*初始权重设定说明!E8 -> 5.6 | V19: =T19*权重调整机制!K22 -> 4.8 | W19: 来源：24年可持续发展报告p120 p103 p104 p121 p125 p102 p107 p150 p97 “预计节约外购电约6000万度，助力碳排放强度降低7.2kgCO2/t-s”-2 “双碳最佳实践能效标杆示范厂”-2 降碳路径 -2 应用清洁能源、智慧能源管理、“在公司内部将一切铁资源回收成钢铁生产原料”、“研究跟踪新型低碳冶金技术应用”、“开展碳管理、碳汇”、公司环保投入金额、推进绿色供应链实践：“与供应商共同开展绿色项目光伏建设EPC项目现场施工和落地”-2 | X19: 8 | Y19: =X19*初始权重设定说明!E8 -> 5.6 | Z19: =X19*权重调整机制!K22 -> 4.8 | AA19: 来源：24年可持续发展报告 p70 p71 p72 p73 p74 p69 p67 中信泰富特钢碳中和路径、绿色低碳三年行动计划（2023-2025） -2 “下降5%”“力争碳排放量较峰值降低80%左右”-2 “双碳最佳实践能效标杆示范厂”-2 “第一阶段为碳达峰阶段”“第二阶段为稳中有降阶段”“第三阶段为碳中和阶段”-2 “应用可再生能源、采购绿电等，提升企业可再生能源比例”、“短期内布局废钢回收产业”、“公司持续推进重点工序、用能设备的绿色低碳工艺与技术改造”、“推进碳管理数字化平台建设”“EATNS碳管理体系认证”、环保项目总投资、节能项目总投资、“绿色供应链建设组”-2 | AB19: 10 | AC19: =AB19*初始权重设定说明!E8 -> 7 | AD19: =AB19*权重调整机制!K22 -> 6 | AE19: 来源：24年社会责任报告 p33 p11 p40 p45 p34 p32 p37 短期目标、中期目标、长期目标 -2 2024年度钢铁极致能效工程能效标杆三年行动先进企业 -2 “实现污染物排放强度大幅降低”-2 全球升温2°C情境下 -2 循环经济：废钢回收利用率100%、探索降碳工艺、低碳技术研发、“深入开展极致能效工程，投资1.3亿元”、“完成碳交易”、年度投入环境保护的资金总额 -2 | AF19: 10 | AG19: =AF19*初始权重设定说明!E8 -> 7 | AH19: =AF19*权重调整机制!K22 -> 6 | AI19: 来源：24年可持续发展报告 p54 p17 p56 p50 p51 p49 p43 p8 公司“13473”绿色低碳发展模式 -2 能效标杆 -2 三个阶段：笃行五年、展望十年、畅想十五年 -2 “按照引进和自主开发绿色能源替代高排放能源两条路径实施，推动多能互补”、废钢回收再利用量、推进全废钢电弧炉流程极致低碳工艺开发100%、“公司建设全流程在线碳管理平台”、环保项目投入 -2 | AJ19: 8 | AK19: =AJ19*初始权重设定说明!E8 -> 5.6 | AL19: =AJ19*权重调整机制!K22 -> 4.8 | AM19: 来源：24年ESG报告 p45 p55 p54 p52 p46 p84 节能减碳行动路径 -2 “双碳最佳实践能效标杆示范企业”-2 可再生能源电量较上年增加、固废综合利用率99.99%、“研发低碳技术”、“提升碳管理体系能力”、环保总投入 -2 | AN19: 6 | AO19: =AN19*初始权重设定说明!E8 -> 4.2 | AP19: =AN19*权重调整机制!K22 -> 3.6 | AQ19: 来源：24年可持续发展报告 p42 p43 p17 p45 p60 p55 p88 p46 短期目标、中期目标、长期目标 -2 “日照基地2025年预计节约4.6万吨标煤”“钢城基地2025年预计节约5.1万吨标煤”-2 双碳最佳实践能效标杆示范企业 -2 采用清洁能源替代传统高碳能源、回收利用占比达到95.27%、“绿色低碳技术研发与应用”、“制定碳管理相关制度”、环保投入 -2 | AR19: 8 | AS19: =AR19*初始权重设定说明!E8 -> 5.6 | AT19: =AR19*权重调整机制!K22 -> 4.8 | AU19: 来源：24年ESG报告 p48 p11 p37 p50 p46 p43 p65 柳钢碳达峰碳中和规划：碳达峰阶段、稳步降碳阶段、深度脱碳阶段、碳中和 -2 《钢铁行业规范条件》-2 环保投入金额、推动可再生能源替代传统能源、资源回收与循环经济 -2 | AV19: 6 | AW19: =AV19*初始权重设定说明!E8 -> 4.2 | AX19: =AV19*权重调整机制!K22 -> 3.6 | AY19: 来源：24年可持续发展报告 p22 p26 p29 p35 p25 p56 战略：短期-中期-长期 -2 双碳最佳实践能效标杆示范厂培育突出进步企业 能效标杆三年行动 -2 包钢“双碳”技术路径图 -2 使用清洁能源、回收再利用的废弃物占比 、低碳技术开发:“实现降碳量40%”、环保投入、《包钢股份碳管理办法》、推行绿色供应链管理 | AZ19: 8 | BA19: =AZ19*初始权重设定说明!E8 -> 5.6 | BB19: =AZ19*权重调整机制!K22 -> 4.8 | BC19: 来源：24年ESGb报告 p53 p4 p60 p50 6C降碳 -2 能效标杆 -2 “替代固体燃料消耗”、使用清洁能源、“固体废弃物511.25万吨，回收利用率100%”、“跟进前沿绿色低碳技术研发和应用”、环保投入 -2 | BD19: 6 | BE19: =BD19*初始权重设定说明!E8 -> 4.2 | BF19: =BD19*权重调整机制!K22 -> 3.6 | BG19: 来源：24年可持续发展报告 p43 p49 p38 p134 南钢股份碳中和技术路线图 -2 “双碳”三步走战略：2021-2030；2031-2035；2036-2050 -2 全面推广节能新技术：系列减排技术与预计贡献值 -2 环保总投入 -2 | BH19: 8 | BI19: =BH19*初始权重设定说明!E8 -> 5.6 | BJ19: =BH19*权重调整机制!K22 -> 4.8 | BK19: 来源：24年可持续发展报告 p36 p41 p52 p108 降碳技术路线 -2 短期目标：到2030年，低碳产品专线具备吨钢二氧化碳排放强度比2020年降低30%的能力、中期目标：到2035年，公司二氧化碳排放总量较峰值降低30% -2 迁钢公司和京唐公司均被评为“2024年度钢铁极致能效工程能效标杆三年行动先进企业”-2 环保总投入 -2 | BL19: 8 | BM19: =BL19*初始权重设定说明!E8 -> 5.6 | BN19: =BL19*权重调整机制!K22 -> 4.8 | BO19: 来源：24年可持续发展报告 p49 公司“6C”降碳路径 -2 环保投入费用 -2 | BP19: 4 | BQ19: =BP19*初始权重设定说明!E8 -> 2.8 | BR19: =BP19*权重调整机制!K22 -> 2.4 | BS19: 来源：24年可持续发展报告 p34 p33 关键绩效2024:开工建设2*135MW余气...年降碳量19.53万吨 -2 在厂区内建设分布式光伏发电设施...减少对传统化石能源的以来 -2 | BT19: 4 | BU19: =BT19*初始权重设定说明!E8 -> 2.8 | BV19: =BT19*权重调整机制!K22 -> 2.4 | BW19: 来源：24年可持续发展报告 p51 p75 p56 气候行动-降碳计划：包括重点工作、工作任务、实施举措、完成时间 -2 智慧能源系统：项目实施后年节约能源6000吨标煤，减少CO2排放约1.8万吨 -2 2024年，公司钢厂顺利通过双碳最佳实践能效标杆示范企业验收公示 -2 公司环保投入总金额145570.7万元 -2 | BX19: 8 | BY19: =BX19*初始权重设定说明!E8 -> 5.6 | BZ19: =BX19*权重调整机制!K22 -> 4.8 | CA19: 来源： 24年可持续报告P21 “凌钢股份以市场化改革为主线，制定《新凌钢中长期可持续高质量发展规划构想》和《凌钢规划调整实施方案（2024-2025）》" -2; P74凌钢降碳发展战略 -2; P75"预计投产后，25年运行期内平均每年可提供515.7万千瓦时绿色能源，相当于每年节约标准煤633.8吨，减少二氧化碳排放约2,871吨" -2 | CB19: 6 | CC19: =CB19*初始权重设定说明!E8 -> 4.2 | CD19: =CB19*权重调整机制!K22 -> 3.6 | CE19: 来源：24年可持续发展报告 p33 p28 p84 公司成立碳达峰碳中和办公室，编制《碳达峰碳中和行动方案》《低碳钢工作方案》，明确碳达峰碳中和战略目标和行动路径 -2 企业分别设定了到2025年、2030年、2035年和2050年完成的公司碳达峰碳中和目标 -2 到2030年和2035年，吨钢CO2排放强度较2020年分别降低20%左右和25% -2 荣获中国钢铁工业协会“2024年度钢铁极致能效工程能效标杆三年行动先进企业”称号 -2 环保投入费用 -2 | CF19: 10 | CG19: =CF19*初始权重设定说明!E8 -> 7 | CH19: =CF19*权重调整机制!K22 -> 6 | CI19: 来源：24年可持续发展报告 p36 p74 公司应对气候变化商业模式-短期、中期、长期 -2 结合中国宝武碳中和冶金路线图 -2 环保总投入 -2 | CJ19: 6 | CK19: =CJ19*初始权重设定说明!E8 -> 4.2 | CL19: =CJ19*权重调整机制!K22 -> 3.6
I20: (0, 2] | J20: 2
I21: (2, 4] | J21: 4
I22: (4, 6] | J22: 6
I23: (6, 8] | J23: 8
I24: (8, 14] | J24: 10
C25: 其他战略 | D25: 企业如尚未制定专门的转型规划，是否已建立低碳与可持续发展相关的其他制度与行动框架 | E25: 相等 | F25: 若企业没有指定专门的转型规划，是否形成覆盖公司层面的低碳/可持续发展顶层战略或专项行动框架 | H25: 若企业尚未制定专门的转型规划，企业是否编制并披露至少一项以低碳、节能、气候、ESG或可持续发展为核心主题的公司层级顶层战略文件或专项行动方案 （一）文件形式关键词（至少命中 1 类） • 规划 / 战略 / 行动方案 / 行动计划 / 管理办法 / 实施方案• 中长期规划• 专项方案• 指导意见 （二）主题关键词（至少命中 1 类） 低碳/气候/能效类：• 绿色低碳• 双碳• 减碳 / 碳减排• 能效提升• 节能降碳• 气候变化 / 气候风险 ESG / 可持续治理类：• ESG• 可持续发展• 环境、社会及管治• 绿色发展• 供应链减碳 / 绿色供应链 | I25: 否 | J25: 0 | M25: =L25*初始权重设定说明!E9 -> 0 | N25: =L25*权重调整机制!K23 -> 0 | Q25: =P25*初始权重设定说明!E9 -> 0 | R25: =P25*权重调整机制!K23 -> 0 | U25: =T25*初始权重设定说明!E9 -> 0 | V25: =T25*权重调整机制!K23 -> 0 | Y25: =X25*初始权重设定说明!E9 -> 0 | Z25: =X25*权重调整机制!K23 -> 0 | AC25: =AB25*初始权重设定说明!E9 -> 0 | AD25: =AB25*权重调整机制!K23 -> 0 | AE25: 来源：24年社会责任报告 p42 低碳生产：明确吨钢综合能耗指标小于等于588千克标准煤/吨的目标 | AF25: 10 | AG25: =AF25*初始权重设定说明!E9 -> 2 | AH25: =AF25*权重调整机制!K23 -> 2 | AK25: =AJ25*初始权重设定说明!E9 -> 0 | AL25: =AJ25*权重调整机制!K23 -> 0 | AO25: =AN25*初始权重设定说明!E9 -> 0 | AP25: =AN25*权重调整机制!K23 -> 0 | AQ25: 来源：24年可持续发展报告 p50 低碳技术：超临界二氧化碳输送管是基于CCUS技术，用于特殊二氧化碳的封存和驱油的产品 | AR25: 10 | AS25: =AR25*初始权重设定说明!E9 -> 2 | AT25: =AR25*权重调整机制!K23 -> 2 | AW25: =AV25*初始权重设定说明!E9 -> 0 | AX25: =AV25*权重调整机制!K23 -> 0 | AY25: 来源：24年可持续发展报告 p25 低碳技术研发：打造CCUS全产业链示范工程 | AZ25: 10 | BA25: =AZ25*初始权重设定说明!E9 -> 2 | BB25: =AZ25*权重调整机制!K23 -> 2 | BE25: =BD25*初始权重设定说明!E9 -> 0 | BF25: =BD25*权重调整机制!K23 -> 0 | BI25: =BH25*初始权重设定说明!E9 -> 0 | BJ25: =BH25*权重调整机制!K23 -> 0 | BM25: =BL25*初始权重设定说明!E9 -> 0 | BN25: =BL25*权重调整机制!K23 -> 0 | BO25: 来源：24年可持续发展报告 p49 根据中国宝武、中南钢铁“双碳”行动方案，结合自身实际，每年形成“双碳”任务清单并推进项目落地 | BP25: 10 | BQ25: =BP25*初始权重设定说明!E9 -> 2 | BR25: =BP25*权重调整机制!K23 -> 2 | BS25: 来源：24年可持续发展报告 p31 持续完善制度建设：《环境保护工作责任规定》《环保责任事故问责追责管理办法》...等20想环保制度及应急预案文件 | BT25: 10 | BU25: =BT25*初始权重设定说明!E9 -> 2 | BV25: =BT25*权重调整机制!K23 -> 2 | BY25: =BX25*初始权重设定说明!E9 -> 0 | BZ25: =BX25*权重调整机制!K23 -> 0 | CC25: =CB25*初始权重设定说明!E9 -> 0 | CD25: =CB25*权重调整机制!K23 -> 0 | CG25: =CF25*初始权重设定说明!E9 -> 0 | CH25: =CF25*权重调整机制!K23 -> 0 | CK25: =CJ25*初始权重设定说明!E9 -> 0 | CL25: =CJ25*权重调整机制!K23 -> 0
I26: 是 | J26: 10
A27: 实施保障（20分） | B27: 治理 | C27: 治理架构 | D27: 企业围绕低碳/绿色/可持续/转型/ESG议题建立的治理层级完整性与权责清晰度 | E27: 相等 | F27: 治理架构完善程度 | H27: 以下按单项累加赋分: • 设立专职部门或明确牵头部门：2分 • 明确由高管层成员分管相关事务：2分 • 建立跨部门协作机制，例如设立工作小组：2分 • 董事会下设专门委员会：2分 • 董事会在章程/议事规则中明确承担ESG/可持续/低碳/转型等战略统筹和监督职责：2分 • 明确将低碳转型目标和战略纳入薪酬激励措施：2分 | I27: 0 | J27: 0 | K27: 来源：24年可持续发展报告 p47 p17 “我们设立战略、风险及ESG委员会，碳中和推进委员会和碳中和办公室”-2 -2 “碳中和办公室：由规划与科技部部长任主任，协同相关部门落实工作”-2 “战略、风险及ESG委员会：由董事长领导”“碳中和推进委员会：由董事长任主任”-2 | L27: 8 | M27: =L27*初始权重设定说明!E10 -> 5.6 | N27: =L27*权重调整机制!K24 -> 4 | O27: 来源：24年可持续发展报告 p13-14 治理架构 -2 管理层、负责机构、碳中和推进委员会、碳中和办公室 -2 -2 “将绿色低碳相关议题纳入董事会的工作范围中”-2 董事会-工作职责-“负责检查指导全面风险管理体系的有效运行”-2 | P27: 10 | Q27: =P27*初始权重设定说明!E10 -> 7 | R27: =P27*权重调整机制!K24 -> 5 | S27: 来源：24年ESG报告 p31 p100 公司战略与ESG委员会 -2 -2 绿色低碳技术工作组、ESG体系管理工作组 -2 公司董事会下设战略与ESG委员会，负责制定和实施公司低碳战略 -2 | T27: 8 | U27: =T27*初始权重设定说明!E10 -> 5.6 | V27: =T27*权重调整机制!K24 -> 4 | W27: 来源：24年可持续发展报告 p3 p27 p96 战略与ESG委员会 -2 -2 “将认为可行的可持续发展或ESG相关提案提交、汇报给董事会进行审议和决策”-2 | X27: 6 | Y27: =X27*初始权重设定说明!E10 -> 4.2 | Z27: =X27*权重调整机制!K24 -> 3 | AA27: 来源：24年可持续发展报告 p11-12 战略、风险及ESG委员会 -2 -2 “审议、批准公司ESG公开信息、ESG相关风险情况及其他重要性事项”-2 明晰各单位工作职责，搭建长效ESG工作机制 -2 ESG协同管理工作组、ESG推进工作组 -2 | AB27: 10 | AC27: =AB27*初始权重设定说明!E10 -> 7 | AD27: =AB27*权重调整机制!K24 -> 5 | AE27: 来源：24年社会责任报告 p18 公司战略委员会负责推动、执行董事会制定的ESG战略 -2 -2 ESG工作领导小组-2 | AF27: 6 | AG27: =AF27*初始权重设定说明!E10 -> 4.2 | AH27: =AF27*权重调整机制!K24 -> 3 | AI27: 来源：24年可持续发展报告 p9 p11 p25 战略、ESG与科技创新委员会 -2 -2 “由董事会审核与公司规划的一致性，对ESG重要性议题做出最终审批”-2 工作推进小组 -2 | AJ27: 8 | AK27: =AJ27*初始权重设定说明!E10 -> 5.6 | AL27: =AJ27*权重调整机制!K24 -> 4 | AM27: 来源：24年ESG报告 p17-18 董事会-战略与可持续发展委员会 -2 -2 “公司将ESG纳入决策范畴”-2 ESG工作组 -2 决策层：对公司ESG管理愿景、目标及策略的制定进行指导 -2 | AN27: 10 | AO27: =AN27*初始权重设定说明!E10 -> 7 | AP27: =AN27*权重调整机制!K24 -> 5 | AQ27: 来源：24年可持续发展报告 p27 p28 战略规划与ESG委员会 -2 -2 “充分纳入公司战略规划及各项重大决策”-2 ESG推进工作领导工作小组 -2 | AR27: 8 | AS27: =AR27*初始权重设定说明!E10 -> 5.6 | AT27: =AR27*权重调整机制!K24 -> 4 | AU27: 来源：24年ESG报告 p36 董事长：全面领导公司环境保护管理工作-2 主管环保副总经理：领导环境保护管理部门，对重大环保问题进行管理和决策 -2 安全环保部：专职负责环境保护管理工作事宜 -2 | AV27: 6 | AW27: =AV27*初始权重设定说明!E10 -> 4.2 | AX27: =AV27*权重调整机制!K24 -> 3 | AY27: 来源：24年可持续发展报告 p80 “包钢股份研究搭建由董事会、董事会战略及ESG委员会、ESG工作小组机构三个层级构成的ESG治理架构”-2 -2 -2 “最高责任机构”、“负责制定ESG目标以及相关制度”“主要协调和执行机构，协调推进ESG相关事宜落地执行”-2 董事会职责：“审议”“批准”-2 | AZ27: 10 | BA27: =AZ27*初始权重设定说明!E10 -> 7 | BB27: =AZ27*权重调整机制!K24 -> 5 | BC27: 来源：24年ESG报告 p11-13 董事会是公司ESG工作的最高领导机构，董事会战略与风险委员会负责公司ESG工作 -2 -2 -2 管理层按照分工负责分管领域内ESG管理实务 -2 | BD27: 8 | BE27: =BD27*初始权重设定说明!E10 -> 5.6 | BF27: =BD27*权重调整机制!K24 -> 4 | BG27: 来源：24年可持续发展报告 p22-23 p41 南钢股份治理架构：战略与ESG委员会 -2 -2 董事长担任战略与ESG委员会主任 -2 成立由高级管理层、相关部门负责人和外部专家为主要成员的低碳及能源战略委员会，负责制定和实施公司低碳及能源战略，统筹相关工作推进 -2 | BH27: 8 | BI27: =BH27*初始权重设定说明!E10 -> 5.6 | BJ27: =BH27*权重调整机制!K24 -> 4 | BK27: 来源：24年可持续发展报告 p12 ESG治理架构 -2 ESG与合规管理委员会 -2 -2 ESG工作小组 -2 董事会为ESG管理工作的最高决策机构，负责审议批准公司ESG目标和规划、ESG报告发布等事项，并对ESG工作进行全面监督 -2 | BL27: 10 | BM27: =BL27*初始权重设定说明!E10 -> 7 | BN27: =BL27*权重调整机制!K24 -> 5 | BO27: 来源：24年可持续发展报告 p12-13 中南股份全面推进ESG理念与企业发展战略深度融合，将ESG管理融入企业经营战略 -2 董事会是公司ESG工作的最高领导机构，对公司ESG战略、管理、绩效和汇报事宜承担全部责任 -2 不断升级和完善跨部门联动的ESG报告编制工作机制 -2 公司董事会秘书具体统筹工作，董事长负责最终决策...负责收集ESG报告写作素材并协助报告编制 -2 | BP27: 8 | BQ27: =BP27*初始权重设定说明!E10 -> 5.6 | BR27: =BP27*权重调整机制!K24 -> 4 | BS27: 来源：24年可持续发展报告 p7-8 ESG管理架构与体系 -2 ESG管理委员会作为公司ESG事宜管理及公开披露的决策层；ESG管理工作小组作为公司ESG事宜的组织层 -2 -2 -2 董事会负责审议公司ESG事宜相关风险及重要性等 -2 | BT27: 10 | BU27: =BT27*初始权重设定说明!E10 -> 7 | BV27: =BT27*权重调整机制!K24 -> 5 | BW27: 来源：24年可持续发展报告 p22-23 可持续发展治理架构：董事会作为决策层，负责确定ESG战略与目标，确保与公司长期愿景及股东利益相契合等一系列职责 -2 公司深刻认识到可持续发展理念的重要性，将其融入治理架构；在公司重大决策过程中，我们将全面融入ESG因素 -2 决策层由董事会及战略委员会组成，负责制定ESG重大决策...执行层由公司各部门及子公司组成...各项工作任务。-2 -2 | BX27: 8 | BY27: =BX27*初始权重设定说明!E10 -> 5.6 | BZ27: =BX27*权重调整机制!K24 -> 4 | CA27: 来源：24年可持续报告 P21" 董事会下设战略与投资委员会，该委员会下设环境、社会及公司治理（ESG）工作组"-2-2; "负责研究、分析和评估公司ESG相关事项并提出建议，"-2; | CB27: 6 | CC27: =CB27*初始权重设定说明!E10 -> 4.2 | CD27: =CB27*权重调整机制!K24 -> 3 | CE27: 来源：24年可持续发展报告 p19 ESG管治架构-新钢股份董事会战略委员会构建形成包括董事会、董事会战略委员会以及ESG工作组三个层级的ESG管理组织架构 -2 -2 -2 报告中明确了董事会、董事会战略委员会和ESG工作组分别的指责 -2 董事会负责审议批准公司ESG战略规划和目标，以及ESG治理架构和重要制度 -2 | CF27: 10 | CG27: =CF27*初始权重设定说明!E10 -> 7 | CH27: =CF27*权重调整机制!K24 -> 5 | CI27: 来源：24年可持续发展报告 p15 p13 董事会设立战略与投资委员会、审计委员会、提名委员会及薪酬与考核委员会，统筹推进ESG工作有序高效开展。成立ESG工作领导小组，负责公司日常运营中的ESG风险与机遇管理、ESG报告编制等工作 -2 -2 -2 董事会作为公司ESG工作的最高领导机构，对公司ESG战略、管理、绩效和汇报事宜承担全部责任 -2 | CJ27: 8 | CK27: =CJ27*初始权重设定说明!E10 -> 5.6 | CL27: =CJ27*权重调整机制!K24 -> 4
I28: (0, 2] | J28: 2
I29: (2, 4] | J29: 4
I30: (4, 6] | J30: 6
I31: (6, 8] | J31: 8
I32: (8, 12] | J32: 10
B33: 风险管理 | C33: 气候风险管理体系 | D33: 1. 全面风险嵌入（ERM化）：将气候风险由单一环保议题上升为公司级战略风险，实质性嵌入ERM及全价值链决策流程。 2. 治理架构多级化：构建“董事会—管理层—执行层”的三级或四级垂直穿透式治理架构。 3. 管控手段数智化：建设并运行“智能气候风险管理信息系统”或数字化管理平台，实现风险数据的常态化监测与可视化。 4. 责任落实绩效化：形成“目标—执行—考核—追责”闭环，并将气候/碳相关指标刚性挂钩领导班子或管理层年度经营业绩评价。 | E33: 相等 | F33: 气候风险管理体系完善程度 | H33: 以下按单项累加赋分: • 流程：是否明确描述 ≥2 个气候风险管理环节（如识别、评估、监测、应对）—2分 • 战略：是否明确表述气候风险被纳入公司整体风险管理、战略规划或ESG重大决策—2分 • 治理：是否明确气候风险管理治理架构（董事会/委员会/管理层）—2分 • 制度：是否有气候风险管理规章制度或管理办法文件—2分 • 是否有气候风险管理数字化系统，或建立常态化监测机制—2分 • 是否将气候风险纳入考核机制或激励政策—2分 | I33: 0 | J33: 0 | K33: 24年可持续发展报告 p76 p48 p56 p55 p56 宝钢股份气候风险管理流程 -2 “并将气候风险管理纳入企业风险管理流程”-2 气候变化风险管治架构及职责 -2 “建立气温实时监控防护机制”-2 | L33: 8 | M33: =L33*初始权重设定说明!E11 -> 5.6 | N33: =L33*权重调整机制!K25 -> 6.4 | O33: 来源：24年可持续发展报告 p16 p13 p15 “中国宝武深化气候变化相关政策制度建设。制修订《碳达峰碳中和管理办法》《能源环保管理办法》等相关制度”-2 | P33: 2 | Q33: =P33*初始权重设定说明!E11 -> 1.4 | R33: =P33*权重调整机制!K25 -> 1.6 | S33: 来源：24年ESG报告 p31 p32 p49 p18 “识别了与自身运营相关的气候风险与机遇并制定应对措施”-2 “从战略高度加强气候相关风险管理”-2 “积极构建气候变化治理架构”-2 将环保、安全等社会责任及ESG相关工作纳入绩效考核体系 -2 | T33: 8 | U33: =T33*初始权重设定说明!E11 -> 5.6 | V33: =T33*权重调整机制!K25 -> 6.4 | W33: 来源：24年可持续发展报告 p100-102 应对气候变化 “公司主动识别分析了影响公司气候变化相关的风险与机遇，并制定气候风险管理办法与应对措施”-2 | X33: 2 | Y33: =X33*初始权重设定说明!E11 -> 1.4 | Z33: =X33*权重调整机制!K25 -> 1.6 | AA33: 来源：24年可持续发展报告 p69 “在此基础上进行了深入的识别与分析，全面评估气候变化相关风险与机遇对公司业务发展的潜在影响，最终依据分析结果制定出针对性应对措施”-2 “将气候变化风险纳入公司整体风险管理框架中”-2 | AB33: 4 | AC33: =AB33*初始权重设定说明!E11 -> 2.8 | AD33: =AB33*权重调整机制!K25 -> 3.2 | AE33: 来源：24年社会责任报告 p32 “公司将应对气候变化纳入整体发展规划”-2 “完善并下发《双碳工作推进体系》…推动应对气候变化治理更规范、高效”-2 | AF33: 4 | AG33: =AF33*初始权重设定说明!E11 -> 2.8 | AH33: =AF33*权重调整机制!K25 -> 3.2 | AI33: 来源：24年可持续发展报告 p57 p53 “公司将气候相关影响、风险和机遇纳入公司战略实施”-2 风险管理流程：识别、管理、检测 -2 “建立有《能源环保管理办法》《碳达峰碳中和管理办法》《环保低碳能源综合评价方案》等管理评价考核办法 -2 治理架构 -2 | AJ33: 8 | AK33: =AJ33*初始权重设定说明!E11 -> 5.6 | AL33: =AJ33*权重调整机制!K25 -> 6.4 | AM33: 来源：24年ESG报告 p44 p47 “公司识别多项…并通过有效措施来适应…带来的影响”-2 “‘董事会-碳中和工作领导小组-碳中和办公室’气候变化相关治理架构”-2 “制定《碳达峰碳中和行动方案》”-2 | AN33: 6 | AO33: =AN33*初始权重设定说明!E11 -> 4.2 | AP33: =AN33*权重调整机制!K25 -> 4.8 | AQ33: 来源：24年ESG报告 p42 “组织对执行层气候治理措施落实的监督和考核”-2 ”气候治理决策层”“气候治理管理层”“气候治理执行层”-2 “组织对执行层气候治理措施落实的监督和考核”-2 | AR33: 6 | AS33: =AR33*初始权重设定说明!E11 -> 4.2 | AT33: =AR33*权重调整机制!K25 -> 4.8 | AU33: 来源：24年ESG报告 p47 p49 “积极识别”“制定契合实际的管理策略及措施”-2 “未来公司将推动气候风险管理融入全面风险管理体系”-2 “全面构建规范化管理体系，制定并颁布《碳达峰碳中和推进管理办法》”-2 “通过建立目标分解、过程跟踪、考核评价闭环机制”-2 | AV33: 8 | AW33: =AV33*初始权重设定说明!E11 -> 5.6 | AX33: =AV33*权重调整机制!K25 -> 6.4 | AY33: 来源：24年可持续发展报告 p22 p19 p24 ”对气候相关风险和机遇进行辨识和梳理”-2 将气候治理纳入核心战略 -2 开展数字化碳管理平台 -2 | AZ33: 6 | BA33: =AZ33*初始权重设定说明!E11 -> 4.2 | BB33: =AZ33*权重调整机制!K25 -> 4.8 | BC33: 来源：24年ESG报告 p51 治理架构 -2 | BD33: 2 | BE33: =BD33*初始权重设定说明!E11 -> 1.4 | BF33: =BD33*权重调整机制!K25 -> 1.6 | BG33: 来源：24年可持续发展报告 p41 p47 p48 气候变化治理机制 -2 公司通过开展政策调研、同业对标，并结合专家意见，识别出与自身运营相关的气候变化相关风险与机遇...融入企业ESG整体管理框架及风险管理体系中 -2 -2 上线智慧能源管理系统 -2 | BH33: 8 | BI33: =BH33*初始权重设定说明!E11 -> 5.6 | BJ33: =BH33*权重调整机制!K25 -> 6.4 | BK33: 来源：24年可持续发展报告 p37 p34 p42 p41 公司结合自身业务特点和经营情况，进行系统性分析和评估 -2 治理：绿色制造委员会 -2 公司积极应对气候变化，持续规范气候治理管理体系...紧密结合公司实际情况，制定了《气候治理管理制度》《碳排放报告与核查管理制度》，从制度层面保障气候治理工作的规范开展 -2 组织公司环保管理绩效监督与考核 -2 智慧碳管理平台 -2 | BL33: 10 | BM33: =BL33*初始权重设定说明!E11 -> 7 | BN33: =BL33*权重调整机制!K25 -> 8 | BO33: 来源：24年可持续发展报告 p49 治理：成立碳中和工作委员会...分层管理架构 -2 健全碳排放预核查机制，成立碳排放核查小组...跟踪年度和月度碳排放量、配额量，控制和减少碳排放-2 | BP33: 4 | BQ33: =BP33*初始权重设定说明!E11 -> 2.8 | BR33: =BP33*权重调整机制!K25 -> 3.2 | BS33: 来源：24年可持续发展报告 p8 ESG管理工作小组对公司ESG领域包括但不限于应对气候变化...进行制定并提出更新建议 -2 | BT33: 2 | BU33: =BT33*初始权重设定说明!E11 -> 1.4 | BV33: =BT33*权重调整机制!K25 -> 1.6 | BW33: 来源：24年可持续发展报告 p50 p48 风险识别、风险评估、风险监督、风险管理 -2 保证气候风险管理与公司整体战略协同共进 -2 治理：管理体系-为有序推进国家双碳目标...并加快构建绿色产业价值链，推动企业可持续发展 -2 公司钢厂制定了《宁波钢铁有限公司碳达峰专项行动方案》-2 治理：监督与考核 -2 风险监督：建立风险监测指标体系，对风险进行实时监测 -2 | BX33: 10 | BY33: =BX33*初始权重设定说明!E11 -> 7 | BZ33: =BX33*权重调整机制!K25 -> 8 | CA33: 来源：24年可持续报告P17 “双重重要性 应对气候变化”-2；P79“环境风险防控：公司建立了环境监测与预警机制”-2 | CB33: 4 | CC33: =CB33*初始权重设定说明!E11 -> 2.8 | CD33: =CB33*权重调整机制!K25 -> 3.2 | CE33: 24年可持续发展报告中未披露关于气候相关风险信息 | CF33: 0 | CG33: =CF33*初始权重设定说明!E11 -> 0 | CH33: =CF33*权重调整机制!K25 -> 0 | CI33: 来源：24年可持续发展报告 p37 p36 公司将气候相关风险识别、评估和管理纳入企业整体风险管理流程 -2 完善应对气候变化治理架构，成立以公司领导为主要负责人的碳中和领导小组和碳中和办公室 -2 | CJ33: 4 | CK33: =CJ33*初始权重设定说明!E11 -> 2.8 | CL33: =CJ33*权重调整机制!K25 -> 3.2
I34: (0, 2] | J34: 2
I35: (2, 4] | J35: 4
I36: (4, 6] | J36: 6
I37: (6, 8] | J37: 8
I38: (8, 12] | J38: 10
C39: 气候相关风险和机遇 | D39: 1. 风险与机遇识别完整性：同时识别转型风险与实体风险，涵盖政策/法律、技术、市场、供应链、声誉、急性与慢性物理风险等；同时识别低碳产品、能源结构优化、政策支持等机遇。 2. 时间维度清晰性：在短期（1–2年）、中期（3–6年）、长期（7年及以上）不同时间框架下开展识别与评估。 3. 财务影响关联性：识别风险和机遇对成本、收入、投资、融资、信用风险等财务事项的影响。 4. 量化深度差异：区分定性判断、间接量化（环保投入、节能降本）与直接量化（营收变化、成本变化、溢价比例、履约成本节约等）。 | E39: 相等 | F39: 风险与机遇识别完善程度 | H39: 以下按单项累加赋分: （1）识别完整性 — 同时识别转型风险与实体风险/物理风险：2 分 — 风险类型覆盖 3 类及以上（政策/技术/市场/声誉/信用等）：2 分 — 同时识别明确的气候相关机遇：2 分 （2）财务影响识别 — 明确风险或机遇与财务结果存在关联：2 分 — 对财务影响进行量化分析：2 分 （3）应对气候影响的措施 — 针对上述识别风险制定了应对措施：2分 | I39: 0 | J39: 0 | K39: 24年可持续发展报告 p52-p55 转型风险、实体风险 -2 气候变化机遇 -2 机遇类型、对财务的影响 -2 “2024年节能低碳投资18.9亿元，2025年预算34.3亿元”-2 应对举措 -2 | L39: 10 | M39: =L39*初始权重设定说明!E12 -> 5 | N39: =L39*权重调整机制!K26 -> 6 | O39: 未披露 | P39: 0 | Q39: =P39*初始权重设定说明!E12 -> 0 | R39: =P39*权重调整机制!K26 -> 0 | S39: 来源：24年ESG报告 p32-34 转型风险、实体风险 -2 政策、法律、技术、市场 -2 机遇描述 -2 管理及应对策略 -2 | T39: 8 | U39: =T39*初始权重设定说明!E12 -> 4 | V39: =T39*权重调整机制!K26 -> 4.8 | W39: 来源：24年可持续发展报告 p101-102 政策与法律法规、技术风险、市场风险、声誉风险 -2 机遇 -2 潜在财务影响-2 应对措施 -2 | X39: 8 | Y39: =X39*初始权重设定说明!E12 -> 4 | Z39: =X39*权重调整机制!K26 -> 4.8 | AA39: 来源：24年可持续发展报告p69-70 政策、技术、市场、声誉 -2 机遇 -2 潜在财务影响 -2 应对措施 -2 | AB39: 8 | AC39: =AB39*初始权重设定说明!E12 -> 4 | AD39: =AB39*权重调整机制!K26 -> 4.8 | AE39: 来源：24年社会责任报告 p33 转型风险、物理风险 -2 应对举措 -2 | AF39: 4 | AG39: =AF39*初始权重设定说明!E12 -> 2 | AH39: =AF39*权重调整机制!K26 -> 2.4 | AI39: 来源：24年可持续发展报告 p55 物理风险、转型风险 -2 政策、技术、市场 -2 机遇 -2 应对措施 -2 | AJ39: 8 | AK39: =AJ39*初始权重设定说明!E12 -> 4 | AL39: =AJ39*权重调整机制!K26 -> 4.8 | AM39: 来源：24年ESG报告 p47 实体风险、过渡风险 -2 应对措施 -2 | AN39: 4 | AO39: =AN39*初始权重设定说明!E12 -> 2 | AP39: =AN39*权重调整机制!K26 -> 2.4 | AQ39: 来源：24年可持续报告 p44-45 物理风险、转型风险 -2 政策、技术、市场、声誉 -2 机遇 -2 | AR39: 6 | AS39: =AR39*初始权重设定说明!E12 -> 3 | AT39: =AR39*权重调整机制!K26 -> 3.6 | AU39: 来源：24年ESG报告 物理风险、转型风险 -2 政策、技术、市场、声誉 -2 机遇 -2 应对措施 -2 | AV39: 8 | AW39: =AV39*初始权重设定说明!E12 -> 4 | AX39: =AV39*权重调整机制!K26 -> 4.8 | AY39: 来源：24年可持续发展报告 p22-25 实体风险、转型风险 -2 政策、技术、市场、声誉 -2 机遇 -2 应对措施 -2 | AZ39: 8 | BA39: =AZ39*初始权重设定说明!E12 -> 4 | BB39: =AZ39*权重调整机制!K26 -> 4.8 | BC39: 来源：24年ESG报告 p52 实体风险、转型风险 -2 机遇 -2 应对举措 -2 | BD39: 6 | BE39: =BD39*初始权重设定说明!E12 -> 3 | BF39: =BD39*权重调整机制!K26 -> 3.6 | BG39: 来源：24年可持续发展报告 p47-48 政策和法律风险、市场风险、技术风险、声誉风险、急性物理风险、慢性物理风险 -2 -2 机遇部分包括：产品与服务、技术投资与开发、资源效率、能源类型 -2 潜在财务风险 -2 应对措施 -2 | BH39: 10 | BI39: =BH39*初始权重设定说明!E12 -> 5 | BJ39: =BH39*权重调整机制!K26 -> 6 | BK39: 来源：24年可持续发展报告 p37 p38 物理风险、转型风险 -2 政策与法律法规、技术和成本、市场、声誉 -2 机遇：产品服务、能源效率、能源来源、碳管理与交易 -2 潜在影响中有关于对财务影响的相关表述，比如“可能带来实物资产减值或损失”、“运营成本上升”等 -2 风险应对能力提升 -2 | BL39: 10 | BM39: =BL39*初始权重设定说明!E12 -> 5 | BN39: =BL39*权重调整机制!K26 -> 6 | BO39: 来源：24年可持续发展报告 p51 物理风险、转型风险 -2 合规风险、技术风险、市场风险、声誉风险 -2 风险描述中有“间接影响营业收入”“增加经营成本”等财务影响表述 -2 应对措施 -2 | BP39: 8 | BQ39: =BP39*初始权重设定说明!E12 -> 4 | BR39: =BP39*权重调整机制!K26 -> 4.8 | BS39: 未披露任何气候相关风险、机遇、应对措施 | BT39: 0 | BU39: =BT39*初始权重设定说明!E12 -> 0 | BV39: =BT39*权重调整机制!K26 -> 0 | BW39: 来源：24年可持续发展报告 p49 p50 物理风险、转型风险 -2 政策风险、市场风险、声誉风险 -2 机遇类型：资源效率提升机遇、绿色钢铁技术机遇、政策补贴与融资优势 -2 对公司财务的影响 -2 应对措施 -2 | BX39: 10 | BY39: =BX39*初始权重设定说明!E12 -> 5 | BZ39: =BX39*权重调整机制!K26 -> 6 | CA39: 来源：24年可持续报告 P76 “影响、风险和机遇管理” 转型风险/实体风险-2； 机遇类型 -2； 风险覆盖类型-2；应对措施-2 | CB39: 8 | CC39: =CB39*初始权重设定说明!E12 -> 4 | CD39: =CB39*权重调整机制!K26 -> 4.8 | CE39: 24年可持续发展报告中未披露关于气候相关风险信息 | CF39: 0 | CG39: =CF39*初始权重设定说明!E12 -> 0 | CH39: =CF39*权重调整机制!K26 -> 0 | CI39: 来源：24年可持续发展报告 p37 转型风险、物理风险 -2 法规风险、技术风险、市场风险、声誉风险 -2 财务或运营影响 -2 应对措施 -2 | CJ39: 8 | CK39: =CJ39*初始权重设定说明!E12 -> 4 | CL39: =CJ39*权重调整机制!K26 -> 4.8
I40: (0, 2] | J40: 2
I41: (2, 4] | J41: 4
I42: (4, 6] | J42: 6
I43: (6, 8] | J43: 8
I44: (8, 12] | J44: 10
C45: 气候压力测试 | D45: 1. 开展情况：明确披露已开展气候情景分析或压力测试。 2. 情景设置特征：情景覆盖转型风险与实体风险，包含中长期时间尺度。 3. 方法论来源：参考国际或行业权威情景与框架（如 IFRS S2、IEA、IPCC、钢铁行业低碳转型情景）。 4. 结果应用：情景分析结果用于评估对经营、成本、收入、资产或融资的潜在影响，并支撑风险管理或战略判断。 | E45: 相等 | F45: 气候压力测试完善程度 | H45: 以下按单项累加赋分: （1）情景分析开展与情景设置 明确披露已开展气候情景分析或压力测试：2 分 情景同时覆盖转型风险与实体风险：2 分 情景包含短中长期时间维度（如 2030 / 2050 或等效表述）：2分 设置多个情景用于对比分析（如低碳转型情景与基准情景、不同实体风险情景）：2分 （2）方法论参考与结果应用 明确引用 IFRS S2、IEA、IPCC 或行业权威研究作为情景或方法论来源：2 分 情景分析结果用于评估对经营、财务或风险管理的影响：1 分 明确说明情景分析结果被用于战略、投资、风险应对或管理决策：1 分 | I45: 0 | J45: 0 | K45: 24年可持续发展报告 p51-p54 气候变化情景分析 -2 "IPCC""IEA" -2 "我们评估列举了2050年零碳排放情景（NZE)”-2 “并通过定量分析对比各类风险可能导致的财务金额减损/增加”-2 -1 | L45: 10 | M45: =L45*初始权重设定说明!E13 -> 1 | N45: =L45*权重调整机制!K27 -> 1 | O45: 未披露 | P45: 0 | Q45: =P45*初始权重设定说明!E13 -> 0 | R45: =P45*权重调整机制!K27 -> 0 | S45: 未披露 | T45: 0 | U45: =T45*初始权重设定说明!E13 -> 0 | V45: =T45*权重调整机制!K27 -> 0 | W45: 未披露 | X45: 0 | Y45: =X45*初始权重设定说明!E13 -> 0 | Z45: =X45*权重调整机制!K27 -> 0 | AA45: 未披露 | AB45: 0 | AC45: =AB45*初始权重设定说明!E13 -> 0 | AD45: =AB45*权重调整机制!K27 -> 0 | AE45: 来源：24年社会责任报告 p33 场景分析（全球升温2摄氏度情景下）-2 转型风险、物理风险-2 影响分析-1 | AF45: 6 | AG45: =AF45*初始权重设定说明!E13 -> 0.6 | AH45: =AF45*权重调整机制!K27 -> 0.6 | AI45: 未披露 | AJ45: 0 | AK45: =AJ45*初始权重设定说明!E13 -> 0 | AL45: =AJ45*权重调整机制!K27 -> 0 | AM45: 未披露 | AN45: 0 | AO45: =AN45*初始权重设定说明!E13 -> 0 | AP45: =AN45*权重调整机制!K27 -> 0 | AQ45: 未披露 | AR45: 0 | AS45: =AR45*初始权重设定说明!E13 -> 0 | AT45: =AR45*权重调整机制!K27 -> 0 | AU45: 来源：24年ESG报告 p48 IFRS S2 -2 | AV45: 2 | AW45: =AV45*初始权重设定说明!E13 -> 0.2 | AX45: =AV45*权重调整机制!K27 -> 0.2 | AY45: 未披露 | AZ45: 0 | BA45: =AZ45*初始权重设定说明!E13 -> 0 | BB45: =AZ45*权重调整机制!K27 -> 0 | BC45: 未披露 | BD45: 0 | BE45: =BD45*初始权重设定说明!E13 -> 0 | BF45: =BD45*权重调整机制!K27 -> 0 | BG45: 未披露 | BH45: 0 | BI45: =BH45*初始权重设定说明!E13 -> 0 | BJ45: =BH45*权重调整机制!K27 -> 0 | BK45: 未披露 | BL45: 0 | BM45: =BL45*初始权重设定说明!E13 -> 0 | BN45: =BL45*权重调整机制!K27 -> 0 | BO45: 未披露 | BP45: 0 | BQ45: =BP45*初始权重设定说明!E13 -> 0 | BR45: =BP45*权重调整机制!K27 -> 0 | BS45: 未披露 | BT45: 0 | BU45: =BT45*初始权重设定说明!E13 -> 0 | BV45: =BT45*权重调整机制!K27 -> 0 | BW45: 未披露 | BX45: 0 | BY45: =BX45*初始权重设定说明!E13 -> 0 | BZ45: =BX45*权重调整机制!K27 -> 0 | CA45: 未披露 | CB45: 0 | CC45: =CB45*初始权重设定说明!E13 -> 0 | CD45: =CB45*权重调整机制!K27 -> 0 | CE45: 未披露 | CF45: 0 | CG45: =CF45*初始权重设定说明!E13 -> 0 | CH45: =CF45*权重调整机制!K27 -> 0 | CI45: 未披露 | CJ45: 0 | CK45: =CJ45*初始权重设定说明!E13 -> 0 | CL45: =CJ45*权重调整机制!K27 -> 0
I46: (0, 2] | J46: 2
I47: (2, 4] | J47: 4
I48: (4, 6] | J48: 6
I49: (6, 8] | J49: 8
I50: (8, 12] | J50: 10
A51: 转型表现 | B51: 碳排放表现 | C51: 碳排放披露情况 | D51: 1. 核心词：范围1、直接排放、范围2、能源间接排放、范围3、价值链排放 2. 范围3类别词：类别1、采购商品、上下游运输、差旅、员工通勤、废弃物 | E51: 相等 | F51: 披露完整度 | H51: 企业披露情况，按分档进行赋分； - 0分：企业未披露范围1、范围2、范围3任意一个，直接赋分0； - 2.5分：仅披露“范围1”或仅披露总量未区分范围 - 5分：完整披露范围1 和 范围2，未披露范围3 - 7.5分：披露范围1、范围2和范围3中的1-2个类别 - 10分：披露范围1、范围2，范围3的披露满足以下任一条件 a) 类别数量 ≥3 b) 包含“类别1：购买的商品/服务”关键项 | I51: 未披露 | J51: 0 | K51: 来源：24年可持续发展报告-附录-可持续发展报告 类别一、类别二、类别三 | L51: 10 | M51: =L51*初始权重设定说明!E14 -> 7 | N51: =L51*权重调整机制!K28 -> 7 | O51: 未披露 | P51: 0 | Q51: =P51*初始权重设定说明!E14 -> 0 | R51: =P51*权重调整机制!K28 -> 0 | S51: 来源：24年ESG报告 范围一、范围二 | T51: 5 | U51: =T51*初始权重设定说明!E14 -> 3.5 | V51: =T51*权重调整机制!K28 -> 3.5 | W51: 来源：24年可持续发展报告 绝对排放量 | X51: 2.5 | Y51: =X51*初始权重设定说明!E14 -> 1.75 | Z51: =X51*权重调整机制!K28 -> 1.75 | AA51: 来源：24年可持续发展报告 范围一、范围二 | AB51: 5 | AC51: =AB51*初始权重设定说明!E14 -> 3.5 | AD51: =AB51*权重调整机制!K28 -> 3.5 | AE51: 24年数据未披露 | AF51: 0 | AG51: =AF51*初始权重设定说明!E14 -> 0 | AH51: =AF51*权重调整机制!K28 -> 0 | AI51: 来源：24年社会责任报告 p8 范围一、范围二 | AJ51: 5 | AK51: =AJ51*初始权重设定说明!E14 -> 3.5 | AL51: =AJ51*权重调整机制!K28 -> 3.5 | AM51: 来源：24年ESG报告 p47 范围一、范围二 | AN51: 5 | AO51: =AN51*初始权重设定说明!E14 -> 3.5 | AP51: =AN51*权重调整机制!K28 -> 3.5 | AQ51: 来源：24年可持续发展报告 p45 范围一、范围二 | AR51: 5 | AS51: =AR51*初始权重设定说明!E14 -> 3.5 | AT51: =AR51*权重调整机制!K28 -> 3.5 | AU51: 来源：24年ESG报告 p51 范围一、范围二、范围三 | AV51: 10 | AW51: =AV51*初始权重设定说明!E14 -> 7 | AX51: =AV51*权重调整机制!K28 -> 7 | AY51: 未披露 | AZ51: 0 | BA51: =AZ51*初始权重设定说明!E14 -> 0 | BB51: =AZ51*权重调整机制!K28 -> 0 | BC51: 来源：24年ESG发展报告 p53 范围一、范围二 | BD51: 5 | BE51: =BD51*初始权重设定说明!E14 -> 3.5 | BF51: =BD51*权重调整机制!K28 -> 3.5 | BG51: 来源：24年可持续发展报告 p49 范围1、范围2、范围3 | BH51: 10 | BI51: =BH51*初始权重设定说明!E14 -> 7 | BJ51: =BH51*权重调整机制!K28 -> 7 | BK51: 来源：24年可持续发展报告 p41 范围1、范围2 | BL51: 5 | BM51: =BL51*初始权重设定说明!E14 -> 3.5 | BN51: =BL51*权重调整机制!K28 -> 3.5 | BO51: 来源：24年可持续发展报告 p52 范围一、范围二 | BP51: 5 | BQ51: =BP51*初始权重设定说明!E14 -> 3.5 | BR51: =BP51*权重调整机制!K28 -> 3.5 | BS51: 未披露 | BT51: 0 | BU51: =BT51*初始权重设定说明!E14 -> 0 | BV51: =BT51*权重调整机制!K28 -> 0 | BW51: 24年可持续发展报告中未披露24年碳排放，但是2025年可持续发展报告中披露了24年的碳排放 p39 范围一：8516409吨、范围二：191310.61吨 | BX51: 5 | BY51: =BX51*初始权重设定说明!E14 -> 3.5 | BZ51: =BX51*权重调整机制!K28 -> 3.5 | CA51: 24年可持续报告中明确表示未披露当期碳排放数据 | CB51: 0 | CC51: =CB51*初始权重设定说明!E14 -> 0 | CD51: =CB51*权重调整机制!K28 -> 0 | CE51: 来源：24年可持续发展报告 p86 范围一、范围二 | CF51: 5 | CG51: =CF51*初始权重设定说明!E14 -> 3.5 | CH51: =CF51*权重调整机制!K28 -> 3.5 | CI51: 来源：24年可持续发展报告 p74 范围一、范围二 | CJ51: 5 | CK51: =CJ51*初始权重设定说明!E14 -> 3.5 | CL51: =CJ51*权重调整机制!K28 -> 3.5
I52: 仅披露范围1 | J52: 2.5
I53: 披露范围1和范围2 | J53: 5
I54: 披露范围1、范围2和范围3中的1-2个类别 | J54: 7.5
I55: 披露范围1、范围2和范围3中的至少3个类别，或至少包含“类别1：购买的商品/服务”关键项 | J55: 10
C56: 物理碳排放强度 | D56: 单位粗钢产量所产生的范围一和范围二的碳排放量 | E56: 环比变化（30%） + 当期横向位置（70%） | F56: 环比变化 | H56: （一）当期物理碳强度计算 当期物理碳强度=当年碳排放量÷当年粗钢产量 单位：吨二氧化碳 / 吨钢 （二）环比变化维度（30%） 1. 环比变化率计算 环比变化率 = (上年物理碳强度 - 当期物理碳强度) ÷ 上年物理碳强度 说明：环比变化率大于0表示碳强度较上年下降，转型表现为正；数值越大表现越好。 2. 行业分位区间确定 对行业内所有企业的"环比变化率"进行排序，确定以下分位点： P10 变化率 = 行业内环比变化率的第 10 分位值 P90 变化率 = 行业内环比变化率的第 90 分位值 3. 归一化赋分 在区间 [P10 变化率，P90 变化率] 内进行线性归一映射： • 当 企业环比变化率 ≤ P10 变化率 时，环比得分 = 0 • 当 企业环比变化率 ≥ P90 变化率 时，环比得分 = 10 • 当 P10 变化率 < 企业环比变化率 < P90 变化率 时： 环比得分 = 10 ×（企业环比变化率 − P10 变化率）÷（P90 变化率 − P10 变化率） | I56: 企业改进率 ≤ P10 改进率 | J56: 1 | K56: 来源：24年可持续发展报告 24、23年数据 类别1+类别2+类别3 24、23年报 | L56: 2.19 | M56: =SUM(L56:L61)*初始权重设定说明!E15 -> 1.533 | N56: =SUM(L56:L61)*权重调整机制!K29 -> 1.533 | O56: 未披露 | P56: 0 | Q56: =SUM(P56:P61)*初始权重设定说明!E15 -> 0 | R56: =SUM(P56:P61)*权重调整机制!K29 -> 0 | S56: 来源：24年可持续发展报告 温室气体排放总量 24、23年数据 24、23年报 | T56: 2.15 | U56: =SUM(T56:T61)*初始权重设定说明!E15 -> 1.96 | V56: =SUM(T56:T61)*权重调整机制!K29 -> 1.96 | W56: 仅披露了绝对排放量，口径不一致，无法比较 | X56: 0 | Y56: =SUM(X56:X61)*初始权重设定说明!E15 -> 0 | Z56: =SUM(X56:X61)*权重调整机制!K29 -> 0 | AA56: 来源：24年可持续发展报告 24、23年温室气体排放总量（范围1+范围2） 24、23年报 | AB56: 3 | AC56: =SUM(AB56:AB61)*初始权重设定说明!E15 -> 3.843 | AD56: =SUM(AB56:AB61)*权重调整机制!K29 -> 3.843 | AE56: 24年数据未披露 | AF56: 0 | AG56: =SUM(AF56:AF61)*初始权重设定说明!E15 -> 0 | AH56: =SUM(AF56:AF61)*权重调整机制!K29 -> 0 | AI56: 来源：24年可持续发展报告 24、23年范围一+范围二 24、23年报 | AJ56: 2.4 | AK56: =SUM(AJ56:AJ61)*初始权重设定说明!E15 -> 4.165 | AL56: =SUM(AJ56:AJ61)*权重调整机制!K29 -> 4.165 | AM56: 来源：24年可持续发展报告 24、23年范围一+范围二 24、23年报 | AN56: 0.69 | AO56: =SUM(AN56:AN61)*初始权重设定说明!E15 -> 1.113 | AP56: =SUM(AN56:AN61)*权重调整机制!K29 -> 1.113 | AQ56: 来源：24年可持续发展报告 24、23年温室气体排放总量（范围1和范围2） 24、23年报 | AR56: 1.83 | AS56: =SUM(AR56:AR61)*初始权重设定说明!E15 -> 2.779 | AT56: =SUM(AR56:AR61)*权重调整机制!K29 -> 2.779 | AU56: 来源：24年可持续发展报告 24、23年范围一+范围二+范围三 24、23年年报 | AV56: 3 | AW56: =SUM(AV56:AV61)*初始权重设定说明!E15 -> 7 | AX56: =SUM(AV56:AV61)*权重调整机制!K29 -> 7 | AY56: 未披露 | AZ56: 0 | BA56: =SUM(AZ56:AZ61)*初始权重设定说明!E15 -> 0 | BB56: =SUM(AZ56:AZ61)*权重调整机制!K29 -> 0 | BC56: 来源：24年可持续发展报告 24、23年范围一+范围二 24、23年年报 | BD56: 1.91 | BE56: =SUM(BD56:BD61)*初始权重设定说明!E15 -> 4.186 | BF56: =SUM(BD56:BD61)*权重调整机制!K29 -> 4.186 | BG56: 来源：24年可持续发展报告 24、23年范围1+范围2 24、23年年报 | BH56: 0 | BI56: =SUM(BH56:BH61)*初始权重设定说明!E15 -> 0 | BJ56: =SUM(BH56:BH61)*权重调整机制!K29 -> 0 | BK56: 来源：24年可持续发展报告 24、23范围1和范围2 24、23年年报 | BL56: 1.84 | BM56: =SUM(BL56:BL61)*初始权重设定说明!E15 -> 2.422 | BN56: =SUM(BL56:BL61)*权重调整机制!K29 -> 2.422 | BO56: 来源：24年可持续发展报告 24、23范围一+范围二 24、23年年报 | BP56: 1.95 | BQ56: =SUM(BP56:BP61)*初始权重设定说明!E15 -> 2.898 | BR56: =SUM(BP56:BP61)*权重调整机制!K29 -> 2.898 | BS56: 未披露 | BT56: 0 | BU56: =SUM(BT56:BT61)*初始权重设定说明!E15 -> 0 | BV56: =SUM(BT56:BT61)*权重调整机制!K29 -> 0 | BW56: 24年可持续发展报告中未披露24年碳排放，但是2025年可持续发展报告中披露了24年的碳排放 p39 范围一：8516409吨、范围二：191310.61吨 24年可持续报告23年数据 24、23年报 | BX56: 2.52 | BY56: =SUM(BX56:BX61)*初始权重设定说明!E15 -> 2.289 | BZ56: =SUM(BX56:BX61)*权重调整机制!K29 -> 2.289 | CA56: 24年可持续报告中明确表示未披露当期碳排放数据 | CB56: 0 | CC56: =SUM(CB56:CB61)*初始权重设定说明!E15 -> 0 | CD56: =SUM(CB56:CB61)*权重调整机制!K29 -> 0 | CE56: 来源：24年可持续发展报告 24、23范围一+范围二 24、23年年报 | CF56: 0.85 | CG56: =SUM(CF56:CF61)*初始权重设定说明!E15 -> 0.833 | CH56: =SUM(CF56:CF61)*权重调整机制!K29 -> 0.833 | CI56: 来源：24年可持续发展报告 24年范围一+范围二 但未披露23年碳排放量 | CJ56: 0 | CK56: =SUM(CJ56:CJ61)*初始权重设定说明!E15 -> 2.646 | CL56: =SUM(CJ56:CJ61)*权重调整机制!K29 -> 2.646
I57: P10 改进率 < 企业改进率 < P90 改进率 | J57: 环比得分 = 10 ×（企业环比变化率 − P10 变化率）÷（P90 变化率 − P10 变化率）
I58: 企业改进率 ≥ P90 改进率 | J58: 10
F59: 当期横向位置 | H59: 当期横向位置维度（70%） 1. 指标表现排序 物理碳强度为反向指标，数值越低表示碳排放控制表现越好。 对行业内披露了当期物理碳强度的所有有效样本企业，按数值从小到大（由优到劣）进行排序，确定企业名次。数值最小的排名第1。2. 排名归一化赋分 计算公式： 当期得分 = 10 × (N - 企业当期名次) ÷ (N - 1) 说明： • N 为参与排名的有效样本总数（即披露了该项数据的企业数量）。 • 排名第1（碳强度最低）的企业得满分10分，排名最后（第N名，碳强度最高）的企业得0分。 • 若企业未披露当期碳排放及产量数据，该项得分为0分。 | I59: 企业指标值 ≤ P10 | J59: 1 | K59: 来源：24年可持续发展报告 24年数据 类别1+类别2+类别3 24年报 | L59: 0 | O59: 未披露 | P59: 0 | S59: 来源：24年可持续发展报告 温室气体排放总量 24、23年数据 24、23年报 | T59: 0.65 | W59: 仅披露了绝对排放量，口径不一致，无法比较 | X59: 0 | AA59: 来源：24年可持续发展报告 24年温室气体排放总量（范围1+范围2） 24年报 | AB59: 2.49 | AE59: 24年数据未披露 | AF59: 0 | AI59: 来源：24年可持续发展报告 24年范围一+范围二 24年报 | AJ59: 3.55 | AM59: 来源：24年可持续发展报告 24年范围一+范围二 24年报 | AN59: 0.9 | AQ59: 来源：24年可持续发展报告 24年温室气体排放总量（范围1和范围2） 24年报 | AR59: 2.14 | AU59: 来源：24年可持续发展报告 24、23年范围一+范围二+范围三 24、23年年报 | AV59: 7 | AY59: 未披露 | AZ59: 0 | BC59: 来源：24年可持续发展报告 24年范围一+范围二 24年年报 | BD59: 4.07 | BG59: 来源：24年可持续发展报告 24年范围1+范围2 24年年报 | BH59: 0 | BK59: 来源：24年可持续发展报告 24范围1和范围2 24年年报 | BL59: 1.62 | BO59: 来源：24年可持续发展报告 24范围一+范围二 24年年报 | BP59: 2.19 | BS59: 未披露 | BT59: 0 | BW59: 24年可持续发展报告中未披露24年碳排放，但是2025年可持续发展报告中披露了24年的碳排放 p39 范围一：8516409吨、范围二：191310.61吨 24年报 | BX59: 0.75 | CA59: 24年可持续报告中明确表示未披露当期碳排放数据 | CB59: 0 | CE59: 来源：24年可持续发展报告 24范围一+范围二 24年年报 | CF59: 0.34 | CI59: 来源：24年可持续发展报告 24年范围一+范围二 24年年报 | CJ59: 3.78
I60: P10 < 企业指标值 < P90 | J60: 当期得分 = 10 ×（企业当期指标值 − P10）÷（P90 − P10）
I61: 企业指标值 ≥ P90 | J61: 10
C62: 营收碳排放强度 | D62: 单位营业收入所产生的范围一和范围二的碳排放量 | E62: 环比变化（30%） + 当期横向位置（70%） | F62: 环比变化 | H62: （一）当期营收碳排放强度计算 当期营收碳排放强度 = 当年碳排放量 ÷ 营业收入 单位：吨二氧化碳 / 万元 （二）环比变化维度（30%） 1. 环比变化率计算 环比变化率 =（上年营收碳排放强度 − 当期营收碳排放强度）÷ 上年营收碳排放强度 环比变化率大于 0 表示单位营收对应的碳排放水平较上年下降，转型表现为正。 2. 行业分位区间确定 对行业内所有企业的"环比变化率"进行排序，确定以下分位点： P10 变化率 = 行业内环比变化率的第 10 分位值 P90 变化率 = 行业内环比变化率的第 90 分位值 3. 归一化赋分 在区间 [P10 变化率，P90 变化率] 内进行线性归一映射： • 当 企业环比变化率 ≤ P10 变化率 时，环比得分 = 0 • 当 企业环比变化率 ≥ P90 变化率 时，环比得分 = 10 • 当 P10 变化率 < 企业环比变化率 < P90 变化率 时： 环比得分 = 10 ×（企业环比变化率 − P10 变化率）÷（P90 变化率 − P10 变化率） | I62: 企业改进率 ≤ P10 改进率 | J62: 0 | K62: 来源：24年可持续发展报告 24、23年数据 类别1+类别2+类别3 24、23年报 | L62: 2.65 | M62: =SUM(L62:L67)*初始权重设定说明!E16 -> 3.843 | N62: =SUM(L62:L67)*权重调整机制!K30 -> 3.843 | O62: 未披露 | P62: 0 | Q62: =SUM(P62:P67)*初始权重设定说明!E16 -> 0 | R62: =SUM(P62:P67)*权重调整机制!K30 -> 0 | S62: 来源：24年可持续发展报告 温室气体排放总量 24、23年数据 24、23年报 | T62: 2.68 | U62: =SUM(T62:T67)*初始权重设定说明!E16 -> 2.408 | V62: =SUM(T62:T67)*权重调整机制!K30 -> 2.408 | W62: 仅披露了绝对排放量，口径不一致，无法比较 | X62: 0 | Y62: =SUM(X62:X67)*初始权重设定说明!E16 -> 0 | Z62: =SUM(X62:X67)*权重调整机制!K30 -> 0 | AA62: 来源：24年可持续发展报告 24、23年温室气体排放总量（范围1+范围2） 24、23年报 | AB62: 3 | AC62: =SUM(AB62:AB67)*初始权重设定说明!E16 -> 4.312 | AD62: =SUM(AB62:AB67)*权重调整机制!K30 -> 4.312 | AE62: 24年数据未披露 | AF62: 0 | AG62: =SUM(AF62:AF67)*初始权重设定说明!E16 -> 0 | AH62: =SUM(AF62:AF67)*权重调整机制!K30 -> 0 | AI62: 来源：24年可持续发展报告 24、23年范围一+范围二 24、23年报 | AJ62: 2.73 | AK62: =SUM(AJ62:AJ67)*初始权重设定说明!E16 -> 5.761 | AL62: =SUM(AJ62:AJ67)*权重调整机制!K30 -> 5.761 | AM62: 来源：24年可持续发展报告 24、23年范围一+范围二 24、23年报 | AN62: 2.18 | AO62: =SUM(AN62:AN67)*初始权重设定说明!E16 -> 1.974 | AP62: =SUM(AN62:AN67)*权重调整机制!K30 -> 1.974 | AQ62: 来源：24年可持续发展报告 24、23年温室气体排放总量（范围1和范围2） 24、23年报 | AR62: 2.41 | AS62: =SUM(AR62:AR67)*初始权重设定说明!E16 -> 3.864 | AT62: =SUM(AR62:AR67)*权重调整机制!K30 -> 3.864 | AU62: 来源：24年可持续发展报告 24、23年范围一+范围二+范围三 24、23年年报 | AV62: 2.8 | AW62: =SUM(AV62:AV67)*初始权重设定说明!E16 -> 4.725 | AX62: =SUM(AV62:AV67)*权重调整机制!K30 -> 4.725 | AY62: 未披露 | AZ62: 0 | BA62: =SUM(AZ62:AZ67)*初始权重设定说明!E16 -> 0 | BB62: =SUM(AZ62:AZ67)*权重调整机制!K30 -> 0 | BC62: 来源：24年可持续发展报告 24、23年范围一+范围二 24、23年年报 | BD62: 2.51 | BE62: =SUM(BD62:BD67)*初始权重设定说明!E16 -> 2.555 | BF62: =SUM(BD62:BD67)*权重调整机制!K30 -> 2.555 | BG62: 来源：24年可持续发展报告 24、23年范围1+范围2 24、23年年报 | BH62: 2.15 | BI62: =SUM(BH62:BH67)*初始权重设定说明!E16 -> 3.689 | BJ62: =SUM(BH62:BH67)*权重调整机制!K30 -> 3.689 | BK62: 来源：24年可持续发展报告 24、23范围1和范围2 24、23年年报 | BL62: 2.58 | BM62: =SUM(BL62:BL67)*初始权重设定说明!E16 -> 2.849 | BN62: =SUM(BL62:BL67)*权重调整机制!K30 -> 2.849 | BO62: 来源：24年可持续发展报告 24、23范围一+范围二 24、23年年报 | BP62: 1.89 | BQ62: =SUM(BP62:BP67)*初始权重设定说明!E16 -> 1.722 | BR62: =SUM(BP62:BP67)*权重调整机制!K30 -> 1.722 | BS62: 未披露 | BT62: 0 | BU62: =SUM(BT62:BT67)*初始权重设定说明!E16 -> 0 | BV62: =SUM(BT62:BT67)*权重调整机制!K30 -> 0 | BW62: 24年可持续发展报告中未披露24年碳排放，但是2025年可持续发展报告中披露了24年的碳排放 p39 范围一：8516409吨、范围二：191310.61吨 24年可持续报告23年数据 24、23年报 | BX62: 3 | BY62: =SUM(BX62:BX67)*初始权重设定说明!E16 -> 7 | BZ62: =SUM(BX62:BX67)*权重调整机制!K30 -> 7 | CA62: 24年可持续报告中明确表示未披露当期碳排放数据 | CB62: 0 | CC62: =SUM(CB62:CB67)*初始权重设定说明!E16 -> 0 | CD62: =SUM(CB62:CB67)*权重调整机制!K30 -> 0 | CE62: 来源：24年可持续发展报告 24、23范围一+范围二 24、23年年报 | CF62: 0 | CG62: =SUM(CF62:CF67)*初始权重设定说明!E16 -> 0 | CH62: =SUM(CF62:CF67)*权重调整机制!K30 -> 0 | CI62: 来源：24年可持续发展报告 24年范围一+范围二 但未披露23年碳排放量 | CJ62: 0 | CK62: =SUM(CJ62:CJ67)*初始权重设定说明!E16 -> 0 | CL62: =SUM(CJ62:CJ67)*权重调整机制!K30 -> 0
I63: P10 改进率 < 企业改进率 < P90 改进率 | J63: 环比得分 = 10 ×（企业环比变化率 − P10 变化率）÷（P90 变化率 − P10 变化率）
I64: 企业改进率 ≥ P90 改进率 | J64: 10
F65: 当期横向位置 | H65: 当期横向位置维度（70%） 1. 行业分位区间确定 对行业内所有企业当期营收碳排放强度进行排序，确定： P10 营收碳排放强度 = 行业内当期营收碳排放强度的第 10 分位值 P90 营收碳排放强度 = 行业内当期营收碳排放强度的第 90 分位值 说明：营收碳排放强度为反向指标，数值越低表示单位营收对应的碳排放水平越低，表现越好。 2. 行业维度归一化赋分 在区间 [P10 营收碳排放强度，P90 营收碳排放强度] 内进行反向线性归一映射： 当 企业当期营收碳排放强度 ≥ P90 营收碳排放强度 时，当期得分 = 0 当 企业当期营收碳排放强度 ≤ P10 营收碳排放强度 时，当期得分 = 10 当 P10 营收碳排放强度 < 企业当期营收碳排放强度 < P90 营收碳排放强度 时： 当期得分 = 10 ×（P90 营收碳排放强度 − 企业当期营收碳排放强度）÷（P90 营收碳排放强度 − P10 营收碳排放强度） | I65: 企业指标值 ≤ P10 | J65: 0 | K65: 来源：24年可持续发展报告 24年数据 类别1+类别2+类别3 24年报 | L65: 2.84 | O65: 未披露 | P65: 0 | S65: 来源：24年可持续发展报告 温室气体排放总量 24、23年数据 24、23年报 | T65: 0.76 | W65: 仅披露了绝对排放量，口径不一致，无法比较 | X65: 0 | AA65: 来源：24年可持续发展报告 24年温室气体排放总量（范围1+范围2） 24年报 | AB65: 3.16 | AE65: 24年数据未披露 | AF65: 0 | AI65: 来源：24年可持续发展报告 24年范围一+范围二 24年报 | AJ65: 5.5 | AM65: 来源：24年可持续发展报告 24年范围一+范围二 24年报 | AN65: 0.64 | AQ65: 来源：24年可持续发展报告 24年温室气体排放总量（范围1和范围2） 24年报 | AR65: 3.11 | AU65: 来源：24年可持续发展报告 24、23年范围一+范围二+范围三 24、23年年报 | AV65: 3.95 | AY65: 未披露 | AZ65: 0 | BC65: 来源：24年可持续发展报告 24年范围一+范围二 24年年报 | BD65: 1.14 | BG65: 来源：24年可持续发展报告 24年范围1+范围2 24年年报 | BH65: 3.12 | BK65: 来源：24年可持续发展报告 24范围1和范围2 24年年报 | BL65: 1.49 | BO65: 来源：24年可持续发展报告 24范围一+范围二 24年年报 | BP65: 0.57 | BS65: 未披露 | BT65: 0 | BW65: 24年可持续发展报告中未披露24年碳排放，但是2025年可持续发展报告中披露了24年的碳排放 p39 范围一：8516409吨、范围二：191310.61吨 24年报 | BX65: 7 | CA65: 24年可持续报告中明确表示未披露当期碳排放数据 | CB65: 0 | CE65: 来源：24年可持续发展报告 24范围一+范围二 24年年报 | CF65: 0 | CI65: 来源：24年可持续发展报告 24年范围一+范围二 24年年报 | CJ65: 0
I66: P10 < 企业指标值 < P90 | J66: 当期得分 = 10 ×（企业当期指标值 − P10）÷（P90 − P10）
I67: 企业指标值 ≥ P90 | J67: 10
B68: 能源使用 | C68: 可再生能源占比 | D68: 自发可再生能源电量，是指企业在自身生产经营边界内，通过自建或控股的可再生能源发电设施，所产生并被企业自身消费的电力。 能源消耗总量：企业当期披露的能源消耗总量（单位 MWh） | E68: 环比变化（30%） + 当期横向位置（70%） | F68: 环比变化 | H68: （一）当期自发可再生能源电量占比计算 当期自发可再生能源电量占比 = 当年企业自发可再生能源发电量 ÷ 当年总能源消耗量 单位：% 注： 自发可再生能源包括但不限于：光伏、风电、生物质能、水电等企业自建或自持发电设施所产生的电量； 能源消耗总量以企业披露的当期能源消耗总量（统一折算为 MWh）为准。 （二）环比变化维度（30%） 1. 环比变化率计算 环比变化率 =（当期自发可再生能源电量占比 − 上年自发可再生能源电量占比）÷ 上年自发可再生能源电量占比 环比变化率大于 0 表示企业自发可再生能源使用水平较上年提升。 2. 行业分位区间确定 对行业内所有企业的"环比变化率"进行排序，确定以下分位点： P10 变化率 = 行业内环比变化率的第 10 分位值 P90 变化率 = 行业内环比变化率的第 90 分位值 3. 归一化赋分 在区间 [P10 变化率，P90 变化率] 内进行线性归一映射： 当 企业环比变化率 ≤ P10 变化率 时，环比得分 = 0 当 企业环比变化率 ≥ P90 变化率 时，环比得分 = 10 当 P10 变化率 < 企业环比变化率 < P90 变化率 时： 环比得分 = 10 ×（企业环比变化率 − P10 变化率）÷（P90 变化率 − P10 变化率） | I68: 企业改进率 ≤ P10 改进率 | J68: 0 | K68: 来源：24年可持续发展报告；自发可再生能源电量、能源总量 23年可持续发展报告-厂内可再生能源发电量，能源总量 | L68: 1.82 | M68: =SUM(L68:L73)*初始权重设定说明!E17 -> 0.392 | N68: =SUM(L68:L73)*权重调整机制!K31 -> 0.392 | O68: 24年可持续发展报告中未披露自发可再生能源发电量与能源总量 | P68: 0 | Q68: =SUM(P68:P73)*初始权重设定说明!E17 -> 0 | R68: =SUM(P68:P73)*权重调整机制!K31 -> 0 | S68: 来源：24年可持续报告 能源总消耗量、清洁能源发电项目 23年可持续发展报告 清洁能源使用量、能源消耗总量 | T68: 1.28 | U68: =SUM(T68:T73)*初始权重设定说明!E17 -> 0.256 | V68: =SUM(T68:T73)*权重调整机制!K31 -> 0.256 | W68: 来源：24年可持续发展报告 24年自发电力 未披露24年能源总量 | X68: 0 | Y68: =SUM(X68:X73)*初始权重设定说明!E17 -> 0 | Z68: =SUM(X68:X73)*权重调整机制!K31 -> 0 | AA68: 来源：24年可持续发展报告中24、23年数据 自发、能源消耗总量 | AB68: 0 | AC68: =SUM(AB68:AB73)*初始权重设定说明!E17 -> 0.024 | AD68: =SUM(AB68:AB73)*权重调整机制!K31 -> 0.024 | AE68: 来源：24年可持续发展报告 可再生能源发电量（风能）+可再生能源发电量（光伏） 24年直接及间接能源总耗量 20-23年均未披露自发电力量 | AF68: 0 | AG68: =SUM(AF68:AF73)*初始权重设定说明!E17 -> 0.032 | AH68: =SUM(AF68:AF73)*权重调整机制!K31 -> 0.032 | AI68: 来源：24年可持续发展报告 光伏发电、能源消费量 23年可持续发展报告：光伏发电量1583.78万千瓦时，能源消耗量 | AJ68: 0.1 | AK68: =SUM(AJ68:AJ73)*初始权重设定说明!E17 -> 0.026 | AL68: =SUM(AJ68:AJ73)*权重调整机制!K31 -> 0.026 | AM68: 来源：24年可持续发展报告-24、23年数据 可再生能源使用量（清洁能源使用量） 综合能耗（标准煤换算） | AN68: 1.42 | AO68: =SUM(AN68:AN73)*初始权重设定说明!E17 -> 0.408 | AP68: =SUM(AN68:AN73)*权重调整机制!K31 -> 0.408 | AQ68: 来源：24年可持续发展报告中24、23年数据 自发电、能源消耗总量 | AR68: 0.79 | AS68: =SUM(AR68:AR73)*初始权重设定说明!E17 -> 1.256 | AT68: =SUM(AR68:AR73)*权重调整机制!K31 -> 1.256 | AU68: 未披露24年自发可持续能源电量 | AV68: 0 | AW68: =SUM(AV68:AV73)*初始权重设定说明!E17 -> 0 | AX68: =SUM(AV68:AV73)*权重调整机制!K31 -> 0 | AY68: 来源：24年可持续发展报告-自由清洁能源年发电量（光伏发电） 能源消耗总量（吨标准煤换算） 23年可持续发展报告-自由清洁能源年发电量（光伏发电） 能源消耗总量（吨标准煤换算） | AZ68: 0.98 | BA68: =SUM(AZ68:AZ73)*初始权重设定说明!E17 -> 0.204 | BB68: =SUM(AZ68:AZ73)*权重调整机制!K31 -> 0.204 | BC68: 来源：24年可持续发展报告中24、23年数据 可再生能源使用量、综合能耗 | BD68: 0.98 | BE68: =SUM(BD68:BD73)*初始权重设定说明!E17 -> 1.018 | BF68: =SUM(BD68:BD73)*权重调整机制!K31 -> 1.018 | BG68: 来源：24可持续发展报告-24、23年可再生能源消耗量-自发绿电数据 | BH68: 2.34 | BI68: =SUM(BH68:BH73)*初始权重设定说明!E17 -> 1.868 | BJ68: =SUM(BH68:BH73)*权重调整机制!K31 -> 1.868 | BK68: 来源：24年可持续发展报告-用电量24、23年数据 自发电量24、23年数据 | BL68: 0.14 | BM68: =SUM(BL68:BL73)*初始权重设定说明!E17 -> 1.428 | BN68: =SUM(BL68:BL73)*权重调整机制!K31 -> 1.428 | BO68: 来源：24年可持续发展报告-全年累计光伏发电量达2014.1万kwh 24年能源消耗总量-4440365吨标准煤约等于36149210MWh 23年社会责任报告-一期项目年发电量2217万kwh 23年能源消耗总量-4668853吨标准煤约等于38002231MWh | BP68: 0.25 | BQ68: =SUM(BP68:BP73)*初始权重设定说明!E17 -> 0.062 | BR68: =SUM(BP68:BP73)*权重调整机制!K31 -> 0.062 | BS68: 来源：24年可持续发展报告-23、24年吨钢电耗 结合钢产量推算23、24年总电耗 24年可持续发展报告-建设光伏发电项目年平均发电量1508.1万千瓦时 无基准年自发可再生能源数据 | BT68: 0 | BU68: =SUM(BT68:BT73)*初始权重设定说明!E17 -> 0.04 | BV68: =SUM(BT68:BT73)*权重调整机制!K31 -> 0.04 | BW68: 来源：24年可持续发展报告-光伏发电、能源消耗总量（标准煤换算为兆瓦时）数据 23年可持续发展报告-清洁能源使用（光伏）、能源消耗总量（标准煤换算）数据 | BX68: 3 | BY68: =SUM(BX68:BX73)*初始权重设定说明!E17 -> 0.608 | BZ68: =SUM(BX68:BX73)*权重调整机制!K31 -> 0.608 | CA68: 未披露24年自发可再生能源发电量 | CB68: 0 | CC68: =SUM(CB68:CB73)*初始权重设定说明!E17 -> 0 | CD68: =SUM(CB68:CB73)*权重调整机制!K31 -> 0 | CE68: 来源：24年可持续发展报告-光伏发电量4174兆瓦时，能源消耗量 23年可持续发展报告-光伏发电量249万千瓦时，能源消耗量 | CF68: 2.88 | CG68: =SUM(CF68:CF73)*初始权重设定说明!E17 -> 0.578 | CH68: =SUM(CF68:CF73)*权重调整机制!K31 -> 0.578 | CI68: 来源：24年可持续发展报告 24、23年清洁能源使用量数据 全年能源消耗总量 | CJ68: 3 | CK68: =SUM(CJ68:CJ73)*初始权重设定说明!E17 -> 1.884 | CL68: =SUM(CJ68:CJ73)*权重调整机制!K31 -> 1.884
I69: P10 改进率 < 企业改进率 < P90 改进率 | J69: 环比得分 = 10 ×（企业环比变化率 − P10 变化率）÷（P90 变化率 − P10 变化率）
I70: 企业改进率 ≥ P90 改进率 | J70: 10
F71: 当期横向位置 | H71: 当期横向位置维度（70%） 1. 行业分位区间确定 对行业内所有企业当期自发可再生能源电量占比进行排序，确定： P10 占比 = 行业内当期自发可再生能源电量占比的第 10 分位值 P90 占比 = 行业内当期自发可再生能源电量占比的第 90 分位值 说明：自发可再生能源电量占比为正向指标，数值越高表示表现越好。 2. 行业维度归一化赋分 在区间 [P10 占比，P90 占比] 内进行线性归一映射： 当 企业当期占比 ≤ P10 占比 时，当期得分 = 0 当 企业当期占比 ≥ P90 占比 时，当期得分 = 10 当 P10 占比 < 企业当期占比 < P90 占比 时： 当期得分 = 10 ×（企业当期占比 − P10 占比）÷（P90 占比 − P10 占比） | I71: 企业指标值 ≤ P10 | J71: 0 | K71: 来源：24年可持续发展报告；自发可再生能源电量、能源总量 | L71: 0.14 | O71: 24年可持续发展报告中未披露自发可再生能源发电量与能源总量 | P71: 0 | S71: 来源：24年可持续报告 24年能源总消耗量、清洁能源发电项目 | T71: 0 | W71: 来源：24年可持续发展报告 24年自发电力 未披露24年能源总量 | X71: 0 | AA71: 来源：24年可持续发展报告中24年数据 自发、能源消耗总量 | AB71: 0.12 | AE71: 来源：24年可持续发展报告 可再生能源发电量（风能）+可再生能源发电量（光伏） 24年直接及间接能源总耗量 | AF71: 0.16 | AI71: 来源：24年可持续发展报告 光伏发电、能源消费量 | AJ71: 0.03 | AM71: 来源：24年可持续发展报告-24年数据 可再生能源使用量（清洁能源使用量） 综合能耗（标准煤换算） | AN71: 0.62 | AQ71: 来源：24年可持续发展报告中24年数据 自发电、能源消耗总量 | AR71: 5.49 | AU71: 未披露24年自发可持续能源电量 | AV71: 0 | AY71: 来源：24年可持续发展报告 -自由清洁能源年发电量（光伏发电） 能源消耗总量（吨标准煤换算） | AZ71: 0.04 | BC71: 来源：24年可持续发展报告中24年数据 可再生能源使用量、综合能耗 | BD71: 4.11 | BG71: 来源：24可持续发展报告-24年可再生能源消耗量-自发绿电 | BH71: 7 | BK71: 来源：24年可持续发展报告-用电量24年数据 自发电量24年数据 | BL71: 7 | BO71: 来源：24年可持续发展报告-全年累计光伏发电量达2014.1万kwh 24年能源消耗总量-4440365吨标准煤约等于36149210MWh | BP71: 0.06 | BS71: 来源：24年可持续发展报告-24年吨钢电耗 结合钢产量推算24年总电耗 24年可持续发展报告-建设光伏发电项目年平均发电量1508.1万千瓦时 | BT71: 0.2 | BW71: 来源：24年可持续发展报告-光伏发电、能源消耗总量（标准煤换算为兆瓦时）数据 | BX71: 0.04 | CA71: 未披露24年自发可再生能源发电量 | CB71: 0 | CE71: 来源：24年可持续发展报告-光伏发电量4174兆瓦时，能源消耗量 | CF71: 0.01 | CI71: 来源：24年可持续发展报告 24年清洁能源使用量数据 全年能源消耗总量 | CJ71: 6.42
I72: P10 < 企业指标值 < P90 | J72: 当期得分 = 10 ×（企业当期指标值 − P10）÷（P90 − P10）
I73: 企业指标值 ≥ P90 | J73: 10
D74: 外购绿电包括： 绿电交易电量 绿证对应电量（如披露） 能源消耗总量：企业当期披露的能源消耗总量（单位 MWh） | E74: 环比变化（30%） + 当期横向位置（70%） | F74: 环比变化 | H74: （一）当期外购绿电占比计算 当期外购绿电占比= 当年企业外购绿电电量 ÷ 当年总能源消耗量 单位：% 注： 外购绿电包括通过绿电交易、清洁电力采购、绿色电力协议（PPA）以及绿证对应电量等方式获得的可再生能源电力； 若企业明确披露当期未采购绿电，则该指标取值为 0。 （二）环比变化维度（30%） 1. 环比变化率计算 环比变化率 =（当期外购绿电占比 − 上年外购绿电占比）÷ 上年外购绿电占比 2. 行业分位区间确定 对行业内所有企业的"环比变化率"进行排序，确定： P10 变化率 = 行业内环比变化率的第 10 分位值 P90 变化率 = 行业内环比变化率的第 90 分位值 3. 归一化赋分 当 企业环比变化率 ≤ P10 变化率 时，环比得分 = 0 当 企业环比变化率 ≥ P90 变化率 时，环比得分 = 10 当 P10 变化率 < 企业环比变化率 < P90 变化率 时： 环比得分 = 10 ×（企业环比变化率 − P10 变化率）÷（P90 变化率 − P10 变化率） | I74: 企业改进率 ≤ P10 改进率 | J74: 0 | K74: 来源：24年可持续发展报告：外购可再生能源电量+外购可再生能源绿证电量、能源总量 23年可持续发展报告外购清洁能源电量，能源总量 | L74: 2.3 | M74: =SUM(L74:L79)*初始权重设定说明!E18 -> 0.672 | N74: =SUM(L74:L79)*权重调整机制!K32 -> 0.672 | O74: 来源：24年可持续发展报告 绿电交易量 未披露能源总量 | P74: 0 | Q74: =SUM(P74:P79)*初始权重设定说明!E18 -> 0 | R74: =SUM(P74:P79)*权重调整机制!K32 -> 0 | S74: 来源：24年可持续报告 24年外购清洁能源电量、24、22年能源总消耗 23年外购清洁能源电量未披露 | T74: 0 | U74: =SUM(T74:T79)*初始权重设定说明!E18 -> 0.054 | V74: =SUM(T74:T79)*权重调整机制!K32 -> 0.054 | W74: 来源：24年可持续发展报告 24年自发电力 未披露24年能源总量 | X74: 0 | Y74: =SUM(X74:X79)*初始权重设定说明!E18 -> 0 | Z74: =SUM(X74:X79)*权重调整机制!K32 -> 0 | AA74: 来源：24年可持续发展报告中24、23年数据 外购、能源消耗总量 | AB74: 3 | AC74: =SUM(AB74:AB79)*初始权重设定说明!E18 -> 0.642 | AD74: =SUM(AB74:AB79)*权重调整机制!K32 -> 0.642 | AE74: 来源：24年可持续发展报告 外购绿电、直接及间接能源总耗量 23年可持续发展报告 累计交易绿电7.9亿千瓦时，能源总耗量 | AF74: 0.78 | AG74: =SUM(AF74:AF79)*初始权重设定说明!E18 -> 0.324 | AH74: =SUM(AF74:AF79)*权重调整机制!K32 -> 0.324 | AI74: 来源：24年可持续发展报告 外购绿电、能源消费量 23年可持续发展报告 采购绿电、能源消耗量 | AJ74: 0.02 | AK74: =SUM(AJ74:AJ79)*初始权重设定说明!E18 -> 0.06 | AL74: =SUM(AJ74:AJ79)*权重调整机制!K32 -> 0.06 | AM74: 来源：24年可持续发展报告 实际购入绿电 综合能耗 23年可持续发展报告 完成绿电交易4.63亿千瓦时，综合能耗 | AN74: 0.21 | AO74: =SUM(AN74:AN79)*初始权重设定说明!E18 -> 0.116 | AP74: =SUM(AN74:AN79)*权重调整机制!K32 -> 0.116 | AQ74: 来源：24年可持续发展报告 24年外购电量未披露 | AR74: 0 | AS74: =SUM(AR74:AR79)*初始权重设定说明!E18 -> 0 | AT74: =SUM(AR74:AR79)*权重调整机制!K32 -> 0 | AU74: 24年可持续发展报告仅披露所属广西钢铁外购绿电，未披露整体范围内 | AV74: 0 | AW74: =SUM(AV74:AV79)*初始权重设定说明!E18 -> 0 | AX74: =SUM(AV74:AV79)*权重调整机制!K32 -> 0 | AY74: 来源：24年可持续发展报告 能源消耗总量 未披露24年外购绿电量 | AZ74: 0 | BA74: =SUM(AZ74:AZ79)*初始权重设定说明!E18 -> 0 | BB74: =SUM(AZ74:AZ79)*权重调整机制!K32 -> 0 | BC74: 来源：24年可持续发展报告 综合能耗 未披露24年外购绿电量 | BD74: 0 | BE74: =SUM(BD74:BD79)*初始权重设定说明!E18 -> 0 | BF74: =SUM(BD74:BD79)*权重调整机制!K32 -> 0 | BG74: 来源：24可持续发展报告-24、23年可再生能源消耗量-外购绿电数据 | BH74: 0 | BI74: =SUM(BH74:BH79)*初始权重设定说明!E18 -> 1.4 | BJ74: =SUM(BH74:BH79)*权重调整机制!K32 -> 1.4 | BK74: 来源：24年可持续发展报告-用电量24、23年数据 外购绿电24、23年数据 | BL74: 0.21 | BM74: =SUM(BL74:BL79)*初始权重设定说明!E18 -> 1.04 | BN74: =SUM(BL74:BL79)*权重调整机制!K32 -> 1.04 | BO74: 24年未披露外购绿电数量 | BP74: 0 | BQ74: =SUM(BP74:BP79)*初始权重设定说明!E18 -> 0 | BR74: =SUM(BP74:BP79)*权重调整机制!K32 -> 0 | BS74: 24年未披露外购绿电数量 | BT74: 0 | BU74: =SUM(BT74:BT79)*初始权重设定说明!E18 -> 0 | BV74: =SUM(BT74:BT79)*权重调整机制!K32 -> 0 | BW74: 来源：24年可持续发展报告-外购电力总量、能源消耗总量（标准煤换算为兆瓦时）数据 23年可持续发展报告-外购电力、能源消耗总量（标准煤换算）数据 | BX74: 0.14 | BY74: =SUM(BX74:BX79)*初始权重设定说明!E18 -> 0.252 | BZ74: =SUM(BX74:BX79)*权重调整机制!K32 -> 0.252 | CA74: 来源：24年可持续发展报告-外购电力、能源消耗总量（吨标准煤换算） 23年可持续发展报告-外购电力总量、能源消耗总量（吨标准煤换算） | CB74: 0.11 | CC74: =SUM(CB74:CB79)*初始权重设定说明!E18 -> 1.422 | CD74: =SUM(CB74:CB79)*权重调整机制!K32 -> 1.422 | CE74: 来源：24年可持续发展报告-绿电交易电量，能源消耗量 23年可持续发展报告-绿电消费量43万千瓦时，能源消耗量 | CF74: 3 | CG74: =SUM(CF74:CF79)*初始权重设定说明!E18 -> 0.6 | CH74: =SUM(CF74:CF79)*权重调整机制!K32 -> 0.6 | CI74: 来源：24年可持续发展报告-公司购买新能源电力16.5亿kwh，全年能源消耗总量 23年未披露 | CJ74: 0 | CK74: =SUM(CJ74:CJ79)*初始权重设定说明!E18 -> 0.774 | CL74: =SUM(CJ74:CJ79)*权重调整机制!K32 -> 0.774
I75: P10 改进率 < 企业改进率 < P90 改进率 | J75: 环比得分 = 10 ×（企业环比变化率 − P10 变化率）÷（P90 变化率 − P10 变化率）
I76: 企业改进率 ≥ P90 改进率 | J76: 10
F77: 当期横向位置 | H77: 当期横向位置维度（70%） 1. 行业分位区间确定 对行业内所有企业当期外购绿电占比进行排序，确定： P10 占比 = 行业内当期外购绿电占比的第 10 分位值 P90 占比 = 行业内当期外购绿电占比的第 90 分位值 说明：外购绿电占比为正向指标，数值越高表示表现越好。 2. 行业维度归一化赋分 当 企业当期占比 ≤ P10 占比 时，当期得分 = 0 当 企业当期占比 ≥ P90 占比 时，当期得分 = 10 当 P10 占比 < 企业当期占比 < P90 占比 时： 当期得分 = 10 ×（企业当期占比 − P10 占比）÷（P90 占比 − P10 占比） （四）综合得分 综合得分 = 环比得分 × 30% + 当期得分 × 70% | I77: 企业指标值 ≤ P10 | J77: 0 | K77: 来源：24年可持续发展报告：外购可再生能源电量+外购可再生能源绿证电量、能源总量 | L77: 1.06 | O77: 来源：24年可持续发展报告 绿电交易量 未披露能源总量 | P77: 0 | S77: 来源：24年可持续报告 24年外购清洁能源电量24年能源总消耗 | T77: 0.27 | W77: 来源：24年可持续发展报告 24年自发电力 未披露24年能源总量 | X77: 0 | AA77: 来源：24年可持续发展报告中24年数据 外购、能源消耗总量 | AB77: 0.21 | AE77: 来源：24年可持续发展报告 外购绿电、直接及间接能源总耗量 | AF77: 0.84 | AI77: 来源：24年可持续发展报告 外购绿电、能源消费量 | AJ77: 0.28 | AM77: 来源：24年可持续发展报告 实际购入绿电 综合能耗 | AN77: 0.37 | AQ77: 来源：24年可持续发展报告 24年外购电量未披露 | AR77: 0 | AU77: 24年可持续发展报告仅披露所属广西钢铁外购绿电，未披露整体范围内 | AV77: 0 | AY77: 来源：24年可持续发展报告 能源消耗总量 未披露24年外购绿电量 | AZ77: 0 | BC77: 来源：24年可持续发展报告 综合能耗 未披露24年外购绿电量 | BD77: 0 | BG77: 来源：24可持续发展报告-24年可再生能源消耗量-外购绿电数据 | BH77: 7 | BK77: 来源：24年可持续发展报告-用电量24年数据 外购绿电24年数据 | BL77: 4.99 | BO77: 24年未披露外购绿电数量 | BP77: 0 | BS77: 24年未披露外购绿电数量 | BT77: 0 | BW77: 来源：24年可持续发展报告-外购电力总量、能源消耗总量（标准煤换算为兆瓦时）数据 | BX77: 1.12 | CA77: 来源：24年可持续发展报告-外购电力、能源消耗总量（吨标准煤换算） | CB77: 7 | CE77: 来源：24年可持续发展报告-绿电交易电量，能源消耗量 | CF77: 0 | CI77: 来源：24年可持续发展报告-公司购买新能源电力16.5亿kwh，全年能源消耗总量 | CJ77: 3.87
I78: P10 < 企业指标值 < P90 | J78: 当期得分 = 10 ×（企业当期指标值 − P10）÷（P90 − P10）
I79: 企业指标值 ≥ P90 | J79: 10
B80: 水资源利用 | C80: 用水效率 | D80: 吨钢耗新水量，指企业在生产过程中对粗钢生产所消耗的新鲜水资源量 用水效率（吨钢耗新水量）= 当期新水消耗量 ÷ 当期粗钢产量 单位：立方米/吨粗钢 | E80: 环比变化（30%） + 当期横向位置（70%） | F80: 环比变化 | H80: （一）计算指标 用水效率（吨钢耗新水量）= 当期新水消耗量 ÷ 当期粗钢产量 单位：立方米/吨粗钢 说明： 用水效率为反向指标，数值越低表示单位产量新水消耗水平越优。 （二）环比变化维度（30%） 1. 环比变化率计算 环比变化率 =（上年吨钢耗新水量 − 当期吨钢耗新水量）÷ 上年吨钢耗新水量 环比变化率大于 0 表示单位产量新水消耗量较上年下降，转型表现为正。 2. 行业分位区间确定 对行业内所有企业的环比变化率进行排序，确定： P10 变化率 = 行业内环比变化率的第 10 分位值 P90 变化率 = 行业内环比变化率的第 90 分位值 3. 归一化赋分 在区间 [P10 变化率，P90 变化率] 内进行线性归一映射： • 当 企业环比变化率 ≤ P10 变化率 时，环比得分 = 0 • 当 企业环比变化率 ≥ P90 变化率 时，环比得分 = 10 • 当 P10 变化率 < 企业环比变化率 < P90 变化率 时： 环比得分 = 10 ×（企业环比变化率 − P10 变化率）÷（P90 变化率 − P10 变化率） | I80: 企业改进率 ≤ P10 改进率 | J80: 0 | K80: 来源：直接采用24年可持续发展报告中24、23年吨钢耗新水量 | L80: 2.1 | M80: =SUM(L80:L85)*初始权重设定说明!E19 -> 0.934 | N80: =SUM(L80:L85)*权重调整机制!K33 -> 0.934 | O80: 来源：直接采用24年可持续发展报告中24、23年数据 吨钢耗新水量 | P80: 1.85 | Q80: =SUM(P80:P85)*初始权重设定说明!E19 -> 0.916 | R80: =SUM(P80:P85)*权重调整机制!K33 -> 0.916 | S80: 来源：直接采用24年可持续发展报告中24、23年数据 吨钢耗新水量 | T80: 1.94 | U80: =SUM(T80:T85)*初始权重设定说明!E19 -> 0.914 | V80: =SUM(T80:T85)*权重调整机制!K33 -> 0.914 | W80: 来源：24年可持续发展报告、23年可持续发展报告 取新水总量 24、23年年报 生产量 | X80: 1.21 | Y80: =SUM(X80:X85)*初始权重设定说明!E19 -> 0.242 | Z80: =SUM(X80:X85)*权重调整机制!K33 -> 0.242 | AA80: 来源：24年可持续发展报告-新水量（市政供水总量+其他类型供水量） 23年吨钢耗新水量 24年年报 | AB80: 0 | AC80: =SUM(AB80:AB85)*初始权重设定说明!E19 -> 0.462 | AD80: =SUM(AB80:AB85)*权重调整机制!K33 -> 0.462 | AE80: 未披露24、23年吨钢耗新水量 | AF80: 0 | AG80: =SUM(AF80:AF85)*初始权重设定说明!E19 -> 0 | AH80: =SUM(AF80:AF85)*权重调整机制!K33 -> 0 | AI80: 来源：24、23年可持续发展报告 吨钢耗新水量下降22.8%，结合23年可持续发展报告中的23年吨钢新鲜水使用量1.8吨水/吨钢，以计算24年相应数据：计算得出24年吨耗新水量为1.39吨/吨 | AJ80: 3 | AK80: =SUM(AJ80:AJ85)*初始权重设定说明!E19 -> 1.546 | AL80: =SUM(AJ80:AJ85)*权重调整机制!K33 -> 1.546 | AM80: 来源：24年可持续发展报告 24、23吨钢新水消耗量 | AN80: 1.89 | AO80: =SUM(AN80:AN85)*初始权重设定说明!E19 -> 1.092 | AP80: =SUM(AN80:AN85)*权重调整机制!K33 -> 1.092 | AQ80: 来源：24年可持续发展报告 24、23耗新水强度 | AR80: 2.28 | AS80: =SUM(AR80:AR85)*初始权重设定说明!E19 -> 1.064 | AT80: =SUM(AR80:AR85)*权重调整机制!K33 -> 1.064 | AU80: 来源：24年可持续发展报告 2024年柳钢股份单位产品用水量-吨钢新水耗 23年未披露吨钢新水数据 | AV80: 0 | AW80: =SUM(AV80:AV85)*初始权重设定说明!E19 -> 1.008 | AX80: =SUM(AV80:AV85)*权重调整机制!K33 -> 1.008 | AY80: 来源：24年可持续发展报告中24、23年的数据 吨钢耗新水量 | AZ80: 2.33 | BA80: =SUM(AZ80:AZ85)*初始权重设定说明!E19 -> 0.466 | BB80: =SUM(AZ80:AZ85)*权重调整机制!K33 -> 0.466 | BC80: 来源：24年可持续发展报告 24、23年吨钢新水消耗量 | BD80: 1.65 | BE80: =SUM(BD80:BD85)*初始权重设定说明!E19 -> 0.69 | BF80: =SUM(BD80:BD85)*权重调整机制!K33 -> 0.69 | BG80: 来源：24年可持续发展报告 24、23年吨钢耗新水量 | BH80: 2.36 | BI80: =SUM(BH80:BH85)*初始权重设定说明!E19 -> 1.01 | BJ80: =SUM(BH80:BH85)*权重调整机制!K33 -> 1.01 | BK80: 来源：24年可持续发展报告-24、23年年度新鲜水用水量 24、23年年报 | BL80: 2.13 | BM80: =SUM(BL80:BL85)*初始权重设定说明!E19 -> 0.764 | BN80: =SUM(BL80:BL85)*权重调整机制!K33 -> 0.764 | BO80: 来源：24年可持续发展报告-24、23年吨钢耗新水量 | BP80: 1.49 | BQ80: =SUM(BP80:BP85)*初始权重设定说明!E19 -> 1.134 | BR80: =SUM(BP80:BP85)*权重调整机制!K33 -> 1.134 | BS80: 来源：24年可持续发展报告-24、23年吨钢耗新水 | BT80: 1.85 | BU80: =SUM(BT80:BT85)*初始权重设定说明!E19 -> 0.896 | BV80: =SUM(BT80:BT85)*权重调整机制!K33 -> 0.896 | BW80: 来源：24年可持续发展报告 新鲜水用量 23年新水量未披露 24年年报 | BX80: 0 | BY80: =SUM(BX80:BX85)*初始权重设定说明!E19 -> 0.87 | BZ80: =SUM(BX80:BX85)*权重调整机制!K33 -> 0.87 | CA80: 来源：24年可持续发展报告-吨钢耗新水 23年可持续发展报告-实现吨钢耗新水0.5t | CB80: 3 | CC80: =SUM(CB80:CB85)*初始权重设定说明!E19 -> 2 | CD80: =SUM(CB80:CB85)*权重调整机制!K33 -> 2 | CE80: 来源：24年可持续发展报告-24、23年吨钢新水量 | CF80: 2.22 | CG80: =SUM(CF80:CF85)*初始权重设定说明!E19 -> 0.492 | CH80: =SUM(CF80:CF85)*权重调整机制!K33 -> 0.492 | CI80: 来源：24年可持续发展报告-24、23年吨钢耗新水量 | CJ80: 2.32 | CK80: =SUM(CJ80:CJ85)*初始权重设定说明!E19 -> 0.648 | CL80: =SUM(CJ80:CJ85)*权重调整机制!K33 -> 0.648
I81: P10 改进率 < 企业改进率 < P90 改进率 | J81: 环比得分 = 10 ×（企业环比变化率 − P10 变化率）÷（P90 变化率 − P10 变化率）
I82: 企业改进率 ≥ P90 改进率 | J82: 10
F83: 当期横向位置 | H83: 当期横向位置维度（70%） 1. 行业分位区间确定 对行业内所有企业当期吨钢耗新水量进行排序，确定： P10 吨钢耗新水量 = 行业内当期吨钢耗新水量的第 10 分位值 P90 吨钢耗新水量 = 行业内当期吨钢耗新水量的第 90 分位值 2. 行业维度归一化赋分（反向） 在区间 [P10 吨钢耗新水量，P90 吨钢耗新水量] 内进行反向线性归一映射： • 当 企业当期吨钢耗新水量 ≥ P90 吨钢耗新水量 时，当期得分 = 0 • 当 企业当期吨钢耗新水量 ≤ P10 吨钢耗新水量 时，当期得分 = 10 • 当 P10 吨钢耗新水量 < 企业当期吨钢耗新水量 < P90 吨钢耗新水量 时： 当期得分 = 10 ×（P90 吨钢耗新水量 − 企业当期吨钢耗新水量）÷（P90 吨钢耗新水量 − P10 吨钢耗新水量） | I83: 企业指标值 ≤ P10 | J83: 0 | K83: 来源：直接采用24年可持续发展报告 吨钢耗新水量； | L83: 2.57 | O83: 来源：直接采用24年可持续发展报告中24年数据 吨钢耗新水量 | P83: 2.73 | S83: 来源：直接采用24年可持续发展报告中24年数据 吨钢耗新水量 | T83: 2.63 | W83: 来源：24年可持续发展报告 取新水总量 24年年报 生产量 | X83: 0 | AA83: 来源：24年可持续发展报告-新水量（市政供水总量+其他类型供水量） 24年年报 | AB83: 2.31 | AE83: 未披露24年吨钢耗新水量 | AF83: 0 | AI83: 来源：24、23年可持续发展报告 吨钢耗新水量下降22.8%，结合23年可持续发展报告中的23年吨钢新鲜水使用量1.8吨水/吨钢，以计算24年相应数据：计算得出24年吨耗新水量为1.39吨/吨 | AJ83: 4.73 | AM83: 来源：24年可持续发展报告 吨钢新水消耗量 | AN83: 3.57 | AQ83: 来源：24年可持续发展报告 耗新水强度 | AR83: 3.04 | AU83: 来源：24年可持续发展报告 2024年柳钢股份单位产品用水量-吨钢新水耗 | AV83: 5.04 | AY83: 来源：24年可持续发展报告 24年吨钢耗新水量 | AZ83: 0 | BC83: 来源：24年可持续发展报告 吨钢新水消耗量 | BD83: 1.8 | BG83: 来源：24年可持续发展报告 24年吨钢号新水量 | BH83: 2.69 | BK83: 来源：24年可持续发展报告-24年年度新鲜水用水量 24年年报 | BL83: 1.69 | BO83: 来源：24年可持续发展报告-24年吨钢耗新水量 | BP83: 4.18 | BS83: 来源：24年可持续发展报告-24年吨钢耗新水 | BT83: 2.63 | BW83: 来源：24年可持续发展报告 新鲜水用量 24年年报 | BX83: 4.35 | CA83: 来源：24年可持续发展报告-吨钢耗新水 | CB83: 7 | CE83: 来源：24年可持续发展报告-24年吨钢新水量 | CF83: 0.24 | CI83: 来源：24年可持续发展报告-24年吨钢耗新水量 | CJ83: 0.92
I84: P10 < 企业指标值 < P90 | J84: 当期得分 = 10 ×（企业当期指标值 − P10）÷（P90 − P10）
I85: 企业指标值 ≥ P90 | J85: 10
B86: 生态保护 | C86: 生物多样性 | D86: 企业在生物多样性保护方面表现，比如制度或组织架构建设、具体措施和实际成效，包括保护区域的生态恢复、物种多样性保护及生态环境修复等。 | E86: 累加 | F86: 企业是否在报告或规划文件中披露其在生物多样性或生态保护方面建立了相应的管理制度、组织安排或管理机制。 | H86: 关键词范围（示例） （一）生物多样性 / 生态 / 自然相关关键词（A 类） 生物多样性 生物多样性保护 生物多样性管理 生态保护 生态系统保护 自然生态保护 自然栖息地 栖息地保护 生态红线 生态敏感区 重要生态功能区 自然资源保护 自然资本 生态环境保护 （二）管理 / 制度 / 治理关键词 管理制度 管理办法 管理体系 管理机制 管理要求 管理责任 治理体系 内部控制 工作机制 组织架构 职责分工 管理流程 管理规划 保护制度 保护规划 保护方案 行动方案 工作方案 专项规划 专项管理办法 管理细则 指引 工作要求 企业披露以下任一情形 → 得 3 分： - 披露与生物多样性、生态保护或自然栖息地保护相关的管理制度、管理办法或制度性文件； - 在公司治理或环境管理体系中，明确将生物多样性或生态保护纳入管理范畴（如作为环境管理、自然资源管理的一部分）； - 披露设立或明确负责生态保护、生物多样性或自然保护事务的管理部门、工作机制或职责分工； - 在企业环境、ESG 或可持续发展管理框架中，明确提出生物多样性保护的管理要求或管理目标。 | I86: 否 | J86: 0 | K86: 来源：24年可持续发展报告 生态系统和生物多样性保护 | L86: 5 | M86: =SUM(L86:L89)*初始权重设定说明!E20 -> 1 | N86: =SUM(L86:L89)*权重调整机制!K34 -> 1 | O86: 来源：24年可持续发展报告 生物多样性保护 | P86: 5 | Q86: =SUM(P86:P89)*初始权重设定说明!E20 -> 1 | R86: =SUM(P86:P89)*权重调整机制!K34 -> 1 | S86: 来源：24年ESG报告 p58 保护生态环境 | T86: 5 | U86: =SUM(T86:T89)*初始权重设定说明!E20 -> 1 | V86: =SUM(T86:T89)*权重调整机制!K34 -> 1 | W86: 来源：24年可持续发展报告 p136 保护生物多样性 | X86: 5 | Y86: =SUM(X86:X89)*初始权重设定说明!E20 -> 1 | Z86: =SUM(X86:X89)*权重调整机制!K34 -> 1 | AA86: 来源：24年可持续发展报告 p94 保护生物多样性 | AB86: 5 | AC86: =SUM(AB86:AB89)*初始权重设定说明!E20 -> 1 | AD86: =SUM(AB86:AB89)*权重调整机制!K34 -> 1 | AE86: 来源：24年社会责任报告 p46 生态系统保护 | AF86: 5 | AG86: =SUM(AF86:AF89)*初始权重设定说明!E20 -> 1 | AH86: =SUM(AF86:AF89)*权重调整机制!K34 -> 1 | AI86: 来源：24年可持续发展报告 p50 生物多样性保护 | AJ86: 5 | AK86: =SUM(AJ86:AJ89)*初始权重设定说明!E20 -> 1 | AL86: =SUM(AJ86:AJ89)*权重调整机制!K34 -> 1 | AM86: 来源：24年ESG报告 p59 生态系统保护 | AN86: 5 | AO86: =SUM(AN86:AN89)*初始权重设定说明!E20 -> 1 | AP86: =SUM(AN86:AN89)*权重调整机制!K34 -> 1 | AQ86: 来源：24年可持续发展报告 p61 生物多样性 | AR86: 5 | AS86: =SUM(AR86:AR89)*初始权重设定说明!E20 -> 1 | AT86: =SUM(AR86:AR89)*权重调整机制!K34 -> 1 | AU86: 来源：24年ESG报告 p39 生物多样性保护工作 | AV86: 5 | AW86: =SUM(AV86:AV89)*初始权重设定说明!E20 -> 1 | AX86: =SUM(AV86:AV89)*权重调整机制!K34 -> 1 | AY86: 来源：24年可持续发展报告 p37 注重生物多样性 | AZ86: 5 | BA86: =SUM(AZ86:AZ89)*初始权重设定说明!E20 -> 1 | BB86: =SUM(AZ86:AZ89)*权重调整机制!K34 -> 1 | BC86: 来源：24年ESG报告 p40 保护生物多样性 | BD86: 5 | BE86: =SUM(BD86:BD89)*初始权重设定说明!E20 -> 1 | BF86: =SUM(BD86:BD89)*权重调整机制!K34 -> 1 | BG86: 来源：24年可持续发展报告 p67 公司致力于推动生态文明建设，承诺在生产经营过程中践行生物多样性的保护和恢复工作 | BH86: 5 | BI86: =SUM(BH86:BH89)*初始权重设定说明!E20 -> 1 | BJ86: =SUM(BH86:BH89)*权重调整机制!K34 -> 1 | BK86: 来源：24年可持续发展报告 p62 生物多样性保护：在项目设计阶段依照相关要求做好生物多样性保护和土地利用评估...避免水土流失和森林砍伐 | BL86: 5 | BM86: =SUM(BL86:BL89)*初始权重设定说明!E20 -> 1 | BN86: =SUM(BL86:BL89)*权重调整机制!K34 -> 1 | BO86: 未披露 | BP86: 0 | BQ86: =SUM(BP86:BP89)*初始权重设定说明!E20 -> 0 | BR86: =SUM(BP86:BP89)*权重调整机制!K34 -> 0 | BS86: 来源：24年可持续发展报告 p38 生态和谐，打造美丽工厂 | BT86: 5 | BU86: =SUM(BT86:BT89)*初始权重设定说明!E20 -> 0.5 | BV86: =SUM(BT86:BT89)*权重调整机制!K34 -> 0.5 | BW86: 来源：24年可持续发展报告 p66 绿色生态园区建设 | BX86: 5 | BY86: =SUM(BX86:BX89)*初始权重设定说明!E20 -> 1 | BZ86: =SUM(BX86:BX89)*权重调整机制!K34 -> 1 | CA86: 来源：24年可持续发展报告 p87-88 生态保护 和谐发展 | CB86: 5 | CC86: =SUM(CB86:CB89)*初始权重设定说明!E20 -> 1 | CD86: =SUM(CB86:CB89)*权重调整机制!K34 -> 1 | CE86: 来源：24年可持续发展报告 p37 积极打造花园工厂、清洁工厂，呈现工业与生态共融的美丽画卷 | CF86: 5 | CG86: =SUM(CF86:CF89)*初始权重设定说明!E20 -> 1 | CH86: =SUM(CF86:CF89)*权重调整机制!K34 -> 1 | CI86: 来源：24年可持续发展报告 p43 打造绿色钢厂-蒹思湖、生态园 | CJ86: 5 | CK86: =SUM(CJ86:CJ89)*初始权重设定说明!E20 -> 1 | CL86: =SUM(CJ86:CJ89)*权重调整机制!K34 -> 1
I87: 是 | J87: 5
F88: 企业是否披露其在自然栖息地保护、生物多样性保护或生态修复方面采取了具体行动或措施。 | H88: 关键词范围（示例） - 栖息地保护 / 恢复 - 生物多样性恢复 - 生态修复 - 生态治理 - 矿区复绿 / 厂区复绿 - 湿地保护 / 修复 - 物种保护 - 自然生态修复工程 企业披露以下任一情形 ： - 开展生态修复或栖息地保护项目 - 实施生物多样性恢复或生态治理行动 - 对生产活动造成的生态影响采取修复措施 | I88: 否 | J88: 0 | K88: 来源：24年可持续发展报告 宝钢股份短期及长期生物多样性管理策略 | L88: 5 | O88: 来源：24年可持续发展报告 p73 “积极推进生物多样性保护和生态修复治理等工作” | P88: 5 | S88: 来源：24年ESG报告 p58 “鼓励各子分公司推进厂区生态恢复治理” | T88: 5 | W88: 来源：24年可持续发展报告 p136 “针对建立生物多样性管理计划” | X88: 5 | AA88: 来源：24年可持续发展报告 p94 p96 “更深入地参与生物多样性保护和生态修复工作” “以期在生物多样性保护与生态环境修复方面做出更为深远和实质性的贡献” | AB88: 5 | AE88: 来源：24年社会责任报告 p46 治理 “明确生态保护责任，坚决筑牢区域生态安全屏障” | AF88: 5 | AI88: 来源：24年可持续发展报告 p50 “种植各种绿色植物，改善厂区环境质量” | AJ88: 5 | AM88: 来源：24年ESG报告 p59 “绿化覆盖率由27.7%提升到35%” | AN88: 5 | AQ88: 来源：24年可持续发展报告 p61 2024年，厂区绿化面积覆盖率进一步提升至26% | AR88: 5 | AU88: 来源：24年ESG报告 p40 柳州本部绿化覆盖率大幅提升至31.2% | AV88: 5 | AY88: 来源：24年可持续发展报告 p37 明确绿色生态修复目标 | AZ88: 5 | BC88: 来源：24年ESG报告 p40 p41 长江流域环境保护总体规划 长江大保护 厂区绿化率 | BD88: 5 | BG88: 来源：24年可持续发展报告 p67 公司致力于推动生态文明建设，承诺在生产经营过程中践行生物多样性的保护和恢复工作 | BH88: 5 | BK88: 来源：24年可持续发展报告 p62 高度重视厂内绿化建设，扎实推进绿地养护工作...加强对厂内栖息的野生动物的保护 | BL88: 5 | BO88: 未披露 | BP88: 0 | BS88: 未披露 | BT88: 0 | BW88: 来源：24年可持续发展报告 p66 常态化开放10个工业旅游景点和环保设施 | BX88: 5 | CA88: 来源：24年可持续发展报告 p87 生态环境修复 | CB88: 5 | CE88: 来源：24年可持续发展报告 p37 绿化率达15%；2025年，对新投产使用的电弧炉区域进行绿化规划；绿化面积达44641平方米 | CF88: 5 | CI88: 来源：24年可持续发展报告 p43 打造绿色钢厂-打造生物栖息佳境 | CJ88: 5
I89: 是 | J89: 5
B90: 公正转型 | C90: 员工培训 | D90: 本指标用于评估企业是否关注并投入员工能力建设，尤其是在转型相关技能方面。 考虑到企业披露口径差异较大，本指标采用是否类累加赋分方式，不对不同披露口径进行强制可比性要求。 | E90: 相等 | F90: 企业是否真实投入并系统性披露员工能力建设，并通过加分识别其是否将培训与绿色低碳、数字化等转型目标相结合。 | H90: 分档赋分： 企业报告或相关文件中未披露员工转型相关培训、能力建设、技能提升相关信息→ 0 分 披露转型间接相关技能培训：“环境相关”“数字化技能”“智能制造”“ESG”等培训→ 5分 披露转型直接相关技能培训：“绿色技能”“低碳”“转型”“节能”"减排“等培训→10分 | I90: 0 | J90: 0 | K90: 来源：24年可持续发展报告 p82 “宝钢股份共开展环保相关培训5场” | L90: 5 | M90: =L90*初始权重设定说明!E21 -> 0.5 | N90: =SUM(L90:L92)*权重调整机制!K35 -> 0.5 | O90: 来源：24年可持续发展报告 p68 环保培训 | P90: 5 | Q90: =P90*初始权重设定说明!E21 -> 0.5 | R90: =SUM(P90:P92)*权重调整机制!K35 -> 0.5 | S90: 来源：24年ESG报告 p18 “开展ESG培训” | T90: 5 | U90: =T90*初始权重设定说明!E21 -> 0.5 | V90: =SUM(T90:T92)*权重调整机制!K35 -> 0.5 | W90: 来源：24年可持续发展报告 p99 “碳排放管理和排污许可相关的知识专业培训” | X90: 5 | Y90: =X90*初始权重设定说明!E21 -> 0.5 | Z90: =SUM(X90:X92)*权重调整机制!K35 -> 0.5 | AA90: 来源：24年可持续发展报告 环保宣贯 | AB90: 5 | AC90: =AB90*初始权重设定说明!E21 -> 0.5 | AD90: =SUM(AB90:AB92)*权重调整机制!K35 -> 0.5 | AE90: 来源：24年社会责任报告 p34 培养懂碳人才 | AF90: 10 | AG90: =AF90*初始权重设定说明!E21 -> 1 | AH90: =SUM(AF90:AF92)*权重调整机制!K35 -> 1 | AI90: 来源：24年可持续发展报告 p53 “碳排放数据质量管理培训” | AJ90: 10 | AK90: =AJ90*初始权重设定说明!E21 -> 1 | AL90: =SUM(AJ90:AJ92)*权重调整机制!K35 -> 1 | AM90: 来源：24年ESG报告 p18 能力提升-持续提升公司ESG人员综合能力 | AN90: 5 | AO90: =AN90*初始权重设定说明!E21 -> 0.5 | AP90: =SUM(AN90:AN92)*权重调整机制!K35 -> 0.5 | AQ90: 来源：24年可持续发展 p48 环境保护培训 | AR90: 5 | AS90: =AR90*初始权重设定说明!E21 -> 0.5 | AT90: =SUM(AR90:AR92)*权重调整机制!K35 -> 0.5 | AU90: 来源：24年ESG报告 p39 环保培训次数 | AV90: 5 | AW90: =AV90*初始权重设定说明!E21 -> 0.5 | AX90: =SUM(AV90:AV92)*权重调整机制!K35 -> 0.5 | AY90: 来源：24年可持续发展报告 p81 ESG培训 | AZ90: 5 | BA90: =AZ90*初始权重设定说明!E21 -> 0.5 | BB90: =SUM(AZ90:AZ92)*权重调整机制!K35 -> 0.5 | BC90: 来源：24年ESG报告 p40 环保培训及宣教 | BD90: 7.5 | BE90: =BD90*初始权重设定说明!E21 -> 0.75 | BF90: =SUM(BD90:BD92)*权重调整机制!K35 -> 0.75 | BG90: 来源：24年可持续发展报告 p44 公司注重提高员工的碳排放专业知识素养，开展了丰富的“双碳”主题培训 | BH90: 10 | BI90: =BH90*初始权重设定说明!E21 -> 1 | BJ90: =SUM(BH90:BH92)*权重调整机制!K35 -> 1 | BK90: 来源：24年可持续发展报告 p40 公司组织或参与低碳培训交流30余次 | BL90: 10 | BM90: =BL90*初始权重设定说明!E21 -> 1 | BN90: =SUM(BL90:BL92)*权重调整机制!K35 -> 1 | BO90: 来源：24年可持续发展报告 p48 环保培训宣贯 “绿色低碳优秀案例”“节能环保金点子” | BP90: 10 | BQ90: =BP90*初始权重设定说明!E21 -> 1 | BR90: =SUM(BP90:BP92)*权重调整机制!K35 -> 1 | BS90: 来源：24年可持续发展报告 p35 培养双碳人才 | BT90: 10 | BU90: =BT90*初始权重设定说明!E21 -> 1 | BV90: =SUM(BT90:BT92)*权重调整机制!K35 -> 1 | BW90: 来源：24年可持续发展报告 p69 “钢铁行业节水减排与废水处理技术”线上培训 | BX90: 10 | BY90: =BX90*初始权重设定说明!E21 -> 1 | BZ90: =SUM(BX90:BX92)*权重调整机制!K35 -> 1 | CA90: 来源：24年可持续报告 P74“组织员工开展低碳节能理念培训，提升全员节能意 识和行动力” | CB90: 10 | CC90: =CB90*初始权重设定说明!E21 -> 1 | CD90: =SUM(CB90:CB92)*权重调整机制!K35 -> 1 | CE90: 来源：24可持续发展报告 p36 低碳人才培养 | CF90: 10 | CG90: =CF90*初始权重设定说明!E21 -> 1 | CH90: =SUM(CF90:CF92)*权重调整机制!K35 -> 1 | CI90: 来源：24年可持续发展报告 p40 重视环保培训-定期开展环保在线监测培训、绿色低碳知识培训 | CJ90: 10 | CK90: =CJ90*初始权重设定说明!E21 -> 1 | CL90: =SUM(CJ90:CJ92)*权重调整机制!K35 -> 1
I91: 5 | J91: 5
I92: 10 | J92: 10
C93: 稳就业与促就业 | D93: 衡量企业在转型过程中是否避免通过大规模裁员转嫁成本，并通过稳定或扩大就业规模，体现对劳动者和社会的责任承担。 | E93: 环比变化（30%） + 当期横向位置（70%） | F93: 环比变化 | H93: （一）就业变化率计算 就业变化率 =（当期员工人数 − 上年员工人数）÷ 上年员工人数 单位：% 说明： 就业变化率为正向指标，数值越高表示企业就业规模扩张越快。若就业变化率为负，说明企业员工规模缩减。 （二）环比变化维度（30%） 说明： 该指标的环比变化维度与当期横向位置维度使用相同的就业变化率数据，为避免重复计算，环比变化维度得分的计算逻辑与横向位置维度一致，均基于行业内P10-P90分位归一化。此处不再重复设置独立的环比变化维度，直接取当期横向位置维度得分作为该指标的总得分。 （三）当期横向位置维度 1. 行业分位区间确定 对行业内所有企业的就业变化率进行排序，确定： P10 就业变化率 = 行业内就业变化率的第 10 分位值 P90 就业变化率 = 行业内就业变化率的第 90 分位值 2. 行业维度归一化赋分（正向） • 当 企业就业变化率 ≤ P10 就业变化率 时，得分 = 0 • 当 企业就业变化率 ≥ P90 就业变化率 时，得分 = 10 • 当 P10 就业变化率 < 企业就业变化率 < P90 就业变化率 时： 得分 = 10 ×（企业就业变化率 − P10 就业变化率）÷（P90 就业变化率 − P10 就业变化率） | I93: 企业指标值 ≤ P10 | J93: 0 | K93: 来源：2024、2023可持续发展报告 员工总数 | L93: 10 | M93: =L93*初始权重设定说明!E22 -> 3 | N93: =L93*权重调整机制!K36 -> 4 | O93: 来源：2024、2023可持续发展报告 员工总数 | P93: 10 | Q93: =P93*初始权重设定说明!E22 -> 3 | R93: =P93*权重调整机制!K36 -> 4 | S93: 来源：24年ESG报告 p121 员工人数 | T93: 3.5 | U93: =T93*初始权重设定说明!E22 -> 1.05 | V93: =T93*权重调整机制!K36 -> 1.4 | W93: 来源：2024、2023可持续发展报告 员工总数 | X93: 5.38 | Y93: =X93*初始权重设定说明!E22 -> 1.614 | Z93: =X93*权重调整机制!K36 -> 2.152 | AA93: 来源：2024、2023可持续发展报告 员工总数 | AB93: 7.27 | AC93: =AB93*初始权重设定说明!E22 -> 2.181 | AD93: =AB93*权重调整机制!K36 -> 2.908 | AE93: 来源：2024、2023社会责任报告 在职员工 | AF93: 1.72 | AG93: =AF93*初始权重设定说明!E22 -> 0.516 | AH93: =AF93*权重调整机制!K36 -> 0.688 | AI93: 来源：2024、2023可持续发展报告 员工总数 | AJ93: 2.03 | AK93: =AJ93*初始权重设定说明!E22 -> 0.609 | AL93: =AJ93*权重调整机制!K36 -> 0.812 | AM93: 来源：24年ESG发展报告 员工总人数 | AN93: 2.81 | AO93: =AN93*初始权重设定说明!E22 -> 0.843 | AP93: =AN93*权重调整机制!K36 -> 1.124 | AQ93: 来源：2024、2023可持续发展报告 员工总数 | AR93: 4.2 | AS93: =AR93*初始权重设定说明!E22 -> 1.26 | AT93: =AR93*权重调整机制!K36 -> 1.68 | AU93: 来源：24年ESG报告 p62 雇员总数 | AV93: 0 | AW93: =AV93*初始权重设定说明!E22 -> 0 | AX93: =AV93*权重调整机制!K36 -> 0 | AY93: 来源；24年可持续发展报告与23年可持续发展报告 员工总数 | AZ93: 1.97 | BA93: =AZ93*初始权重设定说明!E22 -> 0.591 | BB93: =AZ93*权重调整机制!K36 -> 0.788 | BC93: 来源：24年ESG报告 员工总人数 | BD93: 1.88 | BE93: =BD93*初始权重设定说明!E22 -> 0.564 | BF93: =BD93*权重调整机制!K36 -> 0.752 | BG93: 来源：24年可持续发展报告中23、24年员工人数数据 | BH93: 10 | BI93: =BH93*初始权重设定说明!E22 -> 3 | BJ93: =BH93*权重调整机制!K36 -> 4 | BK93: 来源：24年可持续发展报告 员工总数 | BL93: 4.5 | BM93: =BL93*初始权重设定说明!E22 -> 1.35 | BN93: =BL93*权重调整机制!K36 -> 1.8 | BO93: 来源：24年可持续发展报告 员工人数 | BP93: 4.83 | BQ93: =BP93*初始权重设定说明!E22 -> 1.449 | BR93: =BP93*权重调整机制!K36 -> 1.932 | BS93: 来源：24年可持续发展报告-公司员工总数 2023年可持续发展报告-公司在职员工 | BT93: 0.96 | BU93: =BT93*初始权重设定说明!E22 -> 0.288 | BV93: =BT93*权重调整机制!K36 -> 0.384 | BW93: 来源：24、23年可持续发展报告-员工人数相关数据 | BX93: 5.26 | BY93: =BX93*初始权重设定说明!E22 -> 1.578 | BZ93: =BX93*权重调整机制!K36 -> 2.104 | CA93: 来源：24年可持续发展报告-在职员工数量 23年可持续发展报告-员工总数 | CB93: 0 | CC93: =CB93*初始权重设定说明!E22 -> 0 | CD93: =CB93*权重调整机制!K36 -> 0 | CE93: 来源：24年可持续发展报告-24、23年职工总数 | CF93: 6.39 | CG93: =CF93*初始权重设定说明!E22 -> 1.917 | CH93: =CF93*权重调整机制!K36 -> 2.556 | CI93: 来源：24年可持续发展报告-23、24 员工总数 | CJ93: 4.04 | CK93: =CJ93*初始权重设定说明!E22 -> 1.212 | CL93: =CJ93*权重调整机制!K36 -> 1.616
I94: P10 < 企业指标值 < P90 | J94: 环比得分 = 10 ×（企业环比变化率 − P10 变化率）÷（P90 变化率 − P10 变化率）
I97: 企业指标值 ≥ P90 | J97: 10
B98: 研发与创新 | C98: 研发投入占比 | D98: 以“研发投入 / 研发费用 / 研究与开发支出”等为核心关键词，结合财务报表附注中“研发支出”相关披露，提取企业当期研发投入金额；分母采用“营业收入”口径计算研发投入占比。 | E98: 环比变化（30%） + 当期横向位置（70%） | F98: 环比变化 | H98: （一）研发投入占比计算 研发投入占比 = 研发投入 ÷ 当期营业收入 单位：% 说明： 研发投入占比为正向指标，数值越高表示企业对技术进步和转型的资源投入力度越大。 （二）环比变化维度（30%） 1. 环比变化率计算 环比变化率 =（当期研发投入占比 − 上年研发投入占比）÷ 上年研发投入占比 2. 行业分位区间确定 P10 变化率 = 行业内环比变化率的第 10 分位值 P90 变化率 = 行业内环比变化率的第 90 分位值 3. 归一化赋分 • 企业环比变化率 ≤ P10 变化率，环比得分 = 0 • 企业环比变化率 ≥ P90 变化率，环比得分 = 10 • 中间区间： 环比得分 = 10 ×（企业环比变化率 − P10 变化率）÷（P90 变化率 − P10 变化率） | I98: 企业改进率 ≤ P10 改进率 | J98: 0 | K98: 来源：24、23年年报 合并利润表 研发费用、营业总收入 | L98: 2.11 | M98: =SUM(L98:L103)*初始权重设定说明!E23 -> 0.8 | N98: =SUM(L98:L103)*权重调整机制!K37 -> 0.8 | O98: 来源：24、23年年报 合并利润表 研发费用、营业总收入 | P98: 2.42 | Q98: =SUM(P98:P103)*初始权重设定说明!E23 -> 0.938 | R98: =SUM(P98:P103)*权重调整机制!K37 -> 0.938 | S98: 来源：24、23年年报 合并利润表 研发费用、营业总收入 | T98: 0 | U98: =SUM(T98:T103)*初始权重设定说明!E23 -> 0.644 | V98: =SUM(T98:T103)*权重调整机制!K37 -> 0.644 | W98: 来源：24、23年年报 合并利润表 研发费用、营业总收入 | X98: 0.24 | Y98: =SUM(X98:X103)*初始权重设定说明!E23 -> 1.448 | Z98: =SUM(X98:X103)*权重调整机制!K37 -> 1.448 | AA98: 来源：24、23年年报 合并利润表 研发费用、营业总收入 | AB98: 1.27 | AC98: =SUM(AB98:AB103)*初始权重设定说明!E23 -> 1.654 | AD98: =SUM(AB98:AB103)*权重调整机制!K37 -> 1.654 | AE98: 来源：24、23年年报 合并利润表 研发费用、营业总收入 | AF98: 0.84 | AG98: =SUM(AF98:AF103)*初始权重设定说明!E23 -> 0.244 | AH98: =SUM(AF98:AF103)*权重调整机制!K37 -> 0.244 | AI98: 来源：24、23年年报 合并利润表 研发费用、营业总收入 | AJ98: 3 | AK98: =SUM(AJ98:AJ103)*初始权重设定说明!E23 -> 0.94 | AL98: =SUM(AJ98:AJ103)*权重调整机制!K37 -> 0.94 | AM98: 来源：24、23年年报 合并利润表 研发费用、营业总收入 | AN98: 1.3 | AO98: =SUM(AN98:AN103)*初始权重设定说明!E23 -> 0.676 | AP98: =SUM(AN98:AN103)*权重调整机制!K37 -> 0.676 | AQ98: 来源：24、23年年报 合并利润表 研发费用、营业总收入 | AR98: 0.4 | AS98: =SUM(AR98:AR103)*初始权重设定说明!E23 -> 0.836 | AT98: =SUM(AR98:AR103)*权重调整机制!K37 -> 0.836 | AU98: 来源：24、23年年报 合并利润表 研发费用、营业总收入 | AV98: 1.27 | AW98: =SUM(AV98:AV103)*初始权重设定说明!E23 -> 0.822 | AX98: =SUM(AV98:AV103)*权重调整机制!K37 -> 0.822 | AY98: 来源：24、23年年报 合并利润表 研发费用、营业总收入 | AZ98: 3 | BA98: =SUM(AZ98:AZ103)*初始权重设定说明!E23 -> 0.864 | BB98: =SUM(AZ98:AZ103)*权重调整机制!K37 -> 0.864 | BC98: 来源：24、23年年报 合并利润表 研发费用、营业总收入 | BD98: 3 | BE98: =SUM(BD98:BD103)*初始权重设定说明!E23 -> 0.6 | BF98: =SUM(BD98:BD103)*权重调整机制!K37 -> 0.6 | BG98: 来源：24、23年年报 合并利润表 研发费用、营业总收入 | BH98: 2.17 | BI98: =SUM(BH98:BH103)*初始权重设定说明!E23 -> 1.834 | BJ98: =SUM(BH98:BH103)*权重调整机制!K37 -> 1.834 | BK98: 来源：24、23年年报 合并利润表 研发费用、营业总收入 | BL98: 1.76 | BM98: =SUM(BL98:BL103)*初始权重设定说明!E23 -> 0.466 | BN98: =SUM(BL98:BL103)*权重调整机制!K37 -> 0.466 | BO98: 来源：24、23年年报 合并利润表 研发费用、营业总收入 | BP98: 0.71 | BQ98: =SUM(BP98:BP103)*初始权重设定说明!E23 -> 0.824 | BR98: =SUM(BP98:BP103)*权重调整机制!K37 -> 0.824 | BS98: 来源：24、23年年报 合并利润表 研发费用、营业总收入 | BT98: 2.22 | BU98: =SUM(BT98:BT103)*初始权重设定说明!E23 -> 0.444 | BV98: =SUM(BT98:BT103)*权重调整机制!K37 -> 0.444 | BW98: 来源：24、23年年报 合并利润表 研发费用、营业总收入 | BX98: 0 | BY98: =SUM(BX98:BX103)*初始权重设定说明!E23 -> 0.228 | BZ98: =SUM(BX98:BX103)*权重调整机制!K37 -> 0.228 | CA98: 来源：24、23年年报 合并利润表 研发费用、营业总收入 | CB98: 1.9 | CC98: =SUM(CB98:CB103)*初始权重设定说明!E23 -> 0.38 | CD98: =SUM(CB98:CB103)*权重调整机制!K37 -> 0.38 | CE98: 来源：24、23年年报 合并利润表 研发费用、营业总收入 | CF98: 2.89 | CG98: =SUM(CF98:CF103)*初始权重设定说明!E23 -> 0.994 | CH98: =SUM(CF98:CF103)*权重调整机制!K37 -> 0.994 | CI98: 来源：24、23年年报 合并利润表 研发费用、营业总收入 | CJ98: 2.52 | CK98: =SUM(CJ98:CJ103)*初始权重设定说明!E23 -> 1.866 | CL98: =SUM(CJ98:CJ103)*权重调整机制!K37 -> 1.866
I99: P10 改进率 < 企业改进率 < P90 改进率 | J99: 环比得分 = 10 ×（企业环比变化率 − P10 变化率）÷（P90 变化率 − P10 变化率）
I100: 企业改进率 ≥ P90 改进率 | J100: 10
F101: 当期横向位置 | H101: 当期横向位置维度（70%） 1. 行业分位区间确定 P10 研发投入占比 = 行业内当期研发投入占比的第 10 分位值 P90 研发投入占比 = 行业内当期研发投入占比的第 90 分位值 2. 行业维度归一化赋分（正向） • 企业当期占比 ≤ P10，占比得分 = 0 • 企业当期占比 ≥ P90，占比得分 = 10 • 中间区间： 当期得分 = 10 ×（企业当期研发投入占比 − P10）÷（P90 − P10） | I101: 企业指标值 ≤ P10 | J101: 0 | K101: 来源：24年年报 合并利润表 研发费用、营业总收入 | L101: 1.89 | O101: 来源：24年年报 合并利润表 研发费用、营业总收入 | P101: 2.27 | S101: 来源：24年年报 合并利润表 研发费用、营业总收入 | T101: 3.22 | W101: 来源：24年年报 合并利润表 研发费用、营业总收入 | X101: 7 | AA101: 来源：24年年报 合并利润表 研发费用、营业总收入 | AB101: 7 | AE101: 来源：24年年报 合并利润表 研发费用、营业总收入 | AF101: 0.38 | AI101: 来源：24年年报 合并利润表 研发费用、营业总收入 | AJ101: 1.7 | AM101: 来源：24年年报 合并利润表 研发费用、营业总收入 | AN101: 2.08 | AQ101: 来源：24年年报 合并利润表 研发费用、营业总收入 | AR101: 3.78 | AU101: 来源：24年年报 合并利润表 研发费用、营业总收入 | AV101: 2.84 | AY101: 来源：24年年报 合并利润表 研发费用、营业总收入 | AZ101: 1.32 | BC101: 来源：24年年报 合并利润表 研发费用、营业总收入 | BD101: 0 | BG101: 来源：24年年报 合并利润表 研发费用、营业总收入 | BH101: 7 | BK101: 来源：24年年报 合并利润表 研发费用、营业总收入 | BL101: 0.57 | BO101: 来源：24年年报 合并利润表 研发费用、营业总收入 | BP101: 3.41 | BS101: 来源：24年年报 合并利润表 研发费用、营业总收入 | BT101: 0 | BW101: 来源：24年年报 合并利润表 研发费用、营业总收入 | BX101: 1.14 | CA101: 来源：24年年报 合并利润表 研发费用、营业总收入 | CB101: 0 | CE101: 来源：24年年报 合并利润表 研发费用、营业总收入 | CF101: 2.08 | CI101: 来源：24年年报 合并利润表 研发费用、营业总收入 | CJ101: 6.81
I102: P10 < 企业指标值 < P90 | J102: 当期得分 = 10 ×（企业当期指标值 − P10）÷（P90 − P10）
...

Sheet 空值处理统一逻辑说明
A1: 正向指标·空值处理统一逻辑说明（钢铁行业打样版）
A2: 本Sheet用于统一规范正向指标Sheet中【空值处理】列的填写逻辑。所有指标须按下表归入4类规则之一，正向指标Sheet中对应单元格仅保留极简引用词（如"适用规则A（强制-赋0）"）。本表为规则全文，应作为评分手册附录，供使用者查阅。
A3: 一、分类体系总览
A4: 规则编号 | B4: 指标类别 | C4: 触发条件（定义） | D4: 空值处理方式 | E4: 核心理由 | F4: 适用指标示例
A5: 规则A | B5: 强制披露·定性指标 | C5: 监管或主流框架（沪深交易所可持续发展报告指引、TCFD、GRI）明确要求披露的定性指标 | D5: 直接赋 0 分 | E5: 强制披露缺失代表企业在最基础的信息透明度上存在违规或重大疏漏，评价完整性要求最严惩罚 | F5: 碳中和目标、碳达峰目标、转型规划、治理架构、气候风险管理体系、气候相关风险和机遇、碳排放披露情况
A6: 规则B | B6: 强制披露·定量指标（含行业专属关键指标） | C6: 监管明确要求披露的定量指标，以及行业专属的关键转型表现指标——无论是否强制，未披露均视为关键缺失 | D6: 直接赋 0 分 | E6: 定量强制披露缺失表明企业未履行法定义务；行业专属关键指标未披露直接表明转型表现存在重大不透明 | F6: 物理碳排放强度、营收碳排放强度、稳就业与促就业、研发投入占比；系统能效提升、环保减排改造、冶炼技术突破、数字化赋能、产品结构优化、废钢回收率
A7: 规则C | B7: 鼓励披露·定量/定性指标（期望型） | C7: 非强制要求、但政策和主流框架明确鼓励披露的定量指标，企业未披露具有信息不对称风险 | D7: 赋行业下四分位数（P25） | E7: 体现"不披露则假设表现偏下"的政策导向，同时避免赋0对数据稀疏指标造成极端惩罚 | F7: 可再生能源占比、用水效率（吨钢耗新水量）、节能技改投资占比、环保投入金额占比、员工培训
A8: 规则D | B8: 非关键披露·补充项（定性/定量） | C8: 既非强制也非主流框架明确鼓励，属于补充性/加分性指标，企业未披露属正常情况 | D8: 赋行业中位数（P50） | E8: 补充项缺失不代表表现差，使用中位数作为中性假设，不惩罚也不奖励，避免对评分产生系统性偏差 | F8: 其他环境目标、其他战略、气候压力测试、生物多样性
A11: 二、各指标规则对应关系一览表
A12: 序号 | B12: 三级指标名称 | C12: 一级维度 | D12: 规则编号 | E12: 处理方式简述 | F12: 备注
A13: 1 | B13: 碳中和目标 | C13: 目标与战略（25分） | D13: 规则A | E13: 强制披露·定性 → 赋0分
A14: 2 | B14: 碳达峰目标 | D14: 规则A | E14: 强制披露·定性 → 赋0分
A15: 3 | B15: 其他环境目标 | D15: 规则D | E15: 非关键补充 → P50（无折扣）
A16: 4 | B16: 转型规划 | D16: 规则A | E16: 强制披露·定性 → 赋0分
A17: 5 | B17: 其他战略 | D17: 规则D | E17: 非关键补充 → P50（无折扣）
A18: 6 | B18: 治理架构 | C18: 实施保障（20分） | D18: 规则A | E18: 强制披露·定性 → 赋0分
A19: 7 | B19: 气候风险管理体系 | D19: 规则A | E19: 强制披露·定性 → 赋0分
A20: 8 | B20: 气候相关风险和机遇 | D20: 规则A | E20: 强制披露·定性 → 赋0分
A21: 9 | B21: 气候压力测试 | D21: 规则D | E21: 非关键补充 → P50（无折扣）
A22: 10 | B22: 碳排放披露情况 | C22: 转型表现 | D22: 规则A | E22: 强制披露·定性 → 赋0分
A23: 11 | B23: 物理碳排放强度 | D23: 规则B | E23: 强制披露·定量 → 赋0分
A24: 12 | B24: 营收碳排放强度 | D24: 规则B | E24: 强制披露·定量 → 赋0分
A25: 13 | B25: 可再生能源占比 | D25: 规则C | E25: 鼓励披露·定量 → P25
A26: 14 | B26: 用水效率 | D26: 规则C | E26: 鼓励披露·定量 → P25
A27: 15 | B27: 生物多样性 | D27: 规则D | E27: 非关键补充 → P50（无折扣）
A28: 16 | B28: 员工培训 | D28: 规则C | E28: 鼓励披露·定性 → P25对应档
A29: 17 | B29: 稳就业与促就业 | D29: 规则B | E29: 强制披露·定量 → 赋0分
A30: 18 | B30: 研发投入占比 | D30: 规则B | E30: 强制披露·定量 → 赋0分
A31: 19 | B31: 节能技改投资占比 | D31: 规则C | E31: 鼓励披露·定量 → P25
A32: 20 | B32: 环保投入金额占比 | D32: 规则C | E32: 鼓励披露·定量 → P25
A33: 21 | B33: 系统能效提升 | D33: 规则B | E33: 强制披露·定量/行业关键 → 赋0分
A34: 22 | B34: 环保减排改造 | D34: 规则B | E34: 强制披露·定量/行业关键 → 赋0分
... A38: 26 | B38: 废钢回收率 | D38: 规则B | E38: 强制披露·定量/行业关键 → 赋0分

Sheet 初始权重设定说明
A1: 钢铁行业转型金融评价指标体系 —— 权重设定说明
A2: 说明：本表记录每个三级指标初始权重的设定依据，综合参考TCFD、TPI、ICMA CTB、GFANZ等国际框架，以及《转型金融支持经济活动目录》、河北省钢铁行业转型金融工作指引等国内政策文件，结合专家判断形成。
A4: 一级指标 | B4: 二级指标 | C4: 三级指标 | D4: 指标因子 | E4: 当前比重系数 | F4: 权重设定依据（理论+框架参考）
A5: 目标与战略（25分） | B5: 目标和承诺 | C5: 碳中和目标 | D5: 中和年份承诺与覆盖度 | E5: 0.7 | F5: TCFD明确将减排目标列为战略披露核心要素；TPI方法论将量化减排目标作为碳绩效评估的前提条件；GFANZ框架要求主体披露符合1.5°C路径的净零目标。碳中和目标作为企业转型的最高层级承诺，权重应显著高于其他目标类指标。与碳达峰目标并列设为0.7，体现"承诺先行"逻辑。
C6: 碳达峰目标 | D6: 达峰年份承诺与覆盖度 | E6: 0.7 | F6: 《转型金融支持经济活动目录》要求转型主体碳达峰目标不得落后于国家目标；河北省指引将碳达峰作为整体转型方案的首要原则。与碳中和目标并列0.7，体现双碳目标在转型评价中的基础性地位。
C7: 其他环境目标 | D7: 环境目标完整性与质量 | E7: 0.2 | F7: SASB标准要求企业披露与行业相关的环境绩效指标；TCFD建议披露支撑转型路径的配套环境目标（能效、可再生能源等）。该指标为辅助性目标评估，权重设为0.2，与核心碳目标形成"核心+辅助"层级。
B8: 战略和规划 | C8: 转型规划 | D8: 转型规划完善程度 | E8: 0.7 | F8: ICMA CTB将转型战略和实施路径作为气候转型债券的核心评估要素；TCFD《指标、目标和转型计划指南》将转型计划列为关键披露项；GFANZ要求披露涵盖短期、中期、长期的完整转型战略。转型规划是目标落地的直接载体，权重设为0.7，体现"战略可执行性"要求。
C9: 其他战略 | D9: 低碳相关顶层战略 | E9: 0.2 | F9: 作为转型规划的替代性指标，仅在企业未制定专门转型规划时触发。SASB将可持续发展战略纳入治理维度披露。属于补充性评估，权重设为0.2。
A10: 实施保障（20分） | B10: 治理 | C10: 治理架构 | D10: 治理架构完善程度 | E10: 0.7 | F10: TCFD将治理列为四大支柱之首；GFANZ框架将治理体系作为转型计划的基础条件；ICMA CTB要求发行人披露治理架构对转型战略的支撑机制。河北省指引明确将治理纳入整体转型方案评估。权重0.7体现治理的"地基"作用。
B11: 风险管理 | C11: 气候风险管理体系 | D11: 风险管理完善程度 | E11: 0.7 | F11: TCFD第二支柱"风险管理"要求企业描述气候风险的识别、评估、管理和监控流程；河北省指引要求企业将气候风险纳入整体风险管理体系。权重0.7反映风险管理在实施保障中的重要性。
C12: 气候相关风险和机遇 | D12: 风险机遇识别完善程度 | E12: 0.5 | F12: TCFD要求企业识别与其相关的气候相关风险和机遇，并进行财务影响分析。该指标为风险管理的深化延伸，权重略低于管理体系本身（ 0.5）。
C13: 气候压力测试 | D13: 压力测试完善程度 | E13: 0.1 | F13: TCFD建议但不强制要求情景分析；TPI方法论中使用情景对标但未要求企业自行开展压力测试。当前行业压力测试实践尚不成熟，权重设为0.1，作为前瞻性评估的探索性指标。
A14: 转型表现（55分） | B14: 碳排放表现 | C14: 碳排放披露情况 | D14: 披露完整度 | E14: 0.7 | F14: TCFD将温室气体排放披露列为第三支柱"指标与目标"的核心要求；TPI将碳排放数据的可获性作为碳绩效评估的前提；《企业可持续披露准则》要求披露范围一、范围二温室气体排放。数据披露是绩效评估的前提，权重设为0.7。
C15: 物理碳排放强度 | D15: 环比变化+当期横向位置 | E15: 0.7 | F15: TPI方法论的核心指标即为碳排放强度的年度改善率（碳排放管理质量评分）；GFANZ框架以碳强度下降路径作为评估转型进展的关键量化指标。物理碳排放强度是评价企业脱碳进展的最直接指标，权重设为0.7。
C16: 营收碳排放强度 | D16: 环比变化+当期横向位置 | E16: 0.7 | F16: 营收碳排放强度反映企业经济活动的碳效率，是对物理碳排放强度的补充。TCFD鼓励披露碳强度指标，但该指标受产品价格波动影响较大，权重设为0.7作为辅助指标。
B17: 能源使用 | C17: 可再生能源占比 | D17: 自发可再生能源占比 | E17: 0.2 | F17: ICMA CTB将能源结构转型列为转型战略的关键组成部分；TPI将能源转型路径作为评估要素之一。自发可再生能源为企业自有绿电能力，当前钢铁行业自建光伏/风电规模有限，权重设为0.2。
C18: 外购绿电占比 | D18: 外购绿电占比 | E18: 0.2 | F18: 同上。外购绿电反映企业绿色电力采购意愿与能力，当前绿电交易市场处于发展初期，行业差异大，权重设为0.2。
B19: 水资源利用 | C19: 用水效率 | D19: 吨钢耗新水量 | E19: 0.2 | F19: SASB钢铁行业标准要求披露水资源管理和消耗数据；工信部《钢铁行业规范条件（2025年版）》对吨钢耗新水提出明确要求。水效指标与钢铁生产直接相关且数据可获性较高，权重设为0.2。
B20: 生态保护 | C20: 生物多样性 | D20: 制度+行动 | E20: 0.1 | F20: TNFD（自然相关财务披露框架）正在推动生物多样性信息披露，但当前钢铁行业该领域披露尚处起步阶段。权重设为0.1作为前瞻性引导指标。
B21: 公正转型 | C21: 员工培训 | D21: 培训披露 | E21: 0.1 | F21: ICMA CTB提及公正转型的社会维度；ILO公正转型指南强调劳动者技能培训。当前钢铁行业该指标披露形式多样、难以量化比较，权重设为0.1。
C22: 稳就业与促就业 | D22: 员工规模变化 | E22: 0.3 | F22: 公正转型是社会可持续性的核心维度，河北省指引将社会影响纳入转型评估。钢铁行业就业影响显著，权重设为0.3反映公正转型的重要性。
B23: 研发与创新 | C23: 研发投入占比 | D23: 环比变化+当期横向位置 | E23: 0.2 | F23: TPI方法论将低碳技术创新投入作为评估转型准备度的重要因素；河北省指引将技术创新列入转型方案的关键支撑。研发投入是技术突破的资金保障，权重设为0.2。
C24: 节能技改投资占比 | D24: 环比变化+当期横向位置 | E24: 0.2 | F24: 节能技改是钢铁行业最直接的减碳手段之一，但该指标当前行业披露率较低（仅部分龙头企业披露），且与研发投入存在一定重叠，权重设为0.2。
C25: 环保投入金额占比 | D25: 环比变化+当期横向位置 | E25: 0.1 | F25: 环保投入反映企业环境治理的资金承诺，与节能减排间接相关。权重设为0.1，低于节能技改和研发投入。
B26: 行业特定 | C26: 系统能效提升 | D26: 节能技术应用 | E26: 0.3 | F26: 人民银行转型金融标准技术路径之一，权重设为0.3反映其行业特定重要性。
C27: 环保减排改造 | D27: 超低排放改造 | E27: 0.3 | F27: 人民银行转型金融标准技术路径之一，权重设为0.4反映其行业特定重要性。
C28: 冶炼技术突破 | D28: 前沿技术应用 | E28: 0.3 | F28: 人民银行转型金融标准技术路径之一，权重设为0.5反映其行业特定重要性。
C29: 数字化赋能 | D29: 数字化手段应用 | E29: 0.3 | F29: 人民银行转型金融标准技术路径之一，权重设为0.6反映其行业特定重要性。
C30: 产品结构优化 | D30: 高端产品布局+质量奖 | E30: 0.3 | F30: 人民银行转型金融标准技术路径之一，权重设为0.7反映其行业特定重要性。
C31: 废钢回收率 | D31: 环比变化+当期横向位置 | E31: 0.3 | F31: 人民银行转型金融标准技术路径之一，权重设为0.8反映其行业特定重要性。

Sheet 权重调整机制
A1: 钢铁行业转型金融评价指标体系 —— 权重调整机制
A3: 一、权重调整流程
A4: 本评价体系的最终权重，是通过“数据分析 + 统一调整 + 专家修正”三步逐步确定的，具体过程如下： 第一步：根据实际数据表现进行初步调整 在专家给出的初始权重基础上，引入试评分结果，对每个指标进行动态修正。主要考虑两个因素：一是信息披露情况，二是指标是否能有效拉开企业差距。 简单来说，披露充分、区分度高的指标会适当提高权重；披露较少或区分度不明显的指标则会被下调。这样可以让评价体系既有数据基础，也能真正区分企业表现。 同时，对于“转型规划”和“其他战略”这类存在替代关系的指标组合，不参与这一轮调整，以避免核心指标被技术性规则误伤。 第二步：统一各维度权重比例 为了保证整体结构稳定，将三大维度（目标与战略、实施保障、转型表现）的权重固定在25%、20%、55%。在此基础上，对维度内部的指标权重进行同比例调整，使其加总符合设定比例。 调整完成后，再通过统一的数值处理方法，将所有权重保留到1位小数，并消除因四舍五入产生的误差，确保结果严谨一致。 第三步：结合行业重点进行专家修正 前两步主要基于数据，但纯数据方法可能会低估一些“当前披露不充分、但非常重要”的指标。因此，在最后一步引入专家判断进行微调。 例如，对于数字化赋能、废钢回收率等关键转型指标，虽然当前企业披露不多或差异不大，但从行业转型角度看非常重要，因此对其权重进行了适当上调和锁定。 这样可以确保评价结果不仅反映当前情况，也能体现政策导向和行业转型重点。
A6: 二、披露率调整规则
A7: 序号 | B7: 披露率区间 | C7: 调整方向 | D7: 调整系数 | E7: 调整后权重公式 | F7: 调整理由
A8: 1 | B8: 披露率 ≥ 80% | C8: 维持不变 | D8: 1.0 | E8: 调整后权重 = 初始权重 × 1.2 | F8: 数据充分，权重设定合理，无需调整
A9: 2 | B9: 50% ≤ 披露率 < 80% | C9: 维持不变 | D9: 1.0 | E9: 调整后权重 = 初始权重 × 1.0 | F9: 数据尚可，权重可信度可接受
A10: 3 | B10: 20% ≤ 披露率 < 50% | C10: 适当调低 | D10: 0.7 | E10: 调整后权重 = 初始权重 × 0.7 | F10: 数据不足，区分度受限，需降低权重以避免引入过多噪声。说明：权重调低后被释放的权重空间不分配给其他指标，而是缩减至总分中。
A11: 4 | B11: 10% ≤ 披露率 < 20% | C11: 显著调低 | D11: 0.5 | E11: 调整后权重 = 初始权重 × 0.5 | F11: 数据严重不足，该指标评分结果对总分贡献的可信度低。
A12: 5 | B12: 披露率 < 10% | C12: 暂停计分 | D12: 0 | E12: 调整后权重 = 0（该指标不计入总分） | F12: 数据极度匮乏，强行赋分会严重扭曲评价结果。该指标暂停计分，待未来数据改善后恢复。
A14: 三、边际区分度分析
A15: 边际区分度 = 某指标得分的标准差 ÷ 该指标得分的均值 该指标用于衡量各企业在某一指标上的得分差异程度。边际区分度高说明该指标能有效区分不同企业的转型表现；边际区分度低则说明该指标对所有企业的区分效果有限。 校验规则： · 若某指标边际区分度 > 0.5，说明该指标区分效果良好，权重*1.2； · 若 0.3 < 边际区分度 ≤ 0.5，说明该指标有一定区分效果，维持权重不变；（*1.0） · 若0.1<边际区分度 ≤ 0.3，说明该指标在区分企业差异上表现一般，建议调低权重。（*0.7）·若边际区分度≤ 0.1，说明该指标几乎无法区分企业差异，建议调低权重（*0.5）或删除指标
A17: 四、各指标披露率与权重调整记录（待试评分完成后填写）
A18: 一级指标 | B18: 三级指标 | C18: 初始权重 | D18: 披露企业数 | E18: 总企业数 | F18: 披露率 | G18: 边际区分度 | H18: 调整后权重Step1 | I18: 维度归一化后Step2 | J18: 保留一位Step3 | K18: 最终确认权重 | L18: 备注
A19: 目标与战略 | B19: 碳中和目标 | C19: 0.7 | D19: 16 | E19: 20 | F19: =D19/E19 -> 0.8 | G19: 0.586 | H19: =C19*IF(F19>=0.8,1.2,IF(F19>=0.5,1,IF(F19>=0.2,0.7,IF(F19>=0.1,0.5,0))))*IF(G19>0.5,1.2,IF(G19>0.3,1,IF(G19>0.1,0.7,0.5))) -> 1.008 | I19: =H19/SUM($H$19:$H$23)*(25/10) -> 0.86419753 | J19: =ROUND(I19,1) -> 0.9 | K19: 0.9
B20: 碳达峰目标 | C20: 0.7 | D20: 18 | E20: 20 | F20: =D20/E20 -> 0.9 | G20: 0.47 | H20: =C20*IF(F20>=0.8,1.2,IF(F20>=0.5,1,IF(F20>=0.2,0.7,IF(F20>=0.1,0.5,0))))*IF(G20>0.5,1.2,IF(G20>0.3,1,IF(G20>0.1,0.7,0.5))) -> 0.84 | I20: =H20/SUM($H$19:$H$23)*(25/10) -> 0.72016461 | J20: =ROUND(I20,1) -> 0.7 | K20: 0.7
B21: 其他环境目标 | C21: 0.2 | D21: 20 | E21: 20 | F21: =D21/E21 -> 1 | G21: 0.185 | H21: =C21*IF(F21>=0.8,1.2,IF(F21>=0.5,1,IF(F21>=0.2,0.7,IF(F21>=0.1,0.5,0))))*IF(G21>0.5,1.2,IF(G21>0.3,1,IF(G21>0.1,0.7,0.5))) -> 0.168 | I21: =H21/SUM($H$19:$H$23)*(25/10) -> 0.14403292 | J21: =ROUND(I21,1) -> 0.1 | K21: 0.1
B22: 转型规划 | C22: 0.7 | D22: 15 | E22: 20 | F22: =D22/E22 -> 0.75 | G22: 0.25 | H22: 0.7 | I22: =H22/SUM($H$19:$H$23)*(25/10) -> 0.60013717 | J22: =ROUND(I22,1) -> 0.6 | K22: 0.6 | L22: 在本评价体系中，“转型规划”为核心评价项，“其他战略”作为未披露转型规划时的补充项，两者构成一个嵌套的评价模块。为避免在权重调整过程中出现逻辑失真（例如核心指标因企业披露内容趋同而被下调权重，而补充指标反而维持原有权重），本模型将二者作为一个整体进行处理，而不单独调整其相对权重。考虑到该模块整体披露率已达到100%，且“转型规划”属于国内外转型金融框架中的核心要求，本模型对该指标组不再基于披露率或区分度进行权重折减，而是直接采用初始权重参与同维度下的归一化分配。这样可以确保评价结果始终体现“规划先行”的政策导向，避免关键指标在技术性调整中被弱化。
B23: 其他战略 | C23: 0.2 | D23: 5 | E23: 20 | F23: =D23/E23 -> 0.25 | G23: 0 | H23: 0.2 | I23: =H23/SUM($H$19:$H$23)*(25/10) -> 0.17146776 | J23: =ROUND(I23,1) -> 0.2 | K23: 0.2
A24: 实施保障 | B24: 治理架构 | C24: 0.7 | D24: 20 | E24: 20 | F24: =D24/E24 -> 1 | G24: 0.18 | H24: =C24*IF(F24>=0.8,1.2,IF(F24>=0.5,1,IF(F24>=0.2,0.7,IF(F24>=0.1,0.5,0))))*IF(G24>0.5,1.2,IF(G24>0.3,1,IF(G24>0.1,0.7,0.5))) -> 0.588 | I24: =H24/SUM($H$24:$H$27)*(20/10) -> 0.49494949 | J24: =ROUND(I24,1) -> 0.5 | K24: 0.5
B25: 气候风险管理体系 | C25: 0.7 | D25: 19 | E25: 20 | F25: =D25/E25 -> 0.95 | G25: 0.551 | H25: =C25*IF(F25>=0.8,1.2,IF(F25>=0.5,1,IF(F25>=0.2,0.7,IF(F25>=0.1,0.5,0))))*IF(G25>0.5,1.2,IF(G25>0.3,1,IF(G25>0.1,0.7,0.5))) -> 1.008 | I25: =H25/SUM($H$24:$H$27)*(20/10) -> 0.84848485 | J25: =ROUND(I25,1) -> 0.8 | K25: 0.8
B26: 气候相关风险和机遇 | C26: 0.5 | D26: 17 | E26: 20 | F26: =D26/E26 -> 0.85 | G26: 0.502 | H26: =C26*IF(F26>=0.8,1.2,IF(F26>=0.5,1,IF(F26>=0.2,0.7,IF(F26>=0.1,0.5,0))))*IF(G26>0.5,1.2,IF(G26>0.3,1,IF(G26>0.1,0.7,0.5))) -> 0.72 | I26: =H26/SUM($H$24:$H$27)*(20/10) -> 0.60606061 | J26: =ROUND(I26,1) -> 0.6 | K26: 0.6
B27: 气候压力测试 | C27: 0.1 | D27: 3 | E27: 20 | F27: =D27/E27 -> 0.15 | G27: 2.836 | H27: =C27*IF(F27>=0.8,1.2,IF(F27>=0.5,1,IF(F27>=0.2,0.7,IF(F27>=0.1,0.5,0))))*IF(G27>0.5,1.2,IF(G27>0.3,1,IF(G27>0.1,0.7,0.5))) -> 0.06 | I27: =H27/SUM($H$24:$H$27)*(20/10) -> 0.050505051 | J27: =ROUND(I27,1) -> 0.1 | K27: 0.1
A28: 转型表现 | B28: 碳排放披露情况 | C28: 0.7 | D28: 15 | E28: 20 | F28: =D28/E28 -> 0.75 | G28: 0.739 | H28: =C28*IF(F28>=0.8,1.2,IF(F28>=0.5,1,IF(F28>=0.2,0.7,IF(F28>=0.1,0.5,0))))*IF(G28>0.5,1.2,IF(G28>0.3,1,IF(G28>0.1,0.7,0.5))) -> 0.84 | I28: =H28/SUM($H$28:$H$45)*(55/10) -> 0.71296296 | J28: =ROUND(I28,1) -> 0.7 | K28: 0.7
B29: 物理碳排放强度 | C29: 0.7 | D29: 14 | E29: 20 | F29: =D29/E29 -> 0.7 | G29: 1.02 | H29: =C29*IF(F29>=0.8,1.2,IF(F29>=0.5,1,IF(F29>=0.2,0.7,IF(F29>=0.1,0.5,0))))*IF(G29>0.5,1.2,IF(G29>0.3,1,IF(G29>0.1,0.7,0.5))) -> 0.84 | I29: =H29/SUM($H$28:$H$45)*(55/10) -> 0.71296296 | J29: =ROUND(I29,1) -> 0.7 | K29: 0.7
B30: 营收碳排放强度 | C30: 0.7 | D30: 14 | E30: 20 | F30: =D30/E30 -> 0.7 | G30: 0.994 | H30: =C30*IF(F30>=0.8,1.2,IF(F30>=0.5,1,IF(F30>=0.2,0.7,IF(F30>=0.1,0.5,0))))*IF(G30>0.5,1.2,IF(G30>0.3,1,IF(G30>0.1,0.7,0.5))) -> 0.84 | I30: =H30/SUM($H$28:$H$45)*(55/10) -> 0.71296296 | J30: =ROUND(I30,1) -> 0.7 | K30: 0.7
B31: 可再生能源占比 | C31: 0.2 | D31: 16 | E31: 20 | F31: =D31/E31 -> 0.8 | G31: 1.242 | H31: =C31*IF(F31>=0.8,1.2,IF(F31>=0.5,1,IF(F31>=0.2,0.7,IF(F31>=0.1,0.5,0))))*IF(G31>0.5,1.2,IF(G31>0.3,1,IF(G31>0.1,0.7,0.5))) -> 0.288 | I31: =H31/SUM($H$28:$H$45)*(55/10) -> 0.24444444 | J31: =ROUND(I31,1) -> 0.2 | K31: 0.2
B32: 外购绿电占比 | C32: 0.2 | D32: 12 | E32: 20 | F32: =D32/E32 -> 0.6 | G32: 1.123 | H32: =C32*IF(F32>=0.8,1.2,IF(F32>=0.5,1,IF(F32>=0.2,0.7,IF(F32>=0.1,0.5,0))))*IF(G32>0.5,1.2,IF(G32>0.3,1,IF(G32>0.1,0.7,0.5))) -> 0.24 | I32: =H32/SUM($H$28:$H$45)*(55/10) -> 0.2037037 | J32: =ROUND(I32,1) -> 0.2 | K32: 0.2
B33: 用水效率 | C33: 0.2 | D33: 19 | E33: 20 | F33: =D33/E33 -> 0.95 | G33: 0.511 | H33: =C33*IF(F33>=0.8,1.2,IF(F33>=0.5,1,IF(F33>=0.2,0.7,IF(F33>=0.1,0.5,0))))*IF(G33>0.5,1.2,IF(G33>0.3,1,IF(G33>0.1,0.7,0.5))) -> 0.288 | I33: =H33/SUM($H$28:$H$45)*(55/10) -> 0.24444444 | J33: =ROUND(I33,1) -> 0.2 | K33: 0.2
B34: 生物多样性 | C34: 0.1 | D34: 19 | E34: 20 | F34: =D34/E34 -> 0.95 | G34: 0.265 | H34: =C34*IF(F34>=0.8,1.2,IF(F34>=0.5,1,IF(F34>=0.2,0.7,IF(F34>=0.1,0.5,0))))*IF(G34>0.5,1.2,IF(G34>0.3,1,IF(G34>0.1,0.7,0.5))) -> 0.084 | I34: =H34/SUM($H$28:$H$45)*(55/10) -> 0.071296296 | J34: =ROUND(I34,1) -> 0.1 | K34: 0.1
B35: 员工培训 | C35: 0.1 | D35: 20 | E35: 20 | F35: =D35/E35 -> 1 | G35: 0.327 | H35: =C35*IF(F35>=0.8,1.2,IF(F35>=0.5,1,IF(F35>=0.2,0.7,IF(F35>=0.1,0.5,0))))*IF(G35>0.5,1.2,IF(G35>0.3,1,IF(G35>0.1,0.7,0.5))) -> 0.12 | I35: =H35/SUM($H$28:$H$45)*(55/10) -> 0.10185185 | J35: =ROUND(I35,1) -> 0.1 | K35: 0.1
B36: 稳就业与促就业 | C36: 0.3 | D36: 20 | E36: 20 | F36: =D36/E36 -> 1 | G36: 0.724 | H36: =C36*IF(F36>=0.8,1.2,IF(F36>=0.5,1,IF(F36>=0.2,0.7,IF(F36>=0.1,0.5,0))))*IF(G36>0.5,1.2,IF(G36>0.3,1,IF(G36>0.1,0.7,0.5))) -> 0.432 | I36: =H36/SUM($H$28:$H$45)*(55/10) -> 0.36666667 | J36: =ROUND(I36,1) -> 0.4 | K36: 0.4
B37: 研发投入占比 | C37: 0.2 | D37: 20 | E37: 20 | F37: =D37/E37 -> 1 | G37: 0.553 | H37: =C37*IF(F37>=0.8,1.2,IF(F37>=0.5,1,IF(F37>=0.2,0.7,IF(F37>=0.1,0.5,0))))*IF(G37>0.5,1.2,IF(G37>0.3,1,IF(G37>0.1,0.7,0.5))) -> 0.288 | I37: =H37/SUM($H$28:$H$45)*(55/10) -> 0.24444444 | J37: =ROUND(I37,1) -> 0.2 | K37: 0.2
B38: 节能技改投资占比 | C38: 0.2 | D38: 7 | E38: 20 | F38: =D38/E38 -> 0.35 | G38: 3.012 | H38: =C38*IF(F38>=0.8,1.2,IF(F38>=0.5,1,IF(F38>=0.2,0.7,IF(F38>=0.1,0.5,0))))*IF(G38>0.5,1.2,IF(G38>0.3,1,IF(G38>0.1,0.7,0.5))) -> 0.168 | I38: =H38/SUM($H$28:$H$45)*(55/10) -> 0.14259259 | J38: =ROUND(I38,1) -> 0.1 | K38: 0.1
B39: 环保投入金额占比 | C39: 0.1 | D39: 19 | E39: 20 | F39: =D39/E39 -> 0.95 | G39: 0.757 | H39: =C39*IF(F39>=0.8,1.2,IF(F39>=0.5,1,IF(F39>=0.2,0.7,IF(F39>=0.1,0.5,0))))*IF(G39>0.5,1.2,IF(G39>0.3,1,IF(G39>0.1,0.7,0.5))) -> 0.144 | I39: =H39/SUM($H$28:$H$45)*(55/10) -> 0.12222222 | J39: =ROUND(I39,1) -> 0.1 | K39: 0.1
B40: 系统能效提升 | C40: 0.3 | D40: 18 | E40: 20 | F40: =D40/E40 -> 0.9 | G40: 0.443 | H40: =C40*IF(F40>=0.8,1.2,IF(F40>=0.5,1,IF(F40>=0.2,0.7,IF(F40>=0.1,0.5,0))))*IF(G40>0.5,1.2,IF(G40>0.3,1,IF(G40>0.1,0.7,0.5))) -> 0.36 | I40: =H40/SUM($H$28:$H$45)*(55/10) -> 0.30555556 | J40: =ROUND(I40,1) -> 0.3 | K40: 0.3
... B45: 废钢回收率 | C45: 0.3 | D45: 7 | E45: 20 | F45: =D45/E45 -> 0.35 | G45: 0.755 | H45: =C45*IF(F45>=0.8,1.2,IF(F45>=0.5,1,IF(F45>=0.2,0.7,IF(F45>=0.1,0.5,0))))*IF(G45>0.5,1.2,IF(G45>0.3,1,IF(G45>0.1,0.7,0.5))) -> 0.252 | I45: =H45/SUM($H$28:$H$45)*(55/10) -> 0.21388889 | J45: =ROUND(I45,1) -> 0.2 | K45: 0.3
A47: 五、权重调整说明（待试评分完成后填写）
A48: 【填写说明】 在完成试评分后，请： 1. 统计每个指标的实际披露率（披露企业数÷总企业数），填入上方表格； 2. 计算每个指标得分的边际区分度（标准差÷均值），填入上方表格； 3. 根据第二部分的披露率调整规则，确定调整系数； 4. 综合披露率和边际区分度，确定最终调整后权重，填入上方表格； 5. 在此区域填写调整的详细理由和依据，形成"权重调整说明"。
A53: 三级指标 | B53: 权重调整说明
A54: 碳中和目标 | B54: 披露率高（80%），区分度也较好（0.586），能够体现企业的战略前瞻性，因此在数据模型中获得加权提升，最终由0.7上调至0.9。
A55: 碳达峰目标 | B55: 披露率很高（90%），但区分度一般（0.47），属于基础合规性目标，因此维持稳定权重，最终为0.7。
A56: 其他环境目标 | B56: 虽然披露率达到100%，但区分度很低（0.185），已成为行业普遍做法，难以拉开差距，因此下调至0.1。
A57: 转型规划 | B57: 作为核心指标，与“其他战略”构成替代关系。为避免核心指标被技术性降权，该指标不参与区分度调整，按初始逻辑保留并归一化后确定为0.6。
A58: 其他战略 | B58: 作为“转型规划”的替代项，同样不参与数据驱动降权，保持原有权重结构，最终为0.2。
A59: 治理架构 | B59: 行业已基本全覆盖（100%披露），但区分度较低（0.18），属于基础管理要求，因此适当降权至0.5。
A60: 气候风险管理体系 | B60: 披露率（95%）和区分度（0.551）均表现良好，能够有效区分企业管理能力，因此权重由0.7提升至0.8。
A61: 气候相关风险和机遇 | B61: 区分度较好（>0.5），具备一定评价意义，按模型正常调整后小幅提升至0.6。
A62: 气候压力测试 | B62: 区分度虽高，但披露率极低（15%），数据基础不足，因此按规则处理，仍然为0.1低权重。
A63: 碳排放披露情况 | B63: 核心信息披露指标，披露情况良好且具备区分度，维持0.7权重。
A64: 物理碳排放强度 | B64: 核心绩效指标，区分度极高（1.02），能够直接反映减排效果，因此保持0.7高权重。
... A80: 废钢回收率 | B80: 披露率较低（35%）导致模型降权，但其对行业减碳意义重大，经专家上调并锁定为0.3。

Sheet 定量指标统一打分范式
A1: 定量指标统一打分范式 —— P10-P90分位归一化方法
A3: 【反馈回应】当前打分逻辑偏复杂，建议精简预处理步骤，形成统一范式。 【本表目的】将所有定量指标的赋分逻辑统一为"P10-P90分位归一化"范式，降低使用和解释成本。 【适用范围】仅适用于分值关系为"环比变化（30%）+ 当期横向位置（70%）"的定量连续指标。 【不适用的指标类型】定性指标（"相等"/"累加"赋分方式）不在本范式覆盖范围内，保持原赋分逻辑不变。
A5: 一、统一打分范式说明
A6: 所有定量连续指标采用统一的"P10-P90分位归一化"赋分方法，每个指标的总得分由两个维度加权计算： 总得分 = 环比变化得分（30%）+ 当期横向位置得分（70%） 两个维度均采用相同的归一化逻辑：在行业内所有企业数据中确定P10和P90分位值， 将企业实际值线性映射至[0, 10]分区间。
A8: 二、正向指标归一化规则（数值越大越好）
A9: 步骤1：计算指标值 指标值 = 企业当期数据 ÷ 对应产量/营收等基准值 步骤2：确定行业分位区间 对行业内所有企业的指标值排序，确定P10和P90分位值。 步骤3：线性归一化赋分 · 当 指标值 ≤ P10 时，得分 = 0 · 当 指标值 ≥ P90 时，得分 = 10 · 当 P10 < 指标值 < P90 时，得分 = 10 ×（指标值 - P10）÷（P90 - P10） 步骤4：环比变化维度（30%） 计算企业改进率 =（当期指标值 - 上年指标值）÷ 上年指标值 对行业内改进率排序，确定P10和P90，按步骤3归一化，得到上年得分。 步骤5：当期横向位置维度（70%） 直接对当期指标值按步骤3归一化，得到当期得分。 步骤6：计算总得分 总得分 = 上年得分 × 30% + 当期得分 × 70%
A11: 三、反向指标归一化规则（数值越小越好，如用水效率、碳排放强度）
A12: 步骤1-2：同正向指标 步骤3：反向线性归一化赋分 · 当 指标值 ≥ P90 时，得分 = 0（P90对应最差表现） · 当 指标值 ≤ P10 时，得分 = 10（P10对应最优表现） · 当 P10 < 指标值 < P90 时，得分 = 10 ×（P90 - 指标值）÷（P90 - P10） 步骤4-6：同正向指标（上年维度改进率计算时，改进率 =（上年值 - 当期值）÷ 上年值，改进率 > 0 表示改善）
A14: 四、适用本范式的定量指标清单
A15: 序号 | B15: 三级指标 | C15: 指标方向 | D15: 计算公式 | E15: 上年 | F15: 数据来源
A16: 1 | B16: 物理碳排放强度 | C16: 反向（越低越好） | D16: 碳排放总量 ÷ 粗钢产量（tCO2/吨钢） | E16: 上年 | F16: 可持续发展报告
A17: 2 | B17: 营收碳排放强度 | C17: 反向（越低越好） | D17: 碳排放总量 ÷ 营业收入（tCO2/万元） | E17: 上年 | F17: 可持续发展报告
A18: 3 | B18: 可再生能源占比（自发） | C18: 正向（越高越好） | D18: 自发可再生能源发电量 ÷ 总能源消耗量（%） | E18: 上年 | F18: 可持续发展报告
A19: 4 | B19: 外购绿电占比 | C19: 正向（越高越好） | D19: 外购绿电电量 ÷ 总能源消耗量（%） | E19: 上年 | F19: 可持续发展报告
A20: 5 | B20: 用水效率（吨钢耗新水量） | C20: 反向（越低越好） | D20: 新水消耗量 ÷ 粗钢产量（m3/吨钢） | E20: 上年 | F20: 可持续发展报告
A21: 6 | B21: 研发投入占比 | C21: 正向（越高越好） | D21: 研发投入 ÷ 营业收入（%） | E21: 上年 | F21: 可持续发展报告/年报
A22: 7 | B22: 节能技改投资占比 | C22: 正向（越高越好） | D22: 节能技改投资 ÷ 营业收入（%） | E22: 上年 | F22: 可持续发展报告
A23: 8 | B23: 环保投入金额占比 | C23: 正向（越高越好） | D23: 环保投入 ÷ 营业收入（%） | E23: 上年 | F23: 可持续发展报告
A24: 9 | B24: 废钢回收率 | C24: 正向（越高越好） | D24: 废钢回收总量 ÷ 粗钢产量（%） | E24: 上年 | F24: 可持续发展报告
A25: 10 | B25: 稳就业与促就业 | C25: 正向（越高越好） | D25: （当期员工人数 − 上年员工人数）÷ 上年员工人数（%） | E25: 上年 | F25: 年报/可持续发展报告
A26: 五、不适用的定性/分档指标（保持原赋分逻辑不变）
A27: 序号 | B27: 三级指标 | C27: 赋分方式 | D27: 不适用原因 | E27: 保持逻辑说明
A28: 1 | B28: 碳中和/碳达峰目标 | C28: 相等（基础分×范围系数） | D28: 非连续数值指标，为分档赋分 | E28: 保持原逻辑：根据承诺年份和覆盖范围分层赋分
A29: 2 | B29: 其他环境目标 | C29: 相等（数量+质量） | D29: 定性计数指标 | E29: 保持原逻辑：按目标类型数量和质量等级赋分
A30: 3 | B30: 转型规划/其他战略 | C30: 累加 | D30: 定性清单指标 | E30: 保持原逻辑：按规划要素覆盖度逐项累加赋分
A31: 4 | B31: 治理架构/风险管理体系 | C31: 累加 | D31: 定性清单指标 | E31: 保持原逻辑：按管理要素覆盖度逐项累加赋分
A32: 5 | B32: 气候风险和机遇/压力测试 | C32: 累加 | D32: 定性清单指标 | E32: 保持原逻辑：按识别和评估要素逐项累加赋分
A33: 6 | B33: 碳排放披露情况 | C33: 相等（披露完整度） | D33: 定性分档指标 | E33: 保持原逻辑：按披露范围和完整性分档赋分
A34: 7 | B34: 生物多样性/员工培训 | C34: 累加 | D34: 定性清单指标 | E34: 保持原逻辑：按制度建设和行动措施逐项累加赋分
A35: 9 | B35: 系统能效提升/冶炼技术突破 | C35: 累加 | D35: 定性技术清单 | E35: 保持原逻辑：按技术应用情况分档赋分
A36: 10 | B36: 环保减排改造 | C36: 相等（是/否） | D36: 定性二元指标 | E36: 保持原逻辑：按是否完成超低排放改造赋分
A37: 11 | B37: 数字化赋能 | C37: 相等（是/否） | D37: 定性二元指标 | E37: 保持原逻辑：按是否应用数字化手段赋分
A38: 12 | B38: 产品结构优化 | C38: 累加 | D38: 定性分类指标 | E38: 保持原逻辑：按高端产品应用领域逐项累加赋分
